Workbook

Sheet Cover
B2: PORTFOLIO PROJECT 03
B3: Excel Budgeting System
B4: Sampaguita Foods & Distribution Corporation (SFDC)
B5: Monthly budget vs actual, flex budget, reforecast and driver-based FY2026 budget built on the Project 1 ledgers
B7: Prepared by Bengie Hirnani | Version 1.0 | PHP in thousands (unless otherwise stated)
B10: Model status | C10: =Model_Status -> ✔ All 15 integrity checks passed
B11: Scope | C11: Approved FY2025 monthly budget compared with actuals rebuilt from the Project 1 ledgers; variance flags with dual thresholds; flexible budget and operating-profit bridge; rolling full-year reforecast; driver-based FY2026 budget benchmarked against the Project 1 trend forecast; interactive dashboard with month and YTD views.
B12: Data notice | C12: The company, budget and figures are fictional. Actuals reconcile to the Project 1 income statement (control totals on Checks). FY2026 drivers are management assumptions on the Assumptions sheet.
B14: NAVIGATION - click a button to jump to a sheet
B15: DASHBOARD
B16: =HYPERLINK("#Dashboard!A1","Dashboard") -> Dashboard | C16: Month / YTD selector, KPI cards, insights and 4 charts
B18: BUDGET VS ACTUAL
B19: =HYPERLINK("#Variance!A1","Variance") -> Variance | C19: Static budget vs actual with favourable/unfavourable flags
B20: =HYPERLINK("#Flex_Budget!A1","Flex Budget") -> Flex Budget | C20: Flexible budget and operating profit bridge
B21: =HYPERLINK("#Forecast!A1","Forecast") -> Forecast | C21: Rolling full-year reforecast by selected month
B23: BUDGETS
B24: =HYPERLINK("#Budget_FY2026!A1","Budget FY2026") -> Budget FY2026 | C24: Driver-based FY2026 budget by month, compared with the Project 1 trend
B25: =HYPERLINK("#Assumptions!A1","Assumptions") -> Assumptions | C25: FY2026 drivers, thresholds and parameters
B26: =HYPERLINK("#Budget_FY2025!A1","Budget FY2025") -> Budget FY2025 | C26: Approved FY2025 monthly budget (inputs)
B27: =HYPERLINK("#Actuals!A1","Actuals") -> Actuals | C27: FY2025 actuals rebuilt from the ledgers (SUMIFS)
B29: DATA AND CONTROLS
B30: =HYPERLINK("#FS_Data!A1","FS Data") -> FS Data | C30: Project 1 control totals
B31: =HYPERLINK("#Data_Sales!A1","Data Sales") -> Data Sales | C31: Monthly sales ledger (Project 1)
B32: =HYPERLINK("#Data_Expenses!A1","Data Expenses") -> Data Expenses | C32: Monthly expense ledger (Project 1)
B33: =HYPERLINK("#Chart_Data!A1","Chart Data") -> Chart Data | C33: Helper tables for charts
B34: =HYPERLINK("#Lists!A1","Lists") -> Lists | C34: Drop-down lists and selector helpers
B35: =HYPERLINK("#Checks!A1","Checks") -> Checks | C35: Model integrity checks
B36: =HYPERLINK("#Documentation!A1","Documentation") -> Documentation | C36: Purpose, method, conventions, how to update

Sheet Documentation
B1: Budgeting System Documentation
B2: Sampaguita Foods & Distribution Corporation (SFDC) | Documentation
B3: =HYPERLINK("#Cover!A1","◄ Back to Cover") -> ◄ Back to Cover
B5: 1. PURPOSE
B6: Objective | C6: Show a complete management budgeting cycle for a Philippine distributor: approved budget, monthly variance monitoring, flexible-budget diagnosis, reforecasting and next-year budget preparation.
B7: Link to Project 1 | C7: Actual sales, cost of sales and operating expenses are rebuilt from the same ledgers as Project 1 with SUMIFS; depreciation comes from the Project 1 PPE schedule. Operating profit of PHP 58.7 million for FY2025 reconciles exactly (see Checks).
B9: 2. HOW THE MODEL FLOWS
B10: Step 1 | C10: Budget_FY2025 holds the approved monthly budget (inputs). Actuals pulls the ledgers by year, month and category/line.
B11: Step 2 | C11: Variance compares budget and actual for the month or year-to-date selected on the Dashboard, applying the favourable/(unfavourable) sign convention and review flags.
B12: Step 3 | C12: Flex_Budget restates the budget at actual sales to split the operating-profit variance into sales activity and spending effects.
B13: Step 4 | C13: Forecast projects the full year from actuals to date plus run-rate-adjusted budget. Budget_FY2026 applies the Assumptions drivers to FY2025 actuals.
B15: 3. CONVENTIONS
B16: Colours | C16: Blue = input; black = formula on the same sheet; green = formula linking another sheet; yellow fill = key assumption or selector.
B17: Signs | C17: Variance columns are always 'favourable positive'. Costs are shown as positive amounts in the grids.
B18: Units | C18: PHP in thousands unless stated.
B20: 4. KEY ASSUMPTIONS AND LIMITS
B21: Budget basis | C21: FY2025 budget derived from FY2024 actuals with category growth and inflation assumptions (see note on Budget_FY2025). It is a fictional dataset created for demonstration.
B22: Depreciation | C22: Actual depreciation is the Project 1 annual charge spread evenly across months; budget depreciation is PHP 20.8 million spread evenly.
B23: Forecast | C23: Run-rate method is deliberately simple and does not model seasonality of the remaining months beyond the budget phasing.
B24: Not modelled | C24: Cash budget, balance sheet budget, capex budget and departmental (cost-centre) budgets.
B26: 5. HOW TO UPDATE
B27: New month | C27: Append ledger rows to Data_Sales / Data_Expenses and extend the S_ and E_ named ranges (Formulas > Name Manager).
B28: New budget | C28: Overwrite blue cells on Budget_FY2025 or change drivers on Assumptions; confirm the Checks banner stays green.

Sheet Dashboard
B1: Budget vs Actual Dashboard
B2: Sampaguita Foods & Distribution Corporation (SFDC) | PHP in thousands (unless otherwise stated)
B3: =HYPERLINK("#Cover!A1","◄ Back to Cover") -> ◄ Back to Cover
B5: Month | C5: Apr | E5: View | F5: Month | H5: Model integrity | J5: =Model_Status -> ✔ All 15 integrity checks passed
B7: NET SALES | E7: GROSS PROFIT | H7: OPERATING EXPENSES | K7: OPERATING PROFIT
B8: =Variance!D12 -> 79023 | E8: =Variance!D19 -> 20169 | H8: =Variance!D38 -> 15859.417 | K8: =Variance!D39 -> 4309.5833
B9: =IF(Variance!E12>=0,"▲ ","▼ ")&TEXT(ABS(Variance!F12),"0.0%")&IF(Variance!E12>=0," favourable"," unfavourable")&" vs budget" -> ▼ 5.7% unfavourable vs budget | E9: =IF(Variance!E19>=0,"▲ ","▼ ")&TEXT(ABS(Variance!F19),"0.0%")&IF(Variance!E19>=0," favourable"," unfavourable")&" vs budget" -> ▼ 5.3% unfavourable vs budget | H9: =IF(Variance!E38>=0,"▲ ","▼ ")&TEXT(ABS(Variance!F38),"0.0%")&IF(Variance!E38>=0," favourable"," unfavourable")&" vs budget" -> ▲ 0.2% favourable vs budget | K9: =IF(Variance!E39>=0,"▲ ","▼ ")&TEXT(ABS(Variance!F39),"0.0%")&IF(Variance!E39>=0," favourable"," unfavourable")&" vs budget" -> ▼ 20.6% unfavourable vs budget
B11: GROSS MARGIN | E11: OPERATING MARGIN | H11: EXPENSE LINES OVER BUDGET | K11: FULL-YEAR OPERATING PROFIT OUTLOOK
B12: =Variance!D20 -> 0.25522949 | E12: =Variance!D40 -> 0.05453581 | H12: =COUNTIF(Chart_Data!$C$20:$C$32,"<0") -> 4 | K12: =Forecast!P18 -> 52132.285
B13: =TEXT(Variance!E20*100,"+0.00;-0.00")&" pts vs budget ("&TEXT(Variance!C20,"0.0%")&")" -> +0.09 pts vs budget (25.4%) | E13: =TEXT(Variance!E40*100,"+0.00;-0.00")&" pts vs budget ("&TEXT(Variance!C40,"0.0%")&")" -> -1.02 pts vs budget (6.5%) | H13: ="of 13 lines; "&COUNTIFS(Variance!$G$22:$G$35,"▼*")&" breach the review threshold" -> of 13 lines; 1 breach the review threshold | K13: =IF(Forecast!R18>=0,"▲ ","▼ ")&TEXT(ABS(Forecast!R18),"#,##0")&" vs full-year budget" -> ▼ 3,421 vs full-year budget
B15: KEY INSIGHTS (update automatically with the selection)
B16: ="1. Net sales for "&Period_Label&" were PHP "&TEXT(Variance!D12/1000,"#,##0.0")&" million, "&TEXT(ABS(Variance!F12),"0.0%")&IF(Variance!E12>=0," above"," below")&" budget." -> 1. Net sales for Apr FY2025 were PHP 79.0 million, 5.7% below budget.
B17: ="2. Operating profit was PHP "&TEXT(Variance!D39/1000,"#,##0.0")&" million, "&TEXT(ABS(Variance!F39),"0.0%")&IF(Variance!E39>=0," above"," below")&" budget; gross margin "&TEXT(Variance!D20,"0.0%")&" vs "&TEXT(Variance!C20,"0.0%")&" budgeted." -> 2. Operating profit was PHP 4.3 million, 20.6% below budget; gross margin 25.5% vs 25.4% budgeted.
B18: ="3. Largest unfavourable expense line: "&Chart_Data!C34&IF(Chart_Data!C35<0," (PHP "&TEXT(-Chart_Data!C35,"#,##0")&"K over budget).",".")&" Largest favourable: "&Chart_Data!C36&IF(Chart_Data!C37>0," (PHP "&TEXT(Chart_Data!C37,"#,##0")&"K under budget).",".") -> 3. Largest unfavourable expense line: Warehouse rent & utilities (PHP 116K over budget). Largest favourable: Freight & delivery (PHP 73K under budget).
B19: ="4. Flex budget: sales activity added PHP "&TEXT(Flex_Budget!F23,"#,##0;(#,##0)")&"K to budgeted profit; spending and margin effects added PHP "&TEXT(Flex_Budget!G23,"#,##0;(#,##0)")&"K." -> 4. Flex budget: sales activity added PHP (968)K to budgeted profit; spending and margin effects added PHP (149)K.
B20: ="5. Reforecast full-year operating profit PHP "&TEXT(Forecast!P18/1000,"#,##0.0")&" million vs budget PHP "&TEXT(Forecast!Q18/1000,"#,##0.0")&" million. FY2026 budget operating profit: PHP "&TEXT(Budget_FY2026!P39/1000,"#,##0.0")&" million." -> 5. Reforecast full-year operating profit PHP 52.1 million vs budget PHP 55.6 million. FY2026 budget operating profit: PHP 67.4 million.

Sheet Variance
B1: Budget vs Actual Variance Analysis
B2: Sampaguita Foods & Distribution Corporation (SFDC) | PHP in thousands | positive variance = favourable to profit
B3: =HYPERLINK("#Cover!A1","◄ Back to Cover") -> ◄ Back to Cover
B4: ="Period: "&Period_Label -> Period: Apr FY2025
B5: Line | C5: Budget | D5: Actual | E5: Variance F / (U) | F5: Variance % | G5: Review flag
B7: NET SALES
B8: Packaged Food | C8: =(View_Mode="Month")*SUMPRODUCT((Budget_FY2025!$D$6:$O$6=Sel_M)*Budget_FY2025!$D8:$O8)+(View_Mode<>"Month")*SUMPRODUCT((Budget_FY2025!$D$6:$O$6<=Sel_M)*Budget_FY2025!$D8:$O8) -> 32709 | D8: =(View_Mode="Month")*SUMPRODUCT((Actuals!$D$6:$O$6=Sel_M)*Actuals!$D8:$O8)+(View_Mode<>"Month")*SUMPRODUCT((Actuals!$D$6:$O$6<=Sel_M)*Actuals!$D8:$O8) -> 30564 | E8: =D8-C8 -> -2145 | F8: =IFERROR(E8/C8,0) -> -0.065578281 | G8: =IF(AND(ABS(F8)>=Thr_Pct,ABS(E8)>=Thr_Abs),IF(E8>0,"▲ Favourable","▼ Unfavourable"),"● On budget") -> ▼ Unfavourable
B9: Beverages | C9: =(View_Mode="Month")*SUMPRODUCT((Budget_FY2025!$D$6:$O$6=Sel_M)*Budget_FY2025!$D9:$O9)+(View_Mode<>"Month")*SUMPRODUCT((Budget_FY2025!$D$6:$O$6<=Sel_M)*Budget_FY2025!$D9:$O9) -> 25802 | D9: =(View_Mode="Month")*SUMPRODUCT((Actuals!$D$6:$O$6=Sel_M)*Actuals!$D9:$O9)+(View_Mode<>"Month")*SUMPRODUCT((Actuals!$D$6:$O$6<=Sel_M)*Actuals!$D9:$O9) -> 24653 | E9: =D9-C9 -> -1149 | F9: =IFERROR(E9/C9,0) -> -0.044531432 | G9: =IF(AND(ABS(F9)>=Thr_Pct,ABS(E9)>=Thr_Abs),IF(E9>0,"▲ Favourable","▼ Unfavourable"),"● On budget") -> ● On budget
B10: Household & Personal Care | C10: =(View_Mode="Month")*SUMPRODUCT((Budget_FY2025!$D$6:$O$6=Sel_M)*Budget_FY2025!$D10:$O10)+(View_Mode<>"Month")*SUMPRODUCT((Budget_FY2025!$D$6:$O$6<=Sel_M)*Budget_FY2025!$D10:$O10) -> 14233 | D10: =(View_Mode="Month")*SUMPRODUCT((Actuals!$D$6:$O$6=Sel_M)*Actuals!$D10:$O10)+(View_Mode<>"Month")*SUMPRODUCT((Actuals!$D$6:$O$6<=Sel_M)*Actuals!$D10:$O10) -> 13386 | E10: =D10-C10 -> -847 | F10: =IFERROR(E10/C10,0) -> -0.05950959 | G10: =IF(AND(ABS(F10)>=Thr_Pct,ABS(E10)>=Thr_Abs),IF(E10>0,"▲ Favourable","▼ Unfavourable"),"● On budget") -> ▼ Unfavourable
B11: Fresh & Frozen | C11: =(View_Mode="Month")*SUMPRODUCT((Budget_FY2025!$D$6:$O$6=Sel_M)*Budget_FY2025!$D11:$O11)+(View_Mode<>"Month")*SUMPRODUCT((Budget_FY2025!$D$6:$O$6<=Sel_M)*Budget_FY2025!$D11:$O11) -> 11031 | D11: =(View_Mode="Month")*SUMPRODUCT((Actuals!$D$6:$O$6=Sel_M)*Actuals!$D11:$O11)+(View_Mode<>"Month")*SUMPRODUCT((Actuals!$D$6:$O$6<=Sel_M)*Actuals!$D11:$O11) -> 10420 | E11: =D11-C11 -> -611 | F11: =IFERROR(E11/C11,0) -> -0.055389357 | G11: =IF(AND(ABS(F11)>=Thr_Pct,ABS(E11)>=Thr_Abs),IF(E11>0,"▲ Favourable","▼ Unfavourable"),"● On budget") -> ▼ Unfavourable
B12: Total net sales | C12: =(View_Mode="Month")*SUMPRODUCT((Budget_FY2025!$D$6:$O$6=Sel_M)*Budget_FY2025!$D12:$O12)+(View_Mode<>"Month")*SUMPRODUCT((Budget_FY2025!$D$6:$O$6<=Sel_M)*Budget_FY2025!$D12:$O12) -> 83775 | D12: =(View_Mode="Month")*SUMPRODUCT((Actuals!$D$6:$O$6=Sel_M)*Actuals!$D12:$O12)+(View_Mode<>"Month")*SUMPRODUCT((Actuals!$D$6:$O$6<=Sel_M)*Actuals!$D12:$O12) -> 79023 | E12: =D12-C12 -> -4752 | F12: =IFERROR(E12/C12,0) -> -0.056723366 | G12: =IF(AND(ABS(F12)>=Thr_Pct,ABS(E12)>=Thr_Abs),IF(E12>0,"▲ Favourable","▼ Unfavourable"),"● On budget") -> ▼ Unfavourable
B13: COST OF SALES
B14: Packaged Food | C14: =(View_Mode="Month")*SUMPRODUCT((Budget_FY2025!$D$6:$O$6=Sel_M)*Budget_FY2025!$D14:$O14)+(View_Mode<>"Month")*SUMPRODUCT((Budget_FY2025!$D$6:$O$6<=Sel_M)*Budget_FY2025!$D14:$O14) -> 24593 | D14: =(View_Mode="Month")*SUMPRODUCT((Actuals!$D$6:$O$6=Sel_M)*Actuals!$D14:$O14)+(View_Mode<>"Month")*SUMPRODUCT((Actuals!$D$6:$O$6<=Sel_M)*Actuals!$D14:$O14) -> 23005 | E14: =C14-D14 -> 1588 | F14: =IFERROR(E14/C14,0) -> 0.064571219 | G14: =IF(AND(ABS(F14)>=Thr_Pct,ABS(E14)>=Thr_Abs),IF(E14>0,"▲ Favourable","▼ Unfavourable"),"● On budget") -> ▲ Favourable
B15: Beverages | C15: =(View_Mode="Month")*SUMPRODUCT((Budget_FY2025!$D$6:$O$6=Sel_M)*Budget_FY2025!$D15:$O15)+(View_Mode<>"Month")*SUMPRODUCT((Budget_FY2025!$D$6:$O$6<=Sel_M)*Budget_FY2025!$D15:$O15) -> 18919 | D15: =(View_Mode="Month")*SUMPRODUCT((Actuals!$D$6:$O$6=Sel_M)*Actuals!$D15:$O15)+(View_Mode<>"Month")*SUMPRODUCT((Actuals!$D$6:$O$6<=Sel_M)*Actuals!$D15:$O15) -> 18013 | E15: =C15-D15 -> 906 | F15: =IFERROR(E15/C15,0) -> 0.047888366 | G15: =IF(AND(ABS(F15)>=Thr_Pct,ABS(E15)>=Thr_Abs),IF(E15>0,"▲ Favourable","▼ Unfavourable"),"● On budget") -> ● On budget
B16: Household & Personal Care | C16: =(View_Mode="Month")*SUMPRODUCT((Budget_FY2025!$D$6:$O$6=Sel_M)*Budget_FY2025!$D16:$O16)+(View_Mode<>"Month")*SUMPRODUCT((Budget_FY2025!$D$6:$O$6<=Sel_M)*Budget_FY2025!$D16:$O16) -> 9996 | D16: =(View_Mode="Month")*SUMPRODUCT((Actuals!$D$6:$O$6=Sel_M)*Actuals!$D16:$O16)+(View_Mode<>"Month")*SUMPRODUCT((Actuals!$D$6:$O$6<=Sel_M)*Actuals!$D16:$O16) -> 9378 | E16: =C16-D16 -> 618 | F16: =IFERROR(E16/C16,0) -> 0.06182473 | G16: =IF(AND(ABS(F16)>=Thr_Pct,ABS(E16)>=Thr_Abs),IF(E16>0,"▲ Favourable","▼ Unfavourable"),"● On budget") -> ▲ Favourable
B17: Fresh & Frozen | C17: =(View_Mode="Month")*SUMPRODUCT((Budget_FY2025!$D$6:$O$6=Sel_M)*Budget_FY2025!$D17:$O17)+(View_Mode<>"Month")*SUMPRODUCT((Budget_FY2025!$D$6:$O$6<=Sel_M)*Budget_FY2025!$D17:$O17) -> 8958 | D17: =(View_Mode="Month")*SUMPRODUCT((Actuals!$D$6:$O$6=Sel_M)*Actuals!$D17:$O17)+(View_Mode<>"Month")*SUMPRODUCT((Actuals!$D$6:$O$6<=Sel_M)*Actuals!$D17:$O17) -> 8458 | E17: =C17-D17 -> 500 | F17: =IFERROR(E17/C17,0) -> 0.05581603 | G17: =IF(AND(ABS(F17)>=Thr_Pct,ABS(E17)>=Thr_Abs),IF(E17>0,"▲ Favourable","▼ Unfavourable"),"● On budget") -> ▲ Favourable
B18: Total cost of sales | C18: =(View_Mode="Month")*SUMPRODUCT((Budget_FY2025!$D$6:$O$6=Sel_M)*Budget_FY2025!$D18:$O18)+(View_Mode<>"Month")*SUMPRODUCT((Budget_FY2025!$D$6:$O$6<=Sel_M)*Budget_FY2025!$D18:$O18) -> 62466 | D18: =(View_Mode="Month")*SUMPRODUCT((Actuals!$D$6:$O$6=Sel_M)*Actuals!$D18:$O18)+(View_Mode<>"Month")*SUMPRODUCT((Actuals!$D$6:$O$6<=Sel_M)*Actuals!$D18:$O18) -> 58854 | E18: =C18-D18 -> 3612 | F18: =IFERROR(E18/C18,0) -> 0.057823456 | G18: =IF(AND(ABS(F18)>=Thr_Pct,ABS(E18)>=Thr_Abs),IF(E18>0,"▲ Favourable","▼ Unfavourable"),"● On budget") -> ▲ Favourable
B19: Gross profit | C19: =(View_Mode="Month")*SUMPRODUCT((Budget_FY2025!$D$6:$O$6=Sel_M)*Budget_FY2025!$D19:$O19)+(View_Mode<>"Month")*SUMPRODUCT((Budget_FY2025!$D$6:$O$6<=Sel_M)*Budget_FY2025!$D19:$O19) -> 21309 | D19: =(View_Mode="Month")*SUMPRODUCT((Actuals!$D$6:$O$6=Sel_M)*Actuals!$D19:$O19)+(View_Mode<>"Month")*SUMPRODUCT((Actuals!$D$6:$O$6<=Sel_M)*Actuals!$D19:$O19) -> 20169 | E19: =D19-C19 -> -1140 | F19: =IFERROR(E19/C19,0) -> -0.053498522 | G19: =IF(AND(ABS(F19)>=Thr_Pct,ABS(E19)>=Thr_Abs),IF(E19>0,"▲ Favourable","▼ Unfavourable"),"● On budget") -> ▼ Unfavourable
B20: Gross margin % | C20: =IFERROR(C19/C12,0) -> 0.25435989 | D20: =IFERROR(D19/D12,0) -> 0.25522949 | E20: =D20-C20 -> 0.00086959758 | F20: pts
B21: OPERATING EXPENSES
B22: Sales commissions & incentives | C22: =(View_Mode="Month")*SUMPRODUCT((Budget_FY2025!$D$6:$O$6=Sel_M)*Budget_FY2025!$D22:$O22)+(View_Mode<>"Month")*SUMPRODUCT((Budget_FY2025!$D$6:$O$6<=Sel_M)*Budget_FY2025!$D22:$O22) -> 1340 | D22: =(View_Mode="Month")*SUMPRODUCT((Actuals!$D$6:$O$6=Sel_M)*Actuals!$D22:$O22)+(View_Mode<>"Month")*SUMPRODUCT((Actuals!$D$6:$O$6<=Sel_M)*Actuals!$D22:$O22) -> 1284 | E22: =C22-D22 -> 56 | F22: =IFERROR(E22/C22,0) -> 0.041791045 | G22: =IF(AND(ABS(F22)>=Thr_Pct,ABS(E22)>=Thr_Abs),IF(E22>0,"▲ Favourable","▼ Unfavourable"),"● On budget") -> ● On budget
B23: Advertising & promotions | C23: =(View_Mode="Month")*SUMPRODUCT((Budget_FY2025!$D$6:$O$6=Sel_M)*Budget_FY2025!$D23:$O23)+(View_Mode<>"Month")*SUMPRODUCT((Budget_FY2025!$D$6:$O$6<=Sel_M)*Budget_FY2025!$D23:$O23) -> 774 | D23: =(View_Mode="Month")*SUMPRODUCT((Actuals!$D$6:$O$6=Sel_M)*Actuals!$D23:$O23)+(View_Mode<>"Month")*SUMPRODUCT((Actuals!$D$6:$O$6<=Sel_M)*Actuals!$D23:$O23) -> 717 | E23: =C23-D23 -> 57 | F23: =IFERROR(E23/C23,0) -> 0.073643411 | G23: =IF(AND(ABS(F23)>=Thr_Pct,ABS(E23)>=Thr_Abs),IF(E23>0,"▲ Favourable","▼ Unfavourable"),"● On budget") -> ● On budget
B24: Freight & delivery | C24: =(View_Mode="Month")*SUMPRODUCT((Budget_FY2025!$D$6:$O$6=Sel_M)*Budget_FY2025!$D24:$O24)+(View_Mode<>"Month")*SUMPRODUCT((Budget_FY2025!$D$6:$O$6<=Sel_M)*Budget_FY2025!$D24:$O24) -> 2014 | D24: =(View_Mode="Month")*SUMPRODUCT((Actuals!$D$6:$O$6=Sel_M)*Actuals!$D24:$O24)+(View_Mode<>"Month")*SUMPRODUCT((Actuals!$D$6:$O$6<=Sel_M)*Actuals!$D24:$O24) -> 1941 | E24: =C24-D24 -> 73 | F24: =IFERROR(E24/C24,0) -> 0.036246276 | G24: =IF(AND(ABS(F24)>=Thr_Pct,ABS(E24)>=Thr_Abs),IF(E24>0,"▲ Favourable","▼ Unfavourable"),"● On budget") -> ● On budget
B25: Warehouse rent & utilities | C25: =(View_Mode="Month")*SUMPRODUCT((Budget_FY2025!$D$6:$O$6=Sel_M)*Budget_FY2025!$D25:$O25)+(View_Mode<>"Month")*SUMPRODUCT((Budget_FY2025!$D$6:$O$6<=Sel_M)*Budget_FY2025!$D25:$O25) -> 1988 | D25: =(View_Mode="Month")*SUMPRODUCT((Actuals!$D$6:$O$6=Sel_M)*Actuals!$D25:$O25)+(View_Mode<>"Month")*SUMPRODUCT((Actuals!$D$6:$O$6<=Sel_M)*Actuals!$D25:$O25) -> 2104 | E25: =C25-D25 -> -116 | F25: =IFERROR(E25/C25,0) -> -0.058350101 | G25: =IF(AND(ABS(F25)>=Thr_Pct,ABS(E25)>=Thr_Abs),IF(E25>0,"▲ Favourable","▼ Unfavourable"),"● On budget") -> ▼ Unfavourable
B26: Selling & logistics staff costs | C26: =(View_Mode="Month")*SUMPRODUCT((Budget_FY2025!$D$6:$O$6=Sel_M)*Budget_FY2025!$D26:$O26)+(View_Mode<>"Month")*SUMPRODUCT((Budget_FY2025!$D$6:$O$6<=Sel_M)*Budget_FY2025!$D26:$O26) -> 2692 | D26: =(View_Mode="Month")*SUMPRODUCT((Actuals!$D$6:$O$6=Sel_M)*Actuals!$D26:$O26)+(View_Mode<>"Month")*SUMPRODUCT((Actuals!$D$6:$O$6<=Sel_M)*Actuals!$D26:$O26) -> 2730 | E26: =C26-D26 -> -38 | F26: =IFERROR(E26/C26,0) -> -0.014115899 | G26: =IF(AND(ABS(F26)>=Thr_Pct,ABS(E26)>=Thr_Abs),IF(E26>0,"▲ Favourable","▼ Unfavourable"),"● On budget") -> ● On budget
B27: Selling & distribution | C27: =(View_Mode="Month")*SUMPRODUCT((Budget_FY2025!$D$6:$O$6=Sel_M)*Budget_FY2025!$D27:$O27)+(View_Mode<>"Month")*SUMPRODUCT((Budget_FY2025!$D$6:$O$6<=Sel_M)*Budget_FY2025!$D27:$O27) -> 8808 | D27: =(View_Mode="Month")*SUMPRODUCT((Actuals!$D$6:$O$6=Sel_M)*Actuals!$D27:$O27)+(View_Mode<>"Month")*SUMPRODUCT((Actuals!$D$6:$O$6<=Sel_M)*Actuals!$D27:$O27) -> 8776 | E27: =C27-D27 -> 32 | F27: =IFERROR(E27/C27,0) -> 0.0036330609 | G27: =IF(AND(ABS(F27)>=Thr_Pct,ABS(E27)>=Thr_Abs),IF(E27>0,"▲ Favourable","▼ Unfavourable"),"● On budget") -> ● On budget
B28: Salaries & wages (G&A) | C28: =(View_Mode="Month")*SUMPRODUCT((Budget_FY2025!$D$6:$O$6=Sel_M)*Budget_FY2025!$D28:$O28)+(View_Mode<>"Month")*SUMPRODUCT((Budget_FY2025!$D$6:$O$6<=Sel_M)*Budget_FY2025!$D28:$O28) -> 2522 | D28: =(View_Mode="Month")*SUMPRODUCT((Actuals!$D$6:$O$6=Sel_M)*Actuals!$D28:$O28)+(View_Mode<>"Month")*SUMPRODUCT((Actuals!$D$6:$O$6<=Sel_M)*Actuals!$D28:$O28) -> 2562 | E28: =C28-D28 -> -40 | F28: =IFERROR(E28/C28,0) -> -0.015860428 | G28: =IF(AND(ABS(F28)>=Thr_Pct,ABS(E28)>=Thr_Abs),IF(E28>0,"▲ Favourable","▼ Unfavourable"),"● On budget") -> ● On budget
B29: Employee benefits & contributions | C29: =(View_Mode="Month")*SUMPRODUCT((Budget_FY2025!$D$6:$O$6=Sel_M)*Budget_FY2025!$D29:$O29)+(View_Mode<>"Month")*SUMPRODUCT((Budget_FY2025!$D$6:$O$6<=Sel_M)*Budget_FY2025!$D29:$O29) -> 691 | D29: =(View_Mode="Month")*SUMPRODUCT((Actuals!$D$6:$O$6=Sel_M)*Actuals!$D29:$O29)+(View_Mode<>"Month")*SUMPRODUCT((Actuals!$D$6:$O$6<=Sel_M)*Actuals!$D29:$O29) -> 667 | E29: =C29-D29 -> 24 | F29: =IFERROR(E29/C29,0) -> 0.034732272 | G29: =IF(AND(ABS(F29)>=Thr_Pct,ABS(E29)>=Thr_Abs),IF(E29>0,"▲ Favourable","▼ Unfavourable"),"● On budget") -> ● On budget
B30: Professional fees | C30: =(View_Mode="Month")*SUMPRODUCT((Budget_FY2025!$D$6:$O$6=Sel_M)*Budget_FY2025!$D30:$O30)+(View_Mode<>"Month")*SUMPRODUCT((Budget_FY2025!$D$6:$O$6<=Sel_M)*Budget_FY2025!$D30:$O30) -> 335 | D30: =(View_Mode="Month")*SUMPRODUCT((Actuals!$D$6:$O$6=Sel_M)*Actuals!$D30:$O30)+(View_Mode<>"Month")*SUMPRODUCT((Actuals!$D$6:$O$6<=Sel_M)*Actuals!$D30:$O30) -> 330 | E30: =C30-D30 -> 5 | F30: =IFERROR(E30/C30,0) -> 0.014925373 | G30: =IF(AND(ABS(F30)>=Thr_Pct,ABS(E30)>=Thr_Abs),IF(E30>0,"▲ Favourable","▼ Unfavourable"),"● On budget") -> ● On budget
B31: Office rent & utilities | C31: =(View_Mode="Month")*SUMPRODUCT((Budget_FY2025!$D$6:$O$6=Sel_M)*Budget_FY2025!$D31:$O31)+(View_Mode<>"Month")*SUMPRODUCT((Budget_FY2025!$D$6:$O$6<=Sel_M)*Budget_FY2025!$D31:$O31) -> 579 | D31: =(View_Mode="Month")*SUMPRODUCT((Actuals!$D$6:$O$6=Sel_M)*Actuals!$D31:$O31)+(View_Mode<>"Month")*SUMPRODUCT((Actuals!$D$6:$O$6<=Sel_M)*Actuals!$D31:$O31) -> 569 | E31: =C31-D31 -> 10 | F31: =IFERROR(E31/C31,0) -> 0.017271157 | G31: =IF(AND(ABS(F31)>=Thr_Pct,ABS(E31)>=Thr_Abs),IF(E31>0,"▲ Favourable","▼ Unfavourable"),"● On budget") -> ● On budget
B32: Repairs & maintenance | C32: =(View_Mode="Month")*SUMPRODUCT((Budget_FY2025!$D$6:$O$6=Sel_M)*Budget_FY2025!$D32:$O32)+(View_Mode<>"Month")*SUMPRODUCT((Budget_FY2025!$D$6:$O$6<=Sel_M)*Budget_FY2025!$D32:$O32) -> 224 | D32: =(View_Mode="Month")*SUMPRODUCT((Actuals!$D$6:$O$6=Sel_M)*Actuals!$D32:$O32)+(View_Mode<>"Month")*SUMPRODUCT((Actuals!$D$6:$O$6<=Sel_M)*Actuals!$D32:$O32) -> 232 | E32: =C32-D32 -> -8 | F32: =IFERROR(E32/C32,0) -> -0.035714286 | G32: =IF(AND(ABS(F32)>=Thr_Pct,ABS(E32)>=Thr_Abs),IF(E32>0,"▲ Favourable","▼ Unfavourable"),"● On budget") -> ● On budget
B33: Taxes, licenses & insurance | C33: =(View_Mode="Month")*SUMPRODUCT((Budget_FY2025!$D$6:$O$6=Sel_M)*Budget_FY2025!$D33:$O33)+(View_Mode<>"Month")*SUMPRODUCT((Budget_FY2025!$D$6:$O$6<=Sel_M)*Budget_FY2025!$D33:$O33) -> 473 | D33: =(View_Mode="Month")*SUMPRODUCT((Actuals!$D$6:$O$6=Sel_M)*Actuals!$D33:$O33)+(View_Mode<>"Month")*SUMPRODUCT((Actuals!$D$6:$O$6<=Sel_M)*Actuals!$D33:$O33) -> 453 | E33: =C33-D33 -> 20 | F33: =IFERROR(E33/C33,0) -> 0.042283298 | G33: =IF(AND(ABS(F33)>=Thr_Pct,ABS(E33)>=Thr_Abs),IF(E33>0,"▲ Favourable","▼ Unfavourable"),"● On budget") -> ● On budget
... B38: Total operating expenses | C38: =(View_Mode="Month")*SUMPRODUCT((Budget_FY2025!$D$6:$O$6=Sel_M)*Budget_FY2025!$D38:$O38)+(View_Mode<>"Month")*SUMPRODUCT((Budget_FY2025!$D$6:$O$6<=Sel_M)*Budget_FY2025!$D38:$O38) -> 15883.333 | D38: =(View_Mode="Month")*SUMPRODUCT((Actuals!$D$6:$O$6=Sel_M)*Actuals!$D38:$O38)+(View_Mode<>"Month")*SUMPRODUCT((Actuals!$D$6:$O$6<=Sel_M)*Actuals!$D38:$O38) -> 15859.417 | E38: =C38-D38 -> 23.916667 | F38: =IFERROR(E38/C38,0) -> 0.0015057712 | G38: =IF(AND(ABS(F38)>=Thr_Pct,ABS(E38)>=Thr_Abs),IF(E38>0,"▲ Favourable","▼ Unfavourable"),"● On budget") -> ● On budget
B39: Operating profit | C39: =(View_Mode="Month")*SUMPRODUCT((Budget_FY2025!$D$6:$O$6=Sel_M)*Budget_FY2025!$D39:$O39)+(View_Mode<>"Month")*SUMPRODUCT((Budget_FY2025!$D$6:$O$6<=Sel_M)*Budget_FY2025!$D39:$O39) -> 5425.6667 | D39: =(View_Mode="Month")*SUMPRODUCT((Actuals!$D$6:$O$6=Sel_M)*Actuals!$D39:$O39)+(View_Mode<>"Month")*SUMPRODUCT((Actuals!$D$6:$O$6<=Sel_M)*Actuals!$D39:$O39) -> 4309.5833 | E39: =D39-C39 -> -1116.0833 | F39: =IFERROR(E39/C39,0) -> -0.20570437 | G39: =IF(AND(ABS(F39)>=Thr_Pct,ABS(E39)>=Thr_Abs),IF(E39>0,"▲ Favourable","▼ Unfavourable"),"● On budget") -> ▼ Unfavourable
B40: Operating margin % | C40: =IFERROR(C39/C12,0) -> 0.064764747 | D40: =IFERROR(D39/D12,0) -> 0.05453581 | E40: =D40-C40 -> -0.010228937 | F40: pts
B42: Sign convention: revenue and profit lines - actual less budget; cost lines - budget less actual, so a positive number is always good for profit. Flag rules: |variance %| >= threshold AND |variance PHP| >= threshold (Assumptions).

Sheet Flex_Budget
B1: Flexible Budget Analysis
B2: Sampaguita Foods & Distribution Corporation (SFDC) | PHP in thousands | separates the effect of sales activity from cost spending
B3: =HYPERLINK("#Cover!A1","◄ Back to Cover") -> ◄ Back to Cover
B4: ="Period: "&Period_Label -> Period: Apr FY2025
B5: Line | C5: Static budget | D5: Flexed budget | E5: Actual | F5: Sales activity variance | G5: Spending variance
B6: Net sales | C6: =Variance!C12 -> 83775 | D6: =E6 -> 79023 | E6: =Variance!D12 -> 79023 | F6: =D6-C6 -> -4752 | G6: =E6-D6 -> 0
B7: Cost of sales | C7: =Variance!C18 -> 62466 | D7: =C7*IFERROR($E$6/$C$6,1) -> 58922.718 | E7: =Variance!D18 -> 58854 | F7: =C7-D7 -> 3543.2818 | G7: =D7-E7 -> 68.718209
B8: Sales commissions & incentives | C8: =Variance!C22 -> 1340 | D8: =C8*IFERROR($E$6/$C$6,1) -> 1263.9907 | E8: =Variance!D22 -> 1284 | F8: =C8-D8 -> 76.009311 | G8: =D8-E8 -> -20.009311
B9: Advertising & promotions | C9: =Variance!C23 -> 774 | D9: =C9*IFERROR($E$6/$C$6,1) -> 730.09611 | E9: =Variance!D23 -> 717 | F9: =C9-D9 -> 43.903885 | G9: =D9-E9 -> 13.096115
B10: Freight & delivery | C10: =Variance!C24 -> 2014 | D10: =C10*IFERROR($E$6/$C$6,1) -> 1899.7591 | E10: =Variance!D24 -> 1941 | F10: =C10-D10 -> 114.24086 | G10: =D10-E10 -> -41.240859
B11: Bad debts & credit losses | C11: =Variance!C35 -> 124 | D11: =C11*IFERROR($E$6/$C$6,1) -> 116.9663 | E11: =Variance!D35 -> 121 | F11: =C11-D11 -> 7.0336974 | G11: =D11-E11 -> -4.0336974
B12: Contribution margin | C12: =C6-SUM(C7:C11) -> 17057 | D12: =D6-SUM(D7:D11) -> 16089.47 | E12: =E6-SUM(E7:E11) -> 16106 | F12: =F6+SUM(F7:F11) -> -967.53046 | G12: =G6+SUM(G7:G11) -> 16.530457
B13: Warehouse rent & utilities | C13: =Variance!C25 -> 1988 | D13: =C13 -> 1988 | E13: =Variance!D25 -> 2104 | F13: =C13-D13 -> 0 | G13: =D13-E13 -> -116
B14: Selling & logistics staff costs | C14: =Variance!C26 -> 2692 | D14: =C14 -> 2692 | E14: =Variance!D26 -> 2730 | F14: =C14-D14 -> 0 | G14: =D14-E14 -> -38
B15: Salaries & wages (G&A) | C15: =Variance!C28 -> 2522 | D15: =C15 -> 2522 | E15: =Variance!D28 -> 2562 | F15: =C15-D15 -> 0 | G15: =D15-E15 -> -40
B16: Employee benefits & contributions | C16: =Variance!C29 -> 691 | D16: =C16 -> 691 | E16: =Variance!D29 -> 667 | F16: =C16-D16 -> 0 | G16: =D16-E16 -> 24
B17: Professional fees | C17: =Variance!C30 -> 335 | D17: =C17 -> 335 | E17: =Variance!D30 -> 330 | F17: =C17-D17 -> 0 | G17: =D17-E17 -> 5
B18: Office rent & utilities | C18: =Variance!C31 -> 579 | D18: =C18 -> 579 | E18: =Variance!D31 -> 569 | F18: =C18-D18 -> 0 | G18: =D18-E18 -> 10
B19: Repairs & maintenance | C19: =Variance!C32 -> 224 | D19: =C19 -> 224 | E19: =Variance!D32 -> 232 | F19: =C19-D19 -> 0 | G19: =D19-E19 -> -8
B20: Taxes, licenses & insurance | C20: =Variance!C33 -> 473 | D20: =C20 -> 473 | E20: =Variance!D33 -> 453 | F20: =C20-D20 -> 0 | G20: =D20-E20 -> 20
B21: Communication, IT & supplies | C21: =Variance!C34 -> 394 | D21: =C21 -> 394 | E21: =Variance!D34 -> 378 | F21: =C21-D21 -> 0 | G21: =D21-E21 -> 16
B22: Depreciation | C22: =Variance!C37 -> 1733.3333 | D22: =C22 -> 1733.3333 | E22: =Variance!D37 -> 1771.4167 | F22: =C22-D22 -> 0 | G22: =D22-E22 -> -38.083333
B23: Operating profit | C23: =C12-SUM(C13:C22) -> 5425.6667 | D23: =D12-SUM(D13:D22) -> 4458.1362 | E23: =E12-SUM(E13:E22) -> 4309.5833 | F23: =F12+SUM(F13:F22) -> -967.53046 | G23: =G12+SUM(G13:G22) -> -148.55288
B25: OPERATING PROFIT BRIDGE: STATIC BUDGET TO ACTUAL
B26: Static budget operating profit | C26: =C23 -> 5425.6667
B27: Sales activity effect (volume/price/mix at budget margins) | C27: =F23 -> -967.53046
B28: Cost of sales rate effect (margin vs budget ratio) | C28: =G7 -> 68.718209
B29: Variable operating expense spending | C29: =SUM(G8:G11) -> -52.187753
B30: Fixed expense and depreciation spending | C30: =SUM(G13:G22) -> -165.08333
B31: Actual operating profit | C31: =SUM(C26:C30) -> 4309.5833 | D31: =IF(ABS(C31-E23)<=0.5,"✔ agrees to actual","✖ does not agree") -> ✔ agrees to actual
B33: Flexed budget = static budget re-computed at actual net sales: cost of sales and variable expenses scale with sales (budget cost ratio x actual sales); fixed expenses and depreciation do not flex. Sales activity variance = flexed less static budget; spending variance = flexed budget less actual (cost lines) so positive is favourable.

Sheet Forecast
B1: Rolling Full-Year Reforecast
B2: Sampaguita Foods & Distribution Corporation (SFDC) | PHP in thousands | actual for closed months, run-rate adjusted budget for remaining months
B3: =HYPERLINK("#Cover!A1","◄ Back to Cover") -> ◄ Back to Cover
B4: ="Actuals through "&INDEX(Lists!$B$5:$B$16,Sel_M)&" FY"&Act_Year&"; remaining months = budget x YTD run-rate factor" -> Actuals through Apr FY2025; remaining months = budget x YTD run-rate factor
B5: Line | D5: Jan | E5: Feb | F5: Mar | G5: Apr | H5: May | I5: Jun | J5: Jul | K5: Aug | L5: Sep | M5: Oct | N5: Nov | O5: Dec | P5: Full year | Q5: Full-year budget | R5: Variance F / (U)
B6: Month number | D6: 1 | E6: 2 | F6: 3 | G6: 4 | H6: 5 | I6: 6 | J6: 7 | K6: 8 | L6: 9 | M6: 10 | N6: 11 | O6: 12
B8: Run-rate factors (YTD actual / YTD budget)
B9: Net sales factor | C9: =IFERROR(SUMPRODUCT((Actuals!$D$6:$O$6<=Sel_M)*Actuals!$D12:$O12)/SUMPRODUCT((Budget_FY2025!$D$6:$O$6<=Sel_M)*Budget_FY2025!$D12:$O12),1) -> 0.97933558
B10: Cost of sales ratio factor (YTD COGS% / budget COGS%) | C10: =IFERROR((SUMPRODUCT((Actuals!$D$6:$O$6<=Sel_M)*Actuals!$D18:$O18)/SUMPRODUCT((Actuals!$D$6:$O$6<=Sel_M)*Actuals!$D12:$O12))/(SUMPRODUCT((Budget_FY2025!$D$6:$O$6<=Sel_M)*Budget_FY2025!$D18:$O18)/SUMPRODUCT((Budget_FY2025!$D$6:$O$6<=Sel_M)*Budget_FY2025!$D12:$O12)),1) -> 0.99640608
B11: Operating expense factor (YTD actual / YTD budget) | C11: =IFERROR(SUMPRODUCT((Actuals!$D$6:$O$6<=Sel_M)*Actuals!$D38:$O38)/SUMPRODUCT((Budget_FY2025!$D$6:$O$6<=Sel_M)*Budget_FY2025!$D38:$O38),1) -> 1.0045982
B14: Net sales | D14: =IF(D$6<=Sel_M,Actuals!D12,Budget_FY2025!D12*$C$9) -> 74463 | E14: =IF(E$6<=Sel_M,Actuals!E12,Budget_FY2025!E12*$C$9) -> 71689 | F14: =IF(F$6<=Sel_M,Actuals!F12,Budget_FY2025!F12*$C$9) -> 77757 | G14: =IF(G$6<=Sel_M,Actuals!G12,Budget_FY2025!G12*$C$9) -> 79023 | H14: =IF(H$6<=Sel_M,Actuals!H12,Budget_FY2025!H12*$C$9) -> 81807.819 | I14: =IF(I$6<=Sel_M,Actuals!I12,Budget_FY2025!I12*$C$9) -> 79417.26 | J14: =IF(J$6<=Sel_M,Actuals!J12,Budget_FY2025!J12*$C$9) -> 78818.886 | K14: =IF(K$6<=Sel_M,Actuals!K12,Budget_FY2025!K12*$C$9) -> 78437.925 | ... O14: =IF(O$6<=Sel_M,Actuals!O12,Budget_FY2025!O12*$C$9) -> 85703.616 | P14: =SUM(D14:O14) -> 944999.1 | Q14: =Budget_FY2025!P12 -> 964939 | R14: =P14-Q14 -> -19939.901
B15: Cost of sales | D15: =IF(D$6<=Sel_M,Actuals!D18,D14*IFERROR(Budget_FY2025!D18/Budget_FY2025!D12,0)*$C$10) -> 55344 | E15: =IF(E$6<=Sel_M,Actuals!E18,E14*IFERROR(Budget_FY2025!E18/Budget_FY2025!E12,0)*$C$10) -> 53187 | F15: =IF(F$6<=Sel_M,Actuals!F18,F14*IFERROR(Budget_FY2025!F18/Budget_FY2025!F12,0)*$C$10) -> 57725 | G15: =IF(G$6<=Sel_M,Actuals!G18,G14*IFERROR(Budget_FY2025!G18/Budget_FY2025!G12,0)*$C$10) -> 58854 | H15: =IF(H$6<=Sel_M,Actuals!H18,H14*IFERROR(Budget_FY2025!H18/Budget_FY2025!H12,0)*$C$10) -> 60755.275 | I15: =IF(I$6<=Sel_M,Actuals!I18,I14*IFERROR(Budget_FY2025!I18/Budget_FY2025!I12,0)*$C$10) -> 58987.097 | J15: =IF(J$6<=Sel_M,Actuals!J18,J14*IFERROR(Budget_FY2025!J18/Budget_FY2025!J12,0)*$C$10) -> 58541.149 | K15: =IF(K$6<=Sel_M,Actuals!K18,K14*IFERROR(Budget_FY2025!K18/Budget_FY2025!K12,0)*$C$10) -> 58226.936 | ... O15: =IF(O$6<=Sel_M,Actuals!O18,O14*IFERROR(Budget_FY2025!O18/Budget_FY2025!O12,0)*$C$10) -> 63564.649 | P15: =SUM(D15:O15) -> 701824.38 | Q15: =Budget_FY2025!P18 -> 719218 | R15: =Q15-P15 -> 17393.622
B16: Gross profit | D16: =D14-D15 -> 19119 | E16: =E14-E15 -> 18502 | F16: =F14-F15 -> 20032 | G16: =G14-G15 -> 20169 | H16: =H14-H15 -> 21052.543 | I16: =I14-I15 -> 20430.164 | J16: =J14-J15 -> 20277.737 | K16: =K14-K15 -> 20210.989 | ... O16: =O14-O15 -> 22138.966 | P16: =SUM(D16:O16) -> 243174.72 | Q16: =Budget_FY2025!P19 -> 245721 | R16: =P16-Q16 -> -2546.2797
B17: Total operating expenses | D17: =IF(D$6<=Sel_M,Actuals!D38,Budget_FY2025!D38*$C$11) -> 15512.417 | E17: =IF(E$6<=Sel_M,Actuals!E38,Budget_FY2025!E38*$C$11) -> 15380.417 | F17: =IF(F$6<=Sel_M,Actuals!F38,Budget_FY2025!F38*$C$11) -> 16241.417 | G17: =IF(G$6<=Sel_M,Actuals!G38,Budget_FY2025!G38*$C$11) -> 15859.417 | H17: =IF(H$6<=Sel_M,Actuals!H38,Budget_FY2025!H38*$C$11) -> 15760.472 | I17: =IF(I$6<=Sel_M,Actuals!I38,Budget_FY2025!I38*$C$11) -> 15731.338 | J17: =IF(J$6<=Sel_M,Actuals!J38,Budget_FY2025!J38*$C$11) -> 15656.998 | K17: =IF(K$6<=Sel_M,Actuals!K38,Budget_FY2025!K38*$C$11) -> 15823.762 | ... O17: =IF(O$6<=Sel_M,Actuals!O38,Budget_FY2025!O38*$C$11) -> 16845.438 | P17: =SUM(D17:O17) -> 191042.44 | Q17: =Budget_FY2025!P38 -> 190168 | R17: =Q17-P17 -> -874.43556
B18: Operating profit | D18: =D16-D17 -> 3606.5833 | E18: =E16-E17 -> 3121.5833 | F18: =F16-F17 -> 3790.5833 | G18: =G16-G17 -> 4309.5833 | H18: =H16-H17 -> 5292.0715 | I18: =I16-I17 -> 4698.8251 | J18: =J16-J17 -> 4620.7392 | K18: =K16-K17 -> 4387.2271 | ... O18: =O16-O17 -> 5293.5283 | P18: =SUM(D18:O18) -> 52132.285 | Q18: =Budget_FY2025!P39 -> 55553 | R18: =P18-Q18 -> -3420.7152
B19: Operating margin % | D19: =IFERROR(D18/D14,0) -> 0.048434569 | E19: =IFERROR(E18/E14,0) -> 0.043543407 | F19: =IFERROR(F18/F14,0) -> 0.048749094 | G19: =IFERROR(G18/G14,0) -> 0.05453581 | H19: =IFERROR(H18/H14,0) -> 0.064689067 | I19: =IFERROR(I18/I14,0) -> 0.059166295 | J19: =IFERROR(J18/J14,0) -> 0.058624771 | K19: =IFERROR(K18/K14,0) -> 0.055932473 | ... P19: =IFERROR(P18/P14,0) -> 0.055166492 | Q19: =Budget_FY2025!P40 -> 0.057571515
B22: Method: months up to the selected month use actuals. Later months use the approved budget scaled by the YTD run-rate (sales factor), the YTD cost-of-sales ratio relative to budget, and the YTD operating-expense factor. Choose December on the Dashboard to see the full-year actual outcome.

Sheet Budget_FY2026
B1: Driver-Based Budget FY2026 - Monthly
B2: Sampaguita Foods & Distribution Corporation (SFDC) | PHP in thousands | formulas driven by the Assumptions sheet
B3: =HYPERLINK("#Cover!A1","◄ Back to Cover") -> ◄ Back to Cover
B5: Line | C5: Behaviour | D5: Jan | E5: Feb | F5: Mar | G5: Apr | H5: May | I5: Jun | J5: Jul | K5: Aug | L5: Sep | M5: Oct | N5: Nov | O5: Dec | P5: FY total | Q5: FY2025 actual | R5: Growth %
B6: Month number | D6: 1 | E6: 2 | F6: 3 | G6: 4 | H6: 5 | I6: 6 | J6: 7 | K6: 8 | L6: 9 | M6: 10 | N6: 11 | O6: 12
B7: NET SALES
B8: Packaged Food | D8: =Actuals!D8*(1+Assumptions!$C$12) -> 31256.685 | E8: =Actuals!E8*(1+Assumptions!$C$12) -> 30484.56 | F8: =Actuals!F8*(1+Assumptions!$C$12) -> 31685.88 | G8: =Actuals!G8*(1+Assumptions!$C$12) -> 32550.66 | H8: =Actuals!H8*(1+Assumptions!$C$12) -> 33677.43 | I8: =Actuals!I8*(1+Assumptions!$C$12) -> 32825.43 | J8: =Actuals!J8*(1+Assumptions!$C$12) -> 34595.46 | K8: =Actuals!K8*(1+Assumptions!$C$12) -> 34119.405 | ... O8: =Actuals!O8*(1+Assumptions!$C$12) -> 40063.17 | P8: =SUM(D8:O8) -> 407373.15 | Q8: =Actuals!P8 -> 382510 | R8: =IFERROR(P8/Q8-1,0) -> 0.065
B9: Beverages | D9: =Actuals!D9*(1+Assumptions!$C$13) -> 23774.64 | E9: =Actuals!E9*(1+Assumptions!$C$13) -> 22819.8 | F9: =Actuals!F9*(1+Assumptions!$C$13) -> 26678.58 | G9: =Actuals!G9*(1+Assumptions!$C$13) -> 26995.035 | H9: =Actuals!H9*(1+Assumptions!$C$13) -> 27884.175 | I9: =Actuals!I9*(1+Assumptions!$C$13) -> 26847.21 | J9: =Actuals!J9*(1+Assumptions!$C$13) -> 26234.01 | K9: =Actuals!K9*(1+Assumptions!$C$13) -> 26431.11 | ... O9: =Actuals!O9*(1+Assumptions!$C$13) -> 30552.69 | P9: =SUM(D9:O9) -> 319939.29 | Q9: =Actuals!P9 -> 292182 | R9: =IFERROR(P9/Q9-1,0) -> 0.095
B10: Household & Personal Care | D10: =Actuals!D10*(1+Assumptions!$C$14) -> 14108.6 | E10: =Actuals!E10*(1+Assumptions!$C$14) -> 13119.62 | F10: =Actuals!F10*(1+Assumptions!$C$14) -> 14171.14 | G10: =Actuals!G10*(1+Assumptions!$C$14) -> 14189.16 | H10: =Actuals!H10*(1+Assumptions!$C$14) -> 15214.18 | I10: =Actuals!I10*(1+Assumptions!$C$14) -> 14544.26 | J10: =Actuals!J10*(1+Assumptions!$C$14) -> 15340.32 | K10: =Actuals!K10*(1+Assumptions!$C$14) -> 15149.52 | ... O10: =Actuals!O10*(1+Assumptions!$C$14) -> 17752.88 | P10: =SUM(D10:O10) -> 180794.66 | Q10: =Actuals!P10 -> 170561 | R10: =IFERROR(P10/Q10-1,0) -> 0.06
B11: Fresh & Frozen | D11: =Actuals!D11*(1+Assumptions!$C$15) -> 11252.58 | E11: =Actuals!E11*(1+Assumptions!$C$15) -> 10980.52 | F11: =Actuals!F11*(1+Assumptions!$C$15) -> 11453.28 | G11: =Actuals!G11*(1+Assumptions!$C$15) -> 11618.3 | H11: =Actuals!H11*(1+Assumptions!$C$15) -> 11714.19 | I11: =Actuals!I11*(1+Assumptions!$C$15) -> 11548.055 | J11: =Actuals!J11*(1+Assumptions!$C$15) -> 11989.595 | K11: =Actuals!K11*(1+Assumptions!$C$15) -> 11861.37 | ... O11: =Actuals!O11*(1+Assumptions!$C$15) -> 12971.91 | P11: =SUM(D11:O11) -> 141815.73 | Q11: =Actuals!P11 -> 127189 | R11: =IFERROR(P11/Q11-1,0) -> 0.115
B12: Total net sales | D12: =SUM(D8:D11) -> 80392.505 | E12: =SUM(E8:E11) -> 77404.5 | F12: =SUM(F8:F11) -> 83988.88 | G12: =SUM(G8:G11) -> 85353.155 | H12: =SUM(H8:H11) -> 88489.975 | I12: =SUM(I8:I11) -> 85764.955 | J12: =SUM(J8:J11) -> 88159.385 | K12: =SUM(K8:K11) -> 87561.405 | ... P12: =SUM(P8:P11) -> 1049922.8 | Q12: =Actuals!P12 -> 972442 | R12: =IFERROR(P12/Q12-1,0) -> 0.079676562
B13: COST OF SALES
B14: Packaged Food | D14: =D8*(IFERROR(Actuals!D14/Actuals!D8,0)+Assumptions!$D$12) -> 23378.88 | E14: =E8*(IFERROR(Actuals!E14/Actuals!E8,0)+Assumptions!$D$12) -> 22789.935 | F14: =F8*(IFERROR(Actuals!F14/Actuals!F8,0)+Assumptions!$D$12) -> 23681.34 | G14: =G8*(IFERROR(Actuals!G14/Actuals!G8,0)+Assumptions!$D$12) -> 24500.325 | H14: =H8*(IFERROR(Actuals!H14/Actuals!H8,0)+Assumptions!$D$12) -> 25301.205 | I14: =I8*(IFERROR(Actuals!I14/Actuals!I8,0)+Assumptions!$D$12) -> 24614.28 | J14: =J8*(IFERROR(Actuals!J14/Actuals!J8,0)+Assumptions!$D$12) -> 25896.54 | K14: =K8*(IFERROR(Actuals!K14/Actuals!K8,0)+Assumptions!$D$12) -> 25551.48 | ... O14: =O8*(IFERROR(Actuals!O14/Actuals!O8,0)+Assumptions!$D$12) -> 30137.37 | P14: =SUM(D14:O14) -> 305329.11 | Q14: =Actuals!P14 -> 286694 | R14: =IFERROR(P14/Q14-1,0) -> 0.065
B15: Beverages | D15: =D9*(IFERROR(Actuals!D15/Actuals!D9,0)+Assumptions!$D$13) -> 17362.951 | E15: =E9*(IFERROR(Actuals!E15/Actuals!E9,0)+Assumptions!$D$13) -> 16567.7 | F15: =F9*(IFERROR(Actuals!F15/Actuals!F9,0)+Assumptions!$D$13) -> 19419.028 | G15: =G9*(IFERROR(Actuals!G15/Actuals!G9,0)+Assumptions!$D$13) -> 19670.245 | H15: =H9*(IFERROR(Actuals!H15/Actuals!H9,0)+Assumptions!$D$13) -> 20329.847 | I15: =I9*(IFERROR(Actuals!I15/Actuals!I9,0)+Assumptions!$D$13) -> 19597.176 | J15: =J9*(IFERROR(Actuals!J15/Actuals!J9,0)+Assumptions!$D$13) -> 19085.942 | K15: =K9*(IFERROR(Actuals!K15/Actuals!K9,0)+Assumptions!$D$13) -> 19300.168 | ... O15: =O9*(IFERROR(Actuals!O15/Actuals!O9,0)+Assumptions!$D$13) -> 22281.275 | P15: =SUM(D15:O15) -> 233033.12 | Q15: =Actuals!P15 -> 213400 | R15: =IFERROR(P15/Q15-1,0) -> 0.092001506
B16: Household & Personal Care | D16: =D10*(IFERROR(Actuals!D16/Actuals!D10,0)+Assumptions!$D$14) -> 9862.24 | E16: =E10*(IFERROR(Actuals!E16/Actuals!E10,0)+Assumptions!$D$14) -> 9167.94 | F16: =F10*(IFERROR(Actuals!F16/Actuals!F10,0)+Assumptions!$D$14) -> 9931.14 | G16: =G10*(IFERROR(Actuals!G16/Actuals!G10,0)+Assumptions!$D$14) -> 9940.68 | H16: =H10*(IFERROR(Actuals!H16/Actuals!H10,0)+Assumptions!$D$14) -> 10653 | I16: =I10*(IFERROR(Actuals!I16/Actuals!I10,0)+Assumptions!$D$14) -> 10181.3 | J16: =J10*(IFERROR(Actuals!J16/Actuals!J10,0)+Assumptions!$D$14) -> 10742.04 | K16: =K10*(IFERROR(Actuals!K16/Actuals!K10,0)+Assumptions!$D$14) -> 10579.86 | ... O16: =O10*(IFERROR(Actuals!O16/Actuals!O10,0)+Assumptions!$D$14) -> 12411.54 | P16: =SUM(D16:O16) -> 126542.8 | Q16: =Actuals!P16 -> 119380 | R16: =IFERROR(P16/Q16-1,0) -> 0.06
B17: Fresh & Frozen | D17: =D11*(IFERROR(Actuals!D17/Actuals!D11,0)+Assumptions!$D$15) -> 9095.8623 | E17: =E11*(IFERROR(Actuals!E17/Actuals!E11,0)+Assumptions!$D$15) -> 8850.2634 | F17: =F11*(IFERROR(Actuals!F17/Actuals!F11,0)+Assumptions!$D$15) -> 9261.3952 | G17: =G11*(IFERROR(Actuals!G17/Actuals!G11,0)+Assumptions!$D$15) -> 9395.8151 | H17: =H11*(IFERROR(Actuals!H17/Actuals!H11,0)+Assumptions!$D$15) -> 9443.4724 | I17: =I11*(IFERROR(Actuals!I17/Actuals!I11,0)+Assumptions!$D$15) -> 9324.6658 | J17: =J11*(IFERROR(Actuals!J17/Actuals!J11,0)+Assumptions!$D$15) -> 9665.6462 | K17: =K11*(IFERROR(Actuals!K17/Actuals!K11,0)+Assumptions!$D$15) -> 9537.8059 | ... O17: =O11*(IFERROR(Actuals!O17/Actuals!O11,0)+Assumptions!$D$15) -> 10511.214 | P17: =SUM(D17:O17) -> 114502.06 | Q17: =Actuals!P17 -> 103074 | R17: =IFERROR(P17/Q17-1,0) -> 0.11087241
B18: Total cost of sales | D18: =SUM(D14:D17) -> 59699.933 | E18: =SUM(E14:E17) -> 57375.839 | F18: =SUM(F14:F17) -> 62292.903 | G18: =SUM(G14:G17) -> 63507.065 | H18: =SUM(H14:H17) -> 65727.524 | I18: =SUM(I14:I17) -> 63717.421 | J18: =SUM(J14:J17) -> 65390.168 | K18: =SUM(K14:K17) -> 64969.314 | ... P18: =SUM(P14:P17) -> 779407.09 | Q18: =Actuals!P18 -> 722548 | R18: =IFERROR(P18/Q18-1,0) -> 0.07869248
B19: Gross profit | D19: =D12-D18 -> 20692.572 | E19: =E12-E18 -> 20028.661 | F19: =F12-F18 -> 21695.977 | G19: =G12-G18 -> 21846.09 | H19: =H12-H18 -> 22762.451 | I19: =I12-I18 -> 22047.534 | J19: =J12-J18 -> 22769.217 | K19: =K12-K18 -> 22592.091 | ... P19: =P12-P18 -> 270515.74 | Q19: =Actuals!P19 -> 249894 | R19: =IFERROR(P19/Q19-1,0) -> 0.082521952
B20: Gross margin % | D20: =IFERROR(D19/D12,0) -> 0.25739429 | E20: =IFERROR(E19/E12,0) -> 0.25875319 | F20: =IFERROR(F19/F12,0) -> 0.25831964 | G20: =IFERROR(G19/G12,0) -> 0.25594941 | H20: =IFERROR(H19/H12,0) -> 0.25723197 | I20: =IFERROR(I19/I12,0) -> 0.25706926 | J20: =IFERROR(J19/J12,0) -> 0.25827332 | K20: =IFERROR(K19/K12,0) -> 0.25801426 | ... P20: =IFERROR(P19/P12,0) -> 0.25765297 | Q20: =Actuals!P20 -> 0.25697574
B21: OPERATING EXPENSES
B22: Sales commissions & incentives | C22: Variable | D22: =IF(Assumptions!$C$19="Variable",D$12*IFERROR(Actuals!$P22/Actuals!$P$12,0)*(1+Assumptions!$D$19),Actuals!D22*(1+Assumptions!$D$19)) -> 1297.5173 | E22: =IF(Assumptions!$C$19="Variable",E$12*IFERROR(Actuals!$P22/Actuals!$P$12,0)*(1+Assumptions!$D$19),Actuals!E22*(1+Assumptions!$D$19)) -> 1249.2916 | F22: =IF(Assumptions!$C$19="Variable",F$12*IFERROR(Actuals!$P22/Actuals!$P$12,0)*(1+Assumptions!$D$19),Actuals!F22*(1+Assumptions!$D$19)) -> 1355.5621 | G22: =IF(Assumptions!$C$19="Variable",G$12*IFERROR(Actuals!$P22/Actuals!$P$12,0)*(1+Assumptions!$D$19),Actuals!G22*(1+Assumptions!$D$19)) -> 1377.5811 | H22: =IF(Assumptions!$C$19="Variable",H$12*IFERROR(Actuals!$P22/Actuals!$P$12,0)*(1+Assumptions!$D$19),Actuals!H22*(1+Assumptions!$D$19)) -> 1428.2087 | I22: =IF(Assumptions!$C$19="Variable",I$12*IFERROR(Actuals!$P22/Actuals!$P$12,0)*(1+Assumptions!$D$19),Actuals!I22*(1+Assumptions!$D$19)) -> 1384.2275 | J22: =IF(Assumptions!$C$19="Variable",J$12*IFERROR(Actuals!$P22/Actuals!$P$12,0)*(1+Assumptions!$D$19),Actuals!J22*(1+Assumptions!$D$19)) -> 1422.8731 | K22: =IF(Assumptions!$C$19="Variable",K$12*IFERROR(Actuals!$P22/Actuals!$P$12,0)*(1+Assumptions!$D$19),Actuals!K22*(1+Assumptions!$D$19)) -> 1413.2218 | ... O22: =IF(Assumptions!$C$19="Variable",O$12*IFERROR(Actuals!$P22/Actuals!$P$12,0)*(1+Assumptions!$D$19),Actuals!O22*(1+Assumptions!$D$19)) -> 1635.6158 | P22: =SUM(D22:O22) -> 16945.524 | Q22: =Actuals!P22 -> 15695 | R22: =IFERROR(P22/Q22-1,0) -> 0.079676562
B23: Advertising & promotions | C23: Variable | D23: =IF(Assumptions!$C$20="Variable",D$12*IFERROR(Actuals!$P23/Actuals!$P$12,0)*(1+Assumptions!$D$20),Actuals!D23*(1+Assumptions!$D$20)) -> 812.7485 | E23: =IF(Assumptions!$C$20="Variable",E$12*IFERROR(Actuals!$P23/Actuals!$P$12,0)*(1+Assumptions!$D$20),Actuals!E23*(1+Assumptions!$D$20)) -> 782.5405 | F23: =IF(Assumptions!$C$20="Variable",F$12*IFERROR(Actuals!$P23/Actuals!$P$12,0)*(1+Assumptions!$D$20),Actuals!F23*(1+Assumptions!$D$20)) -> 849.10697 | G23: =IF(Assumptions!$C$20="Variable",G$12*IFERROR(Actuals!$P23/Actuals!$P$12,0)*(1+Assumptions!$D$20),Actuals!G23*(1+Assumptions!$D$20)) -> 862.89945 | H23: =IF(Assumptions!$C$20="Variable",H$12*IFERROR(Actuals!$P23/Actuals!$P$12,0)*(1+Assumptions!$D$20),Actuals!H23*(1+Assumptions!$D$20)) -> 894.61193 | I23: =IF(Assumptions!$C$20="Variable",I$12*IFERROR(Actuals!$P23/Actuals!$P$12,0)*(1+Assumptions!$D$20),Actuals!I23*(1+Assumptions!$D$20)) -> 867.06265 | J23: =IF(Assumptions!$C$20="Variable",J$12*IFERROR(Actuals!$P23/Actuals!$P$12,0)*(1+Assumptions!$D$20),Actuals!J23*(1+Assumptions!$D$20)) -> 891.26975 | K23: =IF(Assumptions!$C$20="Variable",K$12*IFERROR(Actuals!$P23/Actuals!$P$12,0)*(1+Assumptions!$D$20),Actuals!K23*(1+Assumptions!$D$20)) -> 885.22432 | ... O23: =IF(Assumptions!$C$20="Variable",O$12*IFERROR(Actuals!$P23/Actuals!$P$12,0)*(1+Assumptions!$D$20),Actuals!O23*(1+Assumptions!$D$20)) -> 1024.5291 | P23: =SUM(D23:O23) -> 10614.462 | Q23: =Actuals!P23 -> 9363 | R23: =IFERROR(P23/Q23-1,0) -> 0.13366039
B24: Freight & delivery | C24: Variable | D24: =IF(Assumptions!$C$21="Variable",D$12*IFERROR(Actuals!$P24/Actuals!$P$12,0)*(1+Assumptions!$D$21),Actuals!D24*(1+Assumptions!$D$21)) -> 1909.9943 | E24: =IF(Assumptions!$C$21="Variable",E$12*IFERROR(Actuals!$P24/Actuals!$P$12,0)*(1+Assumptions!$D$21),Actuals!E24*(1+Assumptions!$D$21)) -> 1839.0042 | F24: =IF(Assumptions!$C$21="Variable",F$12*IFERROR(Actuals!$P24/Actuals!$P$12,0)*(1+Assumptions!$D$21),Actuals!F24*(1+Assumptions!$D$21)) -> 1995.4383 | G24: =IF(Assumptions!$C$21="Variable",G$12*IFERROR(Actuals!$P24/Actuals!$P$12,0)*(1+Assumptions!$D$21),Actuals!G24*(1+Assumptions!$D$21)) -> 2027.8512 | H24: =IF(Assumptions!$C$21="Variable",H$12*IFERROR(Actuals!$P24/Actuals!$P$12,0)*(1+Assumptions!$D$21),Actuals!H24*(1+Assumptions!$D$21)) -> 2102.3769 | I24: =IF(Assumptions!$C$21="Variable",I$12*IFERROR(Actuals!$P24/Actuals!$P$12,0)*(1+Assumptions!$D$21),Actuals!I24*(1+Assumptions!$D$21)) -> 2037.6349 | J24: =IF(Assumptions!$C$21="Variable",J$12*IFERROR(Actuals!$P24/Actuals!$P$12,0)*(1+Assumptions!$D$21),Actuals!J24*(1+Assumptions!$D$21)) -> 2094.5227 | K24: =IF(Assumptions!$C$21="Variable",K$12*IFERROR(Actuals!$P24/Actuals!$P$12,0)*(1+Assumptions!$D$21),Actuals!K24*(1+Assumptions!$D$21)) -> 2080.3156 | ... O24: =IF(Assumptions!$C$21="Variable",O$12*IFERROR(Actuals!$P24/Actuals!$P$12,0)*(1+Assumptions!$D$21),Actuals!O24*(1+Assumptions!$D$21)) -> 2407.6879 | P24: =SUM(D24:O24) -> 24944.448 | Q24: =Actuals!P24 -> 23337 | R24: =IFERROR(P24/Q24-1,0) -> 0.068879796
B25: Warehouse rent & utilities | C25: Fixed | D25: =IF(Assumptions!$C$22="Variable",D$12*IFERROR(Actuals!$P25/Actuals!$P$12,0)*(1+Assumptions!$D$22),Actuals!D25*(1+Assumptions!$D$22)) -> 2233.42 | E25: =IF(Assumptions!$C$22="Variable",E$12*IFERROR(Actuals!$P25/Actuals!$P$12,0)*(1+Assumptions!$D$22),Actuals!E25*(1+Assumptions!$D$22)) -> 2248.26 | F25: =IF(Assumptions!$C$22="Variable",F$12*IFERROR(Actuals!$P25/Actuals!$P$12,0)*(1+Assumptions!$D$22),Actuals!F25*(1+Assumptions!$D$22)) -> 2221.76 | G25: =IF(Assumptions!$C$22="Variable",G$12*IFERROR(Actuals!$P25/Actuals!$P$12,0)*(1+Assumptions!$D$22),Actuals!G25*(1+Assumptions!$D$22)) -> 2230.24 | H25: =IF(Assumptions!$C$22="Variable",H$12*IFERROR(Actuals!$P25/Actuals!$P$12,0)*(1+Assumptions!$D$22),Actuals!H25*(1+Assumptions!$D$22)) -> 2181.48 | I25: =IF(Assumptions!$C$22="Variable",I$12*IFERROR(Actuals!$P25/Actuals!$P$12,0)*(1+Assumptions!$D$22),Actuals!I25*(1+Assumptions!$D$22)) -> 2187.84 | J25: =IF(Assumptions!$C$22="Variable",J$12*IFERROR(Actuals!$P25/Actuals!$P$12,0)*(1+Assumptions!$D$22),Actuals!J25*(1+Assumptions!$D$22)) -> 2184.66 | K25: =IF(Assumptions!$C$22="Variable",K$12*IFERROR(Actuals!$P25/Actuals!$P$12,0)*(1+Assumptions!$D$22),Actuals!K25*(1+Assumptions!$D$22)) -> 2188.9 | ... O25: =IF(Assumptions!$C$22="Variable",O$12*IFERROR(Actuals!$P25/Actuals!$P$12,0)*(1+Assumptions!$D$22),Actuals!O25*(1+Assumptions!$D$22)) -> 2173 | P25: =SUM(D25:O25) -> 26491.52 | Q25: =Actuals!P25 -> 24992 | R25: =IFERROR(P25/Q25-1,0) -> 0.06
B26: Selling & logistics staff costs | C26: Fixed | D26: =IF(Assumptions!$C$23="Variable",D$12*IFERROR(Actuals!$P26/Actuals!$P$12,0)*(1+Assumptions!$D$23),Actuals!D26*(1+Assumptions!$D$23)) -> 2839.005 | E26: =IF(Assumptions!$C$23="Variable",E$12*IFERROR(Actuals!$P26/Actuals!$P$12,0)*(1+Assumptions!$D$23),Actuals!E26*(1+Assumptions!$D$23)) -> 2853.775 | F26: =IF(Assumptions!$C$23="Variable",F$12*IFERROR(Actuals!$P26/Actuals!$P$12,0)*(1+Assumptions!$D$23),Actuals!F26*(1+Assumptions!$D$23)) -> 2909.69 | G26: =IF(Assumptions!$C$23="Variable",G$12*IFERROR(Actuals!$P26/Actuals!$P$12,0)*(1+Assumptions!$D$23),Actuals!G26*(1+Assumptions!$D$23)) -> 2880.15 | H26: =IF(Assumptions!$C$23="Variable",H$12*IFERROR(Actuals!$P26/Actuals!$P$12,0)*(1+Assumptions!$D$23),Actuals!H26*(1+Assumptions!$D$23)) -> 2853.775 | I26: =IF(Assumptions!$C$23="Variable",I$12*IFERROR(Actuals!$P26/Actuals!$P$12,0)*(1+Assumptions!$D$23),Actuals!I26*(1+Assumptions!$D$23)) -> 2865.38 | J26: =IF(Assumptions!$C$23="Variable",J$12*IFERROR(Actuals!$P26/Actuals!$P$12,0)*(1+Assumptions!$D$23),Actuals!J26*(1+Assumptions!$D$23)) -> 2866.435 | K26: =IF(Assumptions!$C$23="Variable",K$12*IFERROR(Actuals!$P26/Actuals!$P$12,0)*(1+Assumptions!$D$23),Actuals!K26*(1+Assumptions!$D$23)) -> 2876.985 | ... O26: =IF(Assumptions!$C$23="Variable",O$12*IFERROR(Actuals!$P26/Actuals!$P$12,0)*(1+Assumptions!$D$23),Actuals!O26*(1+Assumptions!$D$23)) -> 2832.675 | P26: =SUM(D26:O26) -> 34487.95 | Q26: =Actuals!P26 -> 32690 | R26: =IFERROR(P26/Q26-1,0) -> 0.055
B27: Selling & distribution | D27: =SUM(D22:D26) -> 9092.6852 | E27: =SUM(E22:E26) -> 8972.8713 | F27: =SUM(F22:F26) -> 9331.5573 | G27: =SUM(G22:G26) -> 9378.7218 | H27: =SUM(H22:H26) -> 9460.4526 | I27: =SUM(I22:I26) -> 9342.1451 | J27: =SUM(J22:J26) -> 9459.7605 | K27: =SUM(K22:K26) -> 9444.6468 | ... P27: =SUM(P22:P26) -> 113483.9 | Q27: =Actuals!P27 -> 106077 | R27: =IFERROR(P27/Q27-1,0) -> 0.069825727
B28: Salaries & wages (G&A) | C28: Fixed | D28: =IF(Assumptions!$C$24="Variable",D$12*IFERROR(Actuals!$P28/Actuals!$P$12,0)*(1+Assumptions!$D$24),Actuals!D28*(1+Assumptions!$D$24)) -> 2625 | E28: =IF(Assumptions!$C$24="Variable",E$12*IFERROR(Actuals!$P28/Actuals!$P$12,0)*(1+Assumptions!$D$24),Actuals!E28*(1+Assumptions!$D$24)) -> 2657.55 | F28: =IF(Assumptions!$C$24="Variable",F$12*IFERROR(Actuals!$P28/Actuals!$P$12,0)*(1+Assumptions!$D$24),Actuals!F28*(1+Assumptions!$D$24)) -> 2597.7 | G28: =IF(Assumptions!$C$24="Variable",G$12*IFERROR(Actuals!$P28/Actuals!$P$12,0)*(1+Assumptions!$D$24),Actuals!G28*(1+Assumptions!$D$24)) -> 2690.1 | H28: =IF(Assumptions!$C$24="Variable",H$12*IFERROR(Actuals!$P28/Actuals!$P$12,0)*(1+Assumptions!$D$24),Actuals!H28*(1+Assumptions!$D$24)) -> 2695.35 | I28: =IF(Assumptions!$C$24="Variable",I$12*IFERROR(Actuals!$P28/Actuals!$P$12,0)*(1+Assumptions!$D$24),Actuals!I28*(1+Assumptions!$D$24)) -> 2637.6 | J28: =IF(Assumptions!$C$24="Variable",J$12*IFERROR(Actuals!$P28/Actuals!$P$12,0)*(1+Assumptions!$D$24),Actuals!J28*(1+Assumptions!$D$24)) -> 2667 | K28: =IF(Assumptions!$C$24="Variable",K$12*IFERROR(Actuals!$P28/Actuals!$P$12,0)*(1+Assumptions!$D$24),Actuals!K28*(1+Assumptions!$D$24)) -> 2680.65 | ... O28: =IF(Assumptions!$C$24="Variable",O$12*IFERROR(Actuals!$P28/Actuals!$P$12,0)*(1+Assumptions!$D$24),Actuals!O28*(1+Assumptions!$D$24)) -> 2596.65 | P28: =SUM(D28:O28) -> 31723.65 | Q28: =Actuals!P28 -> 30213 | R28: =IFERROR(P28/Q28-1,0) -> 0.05
B29: Employee benefits & contributions | C29: Fixed | D29: =IF(Assumptions!$C$25="Variable",D$12*IFERROR(Actuals!$P29/Actuals!$P$12,0)*(1+Assumptions!$D$25),Actuals!D29*(1+Assumptions!$D$25)) -> 706.65 | E29: =IF(Assumptions!$C$25="Variable",E$12*IFERROR(Actuals!$P29/Actuals!$P$12,0)*(1+Assumptions!$D$25),Actuals!E29*(1+Assumptions!$D$25)) -> 707.7 | F29: =IF(Assumptions!$C$25="Variable",F$12*IFERROR(Actuals!$P29/Actuals!$P$12,0)*(1+Assumptions!$D$25),Actuals!F29*(1+Assumptions!$D$25)) -> 717.15 | G29: =IF(Assumptions!$C$25="Variable",G$12*IFERROR(Actuals!$P29/Actuals!$P$12,0)*(1+Assumptions!$D$25),Actuals!G29*(1+Assumptions!$D$25)) -> 700.35 | H29: =IF(Assumptions!$C$25="Variable",H$12*IFERROR(Actuals!$P29/Actuals!$P$12,0)*(1+Assumptions!$D$25),Actuals!H29*(1+Assumptions!$D$25)) -> 711.9 | I29: =IF(Assumptions!$C$25="Variable",I$12*IFERROR(Actuals!$P29/Actuals!$P$12,0)*(1+Assumptions!$D$25),Actuals!I29*(1+Assumptions!$D$25)) -> 710.85 | J29: =IF(Assumptions!$C$25="Variable",J$12*IFERROR(Actuals!$P29/Actuals!$P$12,0)*(1+Assumptions!$D$25),Actuals!J29*(1+Assumptions!$D$25)) -> 719.25 | K29: =IF(Assumptions!$C$25="Variable",K$12*IFERROR(Actuals!$P29/Actuals!$P$12,0)*(1+Assumptions!$D$25),Actuals!K29*(1+Assumptions!$D$25)) -> 699.3 | ... O29: =IF(Assumptions!$C$25="Variable",O$12*IFERROR(Actuals!$P29/Actuals!$P$12,0)*(1+Assumptions!$D$25),Actuals!O29*(1+Assumptions!$D$25)) -> 699.3 | P29: =SUM(D29:O29) -> 8536.5 | Q29: =Actuals!P29 -> 8130 | R29: =IFERROR(P29/Q29-1,0) -> 0.05
B30: Professional fees | C30: Fixed | D30: =IF(Assumptions!$C$26="Variable",D$12*IFERROR(Actuals!$P30/Actuals!$P$12,0)*(1+Assumptions!$D$26),Actuals!D30*(1+Assumptions!$D$26)) -> 348.4 | E30: =IF(Assumptions!$C$26="Variable",E$12*IFERROR(Actuals!$P30/Actuals!$P$12,0)*(1+Assumptions!$D$26),Actuals!E30*(1+Assumptions!$D$26)) -> 338 | F30: =IF(Assumptions!$C$26="Variable",F$12*IFERROR(Actuals!$P30/Actuals!$P$12,0)*(1+Assumptions!$D$26),Actuals!F30*(1+Assumptions!$D$26)) -> 901.68 | G30: =IF(Assumptions!$C$26="Variable",G$12*IFERROR(Actuals!$P30/Actuals!$P$12,0)*(1+Assumptions!$D$26),Actuals!G30*(1+Assumptions!$D$26)) -> 343.2 | H30: =IF(Assumptions!$C$26="Variable",H$12*IFERROR(Actuals!$P30/Actuals!$P$12,0)*(1+Assumptions!$D$26),Actuals!H30*(1+Assumptions!$D$26)) -> 344.24 | I30: =IF(Assumptions!$C$26="Variable",I$12*IFERROR(Actuals!$P30/Actuals!$P$12,0)*(1+Assumptions!$D$26),Actuals!I30*(1+Assumptions!$D$26)) -> 341.12 | J30: =IF(Assumptions!$C$26="Variable",J$12*IFERROR(Actuals!$P30/Actuals!$P$12,0)*(1+Assumptions!$D$26),Actuals!J30*(1+Assumptions!$D$26)) -> 346.32 | K30: =IF(Assumptions!$C$26="Variable",K$12*IFERROR(Actuals!$P30/Actuals!$P$12,0)*(1+Assumptions!$D$26),Actuals!K30*(1+Assumptions!$D$26)) -> 339.04 | ... O30: =IF(Assumptions!$C$26="Variable",O$12*IFERROR(Actuals!$P30/Actuals!$P$12,0)*(1+Assumptions!$D$26),Actuals!O30*(1+Assumptions!$D$26)) -> 347.36 | P30: =SUM(D30:O30) -> 4680 | Q30: =Actuals!P30 -> 4500 | R30: =IFERROR(P30/Q30-1,0) -> 0.04
B31: Office rent & utilities | C31: Fixed | D31: =IF(Assumptions!$C$27="Variable",D$12*IFERROR(Actuals!$P31/Actuals!$P$12,0)*(1+Assumptions!$D$27),Actuals!D31*(1+Assumptions!$D$27)) -> 596.96 | E31: =IF(Assumptions!$C$27="Variable",E$12*IFERROR(Actuals!$P31/Actuals!$P$12,0)*(1+Assumptions!$D$27),Actuals!E31*(1+Assumptions!$D$27)) -> 603.2 | F31: =IF(Assumptions!$C$27="Variable",F$12*IFERROR(Actuals!$P31/Actuals!$P$12,0)*(1+Assumptions!$D$27),Actuals!F31*(1+Assumptions!$D$27)) -> 585.52 | G31: =IF(Assumptions!$C$27="Variable",G$12*IFERROR(Actuals!$P31/Actuals!$P$12,0)*(1+Assumptions!$D$27),Actuals!G31*(1+Assumptions!$D$27)) -> 591.76 | H31: =IF(Assumptions!$C$27="Variable",H$12*IFERROR(Actuals!$P31/Actuals!$P$12,0)*(1+Assumptions!$D$27),Actuals!H31*(1+Assumptions!$D$27)) -> 583.44 | I31: =IF(Assumptions!$C$27="Variable",I$12*IFERROR(Actuals!$P31/Actuals!$P$12,0)*(1+Assumptions!$D$27),Actuals!I31*(1+Assumptions!$D$27)) -> 590.72 | J31: =IF(Assumptions!$C$27="Variable",J$12*IFERROR(Actuals!$P31/Actuals!$P$12,0)*(1+Assumptions!$D$27),Actuals!J31*(1+Assumptions!$D$27)) -> 600.08 | K31: =IF(Assumptions!$C$27="Variable",K$12*IFERROR(Actuals!$P31/Actuals!$P$12,0)*(1+Assumptions!$D$27),Actuals!K31*(1+Assumptions!$D$27)) -> 603.2 | ... O31: =IF(Assumptions!$C$27="Variable",O$12*IFERROR(Actuals!$P31/Actuals!$P$12,0)*(1+Assumptions!$D$27),Actuals!O31*(1+Assumptions!$D$27)) -> 590.72 | P31: =SUM(D31:O31) -> 7112.56 | Q31: =Actuals!P31 -> 6839 | R31: =IFERROR(P31/Q31-1,0) -> 0.04
B32: Repairs & maintenance | C32: Fixed | D32: =IF(Assumptions!$C$28="Variable",D$12*IFERROR(Actuals!$P32/Actuals!$P$12,0)*(1+Assumptions!$D$28),Actuals!D32*(1+Assumptions!$D$28)) -> 264.71 | E32: =IF(Assumptions!$C$28="Variable",E$12*IFERROR(Actuals!$P32/Actuals!$P$12,0)*(1+Assumptions!$D$28),Actuals!E32*(1+Assumptions!$D$28)) -> 250.29 | F32: =IF(Assumptions!$C$28="Variable",F$12*IFERROR(Actuals!$P32/Actuals!$P$12,0)*(1+Assumptions!$D$28),Actuals!F32*(1+Assumptions!$D$28)) -> 244.11 | G32: =IF(Assumptions!$C$28="Variable",G$12*IFERROR(Actuals!$P32/Actuals!$P$12,0)*(1+Assumptions!$D$28),Actuals!G32*(1+Assumptions!$D$28)) -> 238.96 | H32: =IF(Assumptions!$C$28="Variable",H$12*IFERROR(Actuals!$P32/Actuals!$P$12,0)*(1+Assumptions!$D$28),Actuals!H32*(1+Assumptions!$D$28)) -> 241.02 | I32: =IF(Assumptions!$C$28="Variable",I$12*IFERROR(Actuals!$P32/Actuals!$P$12,0)*(1+Assumptions!$D$28),Actuals!I32*(1+Assumptions!$D$28)) -> 225.57 | J32: =IF(Assumptions!$C$28="Variable",J$12*IFERROR(Actuals!$P32/Actuals!$P$12,0)*(1+Assumptions!$D$28),Actuals!J32*(1+Assumptions!$D$28)) -> 212.18 | K32: =IF(Assumptions!$C$28="Variable",K$12*IFERROR(Actuals!$P32/Actuals!$P$12,0)*(1+Assumptions!$D$28),Actuals!K32*(1+Assumptions!$D$28)) -> 228.66 | ... O32: =IF(Assumptions!$C$28="Variable",O$12*IFERROR(Actuals!$P32/Actuals!$P$12,0)*(1+Assumptions!$D$28),Actuals!O32*(1+Assumptions!$D$28)) -> 246.17 | P32: =SUM(D32:O32) -> 2810.87 | Q32: =Actuals!P32 -> 2729 | R32: =IFERROR(P32/Q32-1,0) -> 0.03
B33: Taxes, licenses & insurance | C33: Fixed | D33: =IF(Assumptions!$C$29="Variable",D$12*IFERROR(Actuals!$P33/Actuals!$P$12,0)*(1+Assumptions!$D$29),Actuals!D33*(1+Assumptions!$D$29)) -> 469.68 | E33: =IF(Assumptions!$C$29="Variable",E$12*IFERROR(Actuals!$P33/Actuals!$P$12,0)*(1+Assumptions!$D$29),Actuals!E33*(1+Assumptions!$D$29)) -> 474.83 | F33: =IF(Assumptions!$C$29="Variable",F$12*IFERROR(Actuals!$P33/Actuals!$P$12,0)*(1+Assumptions!$D$29),Actuals!F33*(1+Assumptions!$D$29)) -> 473.8 | G33: =IF(Assumptions!$C$29="Variable",G$12*IFERROR(Actuals!$P33/Actuals!$P$12,0)*(1+Assumptions!$D$29),Actuals!G33*(1+Assumptions!$D$29)) -> 466.59 | H33: =IF(Assumptions!$C$29="Variable",H$12*IFERROR(Actuals!$P33/Actuals!$P$12,0)*(1+Assumptions!$D$29),Actuals!H33*(1+Assumptions!$D$29)) -> 470.71 | I33: =IF(Assumptions!$C$29="Variable",I$12*IFERROR(Actuals!$P33/Actuals!$P$12,0)*(1+Assumptions!$D$29),Actuals!I33*(1+Assumptions!$D$29)) -> 470.71 | J33: =IF(Assumptions!$C$29="Variable",J$12*IFERROR(Actuals!$P33/Actuals!$P$12,0)*(1+Assumptions!$D$29),Actuals!J33*(1+Assumptions!$D$29)) -> 467.62 | K33: =IF(Assumptions!$C$29="Variable",K$12*IFERROR(Actuals!$P33/Actuals!$P$12,0)*(1+Assumptions!$D$29),Actuals!K33*(1+Assumptions!$D$29)) -> 465.56 | ... O33: =IF(Assumptions!$C$29="Variable",O$12*IFERROR(Actuals!$P33/Actuals!$P$12,0)*(1+Assumptions!$D$29),Actuals!O33*(1+Assumptions!$D$29)) -> 475.86 | P33: =SUM(D33:O33) -> 5648.52 | Q33: =Actuals!P33 -> 5484 | R33: =IFERROR(P33/Q33-1,0) -> 0.03
B34: Communication, IT & supplies | C34: Fixed | D34: =IF(Assumptions!$C$30="Variable",D$12*IFERROR(Actuals!$P34/Actuals!$P$12,0)*(1+Assumptions!$D$30),Actuals!D34*(1+Assumptions!$D$30)) -> 385.84 | E34: =IF(Assumptions!$C$30="Variable",E$12*IFERROR(Actuals!$P34/Actuals!$P$12,0)*(1+Assumptions!$D$30),Actuals!E34*(1+Assumptions!$D$30)) -> 388.96 | F34: =IF(Assumptions!$C$30="Variable",F$12*IFERROR(Actuals!$P34/Actuals!$P$12,0)*(1+Assumptions!$D$30),Actuals!F34*(1+Assumptions!$D$30)) -> 392.08 | G34: =IF(Assumptions!$C$30="Variable",G$12*IFERROR(Actuals!$P34/Actuals!$P$12,0)*(1+Assumptions!$D$30),Actuals!G34*(1+Assumptions!$D$30)) -> 393.12 | H34: =IF(Assumptions!$C$30="Variable",H$12*IFERROR(Actuals!$P34/Actuals!$P$12,0)*(1+Assumptions!$D$30),Actuals!H34*(1+Assumptions!$D$30)) -> 385.84 | I34: =IF(Assumptions!$C$30="Variable",I$12*IFERROR(Actuals!$P34/Actuals!$P$12,0)*(1+Assumptions!$D$30),Actuals!I34*(1+Assumptions!$D$30)) -> 382.72 | J34: =IF(Assumptions!$C$30="Variable",J$12*IFERROR(Actuals!$P34/Actuals!$P$12,0)*(1+Assumptions!$D$30),Actuals!J34*(1+Assumptions!$D$30)) -> 383.76 | K34: =IF(Assumptions!$C$30="Variable",K$12*IFERROR(Actuals!$P34/Actuals!$P$12,0)*(1+Assumptions!$D$30),Actuals!K34*(1+Assumptions!$D$30)) -> 380.64 | ... O34: =IF(Assumptions!$C$30="Variable",O$12*IFERROR(Actuals!$P34/Actuals!$P$12,0)*(1+Assumptions!$D$30),Actuals!O34*(1+Assumptions!$D$30)) -> 386.88 | P34: =SUM(D34:O34) -> 4641.52 | Q34: =Actuals!P34 -> 4463 | R34: =IFERROR(P34/Q34-1,0) -> 0.04
B35: Bad debts & credit losses | C35: Variable | D35: =IF(Assumptions!$C$31="Variable",D$12*IFERROR(Actuals!$P35/Actuals!$P$12,0)*(1+Assumptions!$D$31),Actuals!D35*(1+Assumptions!$D$31)) -> 115.37116 | E35: =IF(Assumptions!$C$31="Variable",E$12*IFERROR(Actuals!$P35/Actuals!$P$12,0)*(1+Assumptions!$D$31),Actuals!E35*(1+Assumptions!$D$31)) -> 111.08308 | F35: =IF(Assumptions!$C$31="Variable",F$12*IFERROR(Actuals!$P35/Actuals!$P$12,0)*(1+Assumptions!$D$31),Actuals!F35*(1+Assumptions!$D$31)) -> 120.53231 | G35: =IF(Assumptions!$C$31="Variable",G$12*IFERROR(Actuals!$P35/Actuals!$P$12,0)*(1+Assumptions!$D$31),Actuals!G35*(1+Assumptions!$D$31)) -> 122.49018 | H35: =IF(Assumptions!$C$31="Variable",H$12*IFERROR(Actuals!$P35/Actuals!$P$12,0)*(1+Assumptions!$D$31),Actuals!H35*(1+Assumptions!$D$31)) -> 126.99183 | I35: =IF(Assumptions!$C$31="Variable",I$12*IFERROR(Actuals!$P35/Actuals!$P$12,0)*(1+Assumptions!$D$31),Actuals!I35*(1+Assumptions!$D$31)) -> 123.08115 | J35: =IF(Assumptions!$C$31="Variable",J$12*IFERROR(Actuals!$P35/Actuals!$P$12,0)*(1+Assumptions!$D$31),Actuals!J35*(1+Assumptions!$D$31)) -> 126.5174 | K35: =IF(Assumptions!$C$31="Variable",K$12*IFERROR(Actuals!$P35/Actuals!$P$12,0)*(1+Assumptions!$D$31),Actuals!K35*(1+Assumptions!$D$31)) -> 125.65924 | ... O35: =IF(Assumptions!$C$31="Variable",O$12*IFERROR(Actuals!$P35/Actuals!$P$12,0)*(1+Assumptions!$D$31),Actuals!O35*(1+Assumptions!$D$31)) -> 145.43381 | P35: =SUM(D35:O35) -> 1506.7426 | Q35: =Actuals!P35 -> 1469 | R35: =IFERROR(P35/Q35-1,0) -> 0.025692734
B36: General & administrative | D36: =SUM(D28:D35) -> 5512.6112 | E36: =SUM(E28:E35) -> 5531.6131 | F36: =SUM(F28:F35) -> 6032.5723 | G36: =SUM(G28:G35) -> 5546.5702 | H36: =SUM(H28:H35) -> 5559.4918 | I36: =SUM(I28:I35) -> 5482.3712 | J36: =SUM(J28:J35) -> 5522.7274 | K36: =SUM(K28:K35) -> 5522.7092 | ... P36: =SUM(P28:P35) -> 66660.363 | Q36: =Actuals!P36 -> 63827 | R36: =IFERROR(P36/Q36-1,0) -> 0.044391286
B37: Depreciation | D37: =Actuals!D37*(1+Dep_Gr26) -> 1913.13 | E37: =Actuals!E37*(1+Dep_Gr26) -> 1913.13 | F37: =Actuals!F37*(1+Dep_Gr26) -> 1913.13 | G37: =Actuals!G37*(1+Dep_Gr26) -> 1913.13 | H37: =Actuals!H37*(1+Dep_Gr26) -> 1913.13 | I37: =Actuals!I37*(1+Dep_Gr26) -> 1913.13 | J37: =Actuals!J37*(1+Dep_Gr26) -> 1913.13 | K37: =Actuals!K37*(1+Dep_Gr26) -> 1913.13 | ... O37: =Actuals!O37*(1+Dep_Gr26) -> 1913.13 | P37: =SUM(D37:O37) -> 22957.56 | Q37: =Actuals!P37 -> 21257 | R37: =IFERROR(P37/Q37-1,0) -> 0.08
B38: Total operating expenses | D38: =D27+D36+D37 -> 16518.426 | E38: =E27+E36+E37 -> 16417.614 | F38: =F27+F36+F37 -> 17277.26 | G38: =G27+G36+G37 -> 16838.422 | H38: =H27+H36+H37 -> 16933.074 | I38: =I27+I36+I37 -> 16737.646 | J38: =J27+J36+J37 -> 16895.618 | K38: =K27+K36+K37 -> 16880.486 | ... P38: =P27+P36+P37 -> 203101.83 | Q38: =Actuals!P38 -> 191161 | R38: =IFERROR(P38/Q38-1,0) -> 0.062464762
B39: Operating profit | D39: =D19-D38 -> 4174.1457 | E39: =E19-E38 -> 3611.0468 | F39: =F19-F38 -> 4418.7174 | G39: =G19-G38 -> 5007.668 | H39: =H19-H38 -> 5829.3765 | I39: =I19-I38 -> 5309.8873 | J39: =J19-J38 -> 5873.5989 | K39: =K19-K38 -> 5711.6053 | ... P39: =P19-P38 -> 67413.914 | Q39: =Actuals!P39 -> 58733 | R39: =IFERROR(P39/Q39-1,0) -> 0.14780302
B40: Operating margin % | D40: =IFERROR(D39/D12,0) -> 0.051922075 | E40: =IFERROR(E39/E12,0) -> 0.046651639 | F40: =IFERROR(F39/F12,0) -> 0.052610743 | G40: =IFERROR(G39/G12,0) -> 0.058669981 | H40: =IFERROR(H39/H12,0) -> 0.065876123 | I40: =IFERROR(I39/I12,0) -> 0.061912087 | J40: =IFERROR(J39/J12,0) -> 0.066624772 | K40: =IFERROR(K39/K12,0) -> 0.065229713 | ... P40: =IFERROR(P39/P12,0) -> 0.064208447 | Q40: =Actuals!P40 -> 0.060397432
B42: Reference: Project 1 statistical trend forecast FY2026
B43: Net sales - trend forecast (Project 1) | P43: =Trend_Sales26 -> 1048257
B44: Net sales - this budget | P44: =P12 -> 1049922.8
B45: Budget above / (below) trend | P45: =P44-P43 -> 1665.835 | Q45: =IFERROR(P44/P43-1,0) -> 0.0015891475
B46: Operating profit - trend forecast (Project 1) | P46: =Trend_OP26 -> 68931
B47: Operating profit - this budget | P47: =P39 -> 67413.914
B48: Budget above / (below) trend | P48: =P47-P46 -> -1517.0855 | Q48: =IFERROR(P47/P46-1,0) -> -0.022008755

Sheet Assumptions
B1: Assumptions and Budget Drivers
B2: Sampaguita Foods & Distribution Corporation (SFDC) | Blue = input, yellow fill = key assumption
B3: =HYPERLINK("#Cover!A1","◄ Back to Cover") -> ◄ Back to Cover
B5: 1. GENERAL PARAMETERS
B6: Actual year analysed (budget vs actual) | C6: 2025 | E6: Ledger year used for actuals. Budget_FY2025 holds the budget approved for this year.
B7: Variance review threshold (% of budget) | C7: 0.05 | E7: A line is flagged when BOTH the % and the peso threshold are exceeded.
B8: Variance review threshold (PHP '000) | C8: 100
B10: 2. FY2026 BUDGET DRIVERS - REVENUE AND COST OF SALES
B11: Product category | C11: Sales growth vs FY2025 | D11: COGS % change (pts) | E11: Basis
B12: Packaged Food | C12: 0.065 | D12: 0 | E12: Below FY2025 growth of 6.8%: category maturing, price competition expected
B13: Beverages | C13: 0.095 | D13: -0.002 | E13: In line with FY2025 growth of 10.4%; new Visayas distribution contract
B14: Household & Personal Care | C14: 0.06 | D14: 0 | E14: Close to FY2025 growth of 6.2%
B15: Fresh & Frozen | C15: 0.115 | D15: -0.003 | E15: Cold-chain capacity added in FY2025 supports growth; procurement savings of 0.3 pt
B17: 3. FY2026 BUDGET DRIVERS - OPERATING EXPENSES
B18: Expense line | C18: Behaviour | D18: Driver | E18: How the driver is applied
B19: Sales commissions & incentives | C19: Variable | D19: 0 | E19: Variable: % change in cost-to-sales ratio vs FY2025 (cost moves with budgeted sales)
B20: Advertising & promotions | C20: Variable | D20: 0.05 | E20: Variable: % change in cost-to-sales ratio vs FY2025 (cost moves with budgeted sales)
B21: Freight & delivery | C21: Variable | D21: -0.01 | E21: Variable: % change in cost-to-sales ratio vs FY2025 (cost moves with budgeted sales)
B22: Warehouse rent & utilities | C22: Fixed | D22: 0.06 | E22: Fixed: % increase on FY2025 actual (inflation / headcount)
B23: Selling & logistics staff costs | C23: Fixed | D23: 0.055 | E23: Fixed: % increase on FY2025 actual (inflation / headcount)
B24: Salaries & wages (G&A) | C24: Fixed | D24: 0.05 | E24: Fixed: % increase on FY2025 actual (inflation / headcount)
B25: Employee benefits & contributions | C25: Fixed | D25: 0.05 | E25: Fixed: % increase on FY2025 actual (inflation / headcount)
B26: Professional fees | C26: Fixed | D26: 0.04 | E26: Fixed: % increase on FY2025 actual (inflation / headcount)
B27: Office rent & utilities | C27: Fixed | D27: 0.04 | E27: Fixed: % increase on FY2025 actual (inflation / headcount)
B28: Repairs & maintenance | C28: Fixed | D28: 0.03 | E28: Fixed: % increase on FY2025 actual (inflation / headcount)
B29: Taxes, licenses & insurance | C29: Fixed | D29: 0.03 | E29: Fixed: % increase on FY2025 actual (inflation / headcount)
B30: Communication, IT & supplies | C30: Fixed | D30: 0.04 | E30: Fixed: % increase on FY2025 actual (inflation / headcount)
B31: Bad debts & credit losses | C31: Variable | D31: -0.05 | E31: Variable: % change in cost-to-sales ratio vs FY2025 (cost moves with budgeted sales)
B33: 4. FY2026 BUDGET DRIVERS - DEPRECIATION
B34: Depreciation growth vs FY2025 | D34: 0.08 | E34: FY2025 capex of PHP 26.9 million is depreciated for a full year in FY2026 (half-year convention in FY2025).
B36: Behaviour (Fixed / Variable) follows the Project 1 chart-of-accounts mapping (Inputs sheet, section 4). Drivers are management assumptions, not forecasts - change the yellow cells to run a different budget.

Sheet Budget_FY2025
B1: Approved Budget FY2025 - Monthly
B2: Sampaguita Foods & Distribution Corporation (SFDC) | PHP in thousands | blue = approved budget input
B3: =HYPERLINK("#Cover!A1","◄ Back to Cover") -> ◄ Back to Cover
B5: Line | C5: Behaviour | D5: Jan | E5: Feb | F5: Mar | G5: Apr | H5: May | I5: Jun | J5: Jul | K5: Aug | L5: Sep | M5: Oct | N5: Nov | O5: Dec | P5: FY total
B6: Month number | D6: 1 | E6: 2 | F6: 3 | G6: 4 | H6: 5 | I6: 6 | J6: 7 | K6: 8 | L6: 9 | M6: 10 | N6: 11 | O6: 12
B7: NET SALES
B8: Packaged Food | D8: 28724 | E8: 27714 | F8: 31971 | G8: 32709 | H8: 32381 | I8: 31302 | J8: 31786 | K8: 31468 | L8: 32550 | M8: 31374 | N8: 32730 | O8: 34946 | P8: =SUM(D8:O8) -> 379655
B9: Beverages | D9: 21254 | E9: 20922 | F9: 24504 | G9: 25802 | H9: 25605 | I9: 24887 | J9: 23729 | K9: 23762 | L9: 23739 | M9: 23477 | N9: 24644 | O9: 26114 | P9: =SUM(D9:O9) -> 288439
B10: Household & Personal Care | D10: 13001 | E10: 12854 | F10: 13854 | G10: 14233 | H10: 14621 | I10: 14188 | J10: 14398 | K10: 14602 | L10: 14350 | M10: 14347 | N10: 14577 | O10: 16058 | P10: =SUM(D10:O10) -> 171083
B11: Fresh & Frozen | D11: 9873 | E11: 10109 | F11: 10769 | G11: 11031 | H11: 10927 | I11: 10716 | J11: 10569 | K11: 10261 | L11: 10502 | M11: 10352 | N11: 10259 | O11: 10394 | P11: =SUM(D11:O11) -> 125762
B12: Total net sales | D12: =SUM(D8:D11) -> 72852 | E12: =SUM(E8:E11) -> 71599 | F12: =SUM(F8:F11) -> 81098 | G12: =SUM(G8:G11) -> 83775 | H12: =SUM(H8:H11) -> 83534 | I12: =SUM(I8:I11) -> 81093 | J12: =SUM(J8:J11) -> 80482 | K12: =SUM(K8:K11) -> 80093 | ... P12: =SUM(P8:P11) -> 964939
B13: COST OF SALES
B14: Packaged Food | D14: 21597 | E14: 20837 | F14: 24038 | G14: 24593 | H14: 24346 | I14: 23535 | J14: 23899 | K14: 23660 | L14: 24473 | M14: 23589 | N14: 24609 | O14: 26275 | P14: =SUM(D14:O14) -> 285451
B15: Beverages | D15: 15584 | E15: 15341 | F15: 17967 | G15: 18919 | H15: 18774 | I15: 18248 | J15: 17399 | K15: 17423 | L15: 17406 | M15: 17214 | N15: 18070 | O15: 19148 | P15: =SUM(D15:O15) -> 211493
B16: Household & Personal Care | D16: 9131 | E16: 9027 | F16: 9730 | G16: 9996 | H16: 10268 | I16: 9964 | J16: 10112 | K16: 10255 | L16: 10078 | M16: 10076 | N16: 10237 | O16: 11277 | P16: =SUM(D16:O16) -> 120151
B17: Fresh & Frozen | D17: 8017 | E17: 8209 | F17: 8745 | G17: 8958 | H17: 8873 | I17: 8702 | J17: 8582 | K17: 8332 | L17: 8528 | M17: 8406 | N17: 8331 | O17: 8440 | P17: =SUM(D17:O17) -> 102123
B18: Total cost of sales | D18: =SUM(D14:D17) -> 54329 | E18: =SUM(E14:E17) -> 53414 | F18: =SUM(F14:F17) -> 60480 | G18: =SUM(G14:G17) -> 62466 | H18: =SUM(H14:H17) -> 62261 | I18: =SUM(I14:I17) -> 60449 | J18: =SUM(J14:J17) -> 59992 | K18: =SUM(K14:K17) -> 59670 | ... P18: =SUM(P14:P17) -> 719218
B19: Gross profit | D19: =D12-D18 -> 18523 | E19: =E12-E18 -> 18185 | F19: =F12-F18 -> 20618 | G19: =G12-G18 -> 21309 | H19: =H12-H18 -> 21273 | I19: =I12-I18 -> 20644 | J19: =J12-J18 -> 20490 | K19: =K12-K18 -> 20423 | ... P19: =P12-P18 -> 245721
B20: Gross margin % | D20: =IFERROR(D19/D12,0) -> 0.2542552 | E20: =IFERROR(E19/E12,0) -> 0.25398399 | F20: =IFERROR(F19/F12,0) -> 0.25423562 | G20: =IFERROR(G19/G12,0) -> 0.25435989 | H20: =IFERROR(H19/H12,0) -> 0.25466277 | I20: =IFERROR(I19/I12,0) -> 0.25457191 | J20: =IFERROR(J19/J12,0) -> 0.25459109 | K20: =IFERROR(K19/K12,0) -> 0.25499107 | ... P20: =IFERROR(P19/P12,0) -> 0.25464926
B21: OPERATING EXPENSES
B22: Sales commissions & incentives | C22: Variable | D22: 1163 | E22: 1135 | F22: 1342 | G22: 1340 | H22: 1334 | I22: 1318 | J22: 1271 | K22: 1331 | L22: 1292 | M22: 1274 | N22: 1300 | O22: 1455 | P22: =SUM(D22:O22) -> 15555
B23: Advertising & promotions | C23: Variable | D23: 678 | E23: 669 | F23: 744 | G23: 774 | H23: 749 | I23: 739 | J23: 753 | K23: 714 | L23: 749 | M23: 915 | N23: 939 | O23: 999 | P23: =SUM(D23:O23) -> 9422
B24: Freight & delivery | C24: Variable | D24: 1803 | E24: 1758 | F24: 1982 | G24: 2014 | H24: 1998 | I24: 1977 | J24: 1956 | K24: 1929 | L24: 1968 | M24: 1901 | N24: 2014 | O24: 2184 | P24: =SUM(D24:O24) -> 23484
B25: Warehouse rent & utilities | C25: Fixed | D25: 2081 | E25: 2113 | F25: 2068 | G25: 1988 | H25: 1986 | I25: 2182 | J25: 2059 | K25: 1938 | L25: 2028 | M25: 1946 | N25: 2139 | O25: 2189 | P25: =SUM(D25:O25) -> 24717
B26: Selling & logistics staff costs | C26: Fixed | D26: 2610 | E26: 2554 | F26: 2554 | G26: 2692 | H26: 2830 | I26: 2575 | J26: 2642 | K26: 2778 | L26: 2852 | M26: 2841 | N26: 2770 | O26: 2903 | P26: =SUM(D26:O26) -> 32601
B27: Selling & distribution | D27: =SUM(D22:D26) -> 8335 | E27: =SUM(E22:E26) -> 8229 | F27: =SUM(F22:F26) -> 8690 | G27: =SUM(G22:G26) -> 8808 | H27: =SUM(H22:H26) -> 8897 | I27: =SUM(I22:I26) -> 8791 | J27: =SUM(J22:J26) -> 8681 | K27: =SUM(K22:K26) -> 8690 | ... P27: =SUM(P22:P26) -> 105779
B28: Salaries & wages (G&A) | C28: Fixed | D28: 2476 | E28: 2636 | F28: 2535 | G28: 2522 | H28: 2374 | I28: 2425 | J28: 2349 | K28: 2603 | L28: 2552 | M28: 2430 | N28: 2654 | O28: 2520 | P28: =SUM(D28:O28) -> 30076
B29: Employee benefits & contributions | C29: Fixed | D29: 643 | E29: 707 | F29: 672 | G29: 691 | H29: 648 | I29: 655 | J29: 705 | K29: 674 | L29: 690 | M29: 691 | N29: 666 | O29: 680 | P29: =SUM(D29:O29) -> 8122
B30: Professional fees | C30: Fixed | D30: 325 | E30: 330 | F30: 860 | G30: 335 | H30: 311 | I30: 330 | J30: 327 | K30: 308 | L30: 308 | M30: 311 | N30: 320 | O30: 330 | P30: =SUM(D30:O30) -> 4395
B31: Office rent & utilities | C31: Fixed | D31: 568 | E31: 560 | F31: 549 | G31: 579 | H31: 536 | I31: 566 | J31: 590 | K31: 579 | L31: 579 | M31: 571 | N31: 582 | O31: 577 | P31: =SUM(D31:O31) -> 6836
B32: Repairs & maintenance | C32: Fixed | D32: 229 | E32: 245 | F32: 222 | G32: 224 | H32: 256 | I32: 210 | J32: 259 | K32: 213 | L32: 199 | M32: 219 | N32: 250 | O32: 226 | P32: =SUM(D32:O32) -> 2752
B33: Taxes, licenses & insurance | C33: Fixed | D33: 470 | E33: 448 | F33: 436 | G33: 473 | H33: 451 | I33: 442 | J33: 440 | K33: 475 | L33: 470 | M33: 443 | N33: 484 | O33: 447 | P33: =SUM(D33:O33) -> 5479
B34: Communication, IT & supplies | C34: Fixed | D34: 379 | E34: 379 | F34: 356 | G34: 394 | H34: 359 | I34: 385 | J34: 378 | K34: 355 | L34: 364 | M34: 363 | N34: 369 | O34: 390 | P34: =SUM(D34:O34) -> 4471
B35: Bad debts & credit losses | C35: Variable | D35: 113 | E35: 107 | F35: 123 | G35: 124 | H35: 123 | I35: 122 | J35: 123 | K35: 121 | L35: 126 | M35: 118 | N35: 123 | O35: 135 | P35: =SUM(D35:O35) -> 1458
B36: General & administrative | D36: =SUM(D28:D35) -> 5203 | E36: =SUM(E28:E35) -> 5412 | F36: =SUM(F28:F35) -> 5753 | G36: =SUM(G28:G35) -> 5342 | H36: =SUM(H28:H35) -> 5058 | I36: =SUM(I28:I35) -> 5135 | J36: =SUM(J28:J35) -> 5171 | K36: =SUM(K28:K35) -> 5328 | ... P36: =SUM(P28:P35) -> 63589
B37: Depreciation | D37: 1733.3333 | E37: 1733.3333 | F37: 1733.3333 | G37: 1733.3333 | H37: 1733.3333 | I37: 1733.3333 | J37: 1733.3333 | K37: 1733.3333 | L37: 1733.3333 | M37: 1733.3333 | N37: 1733.3333 | O37: 1733.3333 | P37: =SUM(D37:O37) -> 20800
B38: Total operating expenses | D38: =D27+D36+D37 -> 15271.333 | E38: =E27+E36+E37 -> 15374.333 | F38: =F27+F36+F37 -> 16176.333 | G38: =G27+G36+G37 -> 15883.333 | H38: =H27+H36+H37 -> 15688.333 | I38: =I27+I36+I37 -> 15659.333 | J38: =J27+J36+J37 -> 15585.333 | K38: =K27+K36+K37 -> 15751.333 | ... P38: =P27+P36+P37 -> 190168
B39: Operating profit | D39: =D19-D38 -> 3251.6667 | E39: =E19-E38 -> 2810.6667 | F39: =F19-F38 -> 4441.6667 | G39: =G19-G38 -> 5425.6667 | H39: =H19-H38 -> 5584.6667 | I39: =I19-I38 -> 4984.6667 | J39: =J19-J38 -> 4904.6667 | K39: =K19-K38 -> 4671.6667 | ... P39: =P19-P38 -> 55553
B40: Operating margin % | D40: =IFERROR(D39/D12,0) -> 0.04463387 | E40: =IFERROR(E39/E12,0) -> 0.039255669 | F40: =IFERROR(F39/F12,0) -> 0.054769127 | G40: =IFERROR(G39/G12,0) -> 0.064764747 | H40: =IFERROR(H39/H12,0) -> 0.066855013 | I40: =IFERROR(I39/I12,0) -> 0.06146852 | J40: =IFERROR(J39/J12,0) -> 0.060941163 | K40: =IFERROR(K39/K12,0) -> 0.058328027 | ... P40: =IFERROR(P39/P12,0) -> 0.057571515
B42: Budget basis (approved Dec 2024): net sales = FY2024 actual by month x (1 + category growth: Packaged Food 6.0%, Beverages 9.0%, Household 6.5%, Fresh & Frozen 10.5%), phased with a seasonal plan that expected a stronger Q2 and weaker Q4 than occurred (annual totals preserved); cost of sales = FY2024 cost ratio by category; variable expenses grow with sales (8.5%); fixed expenses grow 3-4% (inflation); depreciation PHP 20.8 million spread evenly. Values are fictional management inputs.

Sheet Actuals
B1: Actual Results FY2025 - Monthly (from ledgers)
B2: Sampaguita Foods & Distribution Corporation (SFDC) | PHP in thousands | green = formula pulling from Data_Sales / Data_Expenses
B3: =HYPERLINK("#Cover!A1","◄ Back to Cover") -> ◄ Back to Cover
B5: Line | C5: Behaviour | D5: Jan | E5: Feb | F5: Mar | G5: Apr | H5: May | I5: Jun | J5: Jul | K5: Aug | L5: Sep | M5: Oct | N5: Nov | O5: Dec | P5: FY total
B6: Month number | D6: 1 | E6: 2 | F6: 3 | G6: 4 | H6: 5 | I6: 6 | J6: 7 | K6: 8 | L6: 9 | M6: 10 | N6: 11 | O6: 12
B7: NET SALES
B8: Packaged Food | D8: =SUMIFS(S_Sales,S_Year,Act_Year,S_Month,D$6,S_Cat,$B8) -> 29349 | E8: =SUMIFS(S_Sales,S_Year,Act_Year,S_Month,E$6,S_Cat,$B8) -> 28624 | F8: =SUMIFS(S_Sales,S_Year,Act_Year,S_Month,F$6,S_Cat,$B8) -> 29752 | G8: =SUMIFS(S_Sales,S_Year,Act_Year,S_Month,G$6,S_Cat,$B8) -> 30564 | H8: =SUMIFS(S_Sales,S_Year,Act_Year,S_Month,H$6,S_Cat,$B8) -> 31622 | I8: =SUMIFS(S_Sales,S_Year,Act_Year,S_Month,I$6,S_Cat,$B8) -> 30822 | J8: =SUMIFS(S_Sales,S_Year,Act_Year,S_Month,J$6,S_Cat,$B8) -> 32484 | K8: =SUMIFS(S_Sales,S_Year,Act_Year,S_Month,K$6,S_Cat,$B8) -> 32037 | ... O8: =SUMIFS(S_Sales,S_Year,Act_Year,S_Month,O$6,S_Cat,$B8) -> 37618 | P8: =SUM(D8:O8) -> 382510
B9: Beverages | D9: =SUMIFS(S_Sales,S_Year,Act_Year,S_Month,D$6,S_Cat,$B9) -> 21712 | E9: =SUMIFS(S_Sales,S_Year,Act_Year,S_Month,E$6,S_Cat,$B9) -> 20840 | F9: =SUMIFS(S_Sales,S_Year,Act_Year,S_Month,F$6,S_Cat,$B9) -> 24364 | G9: =SUMIFS(S_Sales,S_Year,Act_Year,S_Month,G$6,S_Cat,$B9) -> 24653 | H9: =SUMIFS(S_Sales,S_Year,Act_Year,S_Month,H$6,S_Cat,$B9) -> 25465 | I9: =SUMIFS(S_Sales,S_Year,Act_Year,S_Month,I$6,S_Cat,$B9) -> 24518 | J9: =SUMIFS(S_Sales,S_Year,Act_Year,S_Month,J$6,S_Cat,$B9) -> 23958 | K9: =SUMIFS(S_Sales,S_Year,Act_Year,S_Month,K$6,S_Cat,$B9) -> 24138 | ... O9: =SUMIFS(S_Sales,S_Year,Act_Year,S_Month,O$6,S_Cat,$B9) -> 27902 | P9: =SUM(D9:O9) -> 292182
B10: Household & Personal Care | D10: =SUMIFS(S_Sales,S_Year,Act_Year,S_Month,D$6,S_Cat,$B10) -> 13310 | E10: =SUMIFS(S_Sales,S_Year,Act_Year,S_Month,E$6,S_Cat,$B10) -> 12377 | F10: =SUMIFS(S_Sales,S_Year,Act_Year,S_Month,F$6,S_Cat,$B10) -> 13369 | G10: =SUMIFS(S_Sales,S_Year,Act_Year,S_Month,G$6,S_Cat,$B10) -> 13386 | H10: =SUMIFS(S_Sales,S_Year,Act_Year,S_Month,H$6,S_Cat,$B10) -> 14353 | I10: =SUMIFS(S_Sales,S_Year,Act_Year,S_Month,I$6,S_Cat,$B10) -> 13721 | J10: =SUMIFS(S_Sales,S_Year,Act_Year,S_Month,J$6,S_Cat,$B10) -> 14472 | K10: =SUMIFS(S_Sales,S_Year,Act_Year,S_Month,K$6,S_Cat,$B10) -> 14292 | ... O10: =SUMIFS(S_Sales,S_Year,Act_Year,S_Month,O$6,S_Cat,$B10) -> 16748 | P10: =SUM(D10:O10) -> 170561
B11: Fresh & Frozen | D11: =SUMIFS(S_Sales,S_Year,Act_Year,S_Month,D$6,S_Cat,$B11) -> 10092 | E11: =SUMIFS(S_Sales,S_Year,Act_Year,S_Month,E$6,S_Cat,$B11) -> 9848 | F11: =SUMIFS(S_Sales,S_Year,Act_Year,S_Month,F$6,S_Cat,$B11) -> 10272 | G11: =SUMIFS(S_Sales,S_Year,Act_Year,S_Month,G$6,S_Cat,$B11) -> 10420 | H11: =SUMIFS(S_Sales,S_Year,Act_Year,S_Month,H$6,S_Cat,$B11) -> 10506 | I11: =SUMIFS(S_Sales,S_Year,Act_Year,S_Month,I$6,S_Cat,$B11) -> 10357 | J11: =SUMIFS(S_Sales,S_Year,Act_Year,S_Month,J$6,S_Cat,$B11) -> 10753 | K11: =SUMIFS(S_Sales,S_Year,Act_Year,S_Month,K$6,S_Cat,$B11) -> 10638 | ... O11: =SUMIFS(S_Sales,S_Year,Act_Year,S_Month,O$6,S_Cat,$B11) -> 11634 | P11: =SUM(D11:O11) -> 127189
B12: Total net sales | D12: =SUM(D8:D11) -> 74463 | E12: =SUM(E8:E11) -> 71689 | F12: =SUM(F8:F11) -> 77757 | G12: =SUM(G8:G11) -> 79023 | H12: =SUM(H8:H11) -> 81946 | I12: =SUM(I8:I11) -> 79418 | J12: =SUM(J8:J11) -> 81667 | K12: =SUM(K8:K11) -> 81105 | ... P12: =SUM(P8:P11) -> 972442
B13: COST OF SALES
B14: Packaged Food | D14: =SUMIFS(S_COGS,S_Year,Act_Year,S_Month,D$6,S_Cat,$B14) -> 21952 | E14: =SUMIFS(S_COGS,S_Year,Act_Year,S_Month,E$6,S_Cat,$B14) -> 21399 | F14: =SUMIFS(S_COGS,S_Year,Act_Year,S_Month,F$6,S_Cat,$B14) -> 22236 | G14: =SUMIFS(S_COGS,S_Year,Act_Year,S_Month,G$6,S_Cat,$B14) -> 23005 | H14: =SUMIFS(S_COGS,S_Year,Act_Year,S_Month,H$6,S_Cat,$B14) -> 23757 | I14: =SUMIFS(S_COGS,S_Year,Act_Year,S_Month,I$6,S_Cat,$B14) -> 23112 | J14: =SUMIFS(S_COGS,S_Year,Act_Year,S_Month,J$6,S_Cat,$B14) -> 24316 | K14: =SUMIFS(S_COGS,S_Year,Act_Year,S_Month,K$6,S_Cat,$B14) -> 23992 | ... O14: =SUMIFS(S_COGS,S_Year,Act_Year,S_Month,O$6,S_Cat,$B14) -> 28298 | P14: =SUM(D14:O14) -> 286694
B15: Beverages | D15: =SUMIFS(S_COGS,S_Year,Act_Year,S_Month,D$6,S_Cat,$B15) -> 15900 | E15: =SUMIFS(S_COGS,S_Year,Act_Year,S_Month,E$6,S_Cat,$B15) -> 15172 | F15: =SUMIFS(S_COGS,S_Year,Act_Year,S_Month,F$6,S_Cat,$B15) -> 17783 | G15: =SUMIFS(S_COGS,S_Year,Act_Year,S_Month,G$6,S_Cat,$B15) -> 18013 | H15: =SUMIFS(S_COGS,S_Year,Act_Year,S_Month,H$6,S_Cat,$B15) -> 18617 | I15: =SUMIFS(S_COGS,S_Year,Act_Year,S_Month,I$6,S_Cat,$B15) -> 17946 | J15: =SUMIFS(S_COGS,S_Year,Act_Year,S_Month,J$6,S_Cat,$B15) -> 17478 | K15: =SUMIFS(S_COGS,S_Year,Act_Year,S_Month,K$6,S_Cat,$B15) -> 17674 | ... O15: =SUMIFS(S_COGS,S_Year,Act_Year,S_Month,O$6,S_Cat,$B15) -> 20404 | P15: =SUM(D15:O15) -> 213400
B16: Household & Personal Care | D16: =SUMIFS(S_COGS,S_Year,Act_Year,S_Month,D$6,S_Cat,$B16) -> 9304 | E16: =SUMIFS(S_COGS,S_Year,Act_Year,S_Month,E$6,S_Cat,$B16) -> 8649 | F16: =SUMIFS(S_COGS,S_Year,Act_Year,S_Month,F$6,S_Cat,$B16) -> 9369 | G16: =SUMIFS(S_COGS,S_Year,Act_Year,S_Month,G$6,S_Cat,$B16) -> 9378 | H16: =SUMIFS(S_COGS,S_Year,Act_Year,S_Month,H$6,S_Cat,$B16) -> 10050 | I16: =SUMIFS(S_COGS,S_Year,Act_Year,S_Month,I$6,S_Cat,$B16) -> 9605 | J16: =SUMIFS(S_COGS,S_Year,Act_Year,S_Month,J$6,S_Cat,$B16) -> 10134 | K16: =SUMIFS(S_COGS,S_Year,Act_Year,S_Month,K$6,S_Cat,$B16) -> 9981 | ... O16: =SUMIFS(S_COGS,S_Year,Act_Year,S_Month,O$6,S_Cat,$B16) -> 11709 | P16: =SUM(D16:O16) -> 119380
B17: Fresh & Frozen | D17: =SUMIFS(S_COGS,S_Year,Act_Year,S_Month,D$6,S_Cat,$B17) -> 8188 | E17: =SUMIFS(S_COGS,S_Year,Act_Year,S_Month,E$6,S_Cat,$B17) -> 7967 | F17: =SUMIFS(S_COGS,S_Year,Act_Year,S_Month,F$6,S_Cat,$B17) -> 8337 | G17: =SUMIFS(S_COGS,S_Year,Act_Year,S_Month,G$6,S_Cat,$B17) -> 8458 | H17: =SUMIFS(S_COGS,S_Year,Act_Year,S_Month,H$6,S_Cat,$B17) -> 8501 | I17: =SUMIFS(S_COGS,S_Year,Act_Year,S_Month,I$6,S_Cat,$B17) -> 8394 | J17: =SUMIFS(S_COGS,S_Year,Act_Year,S_Month,J$6,S_Cat,$B17) -> 8701 | K17: =SUMIFS(S_COGS,S_Year,Act_Year,S_Month,K$6,S_Cat,$B17) -> 8586 | ... O17: =SUMIFS(S_COGS,S_Year,Act_Year,S_Month,O$6,S_Cat,$B17) -> 9462 | P17: =SUM(D17:O17) -> 103074
B18: Total cost of sales | D18: =SUM(D14:D17) -> 55344 | E18: =SUM(E14:E17) -> 53187 | F18: =SUM(F14:F17) -> 57725 | G18: =SUM(G14:G17) -> 58854 | H18: =SUM(H14:H17) -> 60925 | I18: =SUM(I14:I17) -> 59057 | J18: =SUM(J14:J17) -> 60629 | K18: =SUM(K14:K17) -> 60233 | ... P18: =SUM(P14:P17) -> 722548
B19: Gross profit | D19: =D12-D18 -> 19119 | E19: =E12-E18 -> 18502 | F19: =F12-F18 -> 20032 | G19: =G12-G18 -> 20169 | H19: =H12-H18 -> 21021 | I19: =I12-I18 -> 20361 | J19: =J12-J18 -> 21038 | K19: =K12-K18 -> 20872 | ... P19: =P12-P18 -> 249894
B20: Gross margin % | D20: =IFERROR(D19/D12,0) -> 0.25675839 | E20: =IFERROR(E19/E12,0) -> 0.25808701 | F20: =IFERROR(F19/F12,0) -> 0.25762311 | G20: =IFERROR(G19/G12,0) -> 0.25522949 | H20: =IFERROR(H19/H12,0) -> 0.25652259 | I20: =IFERROR(I19/I12,0) -> 0.25637765 | J20: =IFERROR(J19/J12,0) -> 0.25760711 | K20: =IFERROR(K19/K12,0) -> 0.25734542 | ... P20: =IFERROR(P19/P12,0) -> 0.25697574
B21: OPERATING EXPENSES
B22: Sales commissions & incentives | C22: Variable | D22: =SUMIFS(E_Amt,E_Year,Act_Year,E_Month,D$6,E_Line,$B22) -> 1171 | E22: =SUMIFS(E_Amt,E_Year,Act_Year,E_Month,E$6,E_Line,$B22) -> 1158 | F22: =SUMIFS(E_Amt,E_Year,Act_Year,E_Month,F$6,E_Line,$B22) -> 1270 | G22: =SUMIFS(E_Amt,E_Year,Act_Year,E_Month,G$6,E_Line,$B22) -> 1284 | H22: =SUMIFS(E_Amt,E_Year,Act_Year,E_Month,H$6,E_Line,$B22) -> 1347 | I22: =SUMIFS(E_Amt,E_Year,Act_Year,E_Month,I$6,E_Line,$B22) -> 1282 | J22: =SUMIFS(E_Amt,E_Year,Act_Year,E_Month,J$6,E_Line,$B22) -> 1314 | K22: =SUMIFS(E_Amt,E_Year,Act_Year,E_Month,K$6,E_Line,$B22) -> 1272 | ... O22: =SUMIFS(E_Amt,E_Year,Act_Year,E_Month,O$6,E_Line,$B22) -> 1546 | P22: =SUM(D22:O22) -> 15695
B23: Advertising & promotions | C23: Variable | D23: =SUMIFS(E_Amt,E_Year,Act_Year,E_Month,D$6,E_Line,$B23) -> 655 | E23: =SUMIFS(E_Amt,E_Year,Act_Year,E_Month,E$6,E_Line,$B23) -> 662 | F23: =SUMIFS(E_Amt,E_Year,Act_Year,E_Month,F$6,E_Line,$B23) -> 703 | G23: =SUMIFS(E_Amt,E_Year,Act_Year,E_Month,G$6,E_Line,$B23) -> 717 | H23: =SUMIFS(E_Amt,E_Year,Act_Year,E_Month,H$6,E_Line,$B23) -> 727 | I23: =SUMIFS(E_Amt,E_Year,Act_Year,E_Month,I$6,E_Line,$B23) -> 728 | J23: =SUMIFS(E_Amt,E_Year,Act_Year,E_Month,J$6,E_Line,$B23) -> 747 | K23: =SUMIFS(E_Amt,E_Year,Act_Year,E_Month,K$6,E_Line,$B23) -> 740 | ... O23: =SUMIFS(E_Amt,E_Year,Act_Year,E_Month,O$6,E_Line,$B23) -> 1027 | P23: =SUM(D23:O23) -> 9363
B24: Freight & delivery | C24: Variable | D24: =SUMIFS(E_Amt,E_Year,Act_Year,E_Month,D$6,E_Line,$B24) -> 1837 | E24: =SUMIFS(E_Amt,E_Year,Act_Year,E_Month,E$6,E_Line,$B24) -> 1670 | F24: =SUMIFS(E_Amt,E_Year,Act_Year,E_Month,F$6,E_Line,$B24) -> 1865 | G24: =SUMIFS(E_Amt,E_Year,Act_Year,E_Month,G$6,E_Line,$B24) -> 1941 | H24: =SUMIFS(E_Amt,E_Year,Act_Year,E_Month,H$6,E_Line,$B24) -> 1936 | I24: =SUMIFS(E_Amt,E_Year,Act_Year,E_Month,I$6,E_Line,$B24) -> 1929 | J24: =SUMIFS(E_Amt,E_Year,Act_Year,E_Month,J$6,E_Line,$B24) -> 2014 | K24: =SUMIFS(E_Amt,E_Year,Act_Year,E_Month,K$6,E_Line,$B24) -> 1914 | ... O24: =SUMIFS(E_Amt,E_Year,Act_Year,E_Month,O$6,E_Line,$B24) -> 2228 | P24: =SUM(D24:O24) -> 23337
B25: Warehouse rent & utilities | C25: Fixed | D25: =SUMIFS(E_Amt,E_Year,Act_Year,E_Month,D$6,E_Line,$B25) -> 2107 | E25: =SUMIFS(E_Amt,E_Year,Act_Year,E_Month,E$6,E_Line,$B25) -> 2121 | F25: =SUMIFS(E_Amt,E_Year,Act_Year,E_Month,F$6,E_Line,$B25) -> 2096 | G25: =SUMIFS(E_Amt,E_Year,Act_Year,E_Month,G$6,E_Line,$B25) -> 2104 | H25: =SUMIFS(E_Amt,E_Year,Act_Year,E_Month,H$6,E_Line,$B25) -> 2058 | I25: =SUMIFS(E_Amt,E_Year,Act_Year,E_Month,I$6,E_Line,$B25) -> 2064 | J25: =SUMIFS(E_Amt,E_Year,Act_Year,E_Month,J$6,E_Line,$B25) -> 2061 | K25: =SUMIFS(E_Amt,E_Year,Act_Year,E_Month,K$6,E_Line,$B25) -> 2065 | ... O25: =SUMIFS(E_Amt,E_Year,Act_Year,E_Month,O$6,E_Line,$B25) -> 2050 | P25: =SUM(D25:O25) -> 24992
B26: Selling & logistics staff costs | C26: Fixed | D26: =SUMIFS(E_Amt,E_Year,Act_Year,E_Month,D$6,E_Line,$B26) -> 2691 | E26: =SUMIFS(E_Amt,E_Year,Act_Year,E_Month,E$6,E_Line,$B26) -> 2705 | F26: =SUMIFS(E_Amt,E_Year,Act_Year,E_Month,F$6,E_Line,$B26) -> 2758 | G26: =SUMIFS(E_Amt,E_Year,Act_Year,E_Month,G$6,E_Line,$B26) -> 2730 | H26: =SUMIFS(E_Amt,E_Year,Act_Year,E_Month,H$6,E_Line,$B26) -> 2705 | I26: =SUMIFS(E_Amt,E_Year,Act_Year,E_Month,I$6,E_Line,$B26) -> 2716 | J26: =SUMIFS(E_Amt,E_Year,Act_Year,E_Month,J$6,E_Line,$B26) -> 2717 | K26: =SUMIFS(E_Amt,E_Year,Act_Year,E_Month,K$6,E_Line,$B26) -> 2727 | ... O26: =SUMIFS(E_Amt,E_Year,Act_Year,E_Month,O$6,E_Line,$B26) -> 2685 | P26: =SUM(D26:O26) -> 32690
B27: Selling & distribution | D27: =SUM(D22:D26) -> 8461 | E27: =SUM(E22:E26) -> 8316 | F27: =SUM(F22:F26) -> 8692 | G27: =SUM(G22:G26) -> 8776 | H27: =SUM(H22:H26) -> 8773 | I27: =SUM(I22:I26) -> 8719 | J27: =SUM(J22:J26) -> 8853 | K27: =SUM(K22:K26) -> 8718 | ... P27: =SUM(P22:P26) -> 106077
B28: Salaries & wages (G&A) | C28: Fixed | D28: =SUMIFS(E_Amt,E_Year,Act_Year,E_Month,D$6,E_Line,$B28) -> 2500 | E28: =SUMIFS(E_Amt,E_Year,Act_Year,E_Month,E$6,E_Line,$B28) -> 2531 | F28: =SUMIFS(E_Amt,E_Year,Act_Year,E_Month,F$6,E_Line,$B28) -> 2474 | G28: =SUMIFS(E_Amt,E_Year,Act_Year,E_Month,G$6,E_Line,$B28) -> 2562 | H28: =SUMIFS(E_Amt,E_Year,Act_Year,E_Month,H$6,E_Line,$B28) -> 2567 | I28: =SUMIFS(E_Amt,E_Year,Act_Year,E_Month,I$6,E_Line,$B28) -> 2512 | J28: =SUMIFS(E_Amt,E_Year,Act_Year,E_Month,J$6,E_Line,$B28) -> 2540 | K28: =SUMIFS(E_Amt,E_Year,Act_Year,E_Month,K$6,E_Line,$B28) -> 2553 | ... O28: =SUMIFS(E_Amt,E_Year,Act_Year,E_Month,O$6,E_Line,$B28) -> 2473 | P28: =SUM(D28:O28) -> 30213
B29: Employee benefits & contributions | C29: Fixed | D29: =SUMIFS(E_Amt,E_Year,Act_Year,E_Month,D$6,E_Line,$B29) -> 673 | E29: =SUMIFS(E_Amt,E_Year,Act_Year,E_Month,E$6,E_Line,$B29) -> 674 | F29: =SUMIFS(E_Amt,E_Year,Act_Year,E_Month,F$6,E_Line,$B29) -> 683 | G29: =SUMIFS(E_Amt,E_Year,Act_Year,E_Month,G$6,E_Line,$B29) -> 667 | H29: =SUMIFS(E_Amt,E_Year,Act_Year,E_Month,H$6,E_Line,$B29) -> 678 | I29: =SUMIFS(E_Amt,E_Year,Act_Year,E_Month,I$6,E_Line,$B29) -> 677 | J29: =SUMIFS(E_Amt,E_Year,Act_Year,E_Month,J$6,E_Line,$B29) -> 685 | K29: =SUMIFS(E_Amt,E_Year,Act_Year,E_Month,K$6,E_Line,$B29) -> 666 | ... O29: =SUMIFS(E_Amt,E_Year,Act_Year,E_Month,O$6,E_Line,$B29) -> 666 | P29: =SUM(D29:O29) -> 8130
B30: Professional fees | C30: Fixed | D30: =SUMIFS(E_Amt,E_Year,Act_Year,E_Month,D$6,E_Line,$B30) -> 335 | E30: =SUMIFS(E_Amt,E_Year,Act_Year,E_Month,E$6,E_Line,$B30) -> 325 | F30: =SUMIFS(E_Amt,E_Year,Act_Year,E_Month,F$6,E_Line,$B30) -> 867 | G30: =SUMIFS(E_Amt,E_Year,Act_Year,E_Month,G$6,E_Line,$B30) -> 330 | H30: =SUMIFS(E_Amt,E_Year,Act_Year,E_Month,H$6,E_Line,$B30) -> 331 | I30: =SUMIFS(E_Amt,E_Year,Act_Year,E_Month,I$6,E_Line,$B30) -> 328 | J30: =SUMIFS(E_Amt,E_Year,Act_Year,E_Month,J$6,E_Line,$B30) -> 333 | K30: =SUMIFS(E_Amt,E_Year,Act_Year,E_Month,K$6,E_Line,$B30) -> 326 | ... O30: =SUMIFS(E_Amt,E_Year,Act_Year,E_Month,O$6,E_Line,$B30) -> 334 | P30: =SUM(D30:O30) -> 4500
B31: Office rent & utilities | C31: Fixed | D31: =SUMIFS(E_Amt,E_Year,Act_Year,E_Month,D$6,E_Line,$B31) -> 574 | E31: =SUMIFS(E_Amt,E_Year,Act_Year,E_Month,E$6,E_Line,$B31) -> 580 | F31: =SUMIFS(E_Amt,E_Year,Act_Year,E_Month,F$6,E_Line,$B31) -> 563 | G31: =SUMIFS(E_Amt,E_Year,Act_Year,E_Month,G$6,E_Line,$B31) -> 569 | H31: =SUMIFS(E_Amt,E_Year,Act_Year,E_Month,H$6,E_Line,$B31) -> 561 | I31: =SUMIFS(E_Amt,E_Year,Act_Year,E_Month,I$6,E_Line,$B31) -> 568 | J31: =SUMIFS(E_Amt,E_Year,Act_Year,E_Month,J$6,E_Line,$B31) -> 577 | K31: =SUMIFS(E_Amt,E_Year,Act_Year,E_Month,K$6,E_Line,$B31) -> 580 | ... O31: =SUMIFS(E_Amt,E_Year,Act_Year,E_Month,O$6,E_Line,$B31) -> 568 | P31: =SUM(D31:O31) -> 6839
B32: Repairs & maintenance | C32: Fixed | D32: =SUMIFS(E_Amt,E_Year,Act_Year,E_Month,D$6,E_Line,$B32) -> 257 | E32: =SUMIFS(E_Amt,E_Year,Act_Year,E_Month,E$6,E_Line,$B32) -> 243 | F32: =SUMIFS(E_Amt,E_Year,Act_Year,E_Month,F$6,E_Line,$B32) -> 237 | G32: =SUMIFS(E_Amt,E_Year,Act_Year,E_Month,G$6,E_Line,$B32) -> 232 | H32: =SUMIFS(E_Amt,E_Year,Act_Year,E_Month,H$6,E_Line,$B32) -> 234 | I32: =SUMIFS(E_Amt,E_Year,Act_Year,E_Month,I$6,E_Line,$B32) -> 219 | J32: =SUMIFS(E_Amt,E_Year,Act_Year,E_Month,J$6,E_Line,$B32) -> 206 | K32: =SUMIFS(E_Amt,E_Year,Act_Year,E_Month,K$6,E_Line,$B32) -> 222 | ... O32: =SUMIFS(E_Amt,E_Year,Act_Year,E_Month,O$6,E_Line,$B32) -> 239 | P32: =SUM(D32:O32) -> 2729
B33: Taxes, licenses & insurance | C33: Fixed | D33: =SUMIFS(E_Amt,E_Year,Act_Year,E_Month,D$6,E_Line,$B33) -> 456 | E33: =SUMIFS(E_Amt,E_Year,Act_Year,E_Month,E$6,E_Line,$B33) -> 461 | F33: =SUMIFS(E_Amt,E_Year,Act_Year,E_Month,F$6,E_Line,$B33) -> 460 | G33: =SUMIFS(E_Amt,E_Year,Act_Year,E_Month,G$6,E_Line,$B33) -> 453 | H33: =SUMIFS(E_Amt,E_Year,Act_Year,E_Month,H$6,E_Line,$B33) -> 457 | I33: =SUMIFS(E_Amt,E_Year,Act_Year,E_Month,I$6,E_Line,$B33) -> 457 | J33: =SUMIFS(E_Amt,E_Year,Act_Year,E_Month,J$6,E_Line,$B33) -> 454 | K33: =SUMIFS(E_Amt,E_Year,Act_Year,E_Month,K$6,E_Line,$B33) -> 452 | ... O33: =SUMIFS(E_Amt,E_Year,Act_Year,E_Month,O$6,E_Line,$B33) -> 462 | P33: =SUM(D33:O33) -> 5484
B34: Communication, IT & supplies | C34: Fixed | D34: =SUMIFS(E_Amt,E_Year,Act_Year,E_Month,D$6,E_Line,$B34) -> 371 | E34: =SUMIFS(E_Amt,E_Year,Act_Year,E_Month,E$6,E_Line,$B34) -> 374 | F34: =SUMIFS(E_Amt,E_Year,Act_Year,E_Month,F$6,E_Line,$B34) -> 377 | G34: =SUMIFS(E_Amt,E_Year,Act_Year,E_Month,G$6,E_Line,$B34) -> 378 | H34: =SUMIFS(E_Amt,E_Year,Act_Year,E_Month,H$6,E_Line,$B34) -> 371 | I34: =SUMIFS(E_Amt,E_Year,Act_Year,E_Month,I$6,E_Line,$B34) -> 368 | J34: =SUMIFS(E_Amt,E_Year,Act_Year,E_Month,J$6,E_Line,$B34) -> 369 | K34: =SUMIFS(E_Amt,E_Year,Act_Year,E_Month,K$6,E_Line,$B34) -> 366 | ... O34: =SUMIFS(E_Amt,E_Year,Act_Year,E_Month,O$6,E_Line,$B34) -> 372 | P34: =SUM(D34:O34) -> 4463
B35: Bad debts & credit losses | C35: Variable | D35: =SUMIFS(E_Amt,E_Year,Act_Year,E_Month,D$6,E_Line,$B35) -> 114 | E35: =SUMIFS(E_Amt,E_Year,Act_Year,E_Month,E$6,E_Line,$B35) -> 105 | F35: =SUMIFS(E_Amt,E_Year,Act_Year,E_Month,F$6,E_Line,$B35) -> 117 | G35: =SUMIFS(E_Amt,E_Year,Act_Year,E_Month,G$6,E_Line,$B35) -> 121 | H35: =SUMIFS(E_Amt,E_Year,Act_Year,E_Month,H$6,E_Line,$B35) -> 125 | I35: =SUMIFS(E_Amt,E_Year,Act_Year,E_Month,I$6,E_Line,$B35) -> 119 | J35: =SUMIFS(E_Amt,E_Year,Act_Year,E_Month,J$6,E_Line,$B35) -> 119 | K35: =SUMIFS(E_Amt,E_Year,Act_Year,E_Month,K$6,E_Line,$B35) -> 124 | ... O35: =SUMIFS(E_Amt,E_Year,Act_Year,E_Month,O$6,E_Line,$B35) -> 145 | P35: =SUM(D35:O35) -> 1469
B36: General & administrative | D36: =SUM(D28:D35) -> 5280 | E36: =SUM(E28:E35) -> 5293 | F36: =SUM(F28:F35) -> 5778 | G36: =SUM(G28:G35) -> 5312 | H36: =SUM(H28:H35) -> 5324 | I36: =SUM(I28:I35) -> 5248 | J36: =SUM(J28:J35) -> 5283 | K36: =SUM(K28:K35) -> 5289 | ... P36: =SUM(P28:P35) -> 63827
B37: Depreciation | D37: =Dep_Act/12 -> 1771.4167 | E37: =Dep_Act/12 -> 1771.4167 | F37: =Dep_Act/12 -> 1771.4167 | G37: =Dep_Act/12 -> 1771.4167 | H37: =Dep_Act/12 -> 1771.4167 | I37: =Dep_Act/12 -> 1771.4167 | J37: =Dep_Act/12 -> 1771.4167 | K37: =Dep_Act/12 -> 1771.4167 | ... O37: =Dep_Act/12 -> 1771.4167 | P37: =SUM(D37:O37) -> 21257
B38: Total operating expenses | D38: =D27+D36+D37 -> 15512.417 | E38: =E27+E36+E37 -> 15380.417 | F38: =F27+F36+F37 -> 16241.417 | G38: =G27+G36+G37 -> 15859.417 | H38: =H27+H36+H37 -> 15868.417 | I38: =I27+I36+I37 -> 15738.417 | J38: =J27+J36+J37 -> 15907.417 | K38: =K27+K36+K37 -> 15778.417 | ... P38: =P27+P36+P37 -> 191161
B39: Operating profit | D39: =D19-D38 -> 3606.5833 | E39: =E19-E38 -> 3121.5833 | F39: =F19-F38 -> 3790.5833 | G39: =G19-G38 -> 4309.5833 | H39: =H19-H38 -> 5152.5833 | I39: =I19-I38 -> 4622.5833 | J39: =J19-J38 -> 5130.5833 | K39: =K19-K38 -> 5093.5833 | ... P39: =P19-P38 -> 58733
B40: Operating margin % | D40: =IFERROR(D39/D12,0) -> 0.048434569 | E40: =IFERROR(E39/E12,0) -> 0.043543407 | F40: =IFERROR(F39/F12,0) -> 0.048749094 | G40: =IFERROR(G39/G12,0) -> 0.05453581 | H40: =IFERROR(H39/H12,0) -> 0.062877789 | I40: =IFERROR(I39/I12,0) -> 0.058205738 | J40: =IFERROR(J39/J12,0) -> 0.062823213 | K40: =IFERROR(K39/K12,0) -> 0.062802334 | ... P40: =IFERROR(P39/P12,0) -> 0.060397432
B42: Depreciation is not in the expense ledger: the Project 1 annual charge (FS_Data) is spread evenly over 12 months. Change Assumptions!C6 to analyse another ledger year (budget comparison is only meaningful for FY2025).

Sheet FS_Data
B1: FS Data - Control Totals from Project 1
B2: Sampaguita Foods & Distribution Corporation (SFDC) | PHP in thousands
B3: =HYPERLINK("#Cover!A1","◄ Back to Cover") -> ◄ Back to Cover
B4: Blue = copied from the Project 1 workbook (sheet named in column F). Used only for reconciliation checks and the depreciation line; all other actuals are rebuilt from the ledgers.
B6: PHP '000 | C6: 2023 | D6: 2024 | E6: 2025 | F6: Source (Project 1)
B7: Net sales | C7: 821118 | D7: 897238 | E7: 972442 | F7: Income_Statement
B8: Cost of sales | C8: 613977 | D8: 668558 | E8: 722548 | F8: Income_Statement
B9: Selling and distribution expenses | C9: 93216 | D9: 99930 | E9: 106077 | F9: Income_Statement
B10: General and administrative expenses | C10: 58315 | D10: 61197 | E10: 63827 | F10: Income_Statement
B11: Depreciation | C11: 17389 | D11: 19250 | E11: 21257 | F11: Income_Statement / Schedules A
B12: Operating profit | C12: 38221 | D12: 48303 | E12: 58733 | F12: Income_Statement
B14: Reference: Project 1 trend projection FY2026 (statistical, 3-point OLS)
B15: Net sales FY2026 (trend forecast) | E15: 1048257 | F15: Trend sheet, PROJECTIONS block
B16: Operating profit FY2026 (trend forecast) | E16: 68931 | F16: Trend sheet, PROJECTIONS block

Sheet Data_Sales
A1: Data - Monthly Sales Ledger (from Project 1)
A2: Month-end net sales and cost of sales by product category and region. Blue = ledger input (fictional data, copied unchanged from the Project 1 workbook, sheet Data_Sales).
A3: =HYPERLINK("#Cover!A1","◄ Back to Cover") -> ◄ Back to Cover
A4: Month-end | B4: Year | C4: Month | D4: Quarter | E4: Region | F4: Category | G4: Net sales | H4: Cost of sales | I4: Gross profit | J4: Record ID
A5: 44957 | B5: 2023 | C5: 1 | D5: Q1 | E5: Luzon | F5: Packaged Food | G5: 14280 | H5: 10782 | I5: =G5-H5 -> 3498 | J5: S202301-LUZ-PAC
A6: 44957 | B6: 2023 | C6: 1 | D6: Q1 | E6: Visayas | F6: Packaged Food | G6: 5799 | H6: 4397 | I6: =G6-H6 -> 1402 | J6: S202301-VIS-PAC
A7: 44957 | B7: 2023 | C7: 1 | D7: Q1 | E7: Mindanao | F7: Packaged Food | G7: 4673 | H7: 3516 | I7: =G7-H7 -> 1157 | J7: S202301-MIN-PAC
A8: 44957 | B8: 2023 | C8: 1 | D8: Q1 | E8: Luzon | F8: Beverages | G8: 10453 | H8: 7688 | I8: =G8-H8 -> 2765 | J8: S202301-LUZ-BEV
A9: 44957 | B9: 2023 | C9: 1 | D9: Q1 | E9: Visayas | F9: Beverages | G9: 4190 | H9: 3081 | I9: =G9-H9 -> 1109 | J9: S202301-VIS-BEV
A10: 44957 | B10: 2023 | C10: 1 | D10: Q1 | E10: Mindanao | F10: Beverages | G10: 3451 | H10: 2545 | I10: =G10-H10 -> 906 | J10: S202301-MIN-BEV
A11: 44957 | B11: 2023 | C11: 1 | D11: Q1 | E11: Luzon | F11: Household & Personal Care | G11: 6743 | H11: 4759 | I11: =G11-H11 -> 1984 | J11: S202301-LUZ-HOU
A12: 44957 | B12: 2023 | C12: 1 | D12: Q1 | E12: Visayas | F12: Household & Personal Care | G12: 2593 | H12: 1831 | I12: =G12-H12 -> 762 | J12: S202301-VIS-HOU
A13: 44957 | B13: 2023 | C13: 1 | D13: Q1 | E13: Mindanao | F13: Household & Personal Care | G13: 2125 | H13: 1504 | I13: =G13-H13 -> 621 | J13: S202301-MIN-HOU
A14: 44957 | B14: 2023 | C14: 1 | D14: Q1 | E14: Luzon | F14: Fresh & Frozen | G14: 4615 | H14: 3775 | I14: =G14-H14 -> 840 | J14: S202301-LUZ-FRE
A15: 44957 | B15: 2023 | C15: 1 | D15: Q1 | E15: Visayas | F15: Fresh & Frozen | G15: 1856 | H15: 1516 | I15: =G15-H15 -> 340 | J15: S202301-VIS-FRE
A16: 44957 | B16: 2023 | C16: 1 | D16: Q1 | E16: Mindanao | F16: Fresh & Frozen | G16: 1490 | H16: 1211 | I16: =G16-H16 -> 279 | J16: S202301-MIN-FRE
... A436: 46022 | B436: 2025 | C436: 12 | D436: Q4 | E436: Mindanao | F436: Fresh & Frozen | G436: 2353 | H436: 1908 | I436: =G436-H436 -> 445 | J436: S202512-MIN-FRE

Sheet Data_Expenses
A1: Data - Monthly Operating Expense Ledger (from Project 1)
A2: Month-end operating expenses by expense line (excludes depreciation, which comes from the PPE schedule). Copied unchanged from Project 1, sheet Data_Expenses.
A3: =HYPERLINK("#Cover!A1","◄ Back to Cover") -> ◄ Back to Cover
A4: Month-end | B4: Year | C4: Month | D4: Expense line | E4: Function | F4: Behaviour | G4: Amount | H4: Record ID
A5: 44957 | B5: 2023 | C5: 1 | D5: Sales commissions & incentives | E5: Selling & Distribution | F5: Variable | G5: 981 | H5: E202301-6101
A6: 44957 | B6: 2023 | C6: 1 | D6: Advertising & promotions | E6: Selling & Distribution | F6: Variable | G6: 559 | H6: E202301-6102
A7: 44957 | B7: 2023 | C7: 1 | D7: Freight & delivery | E7: Selling & Distribution | F7: Variable | G7: 1534 | H7: E202301-6103
A8: 44957 | B8: 2023 | C8: 1 | D8: Warehouse rent & utilities | E8: Selling & Distribution | F8: Fixed | G8: 1908 | H8: E202301-6104
A9: 44957 | B9: 2023 | C9: 1 | D9: Selling & logistics staff costs | E9: Selling & Distribution | F9: Fixed | G9: 2500 | H9: E202301-6105
A10: 44957 | B10: 2023 | C10: 1 | D10: Salaries & wages (G&A) | E10: General & Administrative | F10: Fixed | G10: 2315 | H10: E202301-6201
A11: 44957 | B11: 2023 | C11: 1 | D11: Employee benefits & contributions | E11: General & Administrative | F11: Fixed | G11: 610 | H11: E202301-6202
A12: 44957 | B12: 2023 | C12: 1 | D12: Professional fees | E12: General & Administrative | F12: Fixed | G12: 296 | H12: E202301-6203
A13: 44957 | B13: 2023 | C13: 1 | D13: Office rent & utilities | E13: General & Administrative | F13: Fixed | G13: 522 | H13: E202301-6204
A14: 44957 | B14: 2023 | C14: 1 | D14: Repairs & maintenance | E14: General & Administrative | F14: Fixed | G14: 204 | H14: E202301-6205
A15: 44957 | B15: 2023 | C15: 1 | D15: Taxes, licenses & insurance | E15: General & Administrative | F15: Fixed | G15: 416 | H15: E202301-6206
A16: 44957 | B16: 2023 | C16: 1 | D16: Communication, IT & supplies | E16: General & Administrative | F16: Fixed | G16: 339 | H16: E202301-6207
... A472: 46022 | B472: 2025 | C472: 12 | D472: Bad debts & credit losses | E472: General & Administrative | F472: Variable | G472: 145 | H472: E202512-6208

Sheet Chart_Data
B1: Chart Data
B2: Sampaguita Foods & Distribution Corporation (SFDC) | Helper tables feeding the Dashboard charts
B3: =HYPERLINK("#Cover!A1","◄ Back to Cover") -> ◄ Back to Cover
B4: Month | C4: Budget net sales | D4: Actual net sales | E4: Budget operating profit | F4: Actual operating profit | G4: Cumulative OP variance
A5: 1 | B5: =INDEX(Lists!$B$5:$B$16,$A5) -> Jan | C5: =INDEX(Budget_FY2025!$D$12:$O$12,$A5) -> 72852 | D5: =INDEX(Actuals!$D$12:$O$12,$A5) -> 74463 | E5: =INDEX(Budget_FY2025!$D$39:$O$39,$A5) -> 3251.6667 | F5: =INDEX(Actuals!$D$39:$O$39,$A5) -> 3606.5833 | G5: =SUM($F$5:F5)-SUM($E$5:E5) -> 354.91667
A6: 2 | B6: =INDEX(Lists!$B$5:$B$16,$A6) -> Feb | C6: =INDEX(Budget_FY2025!$D$12:$O$12,$A6) -> 71599 | D6: =INDEX(Actuals!$D$12:$O$12,$A6) -> 71689 | E6: =INDEX(Budget_FY2025!$D$39:$O$39,$A6) -> 2810.6667 | F6: =INDEX(Actuals!$D$39:$O$39,$A6) -> 3121.5833 | G6: =SUM($F$5:F6)-SUM($E$5:E6) -> 665.83333
A7: 3 | B7: =INDEX(Lists!$B$5:$B$16,$A7) -> Mar | C7: =INDEX(Budget_FY2025!$D$12:$O$12,$A7) -> 81098 | D7: =INDEX(Actuals!$D$12:$O$12,$A7) -> 77757 | E7: =INDEX(Budget_FY2025!$D$39:$O$39,$A7) -> 4441.6667 | F7: =INDEX(Actuals!$D$39:$O$39,$A7) -> 3790.5833 | G7: =SUM($F$5:F7)-SUM($E$5:E7) -> 14.75
A8: 4 | B8: =INDEX(Lists!$B$5:$B$16,$A8) -> Apr | C8: =INDEX(Budget_FY2025!$D$12:$O$12,$A8) -> 83775 | D8: =INDEX(Actuals!$D$12:$O$12,$A8) -> 79023 | E8: =INDEX(Budget_FY2025!$D$39:$O$39,$A8) -> 5425.6667 | F8: =INDEX(Actuals!$D$39:$O$39,$A8) -> 4309.5833 | G8: =SUM($F$5:F8)-SUM($E$5:E8) -> -1101.3333
A9: 5 | B9: =INDEX(Lists!$B$5:$B$16,$A9) -> May | C9: =INDEX(Budget_FY2025!$D$12:$O$12,$A9) -> 83534 | D9: =INDEX(Actuals!$D$12:$O$12,$A9) -> 81946 | E9: =INDEX(Budget_FY2025!$D$39:$O$39,$A9) -> 5584.6667 | F9: =INDEX(Actuals!$D$39:$O$39,$A9) -> 5152.5833 | G9: =SUM($F$5:F9)-SUM($E$5:E9) -> -1533.4167
A10: 6 | B10: =INDEX(Lists!$B$5:$B$16,$A10) -> Jun | C10: =INDEX(Budget_FY2025!$D$12:$O$12,$A10) -> 81093 | D10: =INDEX(Actuals!$D$12:$O$12,$A10) -> 79418 | E10: =INDEX(Budget_FY2025!$D$39:$O$39,$A10) -> 4984.6667 | F10: =INDEX(Actuals!$D$39:$O$39,$A10) -> 4622.5833 | G10: =SUM($F$5:F10)-SUM($E$5:E10) -> -1895.5
A11: 7 | B11: =INDEX(Lists!$B$5:$B$16,$A11) -> Jul | C11: =INDEX(Budget_FY2025!$D$12:$O$12,$A11) -> 80482 | D11: =INDEX(Actuals!$D$12:$O$12,$A11) -> 81667 | E11: =INDEX(Budget_FY2025!$D$39:$O$39,$A11) -> 4904.6667 | F11: =INDEX(Actuals!$D$39:$O$39,$A11) -> 5130.5833 | G11: =SUM($F$5:F11)-SUM($E$5:E11) -> -1669.5833
A12: 8 | B12: =INDEX(Lists!$B$5:$B$16,$A12) -> Aug | C12: =INDEX(Budget_FY2025!$D$12:$O$12,$A12) -> 80093 | D12: =INDEX(Actuals!$D$12:$O$12,$A12) -> 81105 | E12: =INDEX(Budget_FY2025!$D$39:$O$39,$A12) -> 4671.6667 | F12: =INDEX(Actuals!$D$39:$O$39,$A12) -> 5093.5833 | G12: =SUM($F$5:F12)-SUM($E$5:E12) -> -1247.6667
A13: 9 | B13: =INDEX(Lists!$B$5:$B$16,$A13) -> Sep | C13: =INDEX(Budget_FY2025!$D$12:$O$12,$A13) -> 81141 | D13: =INDEX(Actuals!$D$12:$O$12,$A13) -> 82028 | E13: =INDEX(Budget_FY2025!$D$39:$O$39,$A13) -> 4745.6667 | F13: =INDEX(Actuals!$D$39:$O$39,$A13) -> 5013.5833 | G13: =SUM($F$5:F13)-SUM($E$5:E13) -> -979.75
A14: 10 | B14: =INDEX(Lists!$B$5:$B$16,$A14) -> Oct | C14: =INDEX(Budget_FY2025!$D$12:$O$12,$A14) -> 79550 | D14: =INDEX(Actuals!$D$12:$O$12,$A14) -> 83643 | E14: =INDEX(Budget_FY2025!$D$39:$O$39,$A14) -> 4508.6667 | F14: =INDEX(Actuals!$D$39:$O$39,$A14) -> 5588.5833 | G14: =SUM($F$5:F14)-SUM($E$5:E14) -> 100.16667
A15: 11 | B15: =INDEX(Lists!$B$5:$B$16,$A15) -> Nov | C15: =INDEX(Budget_FY2025!$D$12:$O$12,$A15) -> 82210 | D15: =INDEX(Actuals!$D$12:$O$12,$A15) -> 85801 | E15: =INDEX(Budget_FY2025!$D$39:$O$39,$A15) -> 4619.6667 | F15: =INDEX(Actuals!$D$39:$O$39,$A15) -> 5840.5833 | G15: =SUM($F$5:F15)-SUM($E$5:E15) -> 1321.0833
A16: 12 | B16: =INDEX(Lists!$B$5:$B$16,$A16) -> Dec | C16: =INDEX(Budget_FY2025!$D$12:$O$12,$A16) -> 87512 | D16: =INDEX(Actuals!$D$12:$O$12,$A16) -> 93902 | E16: =INDEX(Budget_FY2025!$D$39:$O$39,$A16) -> 5603.6667 | F16: =INDEX(Actuals!$D$39:$O$39,$A16) -> 7462.5833 | G16: =SUM($F$5:F16)-SUM($E$5:E16) -> 3180
B19: Expense line (selected period) | C19: Variance F / (U)
B20: =Variance!B22 -> Sales commissions & incentives | C20: =Variance!E22 -> 56
B21: =Variance!B23 -> Advertising & promotions | C21: =Variance!E23 -> 57
B22: =Variance!B24 -> Freight & delivery | C22: =Variance!E24 -> 73
B23: =Variance!B25 -> Warehouse rent & utilities | C23: =Variance!E25 -> -116
B24: =Variance!B26 -> Selling & logistics staff costs | C24: =Variance!E26 -> -38
B25: =Variance!B28 -> Salaries & wages (G&A) | C25: =Variance!E28 -> -40
B26: =Variance!B29 -> Employee benefits & contributions | C26: =Variance!E29 -> 24
B27: =Variance!B30 -> Professional fees | C27: =Variance!E30 -> 5
B28: =Variance!B31 -> Office rent & utilities | C28: =Variance!E31 -> 10
B29: =Variance!B32 -> Repairs & maintenance | C29: =Variance!E32 -> -8
B30: =Variance!B33 -> Taxes, licenses & insurance | C30: =Variance!E33 -> 20
B31: =Variance!B34 -> Communication, IT & supplies | C31: =Variance!E34 -> 16
B32: =Variance!B35 -> Bad debts & credit losses | C32: =Variance!E35 -> 3
B34: Largest unfavourable line | C34: =IF(MIN(C20:C32)<0,INDEX(B20:B32,MATCH(MIN(C20:C32),C20:C32,0)),"none") -> Warehouse rent & utilities
B35: Largest unfavourable amount | C35: =MIN(0,MIN(C20:C32)) -> -116
B36: Largest favourable line | C36: =IF(MAX(C20:C32)>0,INDEX(B20:B32,MATCH(MAX(C20:C32),C20:C32,0)),"none") -> Freight & delivery
B37: Largest favourable amount | C37: =MAX(0,MAX(C20:C32)) -> 73

Sheet Lists
B1: Lists and Selector Helpers
B2: Sampaguita Foods & Distribution Corporation (SFDC) | Drop-down sources
B3: =HYPERLINK("#Cover!A1","◄ Back to Cover") -> ◄ Back to Cover
B4: Month | C4: No. | E4: Item | F4: Value
B5: Jan | C5: 1 | E5: Selected month number | F5: =MATCH(Dashboard!$C$5,$B$5:$B$16,0) -> 4
B6: Feb | C6: 2 | E6: View mode | F6: =Dashboard!$F$5 -> Month
B7: Mar | C7: 3 | E7: Period label | F7: =IF(View_Mode="Month",INDEX($B$5:$B$16,Sel_M),"Jan-"&INDEX($B$5:$B$16,Sel_M)&" YTD")&" FY"&Act_Year -> Apr FY2025
B8: Apr | C8: 4 | E8: View options | F8: Month
B9: May | C9: 5 | F9: YTD
B10: Jun | C10: 6
B11: Jul | C11: 7
B12: Aug | C12: 8
B13: Sep | C13: 9
B14: Oct | C14: 10
B15: Nov | C15: 11
B16: Dec | C16: 12

Sheet Checks
B1: Model Integrity Checks
B2: Sampaguita Foods & Distribution Corporation (SFDC) | Every check compares two independently derived figures
B3: =HYPERLINK("#Cover!A1","◄ Back to Cover") -> ◄ Back to Cover
B5: Status | C5: =IF(COUNTIF(F8:F22,"✖*")=0,"✔ All 15 integrity checks passed","✖ "&COUNTIF(F8:F22,"✖*")&" of 15 checks failed - review Checks sheet") -> ✔ All 15 integrity checks passed
B7: # | C7: Check | D7: Difference | E7: Tolerance | F7: Result
B8: 1 | C8: Actual net sales FY (Actuals) = Project 1 income statement | D8: =Actuals!P12-INDEX(FS_Data!$C$7:$E$7,MATCH(Act_Year,{2023,2024,2025},0)) -> 0 | E8: 0.5 | F8: =IF(ABS(D8)<=E8,"✔ Pass","✖ Fail") -> ✔ Pass
B9: 2 | C9: Actual cost of sales FY = Project 1 | D9: =Actuals!P18-INDEX(FS_Data!$C$8:$E$8,MATCH(Act_Year,{2023,2024,2025},0)) -> 0 | E9: 0.5 | F9: =IF(ABS(D9)<=E9,"✔ Pass","✖ Fail") -> ✔ Pass
B10: 3 | C10: Actual selling & distribution expenses FY = Project 1 | D10: =Actuals!P27-INDEX(FS_Data!$C$9:$E$9,MATCH(Act_Year,{2023,2024,2025},0)) -> 0 | E10: 0.5 | F10: =IF(ABS(D10)<=E10,"✔ Pass","✖ Fail") -> ✔ Pass
B11: 4 | C11: Actual general & administrative expenses FY = Project 1 | D11: =Actuals!P36-INDEX(FS_Data!$C$10:$E$10,MATCH(Act_Year,{2023,2024,2025},0)) -> 0 | E11: 0.5 | F11: =IF(ABS(D11)<=E11,"✔ Pass","✖ Fail") -> ✔ Pass
B12: 5 | C12: Actual depreciation FY = Project 1 | D12: =Actuals!P37-Dep_Act -> 0 | E12: 0.5 | F12: =IF(ABS(D12)<=E12,"✔ Pass","✖ Fail") -> ✔ Pass
B13: 6 | C13: Actual operating profit FY = Project 1 operating profit | D13: =Actuals!P39-INDEX(FS_Data!$C$12:$E$12,MATCH(Act_Year,{2023,2024,2025},0)) -> 0 | E13: 0.5 | F13: =IF(ABS(D13)<=E13,"✔ Pass","✖ Fail") -> ✔ Pass
B14: 7 | C14: Budget gross profit = budget net sales - budget cost of sales (FY) | D14: =Budget_FY2025!P19-(SUM(Budget_FY2025!P8:P11)-SUM(Budget_FY2025!P14:P17)) -> 0 | E14: 0.5 | F14: =IF(ABS(D14)<=E14,"✔ Pass","✖ Fail") -> ✔ Pass
B15: 8 | C15: Variance sheet: operating profit variance = actual - budget | D15: =Variance!E39-(Variance!D39-Variance!C39) -> 0 | E15: 0.5 | F15: =IF(ABS(D15)<=E15,"✔ Pass","✖ Fail") -> ✔ Pass
B16: 9 | C16: Flex budget: static OP + activity + spending effects = actual OP | D16: =Flex_Budget!C31-Flex_Budget!E23 -> 0 | E16: 0.5 | F16: =IF(ABS(D16)<=E16,"✔ Pass","✖ Fail") -> ✔ Pass
B17: 10 | C17: Flex budget operating profit (actual column) = Variance actual operating profit | D17: =Flex_Budget!E23-Variance!D39 -> 0 | E17: 0.5 | F17: =IF(ABS(D17)<=E17,"✔ Pass","✖ Fail") -> ✔ Pass
B18: 11 | C18: Reforecast: months to date equal actuals (YTD operating profit) | D18: =SUMPRODUCT((Forecast!$D$6:$O$6<=Sel_M)*Forecast!$D18:$O18)-SUMPRODUCT((Actuals!$D$6:$O$6<=Sel_M)*Actuals!$D39:$O39) -> 0 | E18: 0.5 | F18: =IF(ABS(D18)<=E18,"✔ Pass","✖ Fail") -> ✔ Pass
B19: 12 | C19: Ledger: Data_Sales net sales for the year = Actuals net sales | D19: =SUMIFS(S_Sales,S_Year,Act_Year)-Actuals!P12 -> 0 | E19: 0.5 | F19: =IF(ABS(D19)<=E19,"✔ Pass","✖ Fail") -> ✔ Pass
B20: 13 | C20: Ledger: Data_Expenses for the year + depreciation = Actuals total operating expenses | D20: =SUMIFS(E_Amt,E_Year,Act_Year)+Dep_Act-Actuals!P38 -> 0 | E20: 0.5 | F20: =IF(ABS(D20)<=E20,"✔ Pass","✖ Fail") -> ✔ Pass
B21: 14 | C21: FY2026 budget: category net sales add to total | D21: =Budget_FY2026!P12-SUM(Budget_FY2026!P8:P11) -> 0 | E21: 0.5 | F21: =IF(ABS(D21)<=E21,"✔ Pass","✖ Fail") -> ✔ Pass
B22: 15 | C22: FY2026 budget: operating profit = gross profit - operating expenses | D22: =Budget_FY2026!P39-(Budget_FY2026!P19-Budget_FY2026!P38) -> 0 | E22: 0.5 | F22: =IF(ABS(D22)<=E22,"✔ Pass","✖ Fail") -> ✔ Pass
