Workbook

Sheet Cover
B2: PORTFOLIO PROJECT 01
B3: Financial Statement Analysis
B4: =Inputs!$C$6 -> Sampaguita Foods & Distribution Corporation (SFDC)
B5: ="Integrated three-statement model and analytical review | FY"&Inputs!D$22&" - FY"&Inputs!F$22 -> Integrated three-statement model and analytical review | FY2023 - FY2025
B7: ="Prepared by "&Inputs!$C$12&" | Version 1.0 | "&Inputs!$C$11 -> Prepared by Bengie Hirnani | Version 1.0 | PHP in thousands (unless otherwise stated)
B10: Model status | C10: =Model_Status -> ✔ All 23 integrity checks passed
B11: Scope | C11: Income statement, balance sheet, cash flow, changes in equity, notes, supporting schedules, horizontal, vertical, trend and common-size analysis, revenue and expense analysis, ratio analysis and an executive dashboard - all formula-driven from one inputs sheet and two transaction ledgers.
B12: Data notice | C12: The company, its figures and the ledgers are entirely fictional and were created for portfolio demonstration. Philippine tax rates are inputs - verify against current BIR rules before reuse.
B14: NAVIGATION - click a button to jump to a sheet
B15: FINANCIAL REPORTS
B16: =HYPERLINK("#Dashboard!A1","Dashboard") -> Dashboard | C16: Executive KPI dashboard with year selector and charts
B17: =HYPERLINK("#Income_Statement!A1","Income Statement") -> Income Statement | C17: Statement of comprehensive income (by function)
B18: =HYPERLINK("#Balance_Sheet!A1","Balance Sheet") -> Balance Sheet | C18: Statement of financial position
B19: =HYPERLINK("#Cash_Flow!A1","Cash Flow") -> Cash Flow | C19: Statement of cash flows (indirect method)
B20: =HYPERLINK("#Equity_Changes!A1","Equity Changes") -> Equity Changes | C20: Statement of changes in equity
B21: =HYPERLINK("#Notes_to_FS!A1","Notes to FS") -> Notes to FS | C21: Notes to the financial statements
B23: ANALYSIS
B24: =HYPERLINK("#Horizontal!A1","Horizontal") -> Horizontal | C24: Horizontal analysis: peso and % change, flags
B25: =HYPERLINK("#Vertical!A1","Vertical") -> Vertical | C25: Vertical analysis: % of net sales / total assets
B26: =HYPERLINK("#Common_Size!A1","Common Size") -> Common Size | C26: Common-size statements with year comparison
B27: =HYPERLINK("#Trend!A1","Trend") -> Trend | C27: Trend indices, CAGR and FY2026-27 projections
B28: =HYPERLINK("#Revenue_Analysis!A1","Revenue Analysis") -> Revenue Analysis | C28: Revenue by month, category, region, quarter (filters)
B29: =HYPERLINK("#Expense_Analysis!A1","Expense Analysis") -> Expense Analysis | C29: Expense analysis, cost behaviour and break-even
B30: =HYPERLINK("#Ratio_Analysis!A1","Ratio Analysis") -> Ratio Analysis | C30: Profitability, liquidity, solvency, efficiency, DuPont
B32: MODEL ENGINE AND CONTROLS
B33: =HYPERLINK("#Inputs!A1","Inputs") -> Inputs | C33: All assumptions and opening balances (blue cells)
B34: =HYPERLINK("#Schedules!A1","Schedules") -> Schedules | C34: PPE, working capital, borrowings and tax schedules
B35: =HYPERLINK("#Data_Sales!A1","Data Sales") -> Data Sales | C35: Monthly sales ledger by category and region
B36: =HYPERLINK("#Data_Expenses!A1","Data Expenses") -> Data Expenses | C36: Monthly operating expense ledger
B37: =HYPERLINK("#Chart_Data!A1","Chart Data") -> Chart Data | C37: Helper tables feeding dashboard charts
B38: =HYPERLINK("#Lists!A1","Lists") -> Lists | C38: Drop-down lists and named labels
B39: =HYPERLINK("#Checks!A1","Checks") -> Checks | C39: Model integrity checks
B40: =HYPERLINK("#Documentation!A1","Documentation") -> Documentation | C40: Purpose, structure, colour legend, assumptions, methodology

Sheet Documentation
B1: Model Documentation
B2: =Inputs!$C$6&" | "&Inputs!$C$11 -> Sampaguita Foods & Distribution Corporation (SFDC) | PHP in thousands (unless otherwise stated)
B3: =HYPERLINK("#Cover!A1","◄ Back to Cover") -> ◄ Back to Cover
B5: 1. PURPOSE AND BUSINESS CONTEXT
B6: Objective | C6: Demonstrate a professional, fully integrated financial statement analysis for a fictional Philippine distribution company: three linked statements, notes, schedules and a complete analytical review (horizontal, vertical, trend, common-size, revenue, expense, profitability, liquidity, solvency and efficiency).
B7: Company | C7: =Inputs!$C$6&" - "&Inputs!$C$9&". Head office: "&Inputs!$C$8&"." -> Sampaguita Foods & Distribution Corporation (SFDC) - Wholesale distribution of packaged food, beverages, household products and fresh & frozen goods. Head office: Taguig City, Metro Manila, Philippines (warehouses: Laguna, Cebu, Davao).
B8: Reporting basis | C8: Philippine Financial Reporting Standards (PFRS), expenses presented by function, financial year ending 31 December, amounts in PHP thousands.
B9: Shared company model | C9: Projects 2-6 of the portfolio (ratio dashboard, budgeting, cost accounting, internal control, tax computation) are built on this same fictional company so figures reconcile across deliverables.
B11: 2. HOW THE MODEL FLOWS
B12: Step 1 - Inputs | C12: Assumptions, opening balances (FY2022), working-capital drivers, PPE additions and disposals, loan movements, tax rates and the expense chart-of-accounts mapping are entered on Inputs (blue cells).
B13: Step 2 - Ledgers | C13: Data_Sales (monthly net sales and cost of sales by category and region) and Data_Expenses (monthly operating expenses by line) feed the income statement through SUMIFS and the analysis sheets through SUMIFS/SUMPRODUCT.
B14: Step 3 - Schedules | C14: Schedules computes PPE roll-forwards and depreciation, working-capital balances from DSO/DIO/DPO drivers, borrowings and finance costs, and the income tax computation (RCIT vs MCIT, final tax).
B15: Step 4 - Statements | C15: Income statement, balance sheet, cash flow (indirect method) and changes in equity are linked. Closing cash is derived from the cash flow statement, so the balance sheet balances by construction - the Checks sheet proves it.
B16: Step 5 - Analysis | C16: Horizontal, vertical, common-size, trend, revenue, expense and ratio sheets read the statements; the dashboard reads Chart_Data. Changing any input updates all of them.
B18: 3. SHEET INDEX
B19: Cover | C19: Title page, model status and navigation
B20: Documentation | C20: Purpose, structure, colour legend, assumptions, methodology
B21: Dashboard | C21: Executive KPI dashboard with year selector and charts
B22: Income Statement | C22: Statement of comprehensive income (by function)
B23: Balance Sheet | C23: Statement of financial position
B24: Cash Flow | C24: Statement of cash flows (indirect method)
B25: Equity Changes | C25: Statement of changes in equity
B26: Notes to FS | C26: Notes to the financial statements
B27: Schedules | C27: PPE, working capital, borrowings and tax schedules
B28: Horizontal | C28: Horizontal analysis: peso and % change, flags
B29: Vertical | C29: Vertical analysis: % of net sales / total assets
B30: Common Size | C30: Common-size statements with year comparison
... B40: Checks | C40: Model integrity checks
B42: 4. COLOUR AND FORMAT CONVENTIONS
B43: Blue text | C43: Hard-coded input or ledger data. Change these cells only.
B44: Black text | C44: Formula calculated on the same sheet.
B45: Green text | C45: Formula that links directly to another sheet.
B46: Yellow fill | C46: Key assumption or selector (drop-down) that drives results.
B47: Number formats | C47: Negative values appear in parentheses; zero appears as a dash; percentages to one decimal; multiples as 0.00x. Expenses are shown as negatives in the statements (positive in analysis tables).
B49: 5. KEY ASSUMPTIONS AND SIMPLIFICATIONS
B50: Tax | C50: Current income tax = higher of RCIT (25% of taxable income) and MCIT (2% of gross income); 20% final tax on bank interest. Rates are inputs. Deferred tax is not modelled.
B51: Working capital | C51: Receivables, inventories, payables, prepayments and accruals are driven by DSO, DIO, DPO and % of operating expenses so that sales changes flow through to cash.
B52: Depreciation | C52: Straight-line by asset class with half-year convention on additions and disposals, capped so net book value never goes negative. Land is not depreciated.
B53: Interest | C53: Finance costs use average balances. Interest income uses prior year-end cash, which avoids a circular reference.
B54: Dividends | C54: Declared and paid in the same year at a payout ratio of net profit.
B55: Not modelled | C55: Leases (PFRS 16), employee benefits (PAS 19), deferred tax (PAS 12 temporary differences), foreign currency, VAT mechanics (covered in Project 6).
B57: 6. EXCEL FEATURES USED
B58: Functions | C58: SUM, SUMIFS, COUNTIFS, SUMPRODUCT, SUBTOTAL, AGGREGATE, IF, IFERROR, AND, OR, INDEX/MATCH, VLOOKUP, OFFSET, CHOOSE-free dynamic selectors, TEXT, LEFT, UPPER, LOWER, ROUNDUP, ROUND, RANK, PERCENTILE, DATE, YEAR, MONTH, EOMONTH, NETWORKDAYS, WORKDAY, PMT, FORECAST, TREND, HYPERLINK.
B59: Controls | C59: Data validation (drop-downs and numeric limits on inputs), named ranges for ledgers and parameters, conditional formatting (checks, flags, data bars, colour scales), error handling with IFERROR, 23 integrity checks with a model-status banner, and sheet navigation links.
B60: Charts | C60: Native Excel charts linked to Chart_Data and the analysis sheets; they redraw when inputs or drop-down selections change.
B61: Pivot-style analysis | C61: Revenue_Analysis and Expense_Analysis provide pivot-style summaries with live filters using formulas. Native PivotTables and slicers can be added on top of the Data_Sales and Data_Expenses ranges (Insert > PivotTable) if desired.
B63: 7. HOW TO UPDATE
B64: Change a driver | C64: Edit a blue cell on Inputs (for example DSO for FY2025). All statements, ratios and charts update; confirm the Checks banner stays green.
B65: Add ledger rows | C65: Append rows at the bottom of Data_Sales or Data_Expenses and extend the named ranges (Formulas > Name Manager) to the new last row.
B66: Use real company data | C66: Replace the opening balances, drivers and ledgers with figures from the company's audited financial statements (SEC Form 17-A on PSE Edge for listed companies).

Sheet Dashboard
B1: Executive Dashboard
B2: =Inputs!$C$6&" | "&Inputs!$C$11 -> Sampaguita Foods & Distribution Corporation (SFDC) | PHP in thousands (unless otherwise stated)
B3: =HYPERLINK("#Cover!A1","◄ Back to Cover") -> ◄ Back to Cover
B5: Fiscal year | C5: 2025 | E5: Model integrity | F5: =Model_Status -> ✔ All 23 integrity checks passed
B7: NET SALES | E7: GROSS PROFIT | H7: EBITDA | K7: NET PROFIT
B8: =Chart_Data!F48 -> 972442 | E8: =Chart_Data!F49 -> 249894 | H8: =Chart_Data!F50 -> 82040 | K8: =Chart_Data!F51 -> 37406
B9: =IF(Chart_Data!H48="n/a","First year in model",IF(Chart_Data!H48>=0,"▲ ","▼ ")&TEXT(ABS(Chart_Data!H48),"0.0%")&" vs FY"&(Dash_Year-1)) -> ▲ 8.4% vs FY2024 | E9: =IF(Chart_Data!H49="n/a","First year in model",IF(Chart_Data!H49>=0,"▲ ","▼ ")&TEXT(ABS(Chart_Data!H49),"0.0%")&" vs FY"&(Dash_Year-1)) -> ▲ 9.3% vs FY2024 | H9: =IF(Chart_Data!H50="n/a","First year in model",IF(Chart_Data!H50>=0,"▲ ","▼ ")&TEXT(ABS(Chart_Data!H50),"0.0%")&" vs FY"&(Dash_Year-1)) -> ▲ 19.0% vs FY2024 | K9: =IF(Chart_Data!H51="n/a","First year in model",IF(Chart_Data!H51>=0,"▲ ","▼ ")&TEXT(ABS(Chart_Data!H51),"0.0%")&" vs FY"&(Dash_Year-1)) -> ▲ 28.9% vs FY2024
B11: TOTAL ASSETS | E11: TOTAL EQUITY | H11: NET DEBT | K11: FREE CASH FLOW
B12: =Chart_Data!F52 -> 478465 | E12: =Chart_Data!F53 -> 244502 | H12: =Chart_Data!F54 -> 51252 | K12: =Chart_Data!F55 -> 30860
B13: =IF(Chart_Data!H52="n/a","First year in model",IF(Chart_Data!H52>=0,"▲ ","▼ ")&TEXT(ABS(Chart_Data!H52),"0.0%")&" vs FY"&(Dash_Year-1)) -> ▲ 3.6% vs FY2024 | E13: =IF(Chart_Data!H53="n/a","First year in model",IF(Chart_Data!H53>=0,"▲ ","▼ ")&TEXT(ABS(Chart_Data!H53),"0.0%")&" vs FY"&(Dash_Year-1)) -> ▲ 12.0% vs FY2024 | H13: =IF(Chart_Data!H54="n/a","First year in model",IF(Chart_Data!H54>=0,"▲ ","▼ ")&TEXT(ABS(Chart_Data!H54),"0.0%")&" vs FY"&(Dash_Year-1)) -> ▼ 28.4% vs FY2024 | K13: =IF(Chart_Data!H55="n/a","First year in model",IF(Chart_Data!H55>=0,"▲ ","▼ ")&TEXT(ABS(Chart_Data!H55),"0.0%")&" vs FY"&(Dash_Year-1)) -> ▲ 131.2% vs FY2024
B80: KEY INSIGHTS (update automatically with the selected year)
B81: ="1. Net sales of PHP "&TEXT(Chart_Data!F48/1000,"#,##0.0")&" million "&IF(Chart_Data!H48="n/a","are the first year of the model period.",IF(Chart_Data!H48>=0,"grew ","fell ")&TEXT(ABS(Chart_Data!H48),"0.0%")&" year-on-year.") -> 1. Net sales of PHP 972.4 million grew 8.4% year-on-year.
B82: ="2. Margins: gross "&TEXT(INDEX(Ratio_Analysis!$D$7:$F$7,MATCH(Dash_Year,Ratio_Analysis!$D$5:$F$5,0)),"0.0%")&", EBITDA "&TEXT(INDEX(Ratio_Analysis!$D$8:$F$8,MATCH(Dash_Year,Ratio_Analysis!$D$5:$F$5,0)),"0.0%")&", net "&TEXT(INDEX(Ratio_Analysis!$D$10:$F$10,MATCH(Dash_Year,Ratio_Analysis!$D$5:$F$5,0)),"0.0%")&"; return on equity "&TEXT(INDEX(Ratio_Analysis!$D$12:$F$12,MATCH(Dash_Year,Ratio_Analysis!$D$5:$F$5,0)),"0.0%")&"." -> 2. Margins: gross 25.7%, EBITDA 8.4%, net 3.8%; return on equity 16.2%.
B83: ="3. Liquidity and leverage: current ratio "&TEXT(INDEX(Ratio_Analysis!$D$16:$F$16,MATCH(Dash_Year,Ratio_Analysis!$D$5:$F$5,0)),"0.00")&"x, borrowings-to-equity "&TEXT(INDEX(Ratio_Analysis!$D$24:$F$24,MATCH(Dash_Year,Ratio_Analysis!$D$5:$F$5,0)),"0.00")&"x, interest cover "&TEXT(INDEX(Ratio_Analysis!$D$28:$F$28,MATCH(Dash_Year,Ratio_Analysis!$D$5:$F$5,0)),"0.0")&"x, net debt "&TEXT(INDEX(Ratio_Analysis!$D$30:$F$30,MATCH(Dash_Year,Ratio_Analysis!$D$5:$F$5,0)),"0.0")&"x EBITDA." -> 3. Liquidity and leverage: current ratio 1.76x, borrowings-to-equity 0.54x, interest cover 5.2x, net debt 0.6x EBITDA.
B84: ="4. Cash: operating cash flow converts "&TEXT(INDEX(Ratio_Analysis!$D$47:$F$47,MATCH(Dash_Year,Ratio_Analysis!$D$5:$F$5,0)),"0%")&" of net profit; free cash flow is PHP "&TEXT(Chart_Data!F55/1000,"#,##0.0")&" million." -> 4. Cash: operating cash flow converts 154% of net profit; free cash flow is PHP 30.9 million.
B85: ="5. Largest category: "&INDEX(Chart_Data!B19:B22,MATCH(MAX(Chart_Data!C19:C22),Chart_Data!C19:C22,0))&" at "&TEXT(MAX(Chart_Data!C19:C22)/SUM(Chart_Data!C19:C22),"0%")&" of net sales." -> 5. Largest category: Packaged Food at 39% of net sales.

Sheet Income_Statement
B1: Statement of Comprehensive Income
B2: =Inputs!$C$6&" | "&Inputs!$C$11 -> Sampaguita Foods & Distribution Corporation (SFDC) | PHP in thousands (unless otherwise stated)
B3: =HYPERLINK("#Cover!A1","◄ Back to Cover") -> ◄ Back to Cover
B4: For the years ended 31 December
B5: PHP '000 | D5: =Inputs!D$22 -> 2023 | E5: =Inputs!E$22 -> 2024 | F5: =Inputs!F$22 -> 2025 | G5: Note
B6: CONTINUING OPERATIONS
B7: Net sales | D7: =SUMIFS(Sales_Net,Sales_Year,D$5) -> 821118 | E7: =SUMIFS(Sales_Net,Sales_Year,E$5) -> 897238 | F7: =SUMIFS(Sales_Net,Sales_Year,F$5) -> 972442 | G7: Note 9
B8: Cost of sales | D8: =-SUMIFS(Sales_COGS,Sales_Year,D$5) -> -613977 | E8: =-SUMIFS(Sales_COGS,Sales_Year,E$5) -> -668558 | F8: =-SUMIFS(Sales_COGS,Sales_Year,F$5) -> -722548 | G8: Note 10
B9: Gross profit | D9: =SUM(D7:D8) -> 207141 | E9: =SUM(E7:E8) -> 228680 | F9: =SUM(F7:F8) -> 249894
B10: Selling and distribution expenses | D10: =-SUMIFS(Exp_Amt,Exp_Year,D$5,Exp_Func,Func_SD) -> -93216 | E10: =-SUMIFS(Exp_Amt,Exp_Year,E$5,Exp_Func,Func_SD) -> -99930 | F10: =-SUMIFS(Exp_Amt,Exp_Year,F$5,Exp_Func,Func_SD) -> -106077 | G10: Note 10
B11: General and administrative expenses | D11: =-SUMIFS(Exp_Amt,Exp_Year,D$5,Exp_Func,Func_GA) -> -58315 | E11: =-SUMIFS(Exp_Amt,Exp_Year,E$5,Exp_Func,Func_GA) -> -61197 | F11: =-SUMIFS(Exp_Amt,Exp_Year,F$5,Exp_Func,Func_GA) -> -63827 | G11: Note 10
B12: Depreciation | D12: =-Schedules!D62 -> -17389 | E12: =-Schedules!E62 -> -19250 | F12: =-Schedules!F62 -> -21257 | G12: Note 6
B13: Operating profit | D13: =SUM(D9:D12) -> 38221 | E13: =SUM(E9:E12) -> 48303 | F13: =SUM(F9:F12) -> 58733
B14: Gain / (loss) on disposal of property and equipment | D14: =Schedules!D67 -> 400 | E14: =Schedules!E67 -> -150 | F14: =Schedules!F67 -> 350
B15: Other income | D15: =Inputs!D27 -> 1350 | E15: =Inputs!E27 -> 1520 | F15: =Inputs!F27 -> 1700
B16: Interest income | D16: =Schedules!D91 -> 775 | E16: =Schedules!E91 -> 873 | F16: =Schedules!F91 -> 1207
B17: Finance costs | D17: =-Schedules!D90 -> -10421 | E17: =-Schedules!E90 -> -11475 | F17: =-Schedules!F90 -> -11696 | G17: Note 7
B18: Profit before income tax | D18: =SUM(D13:D17) -> 30325 | E18: =SUM(E13:E17) -> 39071 | F18: =SUM(F13:F17) -> 50294
B19: Income tax expense | D19: =-Schedules!D103 -> -7843 | E19: =-Schedules!E103 -> -10062 | F19: =-Schedules!F103 -> -12888 | G19: Note 11
B20: Net profit for the year | D20: =SUM(D18:D19) -> 22482 | E20: =SUM(E18:E19) -> 29009 | F20: =SUM(F18:F19) -> 37406
B22: MEMORANDUM ITEMS
B23: EBIT (operating profit + gains and other income) | D23: =SUM(D13:D15) -> 39971 | E23: =SUM(E13:E15) -> 49673 | F23: =SUM(F13:F15) -> 60783
B24: EBITDA | D24: =D23-D12 -> 57360 | E24: =E23-E12 -> 68923 | F24: =F23-F12 -> 82040
B25: Total operating expenses (selling, G&A and depreciation) | D25: =-SUM(D10:D12) -> 168920 | E25: =-SUM(E10:E12) -> 180377 | F25: =-SUM(F10:F12) -> 191161

Sheet Balance_Sheet
B1: Statement of Financial Position
B2: =Inputs!$C$6&" | "&Inputs!$C$11 -> Sampaguita Foods & Distribution Corporation (SFDC) | PHP in thousands (unless otherwise stated)
B3: =HYPERLINK("#Cover!A1","◄ Back to Cover") -> ◄ Back to Cover
B4: As at 31 December
B5: PHP '000 | C5: =Inputs!C$22 -> 2022 | D5: =Inputs!D$22 -> 2023 | E5: =Inputs!E$22 -> 2024 | F5: =Inputs!F$22 -> 2025 | G5: Note
B6: ASSETS
B7: Current assets
B8: Cash and cash equivalents | C8: =Inputs!C38 -> 62000 | D8: =Cash_Flow!D40 -> 58216 | E8: =Cash_Flow!E40 -> 80460 | F8: =Cash_Flow!F40 -> 81748 | G8: Note 3
B9: Trade and other receivables | C9: =Schedules!C73 -> 71000 | D9: =Schedules!D73 -> 80987 | E9: =Schedules!E73 -> 88495 | F9: =Schedules!F73 -> 93248 | G9: Note 4
B10: Inventories | C10: =Schedules!C74 -> 74500 | D10: =Schedules!D74 -> 75696 | E10: =Schedules!E74 -> 80593 | F10: =Schedules!F74 -> 85122 | G10: Note 5
B11: Prepayments and other current assets | C11: =Schedules!C75 -> 11200 | D11: =Schedules!D75 -> 11365 | E11: =Schedules!E75 -> 12085 | F11: =Schedules!F75 -> 12743
B12: Total current assets | C12: =SUM(C8:C11) -> 218700 | D12: =SUM(D8:D11) -> 226264 | E12: =SUM(E8:E11) -> 261633 | F12: =SUM(F8:F11) -> 272861
B13: Non-current assets
B14: Property, plant and equipment, net | C14: =Schedules!C60 -> 174700 | D14: =Schedules!D60 -> 178711 | E14: =Schedules!E60 -> 189761 | F14: =Schedules!F60 -> 194504 | G14: Note 6
B15: Other non-current assets | C15: =Inputs!C50 -> 9800 | D15: =Inputs!D50 -> 10200 | E15: =Inputs!E50 -> 10500 | F15: =Inputs!F50 -> 11100
B16: Total non-current assets | C16: =SUM(C14:C15) -> 184500 | D16: =SUM(D14:D15) -> 188911 | E16: =SUM(E14:E15) -> 200261 | F16: =SUM(F14:F15) -> 205604
B17: TOTAL ASSETS | C17: =C12+C16 -> 403200 | D17: =D12+D16 -> 415175 | E17: =E12+E16 -> 461894 | F17: =F12+F16 -> 478465
B19: LIABILITIES AND EQUITY
B20: Current liabilities
B21: Trade and other payables | C21: =Schedules!C76 -> 62300 | D21: =Schedules!D76 -> 67285 | E21: =Schedules!E76 -> 75098 | F21: =Schedules!F76 -> 83143
B22: Accrued expenses | C22: =Schedules!C77 -> 13400 | D22: =Schedules!D77 -> 13638 | E22: =Schedules!E77 -> 14501 | F22: =Schedules!F77 -> 15291
B23: Income tax payable | C23: =Schedules!C105 -> 2800 | D23: =Schedules!D105 -> 1691 | E23: =Schedules!E105 -> 1977 | F23: =Schedules!F105 -> 2529 | G23: Note 11
B24: Short-term loans | C24: =Schedules!C80 -> 45000 | D24: =Schedules!D80 -> 48000 | E24: =Schedules!E80 -> 42000 | F24: =Schedules!F80 -> 38000 | G24: Note 7
B25: Current portion of long-term loans | C25: =Schedules!C85 -> 12000 | D25: =Schedules!D85 -> 13000 | E25: =Schedules!E85 -> 15000 | F25: =Schedules!F85 -> 16500 | G25: Note 7
B26: Total current liabilities | C26: =SUM(C21:C25) -> 135500 | D26: =SUM(D21:D25) -> 143614 | E26: =SUM(E21:E25) -> 148576 | F26: =SUM(F21:F25) -> 155463
B27: Non-current liabilities
B28: Long-term loans, net of current portion | C28: =Schedules!C86 -> 88000 | D28: =Schedules!D86 -> 75000 | E28: =Schedules!E86 -> 95000 | F28: =Schedules!F86 -> 78500 | G28: Note 7
B29: Total liabilities | C29: =C26+C28 -> 223500 | D29: =D26+D28 -> 218614 | E29: =E26+E28 -> 243576 | F29: =F26+F28 -> 233963
B30: Equity
B31: Share capital | C31: =Inputs!C46 -> 120000 | D31: =Equity_Changes!C11 -> 120000 | E31: =Equity_Changes!C19 -> 120000 | F31: =Equity_Changes!C27 -> 120000 | G31: Note 8
B32: Additional paid-in capital | C32: =Inputs!C47 -> 18000 | D32: =Equity_Changes!D11 -> 18000 | E32: =Equity_Changes!D19 -> 18000 | F32: =Equity_Changes!D27 -> 18000 | G32: Note 8
B33: Retained earnings | C33: =Inputs!C48 -> 41700 | D33: =Equity_Changes!E11 -> 58561 | E33: =Equity_Changes!E19 -> 80318 | F33: =Equity_Changes!E27 -> 106502 | G33: Note 8
B34: Total equity | C34: =SUM(C31:C33) -> 179700 | D34: =SUM(D31:D33) -> 196561 | E34: =SUM(E31:E33) -> 218318 | F34: =SUM(F31:F33) -> 244502
B35: TOTAL LIABILITIES AND EQUITY | C35: =C29+C34 -> 403200 | D35: =D29+D34 -> 415175 | E35: =E29+E34 -> 461894 | F35: =F29+F34 -> 478465
B37: Balance check (assets less liabilities and equity) | C37: =ROUND(C17-C35,0) -> 0 | D37: =ROUND(D17-D35,0) -> 0 | E37: =ROUND(E17-E35,0) -> 0 | F37: =ROUND(F17-F35,0) -> 0

Sheet Cash_Flow
B1: Statement of Cash Flows (Indirect Method)
B2: =Inputs!$C$6&" | "&Inputs!$C$11 -> Sampaguita Foods & Distribution Corporation (SFDC) | PHP in thousands (unless otherwise stated)
B3: =HYPERLINK("#Cover!A1","◄ Back to Cover") -> ◄ Back to Cover
B4: For the years ended 31 December
B5: PHP '000 | D5: =Inputs!D$22 -> 2023 | E5: =Inputs!E$22 -> 2024 | F5: =Inputs!F$22 -> 2025
B6: CASH FLOWS FROM OPERATING ACTIVITIES
B7: Profit before income tax | D7: =Income_Statement!D18 -> 30325 | E7: =Income_Statement!E18 -> 39071 | F7: =Income_Statement!F18 -> 50294
B8: Adjustments: depreciation | D8: =-Income_Statement!D12 -> 17389 | E8: =-Income_Statement!E12 -> 19250 | F8: =-Income_Statement!F12 -> 21257
B9: Adjustments: (gain) / loss on disposal | D9: =-Income_Statement!D14 -> -400 | E9: =-Income_Statement!E14 -> 150 | F9: =-Income_Statement!F14 -> -350
B10: Adjustments: interest income | D10: =-Income_Statement!D16 -> -775 | E10: =-Income_Statement!E16 -> -873 | F10: =-Income_Statement!F16 -> -1207
B11: Adjustments: finance costs | D11: =-Income_Statement!D17 -> 10421 | E11: =-Income_Statement!E17 -> 11475 | F11: =-Income_Statement!F17 -> 11696
B12: Operating profit before working capital changes | D12: =SUM(D7:D11) -> 56960 | E12: =SUM(E7:E11) -> 69073 | F12: =SUM(F7:F11) -> 81690
B13: (Increase) / decrease in trade and other receivables | D13: =Balance_Sheet!C9-Balance_Sheet!D9 -> -9987 | E13: =Balance_Sheet!D9-Balance_Sheet!E9 -> -7508 | F13: =Balance_Sheet!E9-Balance_Sheet!F9 -> -4753
B14: (Increase) / decrease in inventories | D14: =Balance_Sheet!C10-Balance_Sheet!D10 -> -1196 | E14: =Balance_Sheet!D10-Balance_Sheet!E10 -> -4897 | F14: =Balance_Sheet!E10-Balance_Sheet!F10 -> -4529
B15: (Increase) / decrease in prepayments | D15: =Balance_Sheet!C11-Balance_Sheet!D11 -> -165 | E15: =Balance_Sheet!D11-Balance_Sheet!E11 -> -720 | F15: =Balance_Sheet!E11-Balance_Sheet!F11 -> -658
B16: Increase / (decrease) in trade and other payables | D16: =Balance_Sheet!D21-Balance_Sheet!C21 -> 4985 | E16: =Balance_Sheet!E21-Balance_Sheet!D21 -> 7813 | F16: =Balance_Sheet!F21-Balance_Sheet!E21 -> 8045
B17: Increase / (decrease) in accrued expenses | D17: =Balance_Sheet!D22-Balance_Sheet!C22 -> 238 | E17: =Balance_Sheet!E22-Balance_Sheet!D22 -> 863 | F17: =Balance_Sheet!F22-Balance_Sheet!E22 -> 790
B18: Cash generated from operations | D18: =D12+SUM(D13:D17) -> 50835 | E18: =E12+SUM(E13:E17) -> 64624 | F18: =F12+SUM(F13:F17) -> 80585
B19: Interest received | D19: =Schedules!D91 -> 775 | E19: =Schedules!E91 -> 873 | F19: =Schedules!F91 -> 1207
B20: Interest paid | D20: =-Schedules!D90 -> -10421 | E20: =-Schedules!E90 -> -11475 | F20: =-Schedules!F90 -> -11696
B21: Income taxes paid | D21: =-Schedules!D106 -> -8952 | E21: =-Schedules!E106 -> -9776 | F21: =-Schedules!F106 -> -12336
B22: Net cash from operating activities | D22: =SUM(D18:D21) -> 32237 | E22: =SUM(E18:E21) -> 44246 | F22: =SUM(F18:F21) -> 57760
B24: CASH FLOWS FROM INVESTING ACTIVITIES
B25: Purchase of property, plant and equipment | D25: =-Schedules!D61 -> -22100 | E25: =-Schedules!E61 -> -30900 | F25: =-Schedules!F61 -> -26900
B26: Proceeds from disposal of property and equipment | D26: =Schedules!D66 -> 1100 | E26: =Schedules!E66 -> 450 | F26: =Schedules!F66 -> 1250
B27: (Increase) / decrease in other non-current assets | D27: =Balance_Sheet!C15-Balance_Sheet!D15 -> -400 | E27: =Balance_Sheet!D15-Balance_Sheet!E15 -> -300 | F27: =Balance_Sheet!E15-Balance_Sheet!F15 -> -600
B28: Net cash used in investing activities | D28: =SUM(D25:D27) -> -21400 | E28: =SUM(E25:E27) -> -30750 | F28: =SUM(F25:F27) -> -26250
B30: CASH FLOWS FROM FINANCING ACTIVITIES
B31: Proceeds from long-term loans | D31: =Schedules!D82 -> 0 | E31: =Schedules!E82 -> 35000 | F31: =Schedules!F82 -> 0
B32: Repayment of long-term loans | D32: =Schedules!D83 -> -12000 | E32: =Schedules!E83 -> -13000 | F32: =Schedules!F83 -> -15000
B33: Net proceeds from / (repayment of) short-term loans | D33: =Balance_Sheet!D24-Balance_Sheet!C24 -> 3000 | E33: =Balance_Sheet!E24-Balance_Sheet!D24 -> -6000 | F33: =Balance_Sheet!F24-Balance_Sheet!E24 -> -4000
B34: Proceeds from issuance of shares | D34: =Inputs!D55+Inputs!D56 -> 0 | E34: =Inputs!E55+Inputs!E56 -> 0 | F34: =Inputs!F55+Inputs!F56 -> 0
B35: Dividends paid | D35: =Equity_Changes!E9 -> -5621 | E35: =Equity_Changes!E17 -> -7252 | F35: =Equity_Changes!E25 -> -11222
B36: Net cash from / (used in) financing activities | D36: =SUM(D31:D35) -> -14621 | E36: =SUM(E31:E35) -> 8748 | F36: =SUM(F31:F35) -> -30222
B38: Net increase / (decrease) in cash and cash equivalents | D38: =D22+D28+D36 -> -3784 | E38: =E22+E28+E36 -> 22244 | F38: =F22+F28+F36 -> 1288
B39: Cash and cash equivalents at beginning of year | D39: =Balance_Sheet!C8 -> 62000 | E39: =Balance_Sheet!D8 -> 58216 | F39: =Balance_Sheet!E8 -> 80460
B40: Cash and cash equivalents at end of year | D40: =D39+D38 -> 58216 | E40: =E39+E38 -> 80460 | F40: =F39+F38 -> 81748
B42: MEMORANDUM
B43: Free cash flow (operating cash flow less capital expenditure) | D43: =D22+D25 -> 10137 | E43: =E22+E25 -> 13346 | F43: =F22+F25 -> 30860

Sheet Equity_Changes
B1: Statement of Changes in Equity
B2: =Inputs!$C$6&" | "&Inputs!$C$11 -> Sampaguita Foods & Distribution Corporation (SFDC) | PHP in thousands (unless otherwise stated)
B3: =HYPERLINK("#Cover!A1","◄ Back to Cover") -> ◄ Back to Cover
B5: PHP '000 | C5: Share capital | D5: Additional paid-in capital | E5: Retained earnings | F5: Total equity
B6: ="Year ended 31 December "&Inputs!D$22 -> Year ended 31 December 2023
B7: Balance at 1 January | C7: =Inputs!C46 -> 120000 | D7: =Inputs!C47 -> 18000 | E7: =Inputs!C48 -> 41700 | F7: =SUM(C7:E7) -> 179700
B8: Net profit for the year | E8: =Income_Statement!D20 -> 22482 | F8: =SUM(C8:E8) -> 22482
B9: Cash dividends declared and paid | E9: =-MAX(0,ROUND(Inputs!D30*E8,0)) -> -5621 | F9: =SUM(C9:E9) -> -5621
B10: Issuance of shares | C10: =Inputs!D55 -> 0 | D10: =Inputs!D56 -> 0 | F10: =SUM(C10:E10) -> 0
B11: Balance at 31 December | C11: =SUM(C7:C10) -> 120000 | D11: =SUM(D7:D10) -> 18000 | E11: =SUM(E7:E10) -> 58561 | F11: =SUM(C11:E11) -> 196561
B14: ="Year ended 31 December "&Inputs!E$22 -> Year ended 31 December 2024
B15: Balance at 1 January | C15: =C11 -> 120000 | D15: =D11 -> 18000 | E15: =E11 -> 58561 | F15: =SUM(C15:E15) -> 196561
B16: Net profit for the year | E16: =Income_Statement!E20 -> 29009 | F16: =SUM(C16:E16) -> 29009
B17: Cash dividends declared and paid | E17: =-MAX(0,ROUND(Inputs!E30*E16,0)) -> -7252 | F17: =SUM(C17:E17) -> -7252
B18: Issuance of shares | C18: =Inputs!E55 -> 0 | D18: =Inputs!E56 -> 0 | F18: =SUM(C18:E18) -> 0
B19: Balance at 31 December | C19: =SUM(C15:C18) -> 120000 | D19: =SUM(D15:D18) -> 18000 | E19: =SUM(E15:E18) -> 80318 | F19: =SUM(C19:E19) -> 218318
B22: ="Year ended 31 December "&Inputs!F$22 -> Year ended 31 December 2025
B23: Balance at 1 January | C23: =C19 -> 120000 | D23: =D19 -> 18000 | E23: =E19 -> 80318 | F23: =SUM(C23:E23) -> 218318
B24: Net profit for the year | E24: =Income_Statement!F20 -> 37406 | F24: =SUM(C24:E24) -> 37406
B25: Cash dividends declared and paid | E25: =-MAX(0,ROUND(Inputs!F30*E24,0)) -> -11222 | F25: =SUM(C25:E25) -> -11222
B26: Issuance of shares | C26: =Inputs!F55 -> 0 | D26: =Inputs!F56 -> 0 | F26: =SUM(C26:E26) -> 0
B27: Balance at 31 December | C27: =SUM(C23:C26) -> 120000 | D27: =SUM(D23:D26) -> 18000 | E27: =SUM(E23:E26) -> 106502 | F27: =SUM(C27:E27) -> 244502

Sheet Notes_to_FS
B1: Notes to the Financial Statements
B2: =Inputs!$C$6&" | "&Inputs!$C$11 -> Sampaguita Foods & Distribution Corporation (SFDC) | PHP in thousands (unless otherwise stated)
B3: =HYPERLINK("#Cover!A1","◄ Back to Cover") -> ◄ Back to Cover
B5: NOTE 1 - CORPORATE INFORMATION
B6: =Inputs!$C$6&" (the Company) is a domestic corporation registered in the Philippines with its head office in "&Inputs!$C$8&". The Company is engaged in the "&LOWER(Inputs!$C$9)&". The financial statements are presented in Philippine peso, the Company's functional currency, rounded to the nearest thousand unless otherwise stated. All names and figures are fictional and prepared for portfolio demonstration." -> Sampaguita Foods & Distribution Corporation (SFDC) (the Company) is a domestic corporation registered in the Philippines with its head office in Taguig City, Metro Manila, Philippines (warehouses: Laguna, Cebu, Davao). The Company is engaged in the wholesale distribution of packaged food, beverages, household products and fresh & frozen goods. The financial statements are presented in Philippine peso, the Company's functional currency, rounded to the nearest thousand unless otherwise stated. All names and figures are fictional and prepared for portfolio demonstration.
B8: NOTE 2 - BASIS OF PREPARATION AND SIGNIFICANT ACCOUNTING POLICIES
B9: Statement of compliance. The financial statements are prepared in accordance with Philippine Financial Reporting Standards (PFRS) under the historical cost convention, using the accrual basis, with expenses presented by function.
B10: Revenue (PFRS 15). Revenue from the wholesale distribution of goods is recognised at a point in time when control transfers to the customer on delivery, net of trade discounts, returns and value-added tax.
B11: Inventories (PAS 2). Merchandise inventories are stated at the lower of cost (weighted average) and net realisable value.
B12: Property, plant and equipment (PAS 16). Stated at cost less accumulated depreciation. Depreciation is computed on a straight-line basis over the estimated useful lives of the assets (see Inputs); land is not depreciated. Gains and losses on disposal are recognised in profit or loss.
B13: Income taxes (PAS 12). Current income tax is the higher of the regular corporate income tax (RCIT) on taxable income and the minimum corporate income tax (MCIT) on gross income. Interest income from bank deposits is subject to final tax. Deferred tax is not modelled because temporary differences are assumed to be immaterial.
B14: Financial instruments (PFRS 9). Receivables and payables are measured at amortised cost; credit losses are recognised through the bad debts expense line.
B15: Model scope. Leases (PFRS 16), employee benefits (PAS 19) and deferred taxes are outside the scope of this illustrative model.
B17: NOTE 3 - CASH AND CASH EQUIVALENTS
B18: PHP '000 | D18: =Inputs!D$22 -> 2023 | E18: =Inputs!E$22 -> 2024 | F18: =Inputs!F$22 -> 2025
B19: Cash on hand | D19: =ROUND(Balance_Sheet!D8*Inputs!D58,0) -> 873 | E19: =ROUND(Balance_Sheet!E8*Inputs!E58,0) -> 1207 | F19: =ROUND(Balance_Sheet!F8*Inputs!F58,0) -> 1226
B20: Short-term placements (maturity of three months or less) | D20: =ROUND(Balance_Sheet!D8*Inputs!D59,0) -> 6986 | E20: =ROUND(Balance_Sheet!E8*Inputs!E59,0) -> 9655 | F20: =ROUND(Balance_Sheet!F8*Inputs!F59,0) -> 9810
B21: Cash in banks | D21: =Balance_Sheet!D8-D19-D20 -> 50357 | E21: =Balance_Sheet!E8-E19-E20 -> 69598 | F21: =Balance_Sheet!F8-F19-F20 -> 70712
B22: Total cash and cash equivalents | D22: =SUM(D19:D21) -> 58216 | E22: =SUM(E19:E21) -> 80460 | F22: =SUM(F19:F21) -> 81748
B24: NOTE 4 - TRADE AND OTHER RECEIVABLES (AGEING)
B25: PHP '000 | D25: =Inputs!D$22 -> 2023 | E25: =Inputs!E$22 -> 2024 | F25: =Inputs!F$22 -> 2025
B26: 31-60 days | D26: =ROUND(Balance_Sheet!D9*Inputs!D60,0) -> 14578 | E26: =ROUND(Balance_Sheet!E9*Inputs!E60,0) -> 15044 | F26: =ROUND(Balance_Sheet!F9*Inputs!F60,0) -> 14920
B27: 61-90 days | D27: =ROUND(Balance_Sheet!D9*Inputs!D61,0) -> 5669 | E27: =ROUND(Balance_Sheet!E9*Inputs!E61,0) -> 5752 | F27: =ROUND(Balance_Sheet!F9*Inputs!F61,0) -> 5595
B28: Over 90 days | D28: =ROUND(Balance_Sheet!D9*Inputs!D62,0) -> 2835 | E28: =ROUND(Balance_Sheet!E9*Inputs!E62,0) -> 2655 | F28: =ROUND(Balance_Sheet!F9*Inputs!F62,0) -> 2331
B29: Current (0-30 days) | D29: =Balance_Sheet!D9-D26-D27-D28 -> 57905 | E29: =Balance_Sheet!E9-E26-E27-E28 -> 65044 | F29: =Balance_Sheet!F9-F26-F27-F28 -> 70402
B30: Total trade and other receivables | D30: =D29+D26+D27+D28 -> 80987 | E30: =E29+E26+E27+E28 -> 88495 | F30: =F29+F26+F27+F28 -> 93248
B31: Over 90 days as % of total receivables | D31: =IFERROR(D28/D30,0) -> 0.035005618 | E31: =IFERROR(E28/E30,0) -> 0.030001695 | F31: =IFERROR(F28/F30,0) -> 0.024997855
B32: Days sales outstanding | D32: =IFERROR(Balance_Sheet!D9/Income_Statement!D7*Days_Year,0) -> 36.000009 | E32: =IFERROR(Balance_Sheet!E9/Income_Statement!E7*Days_Year,0) -> 36.000119 | F32: =IFERROR(Balance_Sheet!F9/Income_Statement!F7*Days_Year,0) -> 35.000051
B34: NOTE 5 - INVENTORIES (BY PRODUCT CATEGORY)
B35: PHP '000 | D35: =Inputs!D$22 -> 2023 | E35: =Inputs!E$22 -> 2024 | F35: =Inputs!F$22 -> 2025
B36: Packaged Food | D36: =ROUND(Balance_Sheet!D10*SUMIFS(Sales_COGS,Sales_Year,Inputs!D$22,Sales_Cat,"Packaged Food")/SUMIFS(Sales_COGS,Sales_Year,Inputs!D$22),0) -> 30854 | E36: =ROUND(Balance_Sheet!E10*SUMIFS(Sales_COGS,Sales_Year,Inputs!E$22,Sales_Cat,"Packaged Food")/SUMIFS(Sales_COGS,Sales_Year,Inputs!E$22),0) -> 32463 | F36: =ROUND(Balance_Sheet!F10*SUMIFS(Sales_COGS,Sales_Year,Inputs!F$22,Sales_Cat,"Packaged Food")/SUMIFS(Sales_COGS,Sales_Year,Inputs!F$22),0) -> 33775
B37: Beverages | D37: =ROUND(Balance_Sheet!D10*SUMIFS(Sales_COGS,Sales_Year,Inputs!D$22,Sales_Cat,"Beverages")/SUMIFS(Sales_COGS,Sales_Year,Inputs!D$22),0) -> 21726 | E37: =ROUND(Balance_Sheet!E10*SUMIFS(Sales_COGS,Sales_Year,Inputs!E$22,Sales_Cat,"Beverages")/SUMIFS(Sales_COGS,Sales_Year,Inputs!E$22),0) -> 23390 | F37: =ROUND(Balance_Sheet!F10*SUMIFS(Sales_COGS,Sales_Year,Inputs!F$22,Sales_Cat,"Beverages")/SUMIFS(Sales_COGS,Sales_Year,Inputs!F$22),0) -> 25140
B38: Household & Personal Care | D38: =ROUND(Balance_Sheet!D10*SUMIFS(Sales_COGS,Sales_Year,Inputs!D$22,Sales_Cat,"Household & Personal Care")/SUMIFS(Sales_COGS,Sales_Year,Inputs!D$22),0) -> 13000 | E38: =ROUND(Balance_Sheet!E10*SUMIFS(Sales_COGS,Sales_Year,Inputs!E$22,Sales_Cat,"Household & Personal Care")/SUMIFS(Sales_COGS,Sales_Year,Inputs!E$22),0) -> 13600 | F38: =ROUND(Balance_Sheet!F10*SUMIFS(Sales_COGS,Sales_Year,Inputs!F$22,Sales_Cat,"Household & Personal Care")/SUMIFS(Sales_COGS,Sales_Year,Inputs!F$22),0) -> 14064
B39: Fresh & Frozen | D39: =Balance_Sheet!D10-SUM(D36:D38) -> 10116 | E39: =Balance_Sheet!E10-SUM(E36:E38) -> 11140 | F39: =Balance_Sheet!F10-SUM(F36:F38) -> 12143 | G39: Remainder so the note ties to the balance sheet
B40: Total inventories (allocated on cost-of-sales mix) | D40: =SUM(D36:D39) -> 75696 | E40: =SUM(E36:E39) -> 80593 | F40: =SUM(F36:F39) -> 85122
B41: Days inventory on hand | D41: =IFERROR(Balance_Sheet!D10/-Income_Statement!D8*Days_Year,0) -> 45.000122 | E41: =IFERROR(Balance_Sheet!E10/-Income_Statement!E8*Days_Year,0) -> 43.99984 | F41: =IFERROR(Balance_Sheet!F10/-Income_Statement!F8*Days_Year,0) -> 42.999953
B43: NOTE 6 - PROPERTY, PLANT AND EQUIPMENT
B44: PHP '000 | D44: =Inputs!D$22 -> 2023 | E44: =Inputs!E$22 -> 2024 | F44: =Inputs!F$22 -> 2025
B45: Land (net book value) | D45: =Schedules!D16 -> 60000 | E45: =Schedules!E16 -> 60000 | F45: =Schedules!F16 -> 60000
B46: Buildings & warehouse improvements (net book value) | D46: =Schedules!D26 -> 71225 | E46: =Schedules!E26 -> 78692 | F46: =Schedules!F26 -> 81367
B47: Warehouse equipment & racking (net book value) | D47: =Schedules!D36 -> 21317 | E47: =Schedules!E36 -> 25767 | F47: =Schedules!F36 -> 27984
B48: Delivery vehicles (net book value) | D48: =Schedules!D46 -> 22429 | E48: =Schedules!E46 -> 21372 | F48: =Schedules!F46 -> 22443
B49: Office furniture & IT equipment (net book value) | D49: =Schedules!D56 -> 3740 | E49: =Schedules!E56 -> 3930 | F49: =Schedules!F56 -> 2710
B50: Total net book value | D50: =SUM(D45:D49) -> 178711 | E50: =SUM(E45:E49) -> 189761 | F50: =SUM(F45:F49) -> 194504
B52: Cost - opening | D52: =Schedules!C58 -> 260000 | E52: =Schedules!D58 -> 275700 | F52: =Schedules!E58 -> 301000
B53: Additions | D53: =Schedules!D61 -> 22100 | E53: =Schedules!E61 -> 30900 | F53: =Schedules!F61 -> 26900
B54: Disposals | D54: =Schedules!D63 -> -6400 | E54: =Schedules!E63 -> -5600 | F54: =Schedules!F63 -> -7200
B55: Cost - closing | D55: =Schedules!D58 -> 275700 | E55: =Schedules!E58 -> 301000 | F55: =Schedules!F58 -> 320700
B56: Accumulated depreciation - opening | D56: =Schedules!C59 -> 85300 | E56: =Schedules!D59 -> 96989 | F56: =Schedules!E59 -> 111239
B57: Depreciation for the year | D57: =Schedules!D62 -> 17389 | E57: =Schedules!E62 -> 19250 | F57: =Schedules!F62 -> 21257
B58: Disposals | D58: =Schedules!D64 -> -5700 | E58: =Schedules!E64 -> -5000 | F58: =Schedules!F64 -> -6300
B59: Accumulated depreciation - closing | D59: =Schedules!D59 -> 96989 | E59: =Schedules!E59 -> 111239 | F59: =Schedules!F59 -> 126196
B60: Gain / (loss) on disposal recognised | D60: =Schedules!D67 -> 400 | E60: =Schedules!E67 -> -150 | F60: =Schedules!F67 -> 350
B62: NOTE 7 - BORROWINGS
B63: PHP '000 | D63: =Inputs!D$22 -> 2023 | E63: =Inputs!E$22 -> 2024 | F63: =Inputs!F$22 -> 2025
B64: Short-term loans (unsecured working capital lines) | D64: =Balance_Sheet!D24 -> 48000 | E64: =Balance_Sheet!E24 -> 42000 | F64: =Balance_Sheet!F24 -> 38000
B65: Long-term loans - current portion | D65: =Balance_Sheet!D25 -> 13000 | E65: =Balance_Sheet!E25 -> 15000 | F65: =Balance_Sheet!F25 -> 16500
B66: Long-term loans - non-current portion | D66: =Balance_Sheet!D28 -> 75000 | E66: =Balance_Sheet!E28 -> 95000 | F66: =Balance_Sheet!F28 -> 78500
B67: Total borrowings | D67: =SUM(D64:D66) -> 136000 | E67: =SUM(E64:E66) -> 152000 | F67: =SUM(F64:F66) -> 133000
B68: Finance costs for the year | D68: =Schedules!D90 -> 10421 | E68: =Schedules!E90 -> 11475 | F68: =Schedules!F90 -> 11696
B69: Weighted average interest cost on average borrowings | D69: =IFERROR(Schedules!D90/AVERAGE(Schedules!C87,Schedules!D87),0) -> 0.074170819 | E69: =IFERROR(Schedules!E90/AVERAGE(Schedules!D87,Schedules!E87),0) -> 0.0796875 | F69: =IFERROR(Schedules!F90/AVERAGE(Schedules!E87,Schedules!F87),0) -> 0.082077193
B70: Indicative level annual instalment on new term loans (PMT) | D70: =IF(Schedules!D82>0,ROUND(PMT(Inputs!D25,Loan_Tenor,-Schedules!D82),0),0) -> 0 | E70: =IF(Schedules!E82>0,ROUND(PMT(Inputs!E25,Loan_Tenor,-Schedules!E82),0),0) -> 8766 | F70: =IF(Schedules!F82>0,ROUND(PMT(Inputs!F25,Loan_Tenor,-Schedules!F82),0),0) -> 0 | G70: Memo: PMT over the assumed tenor on the year's drawdown
B72: NOTE 8 - EQUITY
B73: PHP '000 | D73: =Inputs!D$22 -> 2023 | E73: =Inputs!E$22 -> 2024 | F73: =Inputs!F$22 -> 2025
B74: Share capital | D74: =Balance_Sheet!D31 -> 120000 | E74: =Balance_Sheet!E31 -> 120000 | F74: =Balance_Sheet!F31 -> 120000
B75: Additional paid-in capital | D75: =Balance_Sheet!D32 -> 18000 | E75: =Balance_Sheet!E32 -> 18000 | F75: =Balance_Sheet!F32 -> 18000
B76: Retained earnings | D76: =Balance_Sheet!D33 -> 58561 | E76: =Balance_Sheet!E33 -> 80318 | F76: =Balance_Sheet!F33 -> 106502
B77: Total equity | D77: =Balance_Sheet!D34 -> 196561 | E77: =Balance_Sheet!E34 -> 218318 | F77: =Balance_Sheet!F34 -> 244502
B78: Shares outstanding (number) | D78: =D74*1000/Par_Value -> 1200000 | E78: =E74*1000/Par_Value -> 1200000 | F78: =F74*1000/Par_Value -> 1200000 | G78: Share capital / par value
B79: Cash dividends declared and paid | D79: =-Equity_Changes!E9 -> 5621 | E79: =-Equity_Changes!E17 -> 7252 | F79: =-Equity_Changes!E25 -> 11222
B80: Dividends per share (PHP) | D80: =IFERROR(D79*1000/D78,0) -> 4.6841667 | E80: =IFERROR(E79*1000/E78,0) -> 6.0433333 | F80: =IFERROR(F79*1000/F78,0) -> 9.3516667
B81: Book value per share (PHP) | D81: =IFERROR(Balance_Sheet!D34*1000/D78,0) -> 163.80083 | E81: =IFERROR(Balance_Sheet!E34*1000/E78,0) -> 181.93167 | F81: =IFERROR(Balance_Sheet!F34*1000/F78,0) -> 203.75167
B82: Dividend payout ratio (dividends / net profit) | D82: =IFERROR(D79/Income_Statement!D20,0) -> 0.25002224 | E82: =IFERROR(E79/Income_Statement!E20,0) -> 0.24999138 | F82: =IFERROR(F79/Income_Statement!F20,0) -> 0.30000535
B84: NOTE 9 - NET SALES (DISAGGREGATION)
B85: PHP '000 | D85: =Inputs!D$22 -> 2023 | E85: =Inputs!E$22 -> 2024 | F85: =Inputs!F$22 -> 2025
B86: Packaged Food | D86: =SUMIFS(Sales_Net,Sales_Year,Inputs!D$22,Sales_Cat,"Packaged Food") -> 331104 | E86: =SUMIFS(Sales_Net,Sales_Year,Inputs!E$22,Sales_Cat,"Packaged Food") -> 358165 | F86: =SUMIFS(Sales_Net,Sales_Year,Inputs!F$22,Sales_Cat,"Packaged Food") -> 382510
B87: Beverages | D87: =SUMIFS(Sales_Net,Sales_Year,Inputs!D$22,Sales_Cat,"Beverages") -> 239746 | E87: =SUMIFS(Sales_Net,Sales_Year,Inputs!E$22,Sales_Cat,"Beverages") -> 264622 | F87: =SUMIFS(Sales_Net,Sales_Year,Inputs!F$22,Sales_Cat,"Beverages") -> 292182
B88: Household & Personal Care | D88: =SUMIFS(Sales_Net,Sales_Year,Inputs!D$22,Sales_Cat,"Household & Personal Care") -> 149705 | E88: =SUMIFS(Sales_Net,Sales_Year,Inputs!E$22,Sales_Cat,"Household & Personal Care") -> 160640 | F88: =SUMIFS(Sales_Net,Sales_Year,Inputs!F$22,Sales_Cat,"Household & Personal Care") -> 170561
B89: Fresh & Frozen | D89: =SUMIFS(Sales_Net,Sales_Year,Inputs!D$22,Sales_Cat,"Fresh & Frozen") -> 100563 | E89: =SUMIFS(Sales_Net,Sales_Year,Inputs!E$22,Sales_Cat,"Fresh & Frozen") -> 113811 | F89: =SUMIFS(Sales_Net,Sales_Year,Inputs!F$22,Sales_Cat,"Fresh & Frozen") -> 127189
B90: Total by product category | D90: =SUM(D86:D89) -> 821118 | E90: =SUM(E86:E89) -> 897238 | F90: =SUM(F86:F89) -> 972442
B91: Luzon | D91: =SUMIFS(Sales_Net,Sales_Year,Inputs!D$22,Sales_Region,"Luzon") -> 477177 | E91: =SUMIFS(Sales_Net,Sales_Year,Inputs!E$22,Sales_Region,"Luzon") -> 514752 | F91: =SUMIFS(Sales_Net,Sales_Year,Inputs!F$22,Sales_Region,"Luzon") -> 554093
B92: Visayas | D92: =SUMIFS(Sales_Net,Sales_Year,Inputs!D$22,Sales_Region,"Visayas") -> 187935 | E92: =SUMIFS(Sales_Net,Sales_Year,Inputs!E$22,Sales_Region,"Visayas") -> 206985 | F92: =SUMIFS(Sales_Net,Sales_Year,Inputs!F$22,Sales_Region,"Visayas") -> 223910
B93: Mindanao | D93: =SUMIFS(Sales_Net,Sales_Year,Inputs!D$22,Sales_Region,"Mindanao") -> 156006 | E93: =SUMIFS(Sales_Net,Sales_Year,Inputs!E$22,Sales_Region,"Mindanao") -> 175501 | F93: =SUMIFS(Sales_Net,Sales_Year,Inputs!F$22,Sales_Region,"Mindanao") -> 194439
B94: Total by region | D94: =SUM(D91:D93) -> 821118 | E94: =SUM(E91:E93) -> 897238 | F94: =SUM(F91:F93) -> 972442
B96: NOTE 10 - COST OF SALES AND OPERATING EXPENSES (BY NATURE)
B97: PHP '000 | D97: =Inputs!D$22 -> 2023 | E97: =Inputs!E$22 -> 2024 | F97: =Inputs!F$22 -> 2025
B98: Cost of sales (merchandise) | D98: =SUMIFS(Sales_COGS,Sales_Year,Inputs!D$22) -> 613977 | E98: =SUMIFS(Sales_COGS,Sales_Year,Inputs!E$22) -> 668558 | F98: =SUMIFS(Sales_COGS,Sales_Year,Inputs!F$22) -> 722548
B99: Sales commissions & incentives | D99: =SUMIFS(Exp_Amt,Exp_Year,Inputs!D$22,Exp_Line,"Sales commissions & incentives") -> 13034 | E99: =SUMIFS(Exp_Amt,Exp_Year,Inputs!E$22,Exp_Line,"Sales commissions & incentives") -> 14338 | F99: =SUMIFS(Exp_Amt,Exp_Year,Inputs!F$22,Exp_Line,"Sales commissions & incentives") -> 15695
B100: Advertising & promotions | D100: =SUMIFS(Exp_Amt,Exp_Year,Inputs!D$22,Exp_Line,"Advertising & promotions") -> 7890 | E100: =SUMIFS(Exp_Amt,Exp_Year,Inputs!E$22,Exp_Line,"Advertising & promotions") -> 8683 | F100: =SUMIFS(Exp_Amt,Exp_Year,Inputs!F$22,Exp_Line,"Advertising & promotions") -> 9363
B101: Freight & delivery | D101: =SUMIFS(Exp_Amt,Exp_Year,Inputs!D$22,Exp_Line,"Freight & delivery") -> 19617 | E101: =SUMIFS(Exp_Amt,Exp_Year,Inputs!E$22,Exp_Line,"Freight & delivery") -> 21643 | F101: =SUMIFS(Exp_Amt,Exp_Year,Inputs!F$22,Exp_Line,"Freight & delivery") -> 23337
B102: Warehouse rent & utilities | D102: =SUMIFS(Exp_Amt,Exp_Year,Inputs!D$22,Exp_Line,"Warehouse rent & utilities") -> 22849 | E102: =SUMIFS(Exp_Amt,Exp_Year,Inputs!E$22,Exp_Line,"Warehouse rent & utilities") -> 23767 | F102: =SUMIFS(Exp_Amt,Exp_Year,Inputs!F$22,Exp_Line,"Warehouse rent & utilities") -> 24992
B103: Selling & logistics staff costs | D103: =SUMIFS(Exp_Amt,Exp_Year,Inputs!D$22,Exp_Line,"Selling & logistics staff costs") -> 29826 | E103: =SUMIFS(Exp_Amt,Exp_Year,Inputs!E$22,Exp_Line,"Selling & logistics staff costs") -> 31499 | F103: =SUMIFS(Exp_Amt,Exp_Year,Inputs!F$22,Exp_Line,"Selling & logistics staff costs") -> 32690
B104: Salaries & wages (G&A) | D104: =SUMIFS(Exp_Amt,Exp_Year,Inputs!D$22,Exp_Line,"Salaries & wages (G&A)") -> 27660 | E104: =SUMIFS(Exp_Amt,Exp_Year,Inputs!E$22,Exp_Line,"Salaries & wages (G&A)") -> 28920 | F104: =SUMIFS(Exp_Amt,Exp_Year,Inputs!F$22,Exp_Line,"Salaries & wages (G&A)") -> 30213
B105: Employee benefits & contributions | D105: =SUMIFS(Exp_Amt,Exp_Year,Inputs!D$22,Exp_Line,"Employee benefits & contributions") -> 7451 | E105: =SUMIFS(Exp_Amt,Exp_Year,Inputs!E$22,Exp_Line,"Employee benefits & contributions") -> 7808 | F105: =SUMIFS(Exp_Amt,Exp_Year,Inputs!F$22,Exp_Line,"Employee benefits & contributions") -> 8130
B106: Professional fees | D106: =SUMIFS(Exp_Amt,Exp_Year,Inputs!D$22,Exp_Line,"Professional fees") -> 4055 | E106: =SUMIFS(Exp_Amt,Exp_Year,Inputs!E$22,Exp_Line,"Professional fees") -> 4266 | F106: =SUMIFS(Exp_Amt,Exp_Year,Inputs!F$22,Exp_Line,"Professional fees") -> 4500
B107: Office rent & utilities | D107: =SUMIFS(Exp_Amt,Exp_Year,Inputs!D$22,Exp_Line,"Office rent & utilities") -> 6240 | E107: =SUMIFS(Exp_Amt,Exp_Year,Inputs!E$22,Exp_Line,"Office rent & utilities") -> 6572 | F107: =SUMIFS(Exp_Amt,Exp_Year,Inputs!F$22,Exp_Line,"Office rent & utilities") -> 6839
B108: Repairs & maintenance | D108: =SUMIFS(Exp_Amt,Exp_Year,Inputs!D$22,Exp_Line,"Repairs & maintenance") -> 2535 | E108: =SUMIFS(Exp_Amt,Exp_Year,Inputs!E$22,Exp_Line,"Repairs & maintenance") -> 2672 | F108: =SUMIFS(Exp_Amt,Exp_Year,Inputs!F$22,Exp_Line,"Repairs & maintenance") -> 2729
B109: Taxes, licenses & insurance | D109: =SUMIFS(Exp_Amt,Exp_Year,Inputs!D$22,Exp_Line,"Taxes, licenses & insurance") -> 5055 | E109: =SUMIFS(Exp_Amt,Exp_Year,Inputs!E$22,Exp_Line,"Taxes, licenses & insurance") -> 5318 | F109: =SUMIFS(Exp_Amt,Exp_Year,Inputs!F$22,Exp_Line,"Taxes, licenses & insurance") -> 5484
B110: Communication, IT & supplies | D110: =SUMIFS(Exp_Amt,Exp_Year,Inputs!D$22,Exp_Line,"Communication, IT & supplies") -> 4088 | E110: =SUMIFS(Exp_Amt,Exp_Year,Inputs!E$22,Exp_Line,"Communication, IT & supplies") -> 4299 | F110: =SUMIFS(Exp_Amt,Exp_Year,Inputs!F$22,Exp_Line,"Communication, IT & supplies") -> 4463
B111: Bad debts & credit losses | D111: =SUMIFS(Exp_Amt,Exp_Year,Inputs!D$22,Exp_Line,"Bad debts & credit losses") -> 1231 | E111: =SUMIFS(Exp_Amt,Exp_Year,Inputs!E$22,Exp_Line,"Bad debts & credit losses") -> 1342 | F111: =SUMIFS(Exp_Amt,Exp_Year,Inputs!F$22,Exp_Line,"Bad debts & credit losses") -> 1469
...

Sheet Schedules
B1: Supporting Schedules
B2: =Inputs!$C$6&" | "&Inputs!$C$11 -> Sampaguita Foods & Distribution Corporation (SFDC) | PHP in thousands (unless otherwise stated)
B3: =HYPERLINK("#Cover!A1","◄ Back to Cover") -> ◄ Back to Cover
B5: PHP '000 | C5: =Inputs!C$22 -> 2022 | D5: =Inputs!D$22 -> 2023 | E5: =Inputs!E$22 -> 2024 | F5: =Inputs!F$22 -> 2025
B6: A. PROPERTY, PLANT AND EQUIPMENT ROLL-FORWARD (by asset class)
B7: Land
B8: Cost - opening | D8: =C11 -> 60000 | E8: =D11 -> 60000 | F8: =E11 -> 60000
B9: Additions | D9: =Inputs!D74 -> 0 | E9: =Inputs!E74 -> 0 | F9: =Inputs!F74 -> 0
B10: Disposals | D10: =-Inputs!D80 -> 0 | E10: =-Inputs!E80 -> 0 | F10: =-Inputs!F80 -> 0
B11: Cost - closing | C11: =Inputs!$D$66 -> 60000 | D11: =SUM(D8:D10) -> 60000 | E11: =SUM(E8:E10) -> 60000 | F11: =SUM(F8:F10) -> 60000
B12: Accumulated depreciation - opening | D12: =C15 -> 0 | E12: =D15 -> 0 | F12: =E15 -> 0
B13: Depreciation for the year | D13: =IF(Inputs!$C$66=0,0,MAX(0,MIN(ROUND((D8+0.5*D9+0.5*D10)/Inputs!$C$66,0),D11-(D12+D14)))) -> 0 | E13: =IF(Inputs!$C$66=0,0,MAX(0,MIN(ROUND((E8+0.5*E9+0.5*E10)/Inputs!$C$66,0),E11-(E12+E14)))) -> 0 | F13: =IF(Inputs!$C$66=0,0,MAX(0,MIN(ROUND((F8+0.5*F9+0.5*F10)/Inputs!$C$66,0),F11-(F12+F14)))) -> 0
B14: Disposals | D14: =-Inputs!D86 -> 0 | E14: =-Inputs!E86 -> 0 | F14: =-Inputs!F86 -> 0
B15: Accumulated depreciation - closing | C15: =Inputs!$E$66 -> 0 | D15: =SUM(D12:D14) -> 0 | E15: =SUM(E12:E14) -> 0 | F15: =SUM(F12:F14) -> 0
B16: Net book value | C16: =C11-C15 -> 60000 | D16: =D11-D15 -> 60000 | E16: =E11-E15 -> 60000 | F16: =F11-F15 -> 60000
B17: Buildings & warehouse improvements
B18: Cost - opening | D18: =C21 -> 96000 | E18: =D21 -> 100500 | F18: =E21 -> 111500
B19: Additions | D19: =Inputs!D75 -> 4500 | E19: =Inputs!E75 -> 11000 | F19: =Inputs!F75 -> 6500
B20: Disposals | D20: =-Inputs!D81 -> 0 | E20: =-Inputs!E81 -> 0 | F20: =-Inputs!F81 -> 0
B21: Cost - closing | C21: =Inputs!$D$67 -> 96000 | D21: =SUM(D18:D20) -> 100500 | E21: =SUM(E18:E20) -> 111500 | F21: =SUM(F18:F20) -> 118000
B22: Accumulated depreciation - opening | D22: =C25 -> 26000 | E22: =D25 -> 29275 | F22: =E25 -> 32808
B23: Depreciation for the year | D23: =IF(Inputs!$C$67=0,0,MAX(0,MIN(ROUND((D18+0.5*D19+0.5*D20)/Inputs!$C$67,0),D21-(D22+D24)))) -> 3275 | E23: =IF(Inputs!$C$67=0,0,MAX(0,MIN(ROUND((E18+0.5*E19+0.5*E20)/Inputs!$C$67,0),E21-(E22+E24)))) -> 3533 | F23: =IF(Inputs!$C$67=0,0,MAX(0,MIN(ROUND((F18+0.5*F19+0.5*F20)/Inputs!$C$67,0),F21-(F22+F24)))) -> 3825
B24: Disposals | D24: =-Inputs!D87 -> 0 | E24: =-Inputs!E87 -> 0 | F24: =-Inputs!F87 -> 0
B25: Accumulated depreciation - closing | C25: =Inputs!$E$67 -> 26000 | D25: =SUM(D22:D24) -> 29275 | E25: =SUM(E22:E24) -> 32808 | F25: =SUM(F22:F24) -> 36633
B26: Net book value | C26: =C21-C25 -> 70000 | D26: =D21-D25 -> 71225 | E26: =E21-E25 -> 78692 | F26: =F21-F25 -> 81367
B27: Warehouse equipment & racking
B28: Cost - opening | D28: =C31 -> 38000 | E28: =D31 -> 43200 | F28: =E31 -> 51600
B29: Additions | D29: =Inputs!D76 -> 5200 | E29: =Inputs!E76 -> 8400 | F29: =Inputs!F76 -> 6800
B30: Disposals | D30: =-Inputs!D82 -> 0 | E30: =-Inputs!E82 -> 0 | F30: =-Inputs!F82 -> 0
B31: Cost - closing | C31: =Inputs!$D$68 -> 38000 | D31: =SUM(D28:D30) -> 43200 | E31: =SUM(E28:E30) -> 51600 | F31: =SUM(F28:F30) -> 58400
B32: Accumulated depreciation - opening | D32: =C35 -> 18500 | E32: =D35 -> 21883 | F32: =E35 -> 25833
B33: Depreciation for the year | D33: =IF(Inputs!$C$68=0,0,MAX(0,MIN(ROUND((D28+0.5*D29+0.5*D30)/Inputs!$C$68,0),D31-(D32+D34)))) -> 3383 | E33: =IF(Inputs!$C$68=0,0,MAX(0,MIN(ROUND((E28+0.5*E29+0.5*E30)/Inputs!$C$68,0),E31-(E32+E34)))) -> 3950 | F33: =IF(Inputs!$C$68=0,0,MAX(0,MIN(ROUND((F28+0.5*F29+0.5*F30)/Inputs!$C$68,0),F31-(F32+F34)))) -> 4583
B34: Disposals | D34: =-Inputs!D88 -> 0 | E34: =-Inputs!E88 -> 0 | F34: =-Inputs!F88 -> 0
B35: Accumulated depreciation - closing | C35: =Inputs!$E$68 -> 18500 | D35: =SUM(D32:D34) -> 21883 | E35: =SUM(E32:E34) -> 25833 | F35: =SUM(F32:F34) -> 30416
B36: Net book value | C36: =C31-C35 -> 19500 | D36: =D31-D35 -> 21317 | E36: =E31-E35 -> 25767 | F36: =F31-F35 -> 27984
B37: Delivery vehicles
B38: Cost - opening | D38: =C41 -> 52000 | E38: =D41 -> 55400 | F38: =E41 -> 57400
B39: Additions | D39: =Inputs!D77 -> 9800 | E39: =Inputs!E77 -> 7600 | F39: =Inputs!F77 -> 10400
B40: Disposals | D40: =-Inputs!D83 -> -6400 | E40: =-Inputs!E83 -> -5600 | F40: =-Inputs!F83 -> -7200
B41: Cost - closing | C41: =Inputs!$D$69 -> 52000 | D41: =SUM(D38:D40) -> 55400 | E41: =SUM(E38:E40) -> 57400 | F41: =SUM(F38:F40) -> 60600
B42: Accumulated depreciation - opening | D42: =C45 -> 31000 | E42: =D45 -> 32971 | F42: =E45 -> 36028
B43: Depreciation for the year | D43: =IF(Inputs!$C$69=0,0,MAX(0,MIN(ROUND((D38+0.5*D39+0.5*D40)/Inputs!$C$69,0),D41-(D42+D44)))) -> 7671 | E43: =IF(Inputs!$C$69=0,0,MAX(0,MIN(ROUND((E38+0.5*E39+0.5*E40)/Inputs!$C$69,0),E41-(E42+E44)))) -> 8057 | F43: =IF(Inputs!$C$69=0,0,MAX(0,MIN(ROUND((F38+0.5*F39+0.5*F40)/Inputs!$C$69,0),F41-(F42+F44)))) -> 8429
B44: Disposals | D44: =-Inputs!D89 -> -5700 | E44: =-Inputs!E89 -> -5000 | F44: =-Inputs!F89 -> -6300
B45: Accumulated depreciation - closing | C45: =Inputs!$E$69 -> 31000 | D45: =SUM(D42:D44) -> 32971 | E45: =SUM(E42:E44) -> 36028 | F45: =SUM(F42:F44) -> 38157
B46: Net book value | C46: =C41-C45 -> 21000 | D46: =D41-D45 -> 22429 | E46: =E41-E45 -> 21372 | F46: =F41-F45 -> 22443
B47: Office furniture & IT equipment
B48: Cost - opening | D48: =C51 -> 14000 | E48: =D51 -> 16600 | F48: =E51 -> 20500
B49: Additions | D49: =Inputs!D78 -> 2600 | E49: =Inputs!E78 -> 3900 | F49: =Inputs!F78 -> 3200
B50: Disposals | D50: =-Inputs!D84 -> 0 | E50: =-Inputs!E84 -> 0 | F50: =-Inputs!F84 -> 0
B51: Cost - closing | C51: =Inputs!$D$70 -> 14000 | D51: =SUM(D48:D50) -> 16600 | E51: =SUM(E48:E50) -> 20500 | F51: =SUM(F48:F50) -> 23700
B52: Accumulated depreciation - opening | D52: =C55 -> 9800 | E52: =D55 -> 12860 | F52: =E55 -> 16570
B53: Depreciation for the year | D53: =IF(Inputs!$C$70=0,0,MAX(0,MIN(ROUND((D48+0.5*D49+0.5*D50)/Inputs!$C$70,0),D51-(D52+D54)))) -> 3060 | E53: =IF(Inputs!$C$70=0,0,MAX(0,MIN(ROUND((E48+0.5*E49+0.5*E50)/Inputs!$C$70,0),E51-(E52+E54)))) -> 3710 | F53: =IF(Inputs!$C$70=0,0,MAX(0,MIN(ROUND((F48+0.5*F49+0.5*F50)/Inputs!$C$70,0),F51-(F52+F54)))) -> 4420
B54: Disposals | D54: =-Inputs!D90 -> 0 | E54: =-Inputs!E90 -> 0 | F54: =-Inputs!F90 -> 0
B55: Accumulated depreciation - closing | C55: =Inputs!$E$70 -> 9800 | D55: =SUM(D52:D54) -> 12860 | E55: =SUM(E52:E54) -> 16570 | F55: =SUM(F52:F54) -> 20990
B56: Net book value | C56: =C51-C55 -> 4200 | D56: =D51-D55 -> 3740 | E56: =E51-E55 -> 3930 | F56: =F51-F55 -> 2710
B57: Total property, plant and equipment
B58: Total cost - closing | C58: =C11+C21+C31+C41+C51 -> 260000 | D58: =D11+D21+D31+D41+D51 -> 275700 | E58: =E11+E21+E31+E41+E51 -> 301000 | F58: =F11+F21+F31+F41+F51 -> 320700
B59: Total accumulated depreciation - closing | C59: =C15+C25+C35+C45+C55 -> 85300 | D59: =D15+D25+D35+D45+D55 -> 96989 | E59: =E15+E25+E35+E45+E55 -> 111239 | F59: =F15+F25+F35+F45+F55 -> 126196
B60: Total net book value | C60: =C16+C26+C36+C46+C56 -> 174700 | D60: =D16+D26+D36+D46+D56 -> 178711 | E60: =E16+E26+E36+E46+E56 -> 189761 | F60: =F16+F26+F36+F46+F56 -> 194504
B61: Total additions (capital expenditure) | D61: =D9+D19+D29+D39+D49 -> 22100 | E61: =E9+E19+E29+E39+E49 -> 30900 | F61: =F9+F19+F29+F39+F49 -> 26900
B62: Total depreciation expense | D62: =D13+D23+D33+D43+D53 -> 17389 | E62: =E13+E23+E33+E43+E53 -> 19250 | F62: =F13+F23+F33+F43+F53 -> 21257
B63: Total disposals - cost | D63: =D10+D20+D30+D40+D50 -> -6400 | E63: =E10+E20+E30+E40+E50 -> -5600 | F63: =F10+F20+F30+F40+F50 -> -7200
B64: Total disposals - accumulated depreciation | D64: =D14+D24+D34+D44+D54 -> -5700 | E64: =E14+E24+E34+E44+E54 -> -5000 | F64: =F14+F24+F34+F44+F54 -> -6300
B65: Net book value of disposals | D65: =-D63+D64 -> 700 | E65: =-E63+E64 -> 600 | F65: =-F63+F64 -> 900
B66: Cash proceeds from disposals | D66: =Inputs!D92+Inputs!D93+Inputs!D94+Inputs!D95+Inputs!D96 -> 1100 | E66: =Inputs!E92+Inputs!E93+Inputs!E94+Inputs!E95+Inputs!E96 -> 450 | F66: =Inputs!F92+Inputs!F93+Inputs!F94+Inputs!F95+Inputs!F96 -> 1250
B67: Gain / (loss) on disposal | D67: =D66-D65 -> 400 | E67: =E66-E65 -> -150 | F67: =F66-F65 -> 350
B69: B. WORKING CAPITAL (driver-based)
B70: Net sales | D70: =Income_Statement!D7 -> 821118 | E70: =Income_Statement!E7 -> 897238 | F70: =Income_Statement!F7 -> 972442
B71: Cost of sales | D71: =-Income_Statement!D8 -> 613977 | E71: =-Income_Statement!E8 -> 668558 | F71: =-Income_Statement!F8 -> 722548
B72: Operating expenses (selling, distribution and G&A) | D72: =-(Income_Statement!D10+Income_Statement!D11) -> 151531 | E72: =-(Income_Statement!E10+Income_Statement!E11) -> 161127 | F72: =-(Income_Statement!F10+Income_Statement!F11) -> 169904
B73: Trade and other receivables | C73: =Inputs!C39 -> 71000 | D73: =ROUND(Inputs!D32*D70/Days_Year,0) -> 80987 | E73: =ROUND(Inputs!E32*E70/Days_Year,0) -> 88495 | F73: =ROUND(Inputs!F32*F70/Days_Year,0) -> 93248
B74: Inventories | C74: =Inputs!C40 -> 74500 | D74: =ROUND(Inputs!D33*D71/Days_Year,0) -> 75696 | E74: =ROUND(Inputs!E33*E71/Days_Year,0) -> 80593 | F74: =ROUND(Inputs!F33*F71/Days_Year,0) -> 85122
B75: Prepayments and other current assets | C75: =Inputs!C41 -> 11200 | D75: =ROUND(Inputs!D35*D72,0) -> 11365 | E75: =ROUND(Inputs!E35*E72,0) -> 12085 | F75: =ROUND(Inputs!F35*F72,0) -> 12743
B76: Trade and other payables | C76: =Inputs!C42 -> 62300 | D76: =ROUND(Inputs!D34*D71/Days_Year,0) -> 67285 | E76: =ROUND(Inputs!E34*E71/Days_Year,0) -> 75098 | F76: =ROUND(Inputs!F34*F71/Days_Year,0) -> 83143
B77: Accrued expenses | C77: =Inputs!C43 -> 13400 | D77: =ROUND(Inputs!D36*D72,0) -> 13638 | E77: =ROUND(Inputs!E36*E72,0) -> 14501 | F77: =ROUND(Inputs!F36*F72,0) -> 15291
B79: C. BORROWINGS AND FINANCE COSTS
B80: Short-term loans - closing | C80: =Inputs!C51 -> 45000 | D80: =Inputs!D51 -> 48000 | E80: =Inputs!E51 -> 42000 | F80: =Inputs!F51 -> 38000
B81: Long-term loans - opening | D81: =C84 -> 100000 | E81: =D84 -> 88000 | F81: =E84 -> 110000
B82: Drawdowns | D82: =Inputs!D52 -> 0 | E82: =Inputs!E52 -> 35000 | F82: =Inputs!F52 -> 0
B83: Repayments | D83: =-Inputs!D53 -> -12000 | E83: =-Inputs!E53 -> -13000 | F83: =-Inputs!F53 -> -15000
B84: Long-term loans - closing (total) | C84: =Inputs!C45 -> 100000 | D84: =SUM(D81:D83) -> 88000 | E84: =SUM(E81:E83) -> 110000 | F84: =SUM(F81:F83) -> 95000
B85: of which current portion | C85: =Inputs!C54 -> 12000 | D85: =Inputs!D54 -> 13000 | E85: =Inputs!E54 -> 15000 | F85: =Inputs!F54 -> 16500
B86: of which non-current portion | C86: =C84-C85 -> 88000 | D86: =D84-D85 -> 75000 | E86: =E84-E85 -> 95000 | F86: =F84-F85 -> 78500
B87: Total borrowings | C87: =C80+C84 -> 145000 | D87: =D80+D84 -> 136000 | E87: =E80+E84 -> 152000 | F87: =F80+F84 -> 133000
B88: Interest on short-term loans | D88: =ROUND(Inputs!D24*AVERAGE(C80,D80),0) -> 3371 | E88: =ROUND(Inputs!E24*AVERAGE(D80,E80),0) -> 3555 | F88: =ROUND(Inputs!F24*AVERAGE(E80,F80),0) -> 3240
B89: Interest on long-term loans | D89: =ROUND(Inputs!D25*AVERAGE(C84,D84),0) -> 7050 | E89: =ROUND(Inputs!E25*AVERAGE(D84,E84),0) -> 7920 | F89: =ROUND(Inputs!F25*AVERAGE(E84,F84),0) -> 8456
B90: Total finance costs | D90: =D88+D89 -> 10421 | E90: =E88+E89 -> 11475 | F90: =F88+F89 -> 11696
B91: Interest income (yield x opening cash) | D91: =ROUND(Inputs!D26*Balance_Sheet!C8,0) -> 775 | E91: =ROUND(Inputs!E26*Balance_Sheet!D8,0) -> 873 | F91: =ROUND(Inputs!F26*Balance_Sheet!E8,0) -> 1207
B93: D. INCOME TAX COMPUTATION (RCIT vs MCIT)
B94: Profit before income tax (per income statement) | D94: =Income_Statement!D18 -> 30325 | E94: =Income_Statement!E18 -> 39071 | F94: =Income_Statement!F18 -> 50294
B95: Add: non-deductible expenses | D95: =Inputs!D28 -> 1200 | E95: =Inputs!E28 -> 1350 | F95: =Inputs!F28 -> 1500
B96: Less: interest income subject to final tax | D96: =-D91 -> -775 | E96: =-E91 -> -873 | F96: =-F91 -> -1207
B97: Taxable income | D97: =SUM(D94:D96) -> 30750 | E97: =SUM(E94:E96) -> 39548 | F97: =SUM(F94:F96) -> 50587
B98: Regular corporate income tax (RCIT) | D98: =ROUND(MAX(0,D97)*Tax_Rate,0) -> 7688 | E98: =ROUND(MAX(0,E97)*Tax_Rate,0) -> 9887 | F98: =ROUND(MAX(0,F97)*Tax_Rate,0) -> 12647
B99: Gross income for MCIT (gross profit + other income) | D99: =Income_Statement!D9+Income_Statement!D15 -> 208491 | E99: =Income_Statement!E9+Income_Statement!E15 -> 230200 | F99: =Income_Statement!F9+Income_Statement!F15 -> 251594
B100: Minimum corporate income tax (MCIT) | D100: =ROUND(D99*MCIT_Rate,0) -> 4170 | E100: =ROUND(E99*MCIT_Rate,0) -> 4604 | F100: =ROUND(F99*MCIT_Rate,0) -> 5032
B101: Current income tax (higher of RCIT and MCIT) | D101: =MAX(D98,D100) -> 7688 | E101: =MAX(E98,E100) -> 9887 | F101: =MAX(F98,F100) -> 12647
B102: Final tax on interest income | D102: =ROUND(D91*Final_Tax_Rate,0) -> 155 | E102: =ROUND(E91*Final_Tax_Rate,0) -> 175 | F102: =ROUND(F91*Final_Tax_Rate,0) -> 241
B103: Total income tax expense | D103: =D101+D102 -> 7843 | E103: =E101+E102 -> 10062 | F103: =F101+F102 -> 12888
B104: Effective tax rate | D104: =IFERROR(D103/D94,0) -> 0.25863149 | E104: =IFERROR(E103/E94,0) -> 0.25753116 | F104: =IFERROR(F103/F94,0) -> 0.25625323
...

Sheet Horizontal
B1: Horizontal Analysis
B2: =Inputs!$C$6&" | "&Inputs!$C$11 -> Sampaguita Foods & Distribution Corporation (SFDC) | PHP in thousands (unless otherwise stated)
B3: =HYPERLINK("#Cover!A1","◄ Back to Cover") -> ◄ Back to Cover
B4: Peso and percentage change year-on-year. Expenses are shown as negatives, so a negative change signals higher cost. Flags trigger above the review threshold set on Inputs.
B5: PHP '000 | C5: =Inputs!D$22 -> 2023 | D5: =Inputs!E$22 -> 2024 | E5: =Inputs!F$22 -> 2025 | F5: Change FY24 vs FY23 | G5: % change | H5: Change FY25 vs FY24 | I5: % change | J5: Flag FY24 | K5: Flag FY25
B6: INCOME STATEMENT
B7: Net sales | C7: =Income_Statement!D7 -> 821118 | D7: =Income_Statement!E7 -> 897238 | E7: =Income_Statement!F7 -> 972442 | F7: =D7-C7 -> 76120 | G7: =IFERROR(F7/ABS(C7),0) -> 0.092702876 | H7: =E7-D7 -> 75204 | I7: =IFERROR(H7/ABS(D7),0) -> 0.083817226 | J7: =IF(ABS(G7)>Var_Threshold,IF(G7>0,"▲ ","▼ ")&TEXT(ABS(G7),"0.0%"),"–") -> – | K7: =IF(ABS(I7)>Var_Threshold,IF(I7>0,"▲ ","▼ ")&TEXT(ABS(I7),"0.0%"),"–") -> –
B8: Cost of sales | C8: =Income_Statement!D8 -> -613977 | D8: =Income_Statement!E8 -> -668558 | E8: =Income_Statement!F8 -> -722548 | F8: =D8-C8 -> -54581 | G8: =IFERROR(F8/ABS(C8),0) -> -0.088897467 | H8: =E8-D8 -> -53990 | I8: =IFERROR(H8/ABS(D8),0) -> -0.080755896 | J8: =IF(ABS(G8)>Var_Threshold,IF(G8>0,"▲ ","▼ ")&TEXT(ABS(G8),"0.0%"),"–") -> – | K8: =IF(ABS(I8)>Var_Threshold,IF(I8>0,"▲ ","▼ ")&TEXT(ABS(I8),"0.0%"),"–") -> –
B9: Gross profit | C9: =Income_Statement!D9 -> 207141 | D9: =Income_Statement!E9 -> 228680 | E9: =Income_Statement!F9 -> 249894 | F9: =D9-C9 -> 21539 | G9: =IFERROR(F9/ABS(C9),0) -> 0.10398231 | H9: =E9-D9 -> 21214 | I9: =IFERROR(H9/ABS(D9),0) -> 0.092767186 | J9: =IF(ABS(G9)>Var_Threshold,IF(G9>0,"▲ ","▼ ")&TEXT(ABS(G9),"0.0%"),"–") -> ▲ 10.4% | K9: =IF(ABS(I9)>Var_Threshold,IF(I9>0,"▲ ","▼ ")&TEXT(ABS(I9),"0.0%"),"–") -> –
B10: Selling and distribution expenses | C10: =Income_Statement!D10 -> -93216 | D10: =Income_Statement!E10 -> -99930 | E10: =Income_Statement!F10 -> -106077 | F10: =D10-C10 -> -6714 | G10: =IFERROR(F10/ABS(C10),0) -> -0.072026262 | H10: =E10-D10 -> -6147 | I10: =IFERROR(H10/ABS(D10),0) -> -0.061513059 | J10: =IF(ABS(G10)>Var_Threshold,IF(G10>0,"▲ ","▼ ")&TEXT(ABS(G10),"0.0%"),"–") -> – | K10: =IF(ABS(I10)>Var_Threshold,IF(I10>0,"▲ ","▼ ")&TEXT(ABS(I10),"0.0%"),"–") -> –
B11: General and administrative expenses | C11: =Income_Statement!D11 -> -58315 | D11: =Income_Statement!E11 -> -61197 | E11: =Income_Statement!F11 -> -63827 | F11: =D11-C11 -> -2882 | G11: =IFERROR(F11/ABS(C11),0) -> -0.049421247 | H11: =E11-D11 -> -2630 | I11: =IFERROR(H11/ABS(D11),0) -> -0.042975963 | J11: =IF(ABS(G11)>Var_Threshold,IF(G11>0,"▲ ","▼ ")&TEXT(ABS(G11),"0.0%"),"–") -> – | K11: =IF(ABS(I11)>Var_Threshold,IF(I11>0,"▲ ","▼ ")&TEXT(ABS(I11),"0.0%"),"–") -> –
B12: Depreciation | C12: =Income_Statement!D12 -> -17389 | D12: =Income_Statement!E12 -> -19250 | E12: =Income_Statement!F12 -> -21257 | F12: =D12-C12 -> -1861 | G12: =IFERROR(F12/ABS(C12),0) -> -0.10702168 | H12: =E12-D12 -> -2007 | I12: =IFERROR(H12/ABS(D12),0) -> -0.10425974 | J12: =IF(ABS(G12)>Var_Threshold,IF(G12>0,"▲ ","▼ ")&TEXT(ABS(G12),"0.0%"),"–") -> ▼ 10.7% | K12: =IF(ABS(I12)>Var_Threshold,IF(I12>0,"▲ ","▼ ")&TEXT(ABS(I12),"0.0%"),"–") -> ▼ 10.4%
B13: Operating profit | C13: =Income_Statement!D13 -> 38221 | D13: =Income_Statement!E13 -> 48303 | E13: =Income_Statement!F13 -> 58733 | F13: =D13-C13 -> 10082 | G13: =IFERROR(F13/ABS(C13),0) -> 0.26378169 | H13: =E13-D13 -> 10430 | I13: =IFERROR(H13/ABS(D13),0) -> 0.21592862 | J13: =IF(ABS(G13)>Var_Threshold,IF(G13>0,"▲ ","▼ ")&TEXT(ABS(G13),"0.0%"),"–") -> ▲ 26.4% | K13: =IF(ABS(I13)>Var_Threshold,IF(I13>0,"▲ ","▼ ")&TEXT(ABS(I13),"0.0%"),"–") -> ▲ 21.6%
B14: Gain / (loss) on disposal of property and equipment | C14: =Income_Statement!D14 -> 400 | D14: =Income_Statement!E14 -> -150 | E14: =Income_Statement!F14 -> 350 | F14: =D14-C14 -> -550 | G14: =IFERROR(F14/ABS(C14),0) -> -1.375 | H14: =E14-D14 -> 500 | I14: =IFERROR(H14/ABS(D14),0) -> 3.3333333 | J14: =IF(ABS(G14)>Var_Threshold,IF(G14>0,"▲ ","▼ ")&TEXT(ABS(G14),"0.0%"),"–") -> ▼ 137.5% | K14: =IF(ABS(I14)>Var_Threshold,IF(I14>0,"▲ ","▼ ")&TEXT(ABS(I14),"0.0%"),"–") -> ▲ 333.3%
B15: Other income | C15: =Income_Statement!D15 -> 1350 | D15: =Income_Statement!E15 -> 1520 | E15: =Income_Statement!F15 -> 1700 | F15: =D15-C15 -> 170 | G15: =IFERROR(F15/ABS(C15),0) -> 0.12592593 | H15: =E15-D15 -> 180 | I15: =IFERROR(H15/ABS(D15),0) -> 0.11842105 | J15: =IF(ABS(G15)>Var_Threshold,IF(G15>0,"▲ ","▼ ")&TEXT(ABS(G15),"0.0%"),"–") -> ▲ 12.6% | K15: =IF(ABS(I15)>Var_Threshold,IF(I15>0,"▲ ","▼ ")&TEXT(ABS(I15),"0.0%"),"–") -> ▲ 11.8%
B16: Interest income | C16: =Income_Statement!D16 -> 775 | D16: =Income_Statement!E16 -> 873 | E16: =Income_Statement!F16 -> 1207 | F16: =D16-C16 -> 98 | G16: =IFERROR(F16/ABS(C16),0) -> 0.12645161 | H16: =E16-D16 -> 334 | I16: =IFERROR(H16/ABS(D16),0) -> 0.38258877 | J16: =IF(ABS(G16)>Var_Threshold,IF(G16>0,"▲ ","▼ ")&TEXT(ABS(G16),"0.0%"),"–") -> ▲ 12.6% | K16: =IF(ABS(I16)>Var_Threshold,IF(I16>0,"▲ ","▼ ")&TEXT(ABS(I16),"0.0%"),"–") -> ▲ 38.3%
B17: Finance costs | C17: =Income_Statement!D17 -> -10421 | D17: =Income_Statement!E17 -> -11475 | E17: =Income_Statement!F17 -> -11696 | F17: =D17-C17 -> -1054 | G17: =IFERROR(F17/ABS(C17),0) -> -0.10114192 | H17: =E17-D17 -> -221 | I17: =IFERROR(H17/ABS(D17),0) -> -0.019259259 | J17: =IF(ABS(G17)>Var_Threshold,IF(G17>0,"▲ ","▼ ")&TEXT(ABS(G17),"0.0%"),"–") -> ▼ 10.1% | K17: =IF(ABS(I17)>Var_Threshold,IF(I17>0,"▲ ","▼ ")&TEXT(ABS(I17),"0.0%"),"–") -> –
B18: Profit before income tax | C18: =Income_Statement!D18 -> 30325 | D18: =Income_Statement!E18 -> 39071 | E18: =Income_Statement!F18 -> 50294 | F18: =D18-C18 -> 8746 | G18: =IFERROR(F18/ABS(C18),0) -> 0.2884089 | H18: =E18-D18 -> 11223 | I18: =IFERROR(H18/ABS(D18),0) -> 0.2872463 | J18: =IF(ABS(G18)>Var_Threshold,IF(G18>0,"▲ ","▼ ")&TEXT(ABS(G18),"0.0%"),"–") -> ▲ 28.8% | K18: =IF(ABS(I18)>Var_Threshold,IF(I18>0,"▲ ","▼ ")&TEXT(ABS(I18),"0.0%"),"–") -> ▲ 28.7%
... B20: Net profit for the year | C20: =Income_Statement!D20 -> 22482 | D20: =Income_Statement!E20 -> 29009 | E20: =Income_Statement!F20 -> 37406 | F20: =D20-C20 -> 6527 | G20: =IFERROR(F20/ABS(C20),0) -> 0.29032115 | H20: =E20-D20 -> 8397 | I20: =IFERROR(H20/ABS(D20),0) -> 0.28946189 | J20: =IF(ABS(G20)>Var_Threshold,IF(G20>0,"▲ ","▼ ")&TEXT(ABS(G20),"0.0%"),"–") -> ▲ 29.0% | K20: =IF(ABS(I20)>Var_Threshold,IF(I20>0,"▲ ","▼ ")&TEXT(ABS(I20),"0.0%"),"–") -> ▲ 28.9%
B21: EBIT (operating profit + gains and other income) | C21: =Income_Statement!D23 -> 39971 | D21: =Income_Statement!E23 -> 49673 | E21: =Income_Statement!F23 -> 60783 | F21: =D21-C21 -> 9702 | G21: =IFERROR(F21/ABS(C21),0) -> 0.24272598 | H21: =E21-D21 -> 11110 | I21: =IFERROR(H21/ABS(D21),0) -> 0.22366275 | J21: =IF(ABS(G21)>Var_Threshold,IF(G21>0,"▲ ","▼ ")&TEXT(ABS(G21),"0.0%"),"–") -> ▲ 24.3% | K21: =IF(ABS(I21)>Var_Threshold,IF(I21>0,"▲ ","▼ ")&TEXT(ABS(I21),"0.0%"),"–") -> ▲ 22.4%
B22: EBITDA | C22: =Income_Statement!D24 -> 57360 | D22: =Income_Statement!E24 -> 68923 | E22: =Income_Statement!F24 -> 82040 | F22: =D22-C22 -> 11563 | G22: =IFERROR(F22/ABS(C22),0) -> 0.20158647 | H22: =E22-D22 -> 13117 | I22: =IFERROR(H22/ABS(D22),0) -> 0.19031383 | J22: =IF(ABS(G22)>Var_Threshold,IF(G22>0,"▲ ","▼ ")&TEXT(ABS(G22),"0.0%"),"–") -> ▲ 20.2% | K22: =IF(ABS(I22)>Var_Threshold,IF(I22>0,"▲ ","▼ ")&TEXT(ABS(I22),"0.0%"),"–") -> ▲ 19.0%
B23: Total operating expenses (selling, G&A and depreciation) | C23: =Income_Statement!D25 -> 168920 | D23: =Income_Statement!E25 -> 180377 | E23: =Income_Statement!F25 -> 191161 | F23: =D23-C23 -> 11457 | G23: =IFERROR(F23/ABS(C23),0) -> 0.067825006 | H23: =E23-D23 -> 10784 | I23: =IFERROR(H23/ABS(D23),0) -> 0.059785893 | J23: =IF(ABS(G23)>Var_Threshold,IF(G23>0,"▲ ","▼ ")&TEXT(ABS(G23),"0.0%"),"–") -> – | K23: =IF(ABS(I23)>Var_Threshold,IF(I23>0,"▲ ","▼ ")&TEXT(ABS(I23),"0.0%"),"–") -> –
B24: STATEMENT OF FINANCIAL POSITION
B25: Cash and cash equivalents | C25: =Balance_Sheet!D8 -> 58216 | D25: =Balance_Sheet!E8 -> 80460 | E25: =Balance_Sheet!F8 -> 81748 | F25: =D25-C25 -> 22244 | G25: =IFERROR(F25/ABS(C25),0) -> 0.38209427 | H25: =E25-D25 -> 1288 | I25: =IFERROR(H25/ABS(D25),0) -> 0.016007954 | J25: =IF(ABS(G25)>Var_Threshold,IF(G25>0,"▲ ","▼ ")&TEXT(ABS(G25),"0.0%"),"–") -> ▲ 38.2% | K25: =IF(ABS(I25)>Var_Threshold,IF(I25>0,"▲ ","▼ ")&TEXT(ABS(I25),"0.0%"),"–") -> –
B26: Trade and other receivables | C26: =Balance_Sheet!D9 -> 80987 | D26: =Balance_Sheet!E9 -> 88495 | E26: =Balance_Sheet!F9 -> 93248 | F26: =D26-C26 -> 7508 | G26: =IFERROR(F26/ABS(C26),0) -> 0.092706237 | H26: =E26-D26 -> 4753 | I26: =IFERROR(H26/ABS(D26),0) -> 0.053709249 | J26: =IF(ABS(G26)>Var_Threshold,IF(G26>0,"▲ ","▼ ")&TEXT(ABS(G26),"0.0%"),"–") -> – | K26: =IF(ABS(I26)>Var_Threshold,IF(I26>0,"▲ ","▼ ")&TEXT(ABS(I26),"0.0%"),"–") -> –
B27: Inventories | C27: =Balance_Sheet!D10 -> 75696 | D27: =Balance_Sheet!E10 -> 80593 | E27: =Balance_Sheet!F10 -> 85122 | F27: =D27-C27 -> 4897 | G27: =IFERROR(F27/ABS(C27),0) -> 0.064692982 | H27: =E27-D27 -> 4529 | I27: =IFERROR(H27/ABS(D27),0) -> 0.056195948 | J27: =IF(ABS(G27)>Var_Threshold,IF(G27>0,"▲ ","▼ ")&TEXT(ABS(G27),"0.0%"),"–") -> – | K27: =IF(ABS(I27)>Var_Threshold,IF(I27>0,"▲ ","▼ ")&TEXT(ABS(I27),"0.0%"),"–") -> –
B28: Prepayments and other current assets | C28: =Balance_Sheet!D11 -> 11365 | D28: =Balance_Sheet!E11 -> 12085 | E28: =Balance_Sheet!F11 -> 12743 | F28: =D28-C28 -> 720 | G28: =IFERROR(F28/ABS(C28),0) -> 0.063352398 | H28: =E28-D28 -> 658 | I28: =IFERROR(H28/ABS(D28),0) -> 0.054447662 | J28: =IF(ABS(G28)>Var_Threshold,IF(G28>0,"▲ ","▼ ")&TEXT(ABS(G28),"0.0%"),"–") -> – | K28: =IF(ABS(I28)>Var_Threshold,IF(I28>0,"▲ ","▼ ")&TEXT(ABS(I28),"0.0%"),"–") -> –
B29: Total current assets | C29: =Balance_Sheet!D12 -> 226264 | D29: =Balance_Sheet!E12 -> 261633 | E29: =Balance_Sheet!F12 -> 272861 | F29: =D29-C29 -> 35369 | G29: =IFERROR(F29/ABS(C29),0) -> 0.1563174 | H29: =E29-D29 -> 11228 | I29: =IFERROR(H29/ABS(D29),0) -> 0.042915076 | J29: =IF(ABS(G29)>Var_Threshold,IF(G29>0,"▲ ","▼ ")&TEXT(ABS(G29),"0.0%"),"–") -> ▲ 15.6% | K29: =IF(ABS(I29)>Var_Threshold,IF(I29>0,"▲ ","▼ ")&TEXT(ABS(I29),"0.0%"),"–") -> –
B30: Property, plant and equipment, net | C30: =Balance_Sheet!D14 -> 178711 | D30: =Balance_Sheet!E14 -> 189761 | E30: =Balance_Sheet!F14 -> 194504 | F30: =D30-C30 -> 11050 | G30: =IFERROR(F30/ABS(C30),0) -> 0.061831672 | H30: =E30-D30 -> 4743 | I30: =IFERROR(H30/ABS(D30),0) -> 0.024994598 | J30: =IF(ABS(G30)>Var_Threshold,IF(G30>0,"▲ ","▼ ")&TEXT(ABS(G30),"0.0%"),"–") -> – | K30: =IF(ABS(I30)>Var_Threshold,IF(I30>0,"▲ ","▼ ")&TEXT(ABS(I30),"0.0%"),"–") -> –
B31: Other non-current assets | C31: =Balance_Sheet!D15 -> 10200 | D31: =Balance_Sheet!E15 -> 10500 | E31: =Balance_Sheet!F15 -> 11100 | F31: =D31-C31 -> 300 | G31: =IFERROR(F31/ABS(C31),0) -> 0.029411765 | H31: =E31-D31 -> 600 | I31: =IFERROR(H31/ABS(D31),0) -> 0.057142857 | J31: =IF(ABS(G31)>Var_Threshold,IF(G31>0,"▲ ","▼ ")&TEXT(ABS(G31),"0.0%"),"–") -> – | K31: =IF(ABS(I31)>Var_Threshold,IF(I31>0,"▲ ","▼ ")&TEXT(ABS(I31),"0.0%"),"–") -> –
B32: Total non-current assets | C32: =Balance_Sheet!D16 -> 188911 | D32: =Balance_Sheet!E16 -> 200261 | E32: =Balance_Sheet!F16 -> 205604 | F32: =D32-C32 -> 11350 | G32: =IFERROR(F32/ABS(C32),0) -> 0.060081202 | H32: =E32-D32 -> 5343 | I32: =IFERROR(H32/ABS(D32),0) -> 0.026680182 | J32: =IF(ABS(G32)>Var_Threshold,IF(G32>0,"▲ ","▼ ")&TEXT(ABS(G32),"0.0%"),"–") -> – | K32: =IF(ABS(I32)>Var_Threshold,IF(I32>0,"▲ ","▼ ")&TEXT(ABS(I32),"0.0%"),"–") -> –
B33: TOTAL ASSETS | C33: =Balance_Sheet!D17 -> 415175 | D33: =Balance_Sheet!E17 -> 461894 | E33: =Balance_Sheet!F17 -> 478465 | F33: =D33-C33 -> 46719 | G33: =IFERROR(F33/ABS(C33),0) -> 0.11252845 | H33: =E33-D33 -> 16571 | I33: =IFERROR(H33/ABS(D33),0) -> 0.035876197 | J33: =IF(ABS(G33)>Var_Threshold,IF(G33>0,"▲ ","▼ ")&TEXT(ABS(G33),"0.0%"),"–") -> ▲ 11.3% | K33: =IF(ABS(I33)>Var_Threshold,IF(I33>0,"▲ ","▼ ")&TEXT(ABS(I33),"0.0%"),"–") -> –
B34: Trade and other payables | C34: =Balance_Sheet!D21 -> 67285 | D34: =Balance_Sheet!E21 -> 75098 | E34: =Balance_Sheet!F21 -> 83143 | F34: =D34-C34 -> 7813 | G34: =IFERROR(F34/ABS(C34),0) -> 0.11611801 | H34: =E34-D34 -> 8045 | I34: =IFERROR(H34/ABS(D34),0) -> 0.10712669 | J34: =IF(ABS(G34)>Var_Threshold,IF(G34>0,"▲ ","▼ ")&TEXT(ABS(G34),"0.0%"),"–") -> ▲ 11.6% | K34: =IF(ABS(I34)>Var_Threshold,IF(I34>0,"▲ ","▼ ")&TEXT(ABS(I34),"0.0%"),"–") -> ▲ 10.7%
B35: Accrued expenses | C35: =Balance_Sheet!D22 -> 13638 | D35: =Balance_Sheet!E22 -> 14501 | E35: =Balance_Sheet!F22 -> 15291 | F35: =D35-C35 -> 863 | G35: =IFERROR(F35/ABS(C35),0) -> 0.063279073 | H35: =E35-D35 -> 790 | I35: =IFERROR(H35/ABS(D35),0) -> 0.054479001 | J35: =IF(ABS(G35)>Var_Threshold,IF(G35>0,"▲ ","▼ ")&TEXT(ABS(G35),"0.0%"),"–") -> – | K35: =IF(ABS(I35)>Var_Threshold,IF(I35>0,"▲ ","▼ ")&TEXT(ABS(I35),"0.0%"),"–") -> –
B36: Income tax payable | C36: =Balance_Sheet!D23 -> 1691 | D36: =Balance_Sheet!E23 -> 1977 | E36: =Balance_Sheet!F23 -> 2529 | F36: =D36-C36 -> 286 | G36: =IFERROR(F36/ABS(C36),0) -> 0.16913069 | H36: =E36-D36 -> 552 | I36: =IFERROR(H36/ABS(D36),0) -> 0.27921093 | J36: =IF(ABS(G36)>Var_Threshold,IF(G36>0,"▲ ","▼ ")&TEXT(ABS(G36),"0.0%"),"–") -> ▲ 16.9% | K36: =IF(ABS(I36)>Var_Threshold,IF(I36>0,"▲ ","▼ ")&TEXT(ABS(I36),"0.0%"),"–") -> ▲ 27.9%
B37: Short-term loans | C37: =Balance_Sheet!D24 -> 48000 | D37: =Balance_Sheet!E24 -> 42000 | E37: =Balance_Sheet!F24 -> 38000 | F37: =D37-C37 -> -6000 | G37: =IFERROR(F37/ABS(C37),0) -> -0.125 | H37: =E37-D37 -> -4000 | I37: =IFERROR(H37/ABS(D37),0) -> -0.095238095 | J37: =IF(ABS(G37)>Var_Threshold,IF(G37>0,"▲ ","▼ ")&TEXT(ABS(G37),"0.0%"),"–") -> ▼ 12.5% | K37: =IF(ABS(I37)>Var_Threshold,IF(I37>0,"▲ ","▼ ")&TEXT(ABS(I37),"0.0%"),"–") -> –
B38: Current portion of long-term loans | C38: =Balance_Sheet!D25 -> 13000 | D38: =Balance_Sheet!E25 -> 15000 | E38: =Balance_Sheet!F25 -> 16500 | F38: =D38-C38 -> 2000 | G38: =IFERROR(F38/ABS(C38),0) -> 0.15384615 | H38: =E38-D38 -> 1500 | I38: =IFERROR(H38/ABS(D38),0) -> 0.1 | J38: =IF(ABS(G38)>Var_Threshold,IF(G38>0,"▲ ","▼ ")&TEXT(ABS(G38),"0.0%"),"–") -> ▲ 15.4% | K38: =IF(ABS(I38)>Var_Threshold,IF(I38>0,"▲ ","▼ ")&TEXT(ABS(I38),"0.0%"),"–") -> –
B39: Total current liabilities | C39: =Balance_Sheet!D26 -> 143614 | D39: =Balance_Sheet!E26 -> 148576 | E39: =Balance_Sheet!F26 -> 155463 | F39: =D39-C39 -> 4962 | G39: =IFERROR(F39/ABS(C39),0) -> 0.034550949 | H39: =E39-D39 -> 6887 | I39: =IFERROR(H39/ABS(D39),0) -> 0.046353381 | J39: =IF(ABS(G39)>Var_Threshold,IF(G39>0,"▲ ","▼ ")&TEXT(ABS(G39),"0.0%"),"–") -> – | K39: =IF(ABS(I39)>Var_Threshold,IF(I39>0,"▲ ","▼ ")&TEXT(ABS(I39),"0.0%"),"–") -> –
B40: Long-term loans, net of current portion | C40: =Balance_Sheet!D28 -> 75000 | D40: =Balance_Sheet!E28 -> 95000 | E40: =Balance_Sheet!F28 -> 78500 | F40: =D40-C40 -> 20000 | G40: =IFERROR(F40/ABS(C40),0) -> 0.26666667 | H40: =E40-D40 -> -16500 | I40: =IFERROR(H40/ABS(D40),0) -> -0.17368421 | J40: =IF(ABS(G40)>Var_Threshold,IF(G40>0,"▲ ","▼ ")&TEXT(ABS(G40),"0.0%"),"–") -> ▲ 26.7% | K40: =IF(ABS(I40)>Var_Threshold,IF(I40>0,"▲ ","▼ ")&TEXT(ABS(I40),"0.0%"),"–") -> ▼ 17.4%
B41: Total liabilities | C41: =Balance_Sheet!D29 -> 218614 | D41: =Balance_Sheet!E29 -> 243576 | E41: =Balance_Sheet!F29 -> 233963 | F41: =D41-C41 -> 24962 | G41: =IFERROR(F41/ABS(C41),0) -> 0.11418299 | H41: =E41-D41 -> -9613 | I41: =IFERROR(H41/ABS(D41),0) -> -0.039466121 | J41: =IF(ABS(G41)>Var_Threshold,IF(G41>0,"▲ ","▼ ")&TEXT(ABS(G41),"0.0%"),"–") -> ▲ 11.4% | K41: =IF(ABS(I41)>Var_Threshold,IF(I41>0,"▲ ","▼ ")&TEXT(ABS(I41),"0.0%"),"–") -> –
B42: Share capital | C42: =Balance_Sheet!D31 -> 120000 | D42: =Balance_Sheet!E31 -> 120000 | E42: =Balance_Sheet!F31 -> 120000 | F42: =D42-C42 -> 0 | G42: =IFERROR(F42/ABS(C42),0) -> 0 | H42: =E42-D42 -> 0 | I42: =IFERROR(H42/ABS(D42),0) -> 0 | J42: =IF(ABS(G42)>Var_Threshold,IF(G42>0,"▲ ","▼ ")&TEXT(ABS(G42),"0.0%"),"–") -> – | K42: =IF(ABS(I42)>Var_Threshold,IF(I42>0,"▲ ","▼ ")&TEXT(ABS(I42),"0.0%"),"–") -> –
B43: Additional paid-in capital | C43: =Balance_Sheet!D32 -> 18000 | D43: =Balance_Sheet!E32 -> 18000 | E43: =Balance_Sheet!F32 -> 18000 | F43: =D43-C43 -> 0 | G43: =IFERROR(F43/ABS(C43),0) -> 0 | H43: =E43-D43 -> 0 | I43: =IFERROR(H43/ABS(D43),0) -> 0 | J43: =IF(ABS(G43)>Var_Threshold,IF(G43>0,"▲ ","▼ ")&TEXT(ABS(G43),"0.0%"),"–") -> – | K43: =IF(ABS(I43)>Var_Threshold,IF(I43>0,"▲ ","▼ ")&TEXT(ABS(I43),"0.0%"),"–") -> –
B44: Retained earnings | C44: =Balance_Sheet!D33 -> 58561 | D44: =Balance_Sheet!E33 -> 80318 | E44: =Balance_Sheet!F33 -> 106502 | F44: =D44-C44 -> 21757 | G44: =IFERROR(F44/ABS(C44),0) -> 0.37152713 | H44: =E44-D44 -> 26184 | I44: =IFERROR(H44/ABS(D44),0) -> 0.32600413 | J44: =IF(ABS(G44)>Var_Threshold,IF(G44>0,"▲ ","▼ ")&TEXT(ABS(G44),"0.0%"),"–") -> ▲ 37.2% | K44: =IF(ABS(I44)>Var_Threshold,IF(I44>0,"▲ ","▼ ")&TEXT(ABS(I44),"0.0%"),"–") -> ▲ 32.6%
B45: Total equity | C45: =Balance_Sheet!D34 -> 196561 | D45: =Balance_Sheet!E34 -> 218318 | E45: =Balance_Sheet!F34 -> 244502 | F45: =D45-C45 -> 21757 | G45: =IFERROR(F45/ABS(C45),0) -> 0.11068829 | H45: =E45-D45 -> 26184 | I45: =IFERROR(H45/ABS(D45),0) -> 0.11993514 | J45: =IF(ABS(G45)>Var_Threshold,IF(G45>0,"▲ ","▼ ")&TEXT(ABS(G45),"0.0%"),"–") -> ▲ 11.1% | K45: =IF(ABS(I45)>Var_Threshold,IF(I45>0,"▲ ","▼ ")&TEXT(ABS(I45),"0.0%"),"–") -> ▲ 12.0%
B46: TOTAL LIABILITIES AND EQUITY | C46: =Balance_Sheet!D35 -> 415175 | D46: =Balance_Sheet!E35 -> 461894 | E46: =Balance_Sheet!F35 -> 478465 | F46: =D46-C46 -> 46719 | G46: =IFERROR(F46/ABS(C46),0) -> 0.11252845 | H46: =E46-D46 -> 16571 | I46: =IFERROR(H46/ABS(D46),0) -> 0.035876197 | J46: =IF(ABS(G46)>Var_Threshold,IF(G46>0,"▲ ","▼ ")&TEXT(ABS(G46),"0.0%"),"–") -> ▲ 11.3% | K46: =IF(ABS(I46)>Var_Threshold,IF(I46>0,"▲ ","▼ ")&TEXT(ABS(I46),"0.0%"),"–") -> –

Sheet Vertical
B1: Vertical Analysis
B2: =Inputs!$C$6&" | "&Inputs!$C$11 -> Sampaguita Foods & Distribution Corporation (SFDC) | PHP in thousands (unless otherwise stated)
B3: =HYPERLINK("#Cover!A1","◄ Back to Cover") -> ◄ Back to Cover
B4: Income statement lines as % of net sales; balance sheet lines as % of total assets.
B5: PHP '000 | C5: =Inputs!D$22 -> 2023 | D5: =Inputs!E$22 -> 2024 | E5: =Inputs!F$22 -> 2025 | F5: ="% FY"&Inputs!D$22 -> % FY2023 | G5: ="% FY"&Inputs!E$22 -> % FY2024 | H5: ="% FY"&Inputs!F$22 -> % FY2025 | I5: Change in % pts (FY25 vs FY23)
B6: INCOME STATEMENT
B7: Net sales | C7: =Income_Statement!D7 -> 821118 | D7: =Income_Statement!E7 -> 897238 | E7: =Income_Statement!F7 -> 972442 | F7: =IFERROR(C7/C$7,0) -> 1 | G7: =IFERROR(D7/D$7,0) -> 1 | H7: =IFERROR(E7/E$7,0) -> 1 | I7: =H7-F7 -> 0
B8: Cost of sales | C8: =Income_Statement!D8 -> -613977 | D8: =Income_Statement!E8 -> -668558 | E8: =Income_Statement!F8 -> -722548 | F8: =IFERROR(C8/C$7,0) -> -0.74773297 | G8: =IFERROR(D8/D$7,0) -> -0.74512894 | H8: =IFERROR(E8/E$7,0) -> -0.74302426 | I8: =H8-F8 -> 0.0047087063
B9: Gross profit | C9: =Income_Statement!D9 -> 207141 | D9: =Income_Statement!E9 -> 228680 | E9: =Income_Statement!F9 -> 249894 | F9: =IFERROR(C9/C$7,0) -> 0.25226703 | G9: =IFERROR(D9/D$7,0) -> 0.25487106 | H9: =IFERROR(E9/E$7,0) -> 0.25697574 | I9: =H9-F9 -> 0.0047087063
B10: Selling and distribution expenses | C10: =Income_Statement!D10 -> -93216 | D10: =Income_Statement!E10 -> -99930 | E10: =Income_Statement!F10 -> -106077 | F10: =IFERROR(C10/C$7,0) -> -0.11352327 | G10: =IFERROR(D10/D$7,0) -> -0.11137513 | H10: =IFERROR(E10/E$7,0) -> -0.10908311 | I10: =H10-F10 -> 0.0044401571
B11: General and administrative expenses | C11: =Income_Statement!D11 -> -58315 | D11: =Income_Statement!E11 -> -61197 | E11: =Income_Statement!F11 -> -63827 | F11: =IFERROR(C11/C$7,0) -> -0.071019025 | G11: =IFERROR(D11/D$7,0) -> -0.068205983 | H11: =IFERROR(E11/E$7,0) -> -0.065635791 | I11: =H11-F11 -> 0.0053832341
B12: Depreciation | C12: =Income_Statement!D12 -> -17389 | D12: =Income_Statement!E12 -> -19250 | E12: =Income_Statement!F12 -> -21257 | F12: =IFERROR(C12/C$7,0) -> -0.021177224 | G12: =IFERROR(D12/D$7,0) -> -0.021454731 | H12: =IFERROR(E12/E$7,0) -> -0.021859401 | I12: =H12-F12 -> -0.00068217716
B13: Operating profit | C13: =Income_Statement!D13 -> 38221 | D13: =Income_Statement!E13 -> 48303 | E13: =Income_Statement!F13 -> 58733 | F13: =IFERROR(C13/C$7,0) -> 0.046547512 | G13: =IFERROR(D13/D$7,0) -> 0.053835214 | H13: =IFERROR(E13/E$7,0) -> 0.060397432 | I13: =H13-F13 -> 0.01384992
B14: Gain / (loss) on disposal of property and equipment | C14: =Income_Statement!D14 -> 400 | D14: =Income_Statement!E14 -> -150 | E14: =Income_Statement!F14 -> 350 | F14: =IFERROR(C14/C$7,0) -> 0.0004871407 | G14: =IFERROR(D14/D$7,0) -> -0.00016717972 | H14: =IFERROR(E14/E$7,0) -> 0.00035991864 | I14: =H14-F14 -> -0.00012722207
B15: Other income | C15: =Income_Statement!D15 -> 1350 | D15: =Income_Statement!E15 -> 1520 | E15: =Income_Statement!F15 -> 1700 | F15: =IFERROR(C15/C$7,0) -> 0.0016440999 | G15: =IFERROR(D15/D$7,0) -> 0.0016940879 | H15: =IFERROR(E15/E$7,0) -> 0.0017481762 | I15: =H15-F15 -> 0.00010407637
B16: Interest income | C16: =Income_Statement!D16 -> 775 | D16: =Income_Statement!E16 -> 873 | E16: =Income_Statement!F16 -> 1207 | F16: =IFERROR(C16/C$7,0) -> 0.00094383511 | G16: =IFERROR(D16/D$7,0) -> 0.00097298599 | H16: =IFERROR(E16/E$7,0) -> 0.0012412051 | I16: =H16-F16 -> 0.00029737002
B17: Finance costs | C17: =Income_Statement!D17 -> -10421 | D17: =Income_Statement!E17 -> -11475 | E17: =Income_Statement!F17 -> -11696 | F17: =IFERROR(C17/C$7,0) -> -0.012691233 | G17: =IFERROR(D17/D$7,0) -> -0.012789249 | H17: =IFERROR(E17/E$7,0) -> -0.012027453 | I17: =H17-F17 -> 0.00066378064
B18: Profit before income tax | C18: =Income_Statement!D18 -> 30325 | D18: =Income_Statement!E18 -> 39071 | E18: =Income_Statement!F18 -> 50294 | F18: =IFERROR(C18/C$7,0) -> 0.036931355 | G18: =IFERROR(D18/D$7,0) -> 0.04354586 | H18: =IFERROR(E18/E$7,0) -> 0.05171928 | I18: =H18-F18 -> 0.014787925
... B20: Net profit for the year | C20: =Income_Statement!D20 -> 22482 | D20: =Income_Statement!E20 -> 29009 | E20: =Income_Statement!F20 -> 37406 | F20: =IFERROR(C20/C$7,0) -> 0.027379743 | G20: =IFERROR(D20/D$7,0) -> 0.032331444 | H20: =IFERROR(E20/E$7,0) -> 0.038466047 | I20: =H20-F20 -> 0.011086304
B21: EBIT (operating profit + gains and other income) | C21: =Income_Statement!D23 -> 39971 | D21: =Income_Statement!E23 -> 49673 | E21: =Income_Statement!F23 -> 60783 | F21: =IFERROR(C21/C$7,0) -> 0.048678753 | G21: =IFERROR(D21/D$7,0) -> 0.055362122 | H21: =IFERROR(E21/E$7,0) -> 0.062505527 | I21: =H21-F21 -> 0.013826775
B22: EBITDA | C22: =Income_Statement!D24 -> 57360 | D22: =Income_Statement!E24 -> 68923 | E22: =Income_Statement!F24 -> 82040 | F22: =IFERROR(C22/C$7,0) -> 0.069855977 | G22: =IFERROR(D22/D$7,0) -> 0.076816853 | H22: =IFERROR(E22/E$7,0) -> 0.084364929 | I22: =H22-F22 -> 0.014508952
B23: Total operating expenses (selling, G&A and depreciation) | C23: =Income_Statement!D25 -> 168920 | D23: =Income_Statement!E25 -> 180377 | E23: =Income_Statement!F25 -> 191161 | F23: =IFERROR(C23/C$7,0) -> 0.20571952 | G23: =IFERROR(D23/D$7,0) -> 0.20103585 | H23: =IFERROR(E23/E$7,0) -> 0.1965783 | I23: =H23-F23 -> -0.0091412141
B24: STATEMENT OF FINANCIAL POSITION
B25: Cash and cash equivalents | C25: =Balance_Sheet!D8 -> 58216 | D25: =Balance_Sheet!E8 -> 80460 | E25: =Balance_Sheet!F8 -> 81748 | F25: =IFERROR(C25/C$33,0) -> 0.14022039 | G25: =IFERROR(D25/D$33,0) -> 0.17419581 | H25: =IFERROR(E25/E$33,0) -> 0.17085471 | I25: =H25-F25 -> 0.030634323
B26: Trade and other receivables | C26: =Balance_Sheet!D9 -> 80987 | D26: =Balance_Sheet!E9 -> 88495 | E26: =Balance_Sheet!F9 -> 93248 | F26: =IFERROR(C26/C$33,0) -> 0.19506714 | G26: =IFERROR(D26/D$33,0) -> 0.19159158 | H26: =IFERROR(E26/E$33,0) -> 0.19488991 | I26: =H26-F26 -> -0.00017723201
B27: Inventories | C27: =Balance_Sheet!D10 -> 75696 | D27: =Balance_Sheet!E10 -> 80593 | E27: =Balance_Sheet!F10 -> 85122 | F27: =IFERROR(C27/C$33,0) -> 0.18232312 | G27: =IFERROR(D27/D$33,0) -> 0.17448376 | H27: =IFERROR(E27/E$33,0) -> 0.17790643 | I27: =H27-F27 -> -0.0044166868
B28: Prepayments and other current assets | C28: =Balance_Sheet!D11 -> 11365 | D28: =Balance_Sheet!E11 -> 12085 | E28: =Balance_Sheet!F11 -> 12743 | F28: =IFERROR(C28/C$33,0) -> 0.027373999 | G28: =IFERROR(D28/D$33,0) -> 0.026164012 | H28: =IFERROR(E28/E$33,0) -> 0.026633087 | I28: =H28-F28 -> -0.00074091186
B29: Total current assets | C29: =Balance_Sheet!D12 -> 226264 | D29: =Balance_Sheet!E12 -> 261633 | E29: =Balance_Sheet!F12 -> 272861 | F29: =IFERROR(C29/C$33,0) -> 0.54498465 | G29: =IFERROR(D29/D$33,0) -> 0.56643516 | H29: =IFERROR(E29/E$33,0) -> 0.57028414 | I29: =H29-F29 -> 0.025299493
B30: Property, plant and equipment, net | C30: =Balance_Sheet!D14 -> 178711 | D30: =Balance_Sheet!E14 -> 189761 | E30: =Balance_Sheet!F14 -> 194504 | F30: =IFERROR(C30/C$33,0) -> 0.4304474 | G30: =IFERROR(D30/D$33,0) -> 0.41083236 | H30: =IFERROR(E30/E$33,0) -> 0.40651667 | I30: =H30-F30 -> -0.023930729
B31: Other non-current assets | C31: =Balance_Sheet!D15 -> 10200 | D31: =Balance_Sheet!E15 -> 10500 | E31: =Balance_Sheet!F15 -> 11100 | F31: =IFERROR(C31/C$33,0) -> 0.024567953 | G31: =IFERROR(D31/D$33,0) -> 0.022732488 | H31: =IFERROR(E31/E$33,0) -> 0.023199189 | I31: =H31-F31 -> -0.0013687642
B32: Total non-current assets | C32: =Balance_Sheet!D16 -> 188911 | D32: =Balance_Sheet!E16 -> 200261 | E32: =Balance_Sheet!F16 -> 205604 | F32: =IFERROR(C32/C$33,0) -> 0.45501535 | G32: =IFERROR(D32/D$33,0) -> 0.43356484 | H32: =IFERROR(E32/E$33,0) -> 0.42971586 | I32: =H32-F32 -> -0.025299493
B33: TOTAL ASSETS | C33: =Balance_Sheet!D17 -> 415175 | D33: =Balance_Sheet!E17 -> 461894 | E33: =Balance_Sheet!F17 -> 478465 | F33: =IFERROR(C33/C$33,0) -> 1 | G33: =IFERROR(D33/D$33,0) -> 1 | H33: =IFERROR(E33/E$33,0) -> 1 | I33: =H33-F33 -> 0
B34: Trade and other payables | C34: =Balance_Sheet!D21 -> 67285 | D34: =Balance_Sheet!E21 -> 75098 | E34: =Balance_Sheet!F21 -> 83143 | F34: =IFERROR(C34/C$33,0) -> 0.16206419 | G34: =IFERROR(D34/D$33,0) -> 0.16258709 | H34: =IFERROR(E34/E$33,0) -> 0.17377029 | I34: =H34-F34 -> 0.011706096
B35: Accrued expenses | C35: =Balance_Sheet!D22 -> 13638 | D35: =Balance_Sheet!E22 -> 14501 | E35: =Balance_Sheet!F22 -> 15291 | F35: =IFERROR(C35/C$33,0) -> 0.032848799 | G35: =IFERROR(D35/D$33,0) -> 0.031394649 | H35: =IFERROR(E35/E$33,0) -> 0.03195845 | I35: =H35-F35 -> -0.00089034824
B36: Income tax payable | C36: =Balance_Sheet!D23 -> 1691 | D36: =Balance_Sheet!E23 -> 1977 | E36: =Balance_Sheet!F23 -> 2529 | F36: =IFERROR(C36/C$33,0) -> 0.0040729813 | G36: =IFERROR(D36/D$33,0) -> 0.0042802028 | H36: =IFERROR(E36/E$33,0) -> 0.0052856531 | I36: =H36-F36 -> 0.0012126718
B37: Short-term loans | C37: =Balance_Sheet!D24 -> 48000 | D37: =Balance_Sheet!E24 -> 42000 | E37: =Balance_Sheet!F24 -> 38000 | F37: =IFERROR(C37/C$33,0) -> 0.1156139 | G37: =IFERROR(D37/D$33,0) -> 0.090929954 | H37: =IFERROR(E37/E$33,0) -> 0.079420647 | I37: =H37-F37 -> -0.03619325
B38: Current portion of long-term loans | C38: =Balance_Sheet!D25 -> 13000 | D38: =Balance_Sheet!E25 -> 15000 | E38: =Balance_Sheet!F25 -> 16500 | F38: =IFERROR(C38/C$33,0) -> 0.031312097 | G38: =IFERROR(D38/D$33,0) -> 0.032474983 | H38: =IFERROR(E38/E$33,0) -> 0.034485281 | I38: =H38-F38 -> 0.0031731837
B39: Total current liabilities | C39: =Balance_Sheet!D26 -> 143614 | D39: =Balance_Sheet!E26 -> 148576 | E39: =Balance_Sheet!F26 -> 155463 | F39: =IFERROR(C39/C$33,0) -> 0.34591196 | G39: =IFERROR(D39/D$33,0) -> 0.32166688 | H39: =IFERROR(E39/E$33,0) -> 0.32492032 | I39: =H39-F39 -> -0.020991647
B40: Long-term loans, net of current portion | C40: =Balance_Sheet!D28 -> 75000 | D40: =Balance_Sheet!E28 -> 95000 | E40: =Balance_Sheet!F28 -> 78500 | F40: =IFERROR(C40/C$33,0) -> 0.18064672 | G40: =IFERROR(D40/D$33,0) -> 0.2056749 | H40: =IFERROR(E40/E$33,0) -> 0.16406634 | I40: =H40-F40 -> -0.016580378
B41: Total liabilities | C41: =Balance_Sheet!D29 -> 218614 | D41: =Balance_Sheet!E29 -> 243576 | E41: =Balance_Sheet!F29 -> 233963 | F41: =IFERROR(C41/C$33,0) -> 0.52655868 | G41: =IFERROR(D41/D$33,0) -> 0.52734177 | H41: =IFERROR(E41/E$33,0) -> 0.48898666 | I41: =H41-F41 -> -0.037572025
B42: Share capital | C42: =Balance_Sheet!D31 -> 120000 | D42: =Balance_Sheet!E31 -> 120000 | E42: =Balance_Sheet!F31 -> 120000 | F42: =IFERROR(C42/C$33,0) -> 0.28903474 | G42: =IFERROR(D42/D$33,0) -> 0.25979987 | H42: =IFERROR(E42/E$33,0) -> 0.25080204 | I42: =H42-F42 -> -0.0382327
B43: Additional paid-in capital | C43: =Balance_Sheet!D32 -> 18000 | D43: =Balance_Sheet!E32 -> 18000 | E43: =Balance_Sheet!F32 -> 18000 | F43: =IFERROR(C43/C$33,0) -> 0.043355212 | G43: =IFERROR(D43/D$33,0) -> 0.03896998 | H43: =IFERROR(E43/E$33,0) -> 0.037620307 | I43: =H43-F43 -> -0.0057349051
B44: Retained earnings | C44: =Balance_Sheet!D33 -> 58561 | D44: =Balance_Sheet!E33 -> 80318 | E44: =Balance_Sheet!F33 -> 106502 | F44: =IFERROR(C44/C$33,0) -> 0.14105136 | G44: =IFERROR(D44/D$33,0) -> 0.17388838 | H44: =IFERROR(E44/E$33,0) -> 0.22259099 | I44: =H44-F44 -> 0.08153963
B45: Total equity | C45: =Balance_Sheet!D34 -> 196561 | D45: =Balance_Sheet!E34 -> 218318 | E45: =Balance_Sheet!F34 -> 244502 | F45: =IFERROR(C45/C$33,0) -> 0.47344132 | G45: =IFERROR(D45/D$33,0) -> 0.47265823 | H45: =IFERROR(E45/E$33,0) -> 0.51101334 | I45: =H45-F45 -> 0.037572025
B46: TOTAL LIABILITIES AND EQUITY | C46: =Balance_Sheet!D35 -> 415175 | D46: =Balance_Sheet!E35 -> 461894 | E46: =Balance_Sheet!F35 -> 478465 | F46: =IFERROR(C46/C$33,0) -> 1 | G46: =IFERROR(D46/D$33,0) -> 1 | H46: =IFERROR(E46/E$33,0) -> 1 | I46: =H46-F46 -> 0

Sheet Common_Size
B1: Common-Size Statements
B2: =Inputs!$C$6&" | "&Inputs!$C$11 -> Sampaguita Foods & Distribution Corporation (SFDC) | PHP in thousands (unless otherwise stated)
B3: =HYPERLINK("#Cover!A1","◄ Back to Cover") -> ◄ Back to Cover
B4: Every line is expressed as a percentage of net sales (income statement) or total assets (balance sheet). Choose two years to compare.
B5: Compare year A | C5: 2023
B6: Compare year B | C6: 2025
B8: Common-size % | C8: =Inputs!D$22 -> 2023 | D8: =Inputs!E$22 -> 2024 | E8: =Inputs!F$22 -> 2025 | F8: ="FY"&Cs_YearA -> FY2023 | G8: ="FY"&Cs_YearB -> FY2025 | H8: Change (pts)
B9: INCOME STATEMENT
B10: Net sales | C10: =Vertical!F7 -> 1 | D10: =Vertical!G7 -> 1 | E10: =Vertical!H7 -> 1 | F10: =INDEX(C10:E10,MATCH(Cs_YearA,FY_List,0)) -> 1 | G10: =INDEX(C10:E10,MATCH(Cs_YearB,FY_List,0)) -> 1 | H10: =G10-F10 -> 0
B11: Cost of sales | C11: =Vertical!F8 -> -0.74773297 | D11: =Vertical!G8 -> -0.74512894 | E11: =Vertical!H8 -> -0.74302426 | F11: =INDEX(C11:E11,MATCH(Cs_YearA,FY_List,0)) -> -0.74773297 | G11: =INDEX(C11:E11,MATCH(Cs_YearB,FY_List,0)) -> -0.74302426 | H11: =G11-F11 -> 0.0047087063
B12: Gross profit | C12: =Vertical!F9 -> 0.25226703 | D12: =Vertical!G9 -> 0.25487106 | E12: =Vertical!H9 -> 0.25697574 | F12: =INDEX(C12:E12,MATCH(Cs_YearA,FY_List,0)) -> 0.25226703 | G12: =INDEX(C12:E12,MATCH(Cs_YearB,FY_List,0)) -> 0.25697574 | H12: =G12-F12 -> 0.0047087063
B13: Selling and distribution expenses | C13: =Vertical!F10 -> -0.11352327 | D13: =Vertical!G10 -> -0.11137513 | E13: =Vertical!H10 -> -0.10908311 | F13: =INDEX(C13:E13,MATCH(Cs_YearA,FY_List,0)) -> -0.11352327 | G13: =INDEX(C13:E13,MATCH(Cs_YearB,FY_List,0)) -> -0.10908311 | H13: =G13-F13 -> 0.0044401571
B14: General and administrative expenses | C14: =Vertical!F11 -> -0.071019025 | D14: =Vertical!G11 -> -0.068205983 | E14: =Vertical!H11 -> -0.065635791 | F14: =INDEX(C14:E14,MATCH(Cs_YearA,FY_List,0)) -> -0.071019025 | G14: =INDEX(C14:E14,MATCH(Cs_YearB,FY_List,0)) -> -0.065635791 | H14: =G14-F14 -> 0.0053832341
B15: Depreciation | C15: =Vertical!F12 -> -0.021177224 | D15: =Vertical!G12 -> -0.021454731 | E15: =Vertical!H12 -> -0.021859401 | F15: =INDEX(C15:E15,MATCH(Cs_YearA,FY_List,0)) -> -0.021177224 | G15: =INDEX(C15:E15,MATCH(Cs_YearB,FY_List,0)) -> -0.021859401 | H15: =G15-F15 -> -0.00068217716
B16: Operating profit | C16: =Vertical!F13 -> 0.046547512 | D16: =Vertical!G13 -> 0.053835214 | E16: =Vertical!H13 -> 0.060397432 | F16: =INDEX(C16:E16,MATCH(Cs_YearA,FY_List,0)) -> 0.046547512 | G16: =INDEX(C16:E16,MATCH(Cs_YearB,FY_List,0)) -> 0.060397432 | H16: =G16-F16 -> 0.01384992
B17: Gain / (loss) on disposal of property and equipment | C17: =Vertical!F14 -> 0.0004871407 | D17: =Vertical!G14 -> -0.00016717972 | E17: =Vertical!H14 -> 0.00035991864 | F17: =INDEX(C17:E17,MATCH(Cs_YearA,FY_List,0)) -> 0.0004871407 | G17: =INDEX(C17:E17,MATCH(Cs_YearB,FY_List,0)) -> 0.00035991864 | H17: =G17-F17 -> -0.00012722207
B18: Other income | C18: =Vertical!F15 -> 0.0016440999 | D18: =Vertical!G15 -> 0.0016940879 | E18: =Vertical!H15 -> 0.0017481762 | F18: =INDEX(C18:E18,MATCH(Cs_YearA,FY_List,0)) -> 0.0016440999 | G18: =INDEX(C18:E18,MATCH(Cs_YearB,FY_List,0)) -> 0.0017481762 | H18: =G18-F18 -> 0.00010407637
B19: Interest income | C19: =Vertical!F16 -> 0.00094383511 | D19: =Vertical!G16 -> 0.00097298599 | E19: =Vertical!H16 -> 0.0012412051 | F19: =INDEX(C19:E19,MATCH(Cs_YearA,FY_List,0)) -> 0.00094383511 | G19: =INDEX(C19:E19,MATCH(Cs_YearB,FY_List,0)) -> 0.0012412051 | H19: =G19-F19 -> 0.00029737002
B20: Finance costs | C20: =Vertical!F17 -> -0.012691233 | D20: =Vertical!G17 -> -0.012789249 | E20: =Vertical!H17 -> -0.012027453 | F20: =INDEX(C20:E20,MATCH(Cs_YearA,FY_List,0)) -> -0.012691233 | G20: =INDEX(C20:E20,MATCH(Cs_YearB,FY_List,0)) -> -0.012027453 | H20: =G20-F20 -> 0.00066378064
B21: Profit before income tax | C21: =Vertical!F18 -> 0.036931355 | D21: =Vertical!G18 -> 0.04354586 | E21: =Vertical!H18 -> 0.05171928 | F21: =INDEX(C21:E21,MATCH(Cs_YearA,FY_List,0)) -> 0.036931355 | G21: =INDEX(C21:E21,MATCH(Cs_YearB,FY_List,0)) -> 0.05171928 | H21: =G21-F21 -> 0.014787925
... B26: Total operating expenses (selling, G&A and depreciation) | C26: =Vertical!F23 -> 0.20571952 | D26: =Vertical!G23 -> 0.20103585 | E26: =Vertical!H23 -> 0.1965783 | F26: =INDEX(C26:E26,MATCH(Cs_YearA,FY_List,0)) -> 0.20571952 | G26: =INDEX(C26:E26,MATCH(Cs_YearB,FY_List,0)) -> 0.1965783 | H26: =G26-F26 -> -0.0091412141
B27: STATEMENT OF FINANCIAL POSITION
B28: Cash and cash equivalents | C28: =Vertical!F25 -> 0.14022039 | D28: =Vertical!G25 -> 0.17419581 | E28: =Vertical!H25 -> 0.17085471 | F28: =INDEX(C28:E28,MATCH(Cs_YearA,FY_List,0)) -> 0.14022039 | G28: =INDEX(C28:E28,MATCH(Cs_YearB,FY_List,0)) -> 0.17085471 | H28: =G28-F28 -> 0.030634323
B29: Trade and other receivables | C29: =Vertical!F26 -> 0.19506714 | D29: =Vertical!G26 -> 0.19159158 | E29: =Vertical!H26 -> 0.19488991 | F29: =INDEX(C29:E29,MATCH(Cs_YearA,FY_List,0)) -> 0.19506714 | G29: =INDEX(C29:E29,MATCH(Cs_YearB,FY_List,0)) -> 0.19488991 | H29: =G29-F29 -> -0.00017723201
B30: Inventories | C30: =Vertical!F27 -> 0.18232312 | D30: =Vertical!G27 -> 0.17448376 | E30: =Vertical!H27 -> 0.17790643 | F30: =INDEX(C30:E30,MATCH(Cs_YearA,FY_List,0)) -> 0.18232312 | G30: =INDEX(C30:E30,MATCH(Cs_YearB,FY_List,0)) -> 0.17790643 | H30: =G30-F30 -> -0.0044166868
B31: Prepayments and other current assets | C31: =Vertical!F28 -> 0.027373999 | D31: =Vertical!G28 -> 0.026164012 | E31: =Vertical!H28 -> 0.026633087 | F31: =INDEX(C31:E31,MATCH(Cs_YearA,FY_List,0)) -> 0.027373999 | G31: =INDEX(C31:E31,MATCH(Cs_YearB,FY_List,0)) -> 0.026633087 | H31: =G31-F31 -> -0.00074091186
B32: Total current assets | C32: =Vertical!F29 -> 0.54498465 | D32: =Vertical!G29 -> 0.56643516 | E32: =Vertical!H29 -> 0.57028414 | F32: =INDEX(C32:E32,MATCH(Cs_YearA,FY_List,0)) -> 0.54498465 | G32: =INDEX(C32:E32,MATCH(Cs_YearB,FY_List,0)) -> 0.57028414 | H32: =G32-F32 -> 0.025299493
B33: Property, plant and equipment, net | C33: =Vertical!F30 -> 0.4304474 | D33: =Vertical!G30 -> 0.41083236 | E33: =Vertical!H30 -> 0.40651667 | F33: =INDEX(C33:E33,MATCH(Cs_YearA,FY_List,0)) -> 0.4304474 | G33: =INDEX(C33:E33,MATCH(Cs_YearB,FY_List,0)) -> 0.40651667 | H33: =G33-F33 -> -0.023930729
B34: Other non-current assets | C34: =Vertical!F31 -> 0.024567953 | D34: =Vertical!G31 -> 0.022732488 | E34: =Vertical!H31 -> 0.023199189 | F34: =INDEX(C34:E34,MATCH(Cs_YearA,FY_List,0)) -> 0.024567953 | G34: =INDEX(C34:E34,MATCH(Cs_YearB,FY_List,0)) -> 0.023199189 | H34: =G34-F34 -> -0.0013687642
B35: Total non-current assets | C35: =Vertical!F32 -> 0.45501535 | D35: =Vertical!G32 -> 0.43356484 | E35: =Vertical!H32 -> 0.42971586 | F35: =INDEX(C35:E35,MATCH(Cs_YearA,FY_List,0)) -> 0.45501535 | G35: =INDEX(C35:E35,MATCH(Cs_YearB,FY_List,0)) -> 0.42971586 | H35: =G35-F35 -> -0.025299493
B36: TOTAL ASSETS | C36: =Vertical!F33 -> 1 | D36: =Vertical!G33 -> 1 | E36: =Vertical!H33 -> 1 | F36: =INDEX(C36:E36,MATCH(Cs_YearA,FY_List,0)) -> 1 | G36: =INDEX(C36:E36,MATCH(Cs_YearB,FY_List,0)) -> 1 | H36: =G36-F36 -> 0
B37: Trade and other payables | C37: =Vertical!F34 -> 0.16206419 | D37: =Vertical!G34 -> 0.16258709 | E37: =Vertical!H34 -> 0.17377029 | F37: =INDEX(C37:E37,MATCH(Cs_YearA,FY_List,0)) -> 0.16206419 | G37: =INDEX(C37:E37,MATCH(Cs_YearB,FY_List,0)) -> 0.17377029 | H37: =G37-F37 -> 0.011706096
B38: Accrued expenses | C38: =Vertical!F35 -> 0.032848799 | D38: =Vertical!G35 -> 0.031394649 | E38: =Vertical!H35 -> 0.03195845 | F38: =INDEX(C38:E38,MATCH(Cs_YearA,FY_List,0)) -> 0.032848799 | G38: =INDEX(C38:E38,MATCH(Cs_YearB,FY_List,0)) -> 0.03195845 | H38: =G38-F38 -> -0.00089034824
B39: Income tax payable | C39: =Vertical!F36 -> 0.0040729813 | D39: =Vertical!G36 -> 0.0042802028 | E39: =Vertical!H36 -> 0.0052856531 | F39: =INDEX(C39:E39,MATCH(Cs_YearA,FY_List,0)) -> 0.0040729813 | G39: =INDEX(C39:E39,MATCH(Cs_YearB,FY_List,0)) -> 0.0052856531 | H39: =G39-F39 -> 0.0012126718
... B49: TOTAL LIABILITIES AND EQUITY | C49: =Vertical!F46 -> 1 | D49: =Vertical!G46 -> 1 | E49: =Vertical!H46 -> 1 | F49: =INDEX(C49:E49,MATCH(Cs_YearA,FY_List,0)) -> 1 | G49: =INDEX(C49:E49,MATCH(Cs_YearB,FY_List,0)) -> 1 | H49: =G49-F49 -> 0

Sheet Trend
B1: Trend Analysis and Projections
B2: =Inputs!$C$6&" | "&Inputs!$C$11 -> Sampaguita Foods & Distribution Corporation (SFDC) | PHP in thousands (unless otherwise stated)
B3: =HYPERLINK("#Cover!A1","◄ Back to Cover") -> ◄ Back to Cover
B4: Index numbers use FY2023 = 100. CAGR is the compound annual growth rate over the period. Projections are statistical extrapolations, not forecasts.
B5: PHP '000 | C5: =Inputs!D$22 -> 2023 | D5: =Inputs!E$22 -> 2024 | E5: =Inputs!F$22 -> 2025 | F5: Index FY2024 | G5: Index FY2025 | H5: YoY FY2024 | I5: YoY FY2025 | J5: CAGR
B6: Net sales | C6: =Income_Statement!D7 -> 821118 | D6: =Income_Statement!E7 -> 897238 | E6: =Income_Statement!F7 -> 972442 | F6: =IFERROR(D6/C6*100,0) -> 109.27029 | G6: =IFERROR(E6/C6*100,0) -> 118.42902 | H6: =IFERROR(D6/C6-1,0) -> 0.092702876 | I6: =IFERROR(E6/D6-1,0) -> 0.083817226 | J6: =IFERROR((E6/C6)^(1/(E$5-C$5))-1,0) -> 0.088250982
B7: Gross profit | C7: =Income_Statement!D9 -> 207141 | D7: =Income_Statement!E9 -> 228680 | E7: =Income_Statement!F9 -> 249894 | F7: =IFERROR(D7/C7*100,0) -> 110.39823 | G7: =IFERROR(E7/C7*100,0) -> 120.63956 | H7: =IFERROR(D7/C7-1,0) -> 0.10398231 | I7: =IFERROR(E7/D7-1,0) -> 0.092767186 | J7: =IFERROR((E7/C7)^(1/(E$5-C$5))-1,0) -> 0.098360434
B8: EBITDA | C8: =Income_Statement!D24 -> 57360 | D8: =Income_Statement!E24 -> 68923 | E8: =Income_Statement!F24 -> 82040 | F8: =IFERROR(D8/C8*100,0) -> 120.15865 | G8: =IFERROR(E8/C8*100,0) -> 143.0265 | H8: =IFERROR(D8/C8-1,0) -> 0.20158647 | I8: =IFERROR(E8/D8-1,0) -> 0.19031383 | J8: =IFERROR((E8/C8)^(1/(E$5-C$5))-1,0) -> 0.19593687
B9: Operating profit | C9: =Income_Statement!D13 -> 38221 | D9: =Income_Statement!E13 -> 48303 | E9: =Income_Statement!F13 -> 58733 | F9: =IFERROR(D9/C9*100,0) -> 126.37817 | G9: =IFERROR(E9/C9*100,0) -> 153.66683 | H9: =IFERROR(D9/C9-1,0) -> 0.26378169 | I9: =IFERROR(E9/D9-1,0) -> 0.21592862 | J9: =IFERROR((E9/C9)^(1/(E$5-C$5))-1,0) -> 0.23962427
B10: Net profit | C10: =Income_Statement!D20 -> 22482 | D10: =Income_Statement!E20 -> 29009 | E10: =Income_Statement!F20 -> 37406 | F10: =IFERROR(D10/C10*100,0) -> 129.03211 | G10: =IFERROR(E10/C10*100,0) -> 166.38199 | H10: =IFERROR(D10/C10-1,0) -> 0.29032115 | I10: =IFERROR(E10/D10-1,0) -> 0.28946189 | J10: =IFERROR((E10/C10)^(1/(E$5-C$5))-1,0) -> 0.28989145
B11: Total assets | C11: =Balance_Sheet!D17 -> 415175 | D11: =Balance_Sheet!E17 -> 461894 | E11: =Balance_Sheet!F17 -> 478465 | F11: =IFERROR(D11/C11*100,0) -> 111.25285 | G11: =IFERROR(E11/C11*100,0) -> 115.24417 | H11: =IFERROR(D11/C11-1,0) -> 0.11252845 | I11: =IFERROR(E11/D11-1,0) -> 0.035876197 | J11: =IFERROR((E11/C11)^(1/(E$5-C$5))-1,0) -> 0.073518394
B12: Total equity | C12: =Balance_Sheet!D34 -> 196561 | D12: =Balance_Sheet!E34 -> 218318 | E12: =Balance_Sheet!F34 -> 244502 | F12: =IFERROR(D12/C12*100,0) -> 111.06883 | G12: =IFERROR(E12/C12*100,0) -> 124.38988 | H12: =IFERROR(D12/C12-1,0) -> 0.11068829 | I12: =IFERROR(E12/D12-1,0) -> 0.11993514 | J12: =IFERROR((E12/C12)^(1/(E$5-C$5))-1,0) -> 0.11530213
B13: Total borrowings | C13: =Schedules!D87 -> 136000 | D13: =Schedules!E87 -> 152000 | E13: =Schedules!F87 -> 133000 | F13: =IFERROR(D13/C13*100,0) -> 111.76471 | G13: =IFERROR(E13/C13*100,0) -> 97.794118 | H13: =IFERROR(D13/C13-1,0) -> 0.11764706 | I13: =IFERROR(E13/D13-1,0) -> -0.125 | J13: =IFERROR((E13/C13)^(1/(E$5-C$5))-1,0) -> -0.011090916
B14: Net cash from operations | C14: =Cash_Flow!D22 -> 32237 | D14: =Cash_Flow!E22 -> 44246 | E14: =Cash_Flow!F22 -> 57760 | F14: =IFERROR(D14/C14*100,0) -> 137.25223 | G14: =IFERROR(E14/C14*100,0) -> 179.173 | H14: =IFERROR(D14/C14-1,0) -> 0.37252226 | I14: =IFERROR(E14/D14-1,0) -> 0.30542874 | J14: =IFERROR((E14/C14)^(1/(E$5-C$5))-1,0) -> 0.33855519
B16: PROJECTIONS (next two years)
B17: PHP '000 | F17: ="FY"&(E$5+1)&" (FORECAST)" -> FY2026 (FORECAST) | G17: ="FY"&(E$5+2)&" (FORECAST)" -> FY2027 (FORECAST) | H17: ="FY"&(E$5+1)&" (CAGR)" -> FY2026 (CAGR) | I17: ="FY"&(E$5+2)&" (CAGR)" -> FY2027 (CAGR) | J17: ="FY"&(E$5+1)&" (TREND)" -> FY2026 (TREND)
B18: Net sales | F18: =FORECAST(E$5+1,$C6:$E6,$C$5:$E$5) -> 1048256.7 | G18: =FORECAST(E$5+2,$C6:$E6,$C$5:$E$5) -> 1123918.7 | H18: =E6*(1+J6) -> 1058261 | I18: =E6*(1+J6)^2 -> 1151653.5 | J18: =TREND($C6:$E6,$C$5:$E$5,E$5+1) -> 1048256.7
B19: Gross profit | F19: =FORECAST(E$5+1,$C7:$E7,$C$5:$E$5) -> 271324.67 | G19: =FORECAST(E$5+2,$C7:$E7,$C$5:$E$5) -> 292701.17 | H19: =E7*(1+J7) -> 274473.68 | I19: =E7*(1+J7)^2 -> 301471.03 | J19: =TREND($C7:$E7,$C$5:$E$5,E$5+1) -> 271324.67
B20: EBITDA | F20: =FORECAST(E$5+1,$C8:$E8,$C$5:$E$5) -> 94121 | G20: =FORECAST(E$5+2,$C8:$E8,$C$5:$E$5) -> 106461 | H20: =E8*(1+J8) -> 98114.661 | I20: =E8*(1+J8)^2 -> 117338.94 | J20: =TREND($C8:$E8,$C$5:$E$5,E$5+1) -> 94121
B21: Operating profit | F21: =FORECAST(E$5+1,$C9:$E9,$C$5:$E$5) -> 68931 | G21: =FORECAST(E$5+2,$C9:$E9,$C$5:$E$5) -> 79187 | H21: =E9*(1+J9) -> 72806.852 | I21: =E9*(1+J9)^2 -> 90253.141 | J21: =TREND($C9:$E9,$C$5:$E$5,E$5+1) -> 68931
B22: Net profit | F22: =FORECAST(E$5+1,$C10:$E10,$C$5:$E$5) -> 44556.333 | G22: =FORECAST(E$5+2,$C10:$E10,$C$5:$E$5) -> 52018.333 | H22: =E10*(1+J10) -> 48249.679 | I22: =E10*(1+J10)^2 -> 62236.849 | J22: =TREND($C10:$E10,$C$5:$E$5,E$5+1) -> 44556.333
B23: Total assets | F23: =FORECAST(E$5+1,$C11:$E11,$C$5:$E$5) -> 515134.67 | G23: =FORECAST(E$5+2,$C11:$E11,$C$5:$E$5) -> 546779.67 | H23: =E11*(1+J11) -> 513640.98 | I23: =E11*(1+J11)^2 -> 551403.04 | J23: =TREND($C11:$E11,$C$5:$E$5,E$5+1) -> 515134.67
B24: Total equity | F24: =FORECAST(E$5+1,$C12:$E12,$C$5:$E$5) -> 267734.67 | G24: =FORECAST(E$5+2,$C12:$E12,$C$5:$E$5) -> 291705.17 | H24: =E12*(1+J12) -> 272693.6 | I24: =E12*(1+J12)^2 -> 304135.75 | J24: =TREND($C12:$E12,$C$5:$E$5,E$5+1) -> 267734.67
B25: Total borrowings | F25: =FORECAST(E$5+1,$C13:$E13,$C$5:$E$5) -> 137333.33 | G25: =FORECAST(E$5+2,$C13:$E13,$C$5:$E$5) -> 135833.33 | H25: =E13*(1+J13) -> 131524.91 | I25: =E13*(1+J13)^2 -> 130066.18 | J25: =TREND($C13:$E13,$C$5:$E$5,E$5+1) -> 137333.33
B26: Net cash from operations | F26: =FORECAST(E$5+1,$C14:$E14,$C$5:$E$5) -> 70270.667 | G26: =FORECAST(E$5+2,$C14:$E14,$C$5:$E$5) -> 83032.167 | H26: =E14*(1+J14) -> 77314.948 | I26: =E14*(1+J14)^2 -> 103490.32 | J26: =TREND($C14:$E14,$C$5:$E$5,E$5+1) -> 70270.667
B28: FORECAST and TREND use ordinary least squares on three data points - treat as indicative only. CAGR-based figures compound the historical growth rate.

Sheet Revenue_Analysis
B1: Revenue Analysis
B2: =Inputs!$C$6&" | "&Inputs!$C$11 -> Sampaguita Foods & Distribution Corporation (SFDC) | PHP in thousands (unless otherwise stated)
B3: =HYPERLINK("#Cover!A1","◄ Back to Cover") -> ◄ Back to Cover
B4: Pick a year, category, region and measure. Every table and chart on this sheet recalculates (SUMPRODUCT on the sales ledger).
B5: Fiscal year | C5: 2025 | E5: Selected measure - total | G5: =SUMPRODUCT((Sales_Year=Rev_Year)*(((Rev_Cat="All")+(Sales_Cat=Rev_Cat))>0)*(((Rev_Region="All")+(Sales_Region=Rev_Region))>0)*((Rev_Idx=1)*Sales_Net+(Rev_Idx=2)*Sales_COGS+(Rev_Idx=3)*Sales_GP)) -> 972442
B6: Category | C6: All | E6: Prior year | G6: =SUMPRODUCT((Sales_Year=Rev_Year-1)*(((Rev_Cat="All")+(Sales_Cat=Rev_Cat))>0)*(((Rev_Region="All")+(Sales_Region=Rev_Region))>0)*((Rev_Idx=1)*Sales_Net+(Rev_Idx=2)*Sales_COGS+(Rev_Idx=3)*Sales_GP)) -> 897238
B7: Region | C7: All | E7: Year-on-year change | G7: =IF(G6=0,"n/a",G5/G6-1) -> 0.083817226
B8: Measure | C8: Net Sales | E8: Average per month | G8: =G5/12 -> 81036.833
B9: Measure index (helper) | C9: =MATCH(Rev_Metric,Metric_List,0) -> 1 | E9: Per working day | G9: =G5/NETWORKDAYS(DATE(Rev_Year,1,1),DATE(Rev_Year,12,31)) -> 3725.8314
B12: Month | C12: Month-end | D12: Selected year | E12: Prior year | F12: YoY % | G12: 3-month moving avg | H12: YTD cumulative | I12: Signal
B13: =TEXT(C13,"mmmm") -> January | C13: =EOMONTH(DATE(Rev_Year,1,1),0) -> 45688 | D13: =SUMPRODUCT((Sales_Date=$C13)*(((Rev_Cat="All")+(Sales_Cat=Rev_Cat))>0)*(((Rev_Region="All")+(Sales_Region=Rev_Region))>0)*((Rev_Idx=1)*Sales_Net+(Rev_Idx=2)*Sales_COGS+(Rev_Idx=3)*Sales_GP)) -> 74463 | E13: =SUMPRODUCT((Sales_Date=EOMONTH($C13,-12))*(((Rev_Cat="All")+(Sales_Cat=Rev_Cat))>0)*(((Rev_Region="All")+(Sales_Region=Rev_Region))>0)*((Rev_Idx=1)*Sales_Net+(Rev_Idx=2)*Sales_COGS+(Rev_Idx=3)*Sales_GP)) -> 68174 | F13: =IF(E13=0,"n/a",D13/E13-1) -> 0.092249245 | G13: – | H13: =SUM($D$13:D13) -> 74463 | I13: =IF(D13>=PERCENTILE($D$13:$D$24,0.75),"▲ Peak",IF(D13<=PERCENTILE($D$13:$D$24,0.25),"▼ Low","")) -> ▼ Low
B14: =TEXT(C14,"mmmm") -> February | C14: =EOMONTH(C13,1) -> 45716 | D14: =SUMPRODUCT((Sales_Date=$C14)*(((Rev_Cat="All")+(Sales_Cat=Rev_Cat))>0)*(((Rev_Region="All")+(Sales_Region=Rev_Region))>0)*((Rev_Idx=1)*Sales_Net+(Rev_Idx=2)*Sales_COGS+(Rev_Idx=3)*Sales_GP)) -> 71689 | E14: =SUMPRODUCT((Sales_Date=EOMONTH($C14,-12))*(((Rev_Cat="All")+(Sales_Cat=Rev_Cat))>0)*(((Rev_Region="All")+(Sales_Region=Rev_Region))>0)*((Rev_Idx=1)*Sales_Net+(Rev_Idx=2)*Sales_COGS+(Rev_Idx=3)*Sales_GP)) -> 66369 | F14: =IF(E14=0,"n/a",D14/E14-1) -> 0.080157905 | G14: – | H14: =SUM($D$13:D14) -> 146152 | I14: =IF(D14>=PERCENTILE($D$13:$D$24,0.75),"▲ Peak",IF(D14<=PERCENTILE($D$13:$D$24,0.25),"▼ Low","")) -> ▼ Low
B15: =TEXT(C15,"mmmm") -> March | C15: =EOMONTH(C14,1) -> 45747 | D15: =SUMPRODUCT((Sales_Date=$C15)*(((Rev_Cat="All")+(Sales_Cat=Rev_Cat))>0)*(((Rev_Region="All")+(Sales_Region=Rev_Region))>0)*((Rev_Idx=1)*Sales_Net+(Rev_Idx=2)*Sales_COGS+(Rev_Idx=3)*Sales_GP)) -> 77757 | E15: =SUMPRODUCT((Sales_Date=EOMONTH($C15,-12))*(((Rev_Cat="All")+(Sales_Cat=Rev_Cat))>0)*(((Rev_Region="All")+(Sales_Region=Rev_Region))>0)*((Rev_Idx=1)*Sales_Net+(Rev_Idx=2)*Sales_COGS+(Rev_Idx=3)*Sales_GP)) -> 72523 | F15: =IF(E15=0,"n/a",D15/E15-1) -> 0.072170208 | G15: =AVERAGE(OFFSET(D15,-2,0,3,1)) -> 74636.333 | H15: =SUM($D$13:D15) -> 223909 | I15: =IF(D15>=PERCENTILE($D$13:$D$24,0.75),"▲ Peak",IF(D15<=PERCENTILE($D$13:$D$24,0.25),"▼ Low","")) -> ▼ Low
B16: =TEXT(C16,"mmmm") -> April | C16: =EOMONTH(C15,1) -> 45777 | D16: =SUMPRODUCT((Sales_Date=$C16)*(((Rev_Cat="All")+(Sales_Cat=Rev_Cat))>0)*(((Rev_Region="All")+(Sales_Region=Rev_Region))>0)*((Rev_Idx=1)*Sales_Net+(Rev_Idx=2)*Sales_COGS+(Rev_Idx=3)*Sales_GP)) -> 79023 | E16: =SUMPRODUCT((Sales_Date=EOMONTH($C16,-12))*(((Rev_Cat="All")+(Sales_Cat=Rev_Cat))>0)*(((Rev_Region="All")+(Sales_Region=Rev_Region))>0)*((Rev_Idx=1)*Sales_Net+(Rev_Idx=2)*Sales_COGS+(Rev_Idx=3)*Sales_GP)) -> 72983 | F16: =IF(E16=0,"n/a",D16/E16-1) -> 0.082758999 | G16: =AVERAGE(OFFSET(D16,-2,0,3,1)) -> 76156.333 | H16: =SUM($D$13:D16) -> 302932 | I16: =IF(D16>=PERCENTILE($D$13:$D$24,0.75),"▲ Peak",IF(D16<=PERCENTILE($D$13:$D$24,0.25),"▼ Low",""))
B17: =TEXT(C17,"mmmm") -> May | C17: =EOMONTH(C16,1) -> 45808 | D17: =SUMPRODUCT((Sales_Date=$C17)*(((Rev_Cat="All")+(Sales_Cat=Rev_Cat))>0)*(((Rev_Region="All")+(Sales_Region=Rev_Region))>0)*((Rev_Idx=1)*Sales_Net+(Rev_Idx=2)*Sales_COGS+(Rev_Idx=3)*Sales_GP)) -> 81946 | E17: =SUMPRODUCT((Sales_Date=EOMONTH($C17,-12))*(((Rev_Cat="All")+(Sales_Cat=Rev_Cat))>0)*(((Rev_Region="All")+(Sales_Region=Rev_Region))>0)*((Rev_Idx=1)*Sales_Net+(Rev_Idx=2)*Sales_COGS+(Rev_Idx=3)*Sales_GP)) -> 74055 | F17: =IF(E17=0,"n/a",D17/E17-1) -> 0.10655594 | G17: =AVERAGE(OFFSET(D17,-2,0,3,1)) -> 79575.333 | H17: =SUM($D$13:D17) -> 384878 | I17: =IF(D17>=PERCENTILE($D$13:$D$24,0.75),"▲ Peak",IF(D17<=PERCENTILE($D$13:$D$24,0.25),"▼ Low",""))
B18: =TEXT(C18,"mmmm") -> June | C18: =EOMONTH(C17,1) -> 45838 | D18: =SUMPRODUCT((Sales_Date=$C18)*(((Rev_Cat="All")+(Sales_Cat=Rev_Cat))>0)*(((Rev_Region="All")+(Sales_Region=Rev_Region))>0)*((Rev_Idx=1)*Sales_Net+(Rev_Idx=2)*Sales_COGS+(Rev_Idx=3)*Sales_GP)) -> 79418 | E18: =SUMPRODUCT((Sales_Date=EOMONTH($C18,-12))*(((Rev_Cat="All")+(Sales_Cat=Rev_Cat))>0)*(((Rev_Region="All")+(Sales_Region=Rev_Region))>0)*((Rev_Idx=1)*Sales_Net+(Rev_Idx=2)*Sales_COGS+(Rev_Idx=3)*Sales_GP)) -> 74488 | F18: =IF(E18=0,"n/a",D18/E18-1) -> 0.066185157 | G18: =AVERAGE(OFFSET(D18,-2,0,3,1)) -> 80129 | H18: =SUM($D$13:D18) -> 464296 | I18: =IF(D18>=PERCENTILE($D$13:$D$24,0.75),"▲ Peak",IF(D18<=PERCENTILE($D$13:$D$24,0.25),"▼ Low",""))
B19: =TEXT(C19,"mmmm") -> July | C19: =EOMONTH(C18,1) -> 45869 | D19: =SUMPRODUCT((Sales_Date=$C19)*(((Rev_Cat="All")+(Sales_Cat=Rev_Cat))>0)*(((Rev_Region="All")+(Sales_Region=Rev_Region))>0)*((Rev_Idx=1)*Sales_Net+(Rev_Idx=2)*Sales_COGS+(Rev_Idx=3)*Sales_GP)) -> 81667 | E19: =SUMPRODUCT((Sales_Date=EOMONTH($C19,-12))*(((Rev_Cat="All")+(Sales_Cat=Rev_Cat))>0)*(((Rev_Region="All")+(Sales_Region=Rev_Region))>0)*((Rev_Idx=1)*Sales_Net+(Rev_Idx=2)*Sales_COGS+(Rev_Idx=3)*Sales_GP)) -> 75320 | F19: =IF(E19=0,"n/a",D19/E19-1) -> 0.084267127 | G19: =AVERAGE(OFFSET(D19,-2,0,3,1)) -> 81010.333 | H19: =SUM($D$13:D19) -> 545963 | I19: =IF(D19>=PERCENTILE($D$13:$D$24,0.75),"▲ Peak",IF(D19<=PERCENTILE($D$13:$D$24,0.25),"▼ Low",""))
B20: =TEXT(C20,"mmmm") -> August | C20: =EOMONTH(C19,1) -> 45900 | D20: =SUMPRODUCT((Sales_Date=$C20)*(((Rev_Cat="All")+(Sales_Cat=Rev_Cat))>0)*(((Rev_Region="All")+(Sales_Region=Rev_Region))>0)*((Rev_Idx=1)*Sales_Net+(Rev_Idx=2)*Sales_COGS+(Rev_Idx=3)*Sales_GP)) -> 81105 | E20: =SUMPRODUCT((Sales_Date=EOMONTH($C20,-12))*(((Rev_Cat="All")+(Sales_Cat=Rev_Cat))>0)*(((Rev_Region="All")+(Sales_Region=Rev_Region))>0)*((Rev_Idx=1)*Sales_Net+(Rev_Idx=2)*Sales_COGS+(Rev_Idx=3)*Sales_GP)) -> 75658 | F20: =IF(E20=0,"n/a",D20/E20-1) -> 0.07199503 | G20: =AVERAGE(OFFSET(D20,-2,0,3,1)) -> 80730 | H20: =SUM($D$13:D20) -> 627068 | I20: =IF(D20>=PERCENTILE($D$13:$D$24,0.75),"▲ Peak",IF(D20<=PERCENTILE($D$13:$D$24,0.25),"▼ Low",""))
B21: =TEXT(C21,"mmmm") -> September | C21: =EOMONTH(C20,1) -> 45930 | D21: =SUMPRODUCT((Sales_Date=$C21)*(((Rev_Cat="All")+(Sales_Cat=Rev_Cat))>0)*(((Rev_Region="All")+(Sales_Region=Rev_Region))>0)*((Rev_Idx=1)*Sales_Net+(Rev_Idx=2)*Sales_COGS+(Rev_Idx=3)*Sales_GP)) -> 82028 | E21: =SUMPRODUCT((Sales_Date=EOMONTH($C21,-12))*(((Rev_Cat="All")+(Sales_Cat=Rev_Cat))>0)*(((Rev_Region="All")+(Sales_Region=Rev_Region))>0)*((Rev_Idx=1)*Sales_Net+(Rev_Idx=2)*Sales_COGS+(Rev_Idx=3)*Sales_GP)) -> 75947 | F21: =IF(E21=0,"n/a",D21/E21-1) -> 0.080068995 | G21: =AVERAGE(OFFSET(D21,-2,0,3,1)) -> 81600 | H21: =SUM($D$13:D21) -> 709096 | I21: =IF(D21>=PERCENTILE($D$13:$D$24,0.75),"▲ Peak",IF(D21<=PERCENTILE($D$13:$D$24,0.25),"▼ Low",""))
B22: =TEXT(C22,"mmmm") -> October | C22: =EOMONTH(C21,1) -> 45961 | D22: =SUMPRODUCT((Sales_Date=$C22)*(((Rev_Cat="All")+(Sales_Cat=Rev_Cat))>0)*(((Rev_Region="All")+(Sales_Region=Rev_Region))>0)*((Rev_Idx=1)*Sales_Net+(Rev_Idx=2)*Sales_COGS+(Rev_Idx=3)*Sales_GP)) -> 83643 | E22: =SUMPRODUCT((Sales_Date=EOMONTH($C22,-12))*(((Rev_Cat="All")+(Sales_Cat=Rev_Cat))>0)*(((Rev_Region="All")+(Sales_Region=Rev_Region))>0)*((Rev_Idx=1)*Sales_Net+(Rev_Idx=2)*Sales_COGS+(Rev_Idx=3)*Sales_GP)) -> 75853 | F22: =IF(E22=0,"n/a",D22/E22-1) -> 0.10269864 | G22: =AVERAGE(OFFSET(D22,-2,0,3,1)) -> 82258.667 | H22: =SUM($D$13:D22) -> 792739 | I22: =IF(D22>=PERCENTILE($D$13:$D$24,0.75),"▲ Peak",IF(D22<=PERCENTILE($D$13:$D$24,0.25),"▼ Low","")) -> ▲ Peak
B23: =TEXT(C23,"mmmm") -> November | C23: =EOMONTH(C22,1) -> 45991 | D23: =SUMPRODUCT((Sales_Date=$C23)*(((Rev_Cat="All")+(Sales_Cat=Rev_Cat))>0)*(((Rev_Region="All")+(Sales_Region=Rev_Region))>0)*((Rev_Idx=1)*Sales_Net+(Rev_Idx=2)*Sales_COGS+(Rev_Idx=3)*Sales_GP)) -> 85801 | E23: =SUMPRODUCT((Sales_Date=EOMONTH($C23,-12))*(((Rev_Cat="All")+(Sales_Cat=Rev_Cat))>0)*(((Rev_Region="All")+(Sales_Region=Rev_Region))>0)*((Rev_Idx=1)*Sales_Net+(Rev_Idx=2)*Sales_COGS+(Rev_Idx=3)*Sales_GP)) -> 79142 | F23: =IF(E23=0,"n/a",D23/E23-1) -> 0.0841399 | G23: =AVERAGE(OFFSET(D23,-2,0,3,1)) -> 83824 | H23: =SUM($D$13:D23) -> 878540 | I23: =IF(D23>=PERCENTILE($D$13:$D$24,0.75),"▲ Peak",IF(D23<=PERCENTILE($D$13:$D$24,0.25),"▼ Low","")) -> ▲ Peak
B24: =TEXT(C24,"mmmm") -> December | C24: =EOMONTH(C23,1) -> 46022 | D24: =SUMPRODUCT((Sales_Date=$C24)*(((Rev_Cat="All")+(Sales_Cat=Rev_Cat))>0)*(((Rev_Region="All")+(Sales_Region=Rev_Region))>0)*((Rev_Idx=1)*Sales_Net+(Rev_Idx=2)*Sales_COGS+(Rev_Idx=3)*Sales_GP)) -> 93902 | E24: =SUMPRODUCT((Sales_Date=EOMONTH($C24,-12))*(((Rev_Cat="All")+(Sales_Cat=Rev_Cat))>0)*(((Rev_Region="All")+(Sales_Region=Rev_Region))>0)*((Rev_Idx=1)*Sales_Net+(Rev_Idx=2)*Sales_COGS+(Rev_Idx=3)*Sales_GP)) -> 86726 | F24: =IF(E24=0,"n/a",D24/E24-1) -> 0.082743353 | G24: =AVERAGE(OFFSET(D24,-2,0,3,1)) -> 87782 | H24: =SUM($D$13:D24) -> 972442 | I24: =IF(D24>=PERCENTILE($D$13:$D$24,0.75),"▲ Peak",IF(D24<=PERCENTILE($D$13:$D$24,0.25),"▼ Low","")) -> ▲ Peak
B25: Total | D25: =SUM(D13:D24) -> 972442 | E25: =SUM(E13:E24) -> 897238 | F25: =IF(E25=0,"n/a",D25/E25-1) -> 0.083817226
B27: SEASONALITY INSIGHTS
B28: Peak month | C28: =INDEX($B$13:$B$24,MATCH(MAX($D$13:$D$24),$D$13:$D$24,0)) -> December | D28: =MAX($D$13:$D$24) -> 93902
B29: Second-highest month | C29: =INDEX($B$13:$B$24,MATCH(_xlfn.AGGREGATE(14,6,$D$13:$D$24,2),$D$13:$D$24,0)) -> November | D29: =_xlfn.AGGREGATE(14,6,$D$13:$D$24,2) -> 85801
B30: Weakest month | C30: =INDEX($B$13:$B$24,MATCH(MIN($D$13:$D$24),$D$13:$D$24,0)) -> February | D30: =MIN($D$13:$D$24) -> 71689
B31: Peak-to-trough spread | D31: =IFERROR(MAX($D$13:$D$24)/MIN($D$13:$D$24)-1,0) -> 0.30985228
B32: Q4 share of annual total | D32: =IFERROR(SUM(D22:D24)/D25,0) -> 0.27080895
B34: BY PRODUCT CATEGORY (region filter applies; selected year)
B35: Category | C35: Selected year | D35: Share of total | E35: Prior year | F35: YoY % | G35: Rank | H35: Gross margin % | I35: Contribution to growth (pts)
B36: =Lists!C5 -> Packaged Food | C36: =SUMPRODUCT((Sales_Year=Rev_Year)*(Sales_Cat=$B36)*(((Rev_Region="All")+(Sales_Region=Rev_Region))>0)*((Rev_Idx=1)*Sales_Net+(Rev_Idx=2)*Sales_COGS+(Rev_Idx=3)*Sales_GP)) -> 382510 | D36: =IFERROR(C36/C$40,0) -> 0.39334994 | E36: =SUMPRODUCT((Sales_Year=Rev_Year-1)*(Sales_Cat=$B36)*(((Rev_Region="All")+(Sales_Region=Rev_Region))>0)*((Rev_Idx=1)*Sales_Net+(Rev_Idx=2)*Sales_COGS+(Rev_Idx=3)*Sales_GP)) -> 358165 | F36: =IF(E36=0,"n/a",C36/E36-1) -> 0.067971466 | G36: =RANK(C36,$C$36:$C$39) -> 1 | H36: =IFERROR(SUMPRODUCT((Sales_Year=Rev_Year)*(Sales_Cat=$B36)*(((Rev_Region="All")+(Sales_Region=Rev_Region))>0)*Sales_GP)/SUMPRODUCT((Sales_Year=Rev_Year)*(Sales_Cat=$B36)*(((Rev_Region="All")+(Sales_Region=Rev_Region))>0)*Sales_Net),0) -> 0.2504928 | I36: =IF($E$40=0,0,(C36-E36)/$E$40) -> 0.027133269
B37: =Lists!C6 -> Beverages | C37: =SUMPRODUCT((Sales_Year=Rev_Year)*(Sales_Cat=$B37)*(((Rev_Region="All")+(Sales_Region=Rev_Region))>0)*((Rev_Idx=1)*Sales_Net+(Rev_Idx=2)*Sales_COGS+(Rev_Idx=3)*Sales_GP)) -> 292182 | D37: =IFERROR(C37/C$40,0) -> 0.30046214 | E37: =SUMPRODUCT((Sales_Year=Rev_Year-1)*(Sales_Cat=$B37)*(((Rev_Region="All")+(Sales_Region=Rev_Region))>0)*((Rev_Idx=1)*Sales_Net+(Rev_Idx=2)*Sales_COGS+(Rev_Idx=3)*Sales_GP)) -> 264622 | F37: =IF(E37=0,"n/a",C37/E37-1) -> 0.10414856 | G37: =RANK(C37,$C$36:$C$39) -> 2 | H37: =IFERROR(SUMPRODUCT((Sales_Year=Rev_Year)*(Sales_Cat=$B37)*(((Rev_Region="All")+(Sales_Region=Rev_Region))>0)*Sales_GP)/SUMPRODUCT((Sales_Year=Rev_Year)*(Sales_Cat=$B37)*(((Rev_Region="All")+(Sales_Region=Rev_Region))>0)*Sales_Net),0) -> 0.26963331 | I37: =IF($E$40=0,0,(C37-E37)/$E$40) -> 0.030716488
B38: =Lists!C7 -> Household & Personal Care | C38: =SUMPRODUCT((Sales_Year=Rev_Year)*(Sales_Cat=$B38)*(((Rev_Region="All")+(Sales_Region=Rev_Region))>0)*((Rev_Idx=1)*Sales_Net+(Rev_Idx=2)*Sales_COGS+(Rev_Idx=3)*Sales_GP)) -> 170561 | D38: =IFERROR(C38/C$40,0) -> 0.17539452 | E38: =SUMPRODUCT((Sales_Year=Rev_Year-1)*(Sales_Cat=$B38)*(((Rev_Region="All")+(Sales_Region=Rev_Region))>0)*((Rev_Idx=1)*Sales_Net+(Rev_Idx=2)*Sales_COGS+(Rev_Idx=3)*Sales_GP)) -> 160640 | F38: =IF(E38=0,"n/a",C38/E38-1) -> 0.061759213 | G38: =RANK(C38,$C$36:$C$39) -> 3 | H38: =IFERROR(SUMPRODUCT((Sales_Year=Rev_Year)*(Sales_Cat=$B38)*(((Rev_Region="All")+(Sales_Region=Rev_Region))>0)*Sales_GP)/SUMPRODUCT((Sales_Year=Rev_Year)*(Sales_Cat=$B38)*(((Rev_Region="All")+(Sales_Region=Rev_Region))>0)*Sales_Net),0) -> 0.30007446 | I38: =IF($E$40=0,0,(C38-E38)/$E$40) -> 0.011057267
B39: =Lists!C8 -> Fresh & Frozen | C39: =SUMPRODUCT((Sales_Year=Rev_Year)*(Sales_Cat=$B39)*(((Rev_Region="All")+(Sales_Region=Rev_Region))>0)*((Rev_Idx=1)*Sales_Net+(Rev_Idx=2)*Sales_COGS+(Rev_Idx=3)*Sales_GP)) -> 127189 | D39: =IFERROR(C39/C$40,0) -> 0.1307934 | E39: =SUMPRODUCT((Sales_Year=Rev_Year-1)*(Sales_Cat=$B39)*(((Rev_Region="All")+(Sales_Region=Rev_Region))>0)*((Rev_Idx=1)*Sales_Net+(Rev_Idx=2)*Sales_COGS+(Rev_Idx=3)*Sales_GP)) -> 113811 | F39: =IF(E39=0,"n/a",C39/E39-1) -> 0.11754576 | G39: =RANK(C39,$C$36:$C$39) -> 4 | H39: =IFERROR(SUMPRODUCT((Sales_Year=Rev_Year)*(Sales_Cat=$B39)*(((Rev_Region="All")+(Sales_Region=Rev_Region))>0)*Sales_GP)/SUMPRODUCT((Sales_Year=Rev_Year)*(Sales_Cat=$B39)*(((Rev_Region="All")+(Sales_Region=Rev_Region))>0)*Sales_Net),0) -> 0.18959973 | I39: =IF($E$40=0,0,(C39-E39)/$E$40) -> 0.014910202
B40: Total | C40: =SUM(C36:C39) -> 972442 | D40: =SUM(D36:D39) -> 1 | E40: =SUM(E36:E39) -> 897238 | F40: =IF(E40=0,"n/a",C40/E40-1) -> 0.083817226 | H40: =IFERROR(SUMPRODUCT((Sales_Year=Rev_Year)*(((Rev_Region="All")+(Sales_Region=Rev_Region))>0)*Sales_GP)/SUMPRODUCT((Sales_Year=Rev_Year)*(((Rev_Region="All")+(Sales_Region=Rev_Region))>0)*Sales_Net),0) -> 0.25697574 | I40: =SUM(I36:I39) -> 0.083817226
B42: BY REGION (category filter applies; selected year)
B43: Region | C43: Selected year | D43: Share of total | E43: Prior year | F43: YoY % | G43: Rank | H43: Gross margin % | I43: Contribution to growth (pts)
B44: =Lists!G5 -> Luzon | C44: =SUMPRODUCT((Sales_Year=Rev_Year)*(Sales_Region=$B44)*(((Rev_Cat="All")+(Sales_Cat=Rev_Cat))>0)*((Rev_Idx=1)*Sales_Net+(Rev_Idx=2)*Sales_COGS+(Rev_Idx=3)*Sales_GP)) -> 554093 | D44: =IFERROR(C44/C$47,0) -> 0.56979542 | E44: =SUMPRODUCT((Sales_Year=Rev_Year-1)*(Sales_Region=$B44)*(((Rev_Cat="All")+(Sales_Cat=Rev_Cat))>0)*((Rev_Idx=1)*Sales_Net+(Rev_Idx=2)*Sales_COGS+(Rev_Idx=3)*Sales_GP)) -> 514752 | F44: =IF(E44=0,"n/a",C44/E44-1) -> 0.076427095 | G44: =RANK(C44,$C$44:$C$46) -> 1 | H44: =IFERROR(SUMPRODUCT((Sales_Year=Rev_Year)*(Sales_Region=$B44)*(((Rev_Cat="All")+(Sales_Cat=Rev_Cat))>0)*Sales_GP)/SUMPRODUCT((Sales_Year=Rev_Year)*(Sales_Region=$B44)*(((Rev_Cat="All")+(Sales_Cat=Rev_Cat))>0)*Sales_Net),0) -> 0.25683775 | I44: =IF($E$47=0,0,(C44-E44)/$E$47) -> 0.043846783
B45: =Lists!G6 -> Visayas | C45: =SUMPRODUCT((Sales_Year=Rev_Year)*(Sales_Region=$B45)*(((Rev_Cat="All")+(Sales_Cat=Rev_Cat))>0)*((Rev_Idx=1)*Sales_Net+(Rev_Idx=2)*Sales_COGS+(Rev_Idx=3)*Sales_GP)) -> 223910 | D45: =IFERROR(C45/C$47,0) -> 0.23025538 | E45: =SUMPRODUCT((Sales_Year=Rev_Year-1)*(Sales_Region=$B45)*(((Rev_Cat="All")+(Sales_Cat=Rev_Cat))>0)*((Rev_Idx=1)*Sales_Net+(Rev_Idx=2)*Sales_COGS+(Rev_Idx=3)*Sales_GP)) -> 206985 | F45: =IF(E45=0,"n/a",C45/E45-1) -> 0.08176921 | G45: =RANK(C45,$C$44:$C$46) -> 2 | H45: =IFERROR(SUMPRODUCT((Sales_Year=Rev_Year)*(Sales_Region=$B45)*(((Rev_Cat="All")+(Sales_Cat=Rev_Cat))>0)*Sales_GP)/SUMPRODUCT((Sales_Year=Rev_Year)*(Sales_Region=$B45)*(((Rev_Cat="All")+(Sales_Cat=Rev_Cat))>0)*Sales_Net),0) -> 0.25700505 | I45: =IF($E$47=0,0,(C45-E45)/$E$47) -> 0.018863445
B46: =Lists!G7 -> Mindanao | C46: =SUMPRODUCT((Sales_Year=Rev_Year)*(Sales_Region=$B46)*(((Rev_Cat="All")+(Sales_Cat=Rev_Cat))>0)*((Rev_Idx=1)*Sales_Net+(Rev_Idx=2)*Sales_COGS+(Rev_Idx=3)*Sales_GP)) -> 194439 | D46: =IFERROR(C46/C$47,0) -> 0.1999492 | E46: =SUMPRODUCT((Sales_Year=Rev_Year-1)*(Sales_Region=$B46)*(((Rev_Cat="All")+(Sales_Cat=Rev_Cat))>0)*((Rev_Idx=1)*Sales_Net+(Rev_Idx=2)*Sales_COGS+(Rev_Idx=3)*Sales_GP)) -> 175501 | F46: =IF(E46=0,"n/a",C46/E46-1) -> 0.10790822 | G46: =RANK(C46,$C$44:$C$46) -> 3 | H46: =IFERROR(SUMPRODUCT((Sales_Year=Rev_Year)*(Sales_Region=$B46)*(((Rev_Cat="All")+(Sales_Cat=Rev_Cat))>0)*Sales_GP)/SUMPRODUCT((Sales_Year=Rev_Year)*(Sales_Region=$B46)*(((Rev_Cat="All")+(Sales_Cat=Rev_Cat))>0)*Sales_Net),0) -> 0.25733521 | I46: =IF($E$47=0,0,(C46-E46)/$E$47) -> 0.021106997
B47: Total | C47: =SUM(C44:C46) -> 972442 | D47: =SUM(D44:D46) -> 1 | E47: =SUM(E44:E46) -> 897238 | F47: =IF(E47=0,"n/a",C47/E47-1) -> 0.083817226 | H47: =IFERROR(SUMPRODUCT((Sales_Year=Rev_Year)*(((Rev_Cat="All")+(Sales_Cat=Rev_Cat))>0)*Sales_GP)/SUMPRODUCT((Sales_Year=Rev_Year)*(((Rev_Cat="All")+(Sales_Cat=Rev_Cat))>0)*Sales_Net),0) -> 0.25697574 | I47: =SUM(I44:I46) -> 0.083817226
B49: BY QUARTER (all filters apply)
B50: Quarter | C50: Selected year | D50: Share of total | E50: Prior year | F50: YoY %
B51: ="Q1" -> Q1 | C51: =SUMPRODUCT((Sales_Year=Rev_Year)*(Sales_Qtr=$B51)*(((Rev_Cat="All")+(Sales_Cat=Rev_Cat))>0)*(((Rev_Region="All")+(Sales_Region=Rev_Region))>0)*((Rev_Idx=1)*Sales_Net+(Rev_Idx=2)*Sales_COGS+(Rev_Idx=3)*Sales_GP)) -> 223909 | D51: =IFERROR(C51/C$55,0) -> 0.23025435 | E51: =SUMPRODUCT((Sales_Year=Rev_Year-1)*(Sales_Qtr=$B51)*(((Rev_Cat="All")+(Sales_Cat=Rev_Cat))>0)*(((Rev_Region="All")+(Sales_Region=Rev_Region))>0)*((Rev_Idx=1)*Sales_Net+(Rev_Idx=2)*Sales_COGS+(Rev_Idx=3)*Sales_GP)) -> 207066 | F51: =IF(E51=0,"n/a",C51/E51-1) -> 0.081341215
B52: ="Q2" -> Q2 | C52: =SUMPRODUCT((Sales_Year=Rev_Year)*(Sales_Qtr=$B52)*(((Rev_Cat="All")+(Sales_Cat=Rev_Cat))>0)*(((Rev_Region="All")+(Sales_Region=Rev_Region))>0)*((Rev_Idx=1)*Sales_Net+(Rev_Idx=2)*Sales_COGS+(Rev_Idx=3)*Sales_GP)) -> 240387 | D52: =IFERROR(C52/C$55,0) -> 0.24719932 | E52: =SUMPRODUCT((Sales_Year=Rev_Year-1)*(Sales_Qtr=$B52)*(((Rev_Cat="All")+(Sales_Cat=Rev_Cat))>0)*(((Rev_Region="All")+(Sales_Region=Rev_Region))>0)*((Rev_Idx=1)*Sales_Net+(Rev_Idx=2)*Sales_COGS+(Rev_Idx=3)*Sales_GP)) -> 221526 | F52: =IF(E52=0,"n/a",C52/E52-1) -> 0.085141248
B53: ="Q3" -> Q3 | C53: =SUMPRODUCT((Sales_Year=Rev_Year)*(Sales_Qtr=$B53)*(((Rev_Cat="All")+(Sales_Cat=Rev_Cat))>0)*(((Rev_Region="All")+(Sales_Region=Rev_Region))>0)*((Rev_Idx=1)*Sales_Net+(Rev_Idx=2)*Sales_COGS+(Rev_Idx=3)*Sales_GP)) -> 244800 | D53: =IFERROR(C53/C$55,0) -> 0.25173738 | E53: =SUMPRODUCT((Sales_Year=Rev_Year-1)*(Sales_Qtr=$B53)*(((Rev_Cat="All")+(Sales_Cat=Rev_Cat))>0)*(((Rev_Region="All")+(Sales_Region=Rev_Region))>0)*((Rev_Idx=1)*Sales_Net+(Rev_Idx=2)*Sales_COGS+(Rev_Idx=3)*Sales_GP)) -> 226925 | F53: =IF(E53=0,"n/a",C53/E53-1) -> 0.078770519
B54: ="Q4" -> Q4 | C54: =SUMPRODUCT((Sales_Year=Rev_Year)*(Sales_Qtr=$B54)*(((Rev_Cat="All")+(Sales_Cat=Rev_Cat))>0)*(((Rev_Region="All")+(Sales_Region=Rev_Region))>0)*((Rev_Idx=1)*Sales_Net+(Rev_Idx=2)*Sales_COGS+(Rev_Idx=3)*Sales_GP)) -> 263346 | D54: =IFERROR(C54/C$55,0) -> 0.27080895 | E54: =SUMPRODUCT((Sales_Year=Rev_Year-1)*(Sales_Qtr=$B54)*(((Rev_Cat="All")+(Sales_Cat=Rev_Cat))>0)*(((Rev_Region="All")+(Sales_Region=Rev_Region))>0)*((Rev_Idx=1)*Sales_Net+(Rev_Idx=2)*Sales_COGS+(Rev_Idx=3)*Sales_GP)) -> 241721 | F54: =IF(E54=0,"n/a",C54/E54-1) -> 0.089462645
B55: Total | C55: =SUM(C51:C54) -> 972442 | D55: =SUM(D51:D54) -> 1 | E55: =SUM(E51:E54) -> 897238 | F55: =IF(E55=0,"n/a",C55/E55-1) -> 0.083817226

Sheet Expense_Analysis
B1: Expense Analysis
B2: =Inputs!$C$6&" | "&Inputs!$C$11 -> Sampaguita Foods & Distribution Corporation (SFDC) | PHP in thousands (unless otherwise stated)
B3: =HYPERLINK("#Cover!A1","◄ Back to Cover") -> ◄ Back to Cover
B4: Operating expenses by function and nature, cost behaviour and break-even, driven by the expense ledger and the chart-of-accounts mapping.
B5: Fiscal year | C5: 2025
B6: Net sales - selected year | C6: =INDEX(Income_Statement!$D$7:$F$7,MATCH(Exp_SelYear,Income_Statement!$D$5:$F$5,0)) -> 972442
B7: Net sales - prior year | C7: =IFERROR(INDEX(Income_Statement!$D$7:$F$7,MATCH(Exp_SelYear-1,Income_Statement!$D$5:$F$5,0)),0) -> 897238
B8: Net sales growth | C8: =IF(C7=0,0,C6/C7-1) -> 0.083817226
B10: A. COSTS BY FUNCTION
B11: Cost category | C11: Selected year | D11: % of net sales | E11: Prior year | F11: YoY % | G11: Share of operating expenses | J11: Review flag
B12: Selling & distribution | C12: =SUMIFS(Exp_Amt,Exp_Year,Exp_SelYear,Exp_Func,Func_SD) -> 106077 | D12: =IFERROR(C12/$C$6,0) -> 0.10908311 | E12: =SUMIFS(Exp_Amt,Exp_Year,Exp_SelYear-1,Exp_Func,Func_SD) -> 99930 | F12: =IF(E12=0,"n/a",C12/E12-1) -> 0.061513059 | G12: =IFERROR(C12/$C$15,0) -> 0.55490921 | J12: =IF(E12=0,"",IF(F12>$C$8+Var_Threshold,"▲ Outpacing sales",IF(F12<$C$8-Var_Threshold,"▼ Below sales growth","● In line"))) -> ● In line
B13: General & administrative | C13: =SUMIFS(Exp_Amt,Exp_Year,Exp_SelYear,Exp_Func,Func_GA) -> 63827 | D13: =IFERROR(C13/$C$6,0) -> 0.065635791 | E13: =SUMIFS(Exp_Amt,Exp_Year,Exp_SelYear-1,Exp_Func,Func_GA) -> 61197 | F13: =IF(E13=0,"n/a",C13/E13-1) -> 0.042975963 | G13: =IFERROR(C13/$C$15,0) -> 0.33389133 | J13: =IF(E13=0,"",IF(F13>$C$8+Var_Threshold,"▲ Outpacing sales",IF(F13<$C$8-Var_Threshold,"▼ Below sales growth","● In line"))) -> ● In line
B14: Depreciation | C14: =-INDEX(Income_Statement!$D$12:$F$12,MATCH(Exp_SelYear,Income_Statement!$D$5:$F$5,0)) -> 21257 | D14: =IFERROR(C14/$C$6,0) -> 0.021859401 | E14: =IFERROR(-INDEX(Income_Statement!$D$12:$F$12,MATCH(Exp_SelYear-1,Income_Statement!$D$5:$F$5,0)),0) -> 19250 | F14: =IF(E14=0,"n/a",C14/E14-1) -> 0.10425974 | G14: =IFERROR(C14/$C$15,0) -> 0.11119946 | J14: =IF(E14=0,"",IF(F14>$C$8+Var_Threshold,"▲ Outpacing sales",IF(F14<$C$8-Var_Threshold,"▼ Below sales growth","● In line"))) -> ● In line
B15: Total operating expenses | C15: =SUM(C12:C14) -> 191161 | D15: =IFERROR(C15/$C$6,0) -> 0.1965783 | E15: =SUM(E12:E14) -> 180377 | F15: =IF(E15=0,"n/a",C15/E15-1) -> 0.059785893 | G15: =IFERROR(C15/$C$15,0) -> 1 | J15: =IF(E15=0,"",IF(F15>$C$8+Var_Threshold,"▲ Outpacing sales",IF(F15<$C$8-Var_Threshold,"▼ Below sales growth","● In line"))) -> ● In line
B16: Finance costs | C16: =-INDEX(Income_Statement!$D$17:$F$17,MATCH(Exp_SelYear,Income_Statement!$D$5:$F$5,0)) -> 11696 | D16: =IFERROR(C16/$C$6,0) -> 0.012027453 | E16: =IFERROR(-INDEX(Income_Statement!$D$17:$F$17,MATCH(Exp_SelYear-1,Income_Statement!$D$5:$F$5,0)),0) -> 11475 | F16: =IF(E16=0,"n/a",C16/E16-1) -> 0.019259259 | J16: =IF(E16=0,"",IF(F16>$C$8+Var_Threshold,"▲ Outpacing sales",IF(F16<$C$8-Var_Threshold,"▼ Below sales growth","● In line"))) -> ● In line
B17: Cost of sales | C17: =-INDEX(Income_Statement!$D$8:$F$8,MATCH(Exp_SelYear,Income_Statement!$D$5:$F$5,0)) -> 722548 | D17: =IFERROR(C17/$C$6,0) -> 0.74302426 | E17: =IFERROR(-INDEX(Income_Statement!$D$8:$F$8,MATCH(Exp_SelYear-1,Income_Statement!$D$5:$F$5,0)),0) -> 668558 | F17: =IF(E17=0,"n/a",C17/E17-1) -> 0.080755896 | J17: =IF(E17=0,"",IF(F17>$C$8+Var_Threshold,"▲ Outpacing sales",IF(F17<$C$8-Var_Threshold,"▼ Below sales growth","● In line"))) -> ● In line
B19: B. OPERATING EXPENSES BY NATURE (ledger)
B20: Expense line | C20: Selected year | D20: % of net sales | E20: Prior year | F20: YoY % | G20: Share of ledger total | H20: Rank | I20: Behaviour | J20: Review flag
B21: =Inputs!B100 -> Sales commissions & incentives | C21: =SUMIFS(Exp_Amt,Exp_Year,Exp_SelYear,Exp_Line,$B21) -> 15695 | D21: =IFERROR(C21/$C$6,0) -> 0.01613978 | E21: =SUMIFS(Exp_Amt,Exp_Year,Exp_SelYear-1,Exp_Line,$B21) -> 14338 | F21: =IF(E21=0,"n/a",C21/E21-1) -> 0.094643604 | G21: =IFERROR(C21/C$34,0) -> 0.092375695 | H21: =RANK(C21,$C$21:$C$33) -> 5 | I21: =VLOOKUP(B21,Map_Table,4,FALSE()) -> Variable | J21: =IF(E21=0,"",IF(F21>$C$8+Var_Threshold,"▲ Outpacing sales",IF(F21<$C$8-Var_Threshold,"▼ Below sales growth","● In line"))) -> ● In line
B22: =Inputs!B101 -> Advertising & promotions | C22: =SUMIFS(Exp_Amt,Exp_Year,Exp_SelYear,Exp_Line,$B22) -> 9363 | D22: =IFERROR(C22/$C$6,0) -> 0.0096283377 | E22: =SUMIFS(Exp_Amt,Exp_Year,Exp_SelYear-1,Exp_Line,$B22) -> 8683 | F22: =IF(E22=0,"n/a",C22/E22-1) -> 0.078313947 | G22: =IFERROR(C22/C$34,0) -> 0.05510759 | H22: =RANK(C22,$C$21:$C$33) -> 6 | I22: =VLOOKUP(B22,Map_Table,4,FALSE()) -> Variable | J22: =IF(E22=0,"",IF(F22>$C$8+Var_Threshold,"▲ Outpacing sales",IF(F22<$C$8-Var_Threshold,"▼ Below sales growth","● In line"))) -> ● In line
B23: =Inputs!B102 -> Freight & delivery | C23: =SUMIFS(Exp_Amt,Exp_Year,Exp_SelYear,Exp_Line,$B23) -> 23337 | D23: =IFERROR(C23/$C$6,0) -> 0.023998346 | E23: =SUMIFS(Exp_Amt,Exp_Year,Exp_SelYear-1,Exp_Line,$B23) -> 21643 | F23: =IF(E23=0,"n/a",C23/E23-1) -> 0.07827011 | G23: =IFERROR(C23/C$34,0) -> 0.13735404 | H23: =RANK(C23,$C$21:$C$33) -> 4 | I23: =VLOOKUP(B23,Map_Table,4,FALSE()) -> Variable | J23: =IF(E23=0,"",IF(F23>$C$8+Var_Threshold,"▲ Outpacing sales",IF(F23<$C$8-Var_Threshold,"▼ Below sales growth","● In line"))) -> ● In line
B24: =Inputs!B103 -> Warehouse rent & utilities | C24: =SUMIFS(Exp_Amt,Exp_Year,Exp_SelYear,Exp_Line,$B24) -> 24992 | D24: =IFERROR(C24/$C$6,0) -> 0.025700247 | E24: =SUMIFS(Exp_Amt,Exp_Year,Exp_SelYear-1,Exp_Line,$B24) -> 23767 | F24: =IF(E24=0,"n/a",C24/E24-1) -> 0.051542054 | G24: =IFERROR(C24/C$34,0) -> 0.14709483 | H24: =RANK(C24,$C$21:$C$33) -> 3 | I24: =VLOOKUP(B24,Map_Table,4,FALSE()) -> Fixed | J24: =IF(E24=0,"",IF(F24>$C$8+Var_Threshold,"▲ Outpacing sales",IF(F24<$C$8-Var_Threshold,"▼ Below sales growth","● In line"))) -> ● In line
B25: =Inputs!B104 -> Selling & logistics staff costs | C25: =SUMIFS(Exp_Amt,Exp_Year,Exp_SelYear,Exp_Line,$B25) -> 32690 | D25: =IFERROR(C25/$C$6,0) -> 0.033616401 | E25: =SUMIFS(Exp_Amt,Exp_Year,Exp_SelYear-1,Exp_Line,$B25) -> 31499 | F25: =IF(E25=0,"n/a",C25/E25-1) -> 0.037810724 | G25: =IFERROR(C25/C$34,0) -> 0.19240277 | H25: =RANK(C25,$C$21:$C$33) -> 1 | I25: =VLOOKUP(B25,Map_Table,4,FALSE()) -> Fixed | J25: =IF(E25=0,"",IF(F25>$C$8+Var_Threshold,"▲ Outpacing sales",IF(F25<$C$8-Var_Threshold,"▼ Below sales growth","● In line"))) -> ● In line
B26: =Inputs!B105 -> Salaries & wages (G&A) | C26: =SUMIFS(Exp_Amt,Exp_Year,Exp_SelYear,Exp_Line,$B26) -> 30213 | D26: =IFERROR(C26/$C$6,0) -> 0.031069205 | E26: =SUMIFS(Exp_Amt,Exp_Year,Exp_SelYear-1,Exp_Line,$B26) -> 28920 | F26: =IF(E26=0,"n/a",C26/E26-1) -> 0.044709544 | G26: =IFERROR(C26/C$34,0) -> 0.17782395 | H26: =RANK(C26,$C$21:$C$33) -> 2 | I26: =VLOOKUP(B26,Map_Table,4,FALSE()) -> Fixed | J26: =IF(E26=0,"",IF(F26>$C$8+Var_Threshold,"▲ Outpacing sales",IF(F26<$C$8-Var_Threshold,"▼ Below sales growth","● In line"))) -> ● In line
B27: =Inputs!B106 -> Employee benefits & contributions | C27: =SUMIFS(Exp_Amt,Exp_Year,Exp_SelYear,Exp_Line,$B27) -> 8130 | D27: =IFERROR(C27/$C$6,0) -> 0.0083603958 | E27: =SUMIFS(Exp_Amt,Exp_Year,Exp_SelYear-1,Exp_Line,$B27) -> 7808 | F27: =IF(E27=0,"n/a",C27/E27-1) -> 0.041239754 | G27: =IFERROR(C27/C$34,0) -> 0.047850551 | H27: =RANK(C27,$C$21:$C$33) -> 7 | I27: =VLOOKUP(B27,Map_Table,4,FALSE()) -> Fixed | J27: =IF(E27=0,"",IF(F27>$C$8+Var_Threshold,"▲ Outpacing sales",IF(F27<$C$8-Var_Threshold,"▼ Below sales growth","● In line"))) -> ● In line
B28: =Inputs!B107 -> Professional fees | C28: =SUMIFS(Exp_Amt,Exp_Year,Exp_SelYear,Exp_Line,$B28) -> 4500 | D28: =IFERROR(C28/$C$6,0) -> 0.0046275253 | E28: =SUMIFS(Exp_Amt,Exp_Year,Exp_SelYear-1,Exp_Line,$B28) -> 4266 | F28: =IF(E28=0,"n/a",C28/E28-1) -> 0.054852321 | G28: =IFERROR(C28/C$34,0) -> 0.026485545 | H28: =RANK(C28,$C$21:$C$33) -> 10 | I28: =VLOOKUP(B28,Map_Table,4,FALSE()) -> Fixed | J28: =IF(E28=0,"",IF(F28>$C$8+Var_Threshold,"▲ Outpacing sales",IF(F28<$C$8-Var_Threshold,"▼ Below sales growth","● In line"))) -> ● In line
B29: =Inputs!B108 -> Office rent & utilities | C29: =SUMIFS(Exp_Amt,Exp_Year,Exp_SelYear,Exp_Line,$B29) -> 6839 | D29: =IFERROR(C29/$C$6,0) -> 0.0070328102 | E29: =SUMIFS(Exp_Amt,Exp_Year,Exp_SelYear-1,Exp_Line,$B29) -> 6572 | F29: =IF(E29=0,"n/a",C29/E29-1) -> 0.040626902 | G29: =IFERROR(C29/C$34,0) -> 0.040252142 | H29: =RANK(C29,$C$21:$C$33) -> 8 | I29: =VLOOKUP(B29,Map_Table,4,FALSE()) -> Fixed | J29: =IF(E29=0,"",IF(F29>$C$8+Var_Threshold,"▲ Outpacing sales",IF(F29<$C$8-Var_Threshold,"▼ Below sales growth","● In line"))) -> ● In line
B30: =Inputs!B109 -> Repairs & maintenance | C30: =SUMIFS(Exp_Amt,Exp_Year,Exp_SelYear,Exp_Line,$B30) -> 2729 | D30: =IFERROR(C30/$C$6,0) -> 0.002806337 | E30: =SUMIFS(Exp_Amt,Exp_Year,Exp_SelYear-1,Exp_Line,$B30) -> 2672 | F30: =IF(E30=0,"n/a",C30/E30-1) -> 0.021332335 | G30: =IFERROR(C30/C$34,0) -> 0.016062011 | H30: =RANK(C30,$C$21:$C$33) -> 12 | I30: =VLOOKUP(B30,Map_Table,4,FALSE()) -> Fixed | J30: =IF(E30=0,"",IF(F30>$C$8+Var_Threshold,"▲ Outpacing sales",IF(F30<$C$8-Var_Threshold,"▼ Below sales growth","● In line"))) -> ● In line
B31: =Inputs!B110 -> Taxes, licenses & insurance | C31: =SUMIFS(Exp_Amt,Exp_Year,Exp_SelYear,Exp_Line,$B31) -> 5484 | D31: =IFERROR(C31/$C$6,0) -> 0.0056394109 | E31: =SUMIFS(Exp_Amt,Exp_Year,Exp_SelYear-1,Exp_Line,$B31) -> 5318 | F31: =IF(E31=0,"n/a",C31/E31-1) -> 0.031214742 | G31: =IFERROR(C31/C$34,0) -> 0.032277051 | H31: =RANK(C31,$C$21:$C$33) -> 9 | I31: =VLOOKUP(B31,Map_Table,4,FALSE()) -> Fixed | J31: =IF(E31=0,"",IF(F31>$C$8+Var_Threshold,"▲ Outpacing sales",IF(F31<$C$8-Var_Threshold,"▼ Below sales growth","● In line"))) -> ● In line
B32: =Inputs!B111 -> Communication, IT & supplies | C32: =SUMIFS(Exp_Amt,Exp_Year,Exp_SelYear,Exp_Line,$B32) -> 4463 | D32: =IFERROR(C32/$C$6,0) -> 0.0045894768 | E32: =SUMIFS(Exp_Amt,Exp_Year,Exp_SelYear-1,Exp_Line,$B32) -> 4299 | F32: =IF(E32=0,"n/a",C32/E32-1) -> 0.038148407 | G32: =IFERROR(C32/C$34,0) -> 0.026267775 | H32: =RANK(C32,$C$21:$C$33) -> 11 | I32: =VLOOKUP(B32,Map_Table,4,FALSE()) -> Fixed | J32: =IF(E32=0,"",IF(F32>$C$8+Var_Threshold,"▲ Outpacing sales",IF(F32<$C$8-Var_Threshold,"▼ Below sales growth","● In line"))) -> ● In line
B33: =Inputs!B112 -> Bad debts & credit losses | C33: =SUMIFS(Exp_Amt,Exp_Year,Exp_SelYear,Exp_Line,$B33) -> 1469 | D33: =IFERROR(C33/$C$6,0) -> 0.0015106299 | E33: =SUMIFS(Exp_Amt,Exp_Year,Exp_SelYear-1,Exp_Line,$B33) -> 1342 | F33: =IF(E33=0,"n/a",C33/E33-1) -> 0.094634873 | G33: =IFERROR(C33/C$34,0) -> 0.008646059 | H33: =RANK(C33,$C$21:$C$33) -> 13 | I33: =VLOOKUP(B33,Map_Table,4,FALSE()) -> Variable | J33: =IF(E33=0,"",IF(F33>$C$8+Var_Threshold,"▲ Outpacing sales",IF(F33<$C$8-Var_Threshold,"▼ Below sales growth","● In line"))) -> ● In line
B34: Total ledger expenses | C34: =SUM(C21:C33) -> 169904 | D34: =IFERROR(C34/$C$6,0) -> 0.1747189 | E34: =SUM(E21:E33) -> 161127 | F34: =IF(E34=0,"n/a",C34/E34-1) -> 0.054472559 | G34: =SUM(G21:G33) -> 1
B36: C. COST BEHAVIOUR AND BREAK-EVEN ANALYSIS
B37: Net sales | C37: =C6 -> 972442
B38: Less: variable cost of sales | C38: =C17 -> 722548
B39: Less: variable operating expenses | C39: =SUMIFS(Exp_Amt,Exp_Year,Exp_SelYear,Exp_Behav,Lists!$Q$5) -> 49864
B40: Contribution margin | C40: =C37-C38-C39 -> 200030
B41: Contribution margin ratio | C41: =IFERROR(C40/C37,0) -> 0.20569864
B42: Less: fixed operating expenses | C42: =SUMIFS(Exp_Amt,Exp_Year,Exp_SelYear,Exp_Behav,Lists!$Q$6) -> 120040
B43: Less: depreciation (fixed) | C43: =C14 -> 21257
B44: Operating profit (derived) | C44: =C40-C42-C43 -> 58733
B45: Break-even net sales (operating level) | C45: =IFERROR((C42+C43)/C41,0) -> 686912.65 | E45: ="Break-even sits at "&TEXT(IFERROR(C45/C6,0),"0.0%")&" of actual net sales; each 1% fall in sales reduces operating profit by about "&TEXT(IFERROR(C48*1%,0),"0.0%")&"." -> Break-even sits at 70.6% of actual net sales; each 1% fall in sales reduces operating profit by about 3.4%.
B46: Margin of safety (PHP '000) | C46: =C37-C45 -> 285529.35
B47: Margin of safety (%) | C47: =IFERROR(C46/C37,0) -> 0.29362096
B48: Degree of operating leverage | C48: =IFERROR(C40/C44,0) -> 3.4057515
B49: Operating profit per income statement | C49: =INDEX(Income_Statement!$D$13:$F$13,MATCH(Exp_SelYear,Income_Statement!$D$5:$F$5,0)) -> 58733
B50: Difference (should be 0) | C50: =ROUND(C44-C49,0) -> 0
B52: D. MONTHLY OPERATING EXPENSE PROFILE
B53: Month | C53: Month-end | D53: Selling & distribution | E53: General & administrative | F53: Total | G53: % of month's net sales | H53: Net sales
B54: =TEXT(C54,"mmmm") -> January | C54: =EOMONTH(DATE(Exp_SelYear,1,1),0) -> 45688 | D54: =SUMIFS(Exp_Amt,Exp_Date,$C54,Exp_Func,Func_SD) -> 8461 | E54: =SUMIFS(Exp_Amt,Exp_Date,$C54,Exp_Func,Func_GA) -> 5280 | F54: =D54+E54 -> 13741 | G54: =IFERROR(F54/H54,0) -> 0.1845346 | H54: =SUMIFS(Sales_Net,Sales_Date,$C54) -> 74463
B55: =TEXT(C55,"mmmm") -> February | C55: =EOMONTH(C54,1) -> 45716 | D55: =SUMIFS(Exp_Amt,Exp_Date,$C55,Exp_Func,Func_SD) -> 8316 | E55: =SUMIFS(Exp_Amt,Exp_Date,$C55,Exp_Func,Func_GA) -> 5293 | F55: =D55+E55 -> 13609 | G55: =IFERROR(F55/H55,0) -> 0.18983387 | H55: =SUMIFS(Sales_Net,Sales_Date,$C55) -> 71689
B56: =TEXT(C56,"mmmm") -> March | C56: =EOMONTH(C55,1) -> 45747 | D56: =SUMIFS(Exp_Amt,Exp_Date,$C56,Exp_Func,Func_SD) -> 8692 | E56: =SUMIFS(Exp_Amt,Exp_Date,$C56,Exp_Func,Func_GA) -> 5778 | F56: =D56+E56 -> 14470 | G56: =IFERROR(F56/H56,0) -> 0.18609257 | H56: =SUMIFS(Sales_Net,Sales_Date,$C56) -> 77757
B57: =TEXT(C57,"mmmm") -> April | C57: =EOMONTH(C56,1) -> 45777 | D57: =SUMIFS(Exp_Amt,Exp_Date,$C57,Exp_Func,Func_SD) -> 8776 | E57: =SUMIFS(Exp_Amt,Exp_Date,$C57,Exp_Func,Func_GA) -> 5312 | F57: =D57+E57 -> 14088 | G57: =IFERROR(F57/H57,0) -> 0.17827721 | H57: =SUMIFS(Sales_Net,Sales_Date,$C57) -> 79023
B58: =TEXT(C58,"mmmm") -> May | C58: =EOMONTH(C57,1) -> 45808 | D58: =SUMIFS(Exp_Amt,Exp_Date,$C58,Exp_Func,Func_SD) -> 8773 | E58: =SUMIFS(Exp_Amt,Exp_Date,$C58,Exp_Func,Func_GA) -> 5324 | F58: =D58+E58 -> 14097 | G58: =IFERROR(F58/H58,0) -> 0.17202792 | H58: =SUMIFS(Sales_Net,Sales_Date,$C58) -> 81946
B59: =TEXT(C59,"mmmm") -> June | C59: =EOMONTH(C58,1) -> 45838 | D59: =SUMIFS(Exp_Amt,Exp_Date,$C59,Exp_Func,Func_SD) -> 8719 | E59: =SUMIFS(Exp_Amt,Exp_Date,$C59,Exp_Func,Func_GA) -> 5248 | F59: =D59+E59 -> 13967 | G59: =IFERROR(F59/H59,0) -> 0.17586693 | H59: =SUMIFS(Sales_Net,Sales_Date,$C59) -> 79418
B60: =TEXT(C60,"mmmm") -> July | C60: =EOMONTH(C59,1) -> 45869 | D60: =SUMIFS(Exp_Amt,Exp_Date,$C60,Exp_Func,Func_SD) -> 8853 | E60: =SUMIFS(Exp_Amt,Exp_Date,$C60,Exp_Func,Func_GA) -> 5283 | F60: =D60+E60 -> 14136 | G60: =IFERROR(F60/H60,0) -> 0.17309317 | H60: =SUMIFS(Sales_Net,Sales_Date,$C60) -> 81667
B61: =TEXT(C61,"mmmm") -> August | C61: =EOMONTH(C60,1) -> 45900 | D61: =SUMIFS(Exp_Amt,Exp_Date,$C61,Exp_Func,Func_SD) -> 8718 | E61: =SUMIFS(Exp_Amt,Exp_Date,$C61,Exp_Func,Func_GA) -> 5289 | F61: =D61+E61 -> 14007 | G61: =IFERROR(F61/H61,0) -> 0.17270205 | H61: =SUMIFS(Sales_Net,Sales_Date,$C61) -> 81105
B62: =TEXT(C62,"mmmm") -> September | C62: =EOMONTH(C61,1) -> 45930 | D62: =SUMIFS(Exp_Amt,Exp_Date,$C62,Exp_Func,Func_SD) -> 8952 | E62: =SUMIFS(Exp_Amt,Exp_Date,$C62,Exp_Func,Func_GA) -> 5255 | F62: =D62+E62 -> 14207 | G62: =IFERROR(F62/H62,0) -> 0.17319696 | H62: =SUMIFS(Sales_Net,Sales_Date,$C62) -> 82028
B63: =TEXT(C63,"mmmm") -> October | C63: =EOMONTH(C62,1) -> 45961 | D63: =SUMIFS(Exp_Amt,Exp_Date,$C63,Exp_Func,Func_SD) -> 9062 | E63: =SUMIFS(Exp_Amt,Exp_Date,$C63,Exp_Func,Func_GA) -> 5270 | F63: =D63+E63 -> 14332 | G63: =IFERROR(F63/H63,0) -> 0.17134727 | H63: =SUMIFS(Sales_Net,Sales_Date,$C63) -> 83643
B64: =TEXT(C64,"mmmm") -> November | C64: =EOMONTH(C63,1) -> 45991 | D64: =SUMIFS(Exp_Amt,Exp_Date,$C64,Exp_Func,Func_SD) -> 9219 | E64: =SUMIFS(Exp_Amt,Exp_Date,$C64,Exp_Func,Func_GA) -> 5236 | F64: =D64+E64 -> 14455 | G64: =IFERROR(F64/H64,0) -> 0.16847123 | H64: =SUMIFS(Sales_Net,Sales_Date,$C64) -> 85801
B65: =TEXT(C65,"mmmm") -> December | C65: =EOMONTH(C64,1) -> 46022 | D65: =SUMIFS(Exp_Amt,Exp_Date,$C65,Exp_Func,Func_SD) -> 9536 | E65: =SUMIFS(Exp_Amt,Exp_Date,$C65,Exp_Func,Func_GA) -> 5259 | F65: =D65+E65 -> 14795 | G65: =IFERROR(F65/H65,0) -> 0.15755788 | H65: =SUMIFS(Sales_Net,Sales_Date,$C65) -> 93902
B66: Total | D66: =SUM(D54:D65) -> 106077 | E66: =SUM(E54:E65) -> 63827 | F66: =SUM(F54:F65) -> 169904 | G66: =IFERROR(F66/H66,0) -> 0.1747189 | H66: =SUM(H54:H65) -> 972442

Sheet Ratio_Analysis
B1: Ratio Analysis
B2: =Inputs!$C$6&" | "&Inputs!$C$11 -> Sampaguita Foods & Distribution Corporation (SFDC) | PHP in thousands (unless otherwise stated)
B3: =HYPERLINK("#Cover!A1","◄ Back to Cover") -> ◄ Back to Cover
B4: Ratios use year-end balances unless 'average' is stated. Benchmarks are illustrative industry reference points (blue inputs) - replace with peer data.
B5: Ratio | D5: =Inputs!D$22 -> 2023 | E5: =Inputs!E$22 -> 2024 | F5: =Inputs!F$22 -> 2025 | G5: Benchmark | H5: Better if | I5: ="FY"&Inputs!F$22&" status" -> FY2025 status | J5: Definition
B6: PROFITABILITY
B7: Gross profit margin | D7: =IFERROR(Income_Statement!D9/Income_Statement!D7,0) -> 0.25226703 | E7: =IFERROR(Income_Statement!E9/Income_Statement!E7,0) -> 0.25487106 | F7: =IFERROR(Income_Statement!F9/Income_Statement!F7,0) -> 0.25697574 | G7: 0.25 | H7: Higher | I7: =IF(H7="Higher",IF(F7>=G7,"✔ Meets","▼ Below"),IF(F7<=G7,"✔ Meets","▲ Above")) -> ✔ Meets | J7: Gross profit / net sales
B8: EBITDA margin | D8: =IFERROR(Income_Statement!D24/Income_Statement!D7,0) -> 0.069855977 | E8: =IFERROR(Income_Statement!E24/Income_Statement!E7,0) -> 0.076816853 | F8: =IFERROR(Income_Statement!F24/Income_Statement!F7,0) -> 0.084364929 | G8: 0.07 | H8: Higher | I8: =IF(H8="Higher",IF(F8>=G8,"✔ Meets","▼ Below"),IF(F8<=G8,"✔ Meets","▲ Above")) -> ✔ Meets | J8: EBITDA / net sales
B9: Operating profit margin | D9: =IFERROR(Income_Statement!D13/Income_Statement!D7,0) -> 0.046547512 | E9: =IFERROR(Income_Statement!E13/Income_Statement!E7,0) -> 0.053835214 | F9: =IFERROR(Income_Statement!F13/Income_Statement!F7,0) -> 0.060397432 | G9: 0.045 | H9: Higher | I9: =IF(H9="Higher",IF(F9>=G9,"✔ Meets","▼ Below"),IF(F9<=G9,"✔ Meets","▲ Above")) -> ✔ Meets | J9: Operating profit / net sales
B10: Net profit margin | D10: =IFERROR(Income_Statement!D20/Income_Statement!D7,0) -> 0.027379743 | E10: =IFERROR(Income_Statement!E20/Income_Statement!E7,0) -> 0.032331444 | F10: =IFERROR(Income_Statement!F20/Income_Statement!F7,0) -> 0.038466047 | G10: 0.03 | H10: Higher | I10: =IF(H10="Higher",IF(F10>=G10,"✔ Meets","▼ Below"),IF(F10<=G10,"✔ Meets","▲ Above")) -> ✔ Meets | J10: Net profit / net sales
B11: Return on assets (average) | D11: =IFERROR(Income_Statement!D20/AVERAGE(Balance_Sheet!C17,Balance_Sheet!D17),0) -> 0.054943027 | E11: =IFERROR(Income_Statement!E20/AVERAGE(Balance_Sheet!D17,Balance_Sheet!E17),0) -> 0.06614987 | F11: =IFERROR(Income_Statement!F20/AVERAGE(Balance_Sheet!E17,Balance_Sheet!F17),0) -> 0.07955685 | G11: 0.06 | H11: Higher | I11: =IF(H11="Higher",IF(F11>=G11,"✔ Meets","▼ Below"),IF(F11<=G11,"✔ Meets","▲ Above")) -> ✔ Meets | J11: Net profit / average total assets
B12: Return on equity (average) | D12: =IFERROR(Income_Statement!D20/AVERAGE(Balance_Sheet!C34,Balance_Sheet!D34),0) -> 0.11950215 | E12: =IFERROR(Income_Statement!E20/AVERAGE(Balance_Sheet!D34,Balance_Sheet!E34),0) -> 0.13984318 | F12: =IFERROR(Income_Statement!F20/AVERAGE(Balance_Sheet!E34,Balance_Sheet!F34),0) -> 0.16164384 | G12: 0.14 | H12: Higher | I12: =IF(H12="Higher",IF(F12>=G12,"✔ Meets","▼ Below"),IF(F12<=G12,"✔ Meets","▲ Above")) -> ✔ Meets | J12: Net profit / average total equity
B13: Return on capital employed | D13: =IFERROR(Income_Statement!D23/(Balance_Sheet!D17-Balance_Sheet!D26),0) -> 0.14718977 | E13: =IFERROR(Income_Statement!E23/(Balance_Sheet!E17-Balance_Sheet!E26),0) -> 0.15853861 | F13: =IFERROR(Income_Statement!F23/(Balance_Sheet!F17-Balance_Sheet!F26),0) -> 0.1881815 | G13: 0.12 | H13: Higher | I13: =IF(H13="Higher",IF(F13>=G13,"✔ Meets","▼ Below"),IF(F13<=G13,"✔ Meets","▲ Above")) -> ✔ Meets | J13: EBIT / (total assets - current liabilities)
B14: ="Commentary: gross margin "&IF(F7>=E7,"improved","weakened")&" to "&TEXT(F7,"0.0%")&" from "&TEXT(E7,"0.0%")&"; EBITDA margin "&TEXT(F8,"0.0%")&" and net margin "&TEXT(F10,"0.0%")&". Return on equity "&IF(F12>=E12,"rose","fell")&" to "&TEXT(F12,"0.0%")&" against a benchmark of "&TEXT(G12,"0.0%")&"." -> Commentary: gross margin improved to 25.7% from 25.5%; EBITDA margin 8.4% and net margin 3.8%. Return on equity rose to 16.2% against a benchmark of 14.0%.
B15: LIQUIDITY
B16: Current ratio | D16: =IFERROR(Balance_Sheet!D12/Balance_Sheet!D26,0) -> 1.575501 | E16: =IFERROR(Balance_Sheet!E12/Balance_Sheet!E26,0) -> 1.7609372 | F16: =IFERROR(Balance_Sheet!F12/Balance_Sheet!F26,0) -> 1.7551507 | G16: 1.5 | H16: Higher | I16: =IF(H16="Higher",IF(F16>=G16,"✔ Meets","▼ Below"),IF(F16<=G16,"✔ Meets","▲ Above")) -> ✔ Meets | J16: Current assets / current liabilities
B17: Quick ratio | D17: =IFERROR((Balance_Sheet!D8+Balance_Sheet!D9)/Balance_Sheet!D26,0) -> 0.96928572 | E17: =IFERROR((Balance_Sheet!E8+Balance_Sheet!E9)/Balance_Sheet!E26,0) -> 1.1371621 | F17: =IFERROR((Balance_Sheet!F8+Balance_Sheet!F9)/Balance_Sheet!F26,0) -> 1.125644 | G17: 0.9 | H17: Higher | I17: =IF(H17="Higher",IF(F17>=G17,"✔ Meets","▼ Below"),IF(F17<=G17,"✔ Meets","▲ Above")) -> ✔ Meets | J17: (Cash + receivables) / current liabilities
B18: Cash ratio | D18: =IFERROR(Balance_Sheet!D8/Balance_Sheet!D26,0) -> 0.40536438 | E18: =IFERROR(Balance_Sheet!E8/Balance_Sheet!E26,0) -> 0.54154103 | F18: =IFERROR(Balance_Sheet!F8/Balance_Sheet!F26,0) -> 0.52583573 | G18: 0.3 | H18: Higher | I18: =IF(H18="Higher",IF(F18>=G18,"✔ Meets","▼ Below"),IF(F18<=G18,"✔ Meets","▲ Above")) -> ✔ Meets | J18: Cash / current liabilities
B19: Working capital (PHP '000) | D19: =Balance_Sheet!D12-Balance_Sheet!D26 -> 82650 | E19: =Balance_Sheet!E12-Balance_Sheet!E26 -> 113057 | F19: =Balance_Sheet!F12-Balance_Sheet!F26 -> 117398 | I19: – | J19: Current assets - current liabilities
B20: Working capital as % of net sales | D20: =IFERROR(D19/Income_Statement!D7,0) -> 0.10065545 | E20: =IFERROR(E19/Income_Statement!E7,0) -> 0.12600559 | F20: =IFERROR(F19/Income_Statement!F7,0) -> 0.12072494 | I20: – | J20: Working capital / net sales
B21: Operating cash flow ratio | D21: =IFERROR(Cash_Flow!D22/Balance_Sheet!D26,0) -> 0.22446976 | E21: =IFERROR(Cash_Flow!E22/Balance_Sheet!E26,0) -> 0.29780045 | F21: =IFERROR(Cash_Flow!F22/Balance_Sheet!F26,0) -> 0.37153535 | G21: 0.35 | H21: Higher | I21: =IF(H21="Higher",IF(F21>=G21,"✔ Meets","▼ Below"),IF(F21<=G21,"✔ Meets","▲ Above")) -> ✔ Meets | J21: Net cash from operations / current liabilities
B22: ="Commentary: current ratio "&IF(F16>=E16,"strengthened","softened")&" to "&TEXT(F16,"0.00")&"x (quick ratio "&TEXT(F17,"0.00")&"x). Working capital stands at PHP "&TEXT(F19/1000,"#,##0.0")&" million and operating cash flow covers "&TEXT(F21,"0.00")&"x of current liabilities." -> Commentary: current ratio softened to 1.76x (quick ratio 1.13x). Working capital stands at PHP 117.4 million and operating cash flow covers 0.37x of current liabilities.
B23: SOLVENCY AND COVERAGE
B24: Borrowings-to-equity | D24: =IFERROR(Schedules!D87/Balance_Sheet!D34,0) -> 0.69189717 | E24: =IFERROR(Schedules!E87/Balance_Sheet!E34,0) -> 0.6962321 | F24: =IFERROR(Schedules!F87/Balance_Sheet!F34,0) -> 0.54396283 | G24: 1 | H24: Lower | I24: =IF(H24="Higher",IF(F24>=G24,"✔ Meets","▼ Below"),IF(F24<=G24,"✔ Meets","▲ Above")) -> ✔ Meets | J24: Total borrowings / total equity
B25: Total liabilities-to-equity | D25: =IFERROR(Balance_Sheet!D29/Balance_Sheet!D34,0) -> 1.1121942 | E25: =IFERROR(Balance_Sheet!E29/Balance_Sheet!E34,0) -> 1.1156936 | F25: =IFERROR(Balance_Sheet!F29/Balance_Sheet!F34,0) -> 0.95689606 | G25: 1.5 | H25: Lower | I25: =IF(H25="Higher",IF(F25>=G25,"✔ Meets","▼ Below"),IF(F25<=G25,"✔ Meets","▲ Above")) -> ✔ Meets | J25: Total liabilities / total equity
B26: Debt ratio | D26: =IFERROR(Balance_Sheet!D29/Balance_Sheet!D17,0) -> 0.52655868 | E26: =IFERROR(Balance_Sheet!E29/Balance_Sheet!E17,0) -> 0.52734177 | F26: =IFERROR(Balance_Sheet!F29/Balance_Sheet!F17,0) -> 0.48898666 | G26: 0.6 | H26: Lower | I26: =IF(H26="Higher",IF(F26>=G26,"✔ Meets","▼ Below"),IF(F26<=G26,"✔ Meets","▲ Above")) -> ✔ Meets | J26: Total liabilities / total assets
B27: Equity ratio | D27: =IFERROR(Balance_Sheet!D34/Balance_Sheet!D17,0) -> 0.47344132 | E27: =IFERROR(Balance_Sheet!E34/Balance_Sheet!E17,0) -> 0.47265823 | F27: =IFERROR(Balance_Sheet!F34/Balance_Sheet!F17,0) -> 0.51101334 | G27: 0.4 | H27: Higher | I27: =IF(H27="Higher",IF(F27>=G27,"✔ Meets","▼ Below"),IF(F27<=G27,"✔ Meets","▲ Above")) -> ✔ Meets | J27: Total equity / total assets
B28: Interest cover | D28: =IFERROR(Income_Statement!D23/-Income_Statement!D17,0) -> 3.8356204 | E28: =IFERROR(Income_Statement!E23/-Income_Statement!E17,0) -> 4.3288017 | F28: =IFERROR(Income_Statement!F23/-Income_Statement!F17,0) -> 5.1969049 | G28: 4 | H28: Higher | I28: =IF(H28="Higher",IF(F28>=G28,"✔ Meets","▼ Below"),IF(F28<=G28,"✔ Meets","▲ Above")) -> ✔ Meets | J28: EBIT / finance costs
B29: EBITDA interest cover | D29: =IFERROR(Income_Statement!D24/-Income_Statement!D17,0) -> 5.5042702 | E29: =IFERROR(Income_Statement!E24/-Income_Statement!E17,0) -> 6.0063617 | F29: =IFERROR(Income_Statement!F24/-Income_Statement!F17,0) -> 7.0143639 | G29: 6 | H29: Higher | I29: =IF(H29="Higher",IF(F29>=G29,"✔ Meets","▼ Below"),IF(F29<=G29,"✔ Meets","▲ Above")) -> ✔ Meets | J29: EBITDA / finance costs
B30: Net debt / EBITDA | D30: =IFERROR((Schedules!D87-Balance_Sheet!D8)/Income_Statement!D24,0) -> 1.3560669 | E30: =IFERROR((Schedules!E87-Balance_Sheet!E8)/Income_Statement!E24,0) -> 1.0379699 | F30: =IFERROR((Schedules!F87-Balance_Sheet!F8)/Income_Statement!F24,0) -> 0.62471965 | G30: 2.5 | H30: Lower | I30: =IF(H30="Higher",IF(F30>=G30,"✔ Meets","▼ Below"),IF(F30<=G30,"✔ Meets","▲ Above")) -> ✔ Meets | J30: (Borrowings - cash) / EBITDA
B31: Debt service cover ratio | D31: =IFERROR(Income_Statement!D24/(Schedules!D90-Schedules!D83),0) -> 2.5583159 | E31: =IFERROR(Income_Statement!E24/(Schedules!E90-Schedules!E83),0) -> 2.8160572 | F31: =IFERROR(Income_Statement!F24/(Schedules!F90-Schedules!F83),0) -> 3.0731196 | G31: 1.5 | H31: Higher | I31: =IF(H31="Higher",IF(F31>=G31,"✔ Meets","▼ Below"),IF(F31<=G31,"✔ Meets","▲ Above")) -> ✔ Meets | J31: EBITDA / (finance costs + scheduled principal repaid)
B32: ="Commentary: borrowings-to-equity "&IF(F24<=E24,"declined","rose")&" to "&TEXT(F24,"0.00")&"x; interest cover is "&TEXT(F28,"0.0")&"x and net debt is "&TEXT(F30,"0.0")&"x EBITDA. Debt service cover of "&TEXT(F31,"0.00")&"x "&IF(F31>=G31,"exceeds","is below")&" the "&TEXT(G31,"0.0")&"x reference level." -> Commentary: borrowings-to-equity declined to 0.54x; interest cover is 5.2x and net debt is 0.6x EBITDA. Debt service cover of 3.07x exceeds the 1.5x reference level.
B33: EFFICIENCY (ACTIVITY)
B34: Receivables turnover (average) | D34: =IFERROR(Income_Statement!D7/AVERAGE(Balance_Sheet!C9,Balance_Sheet!D9),0) -> 10.805108 | E34: =IFERROR(Income_Statement!E7/AVERAGE(Balance_Sheet!D9,Balance_Sheet!E9),0) -> 10.588003 | F34: =IFERROR(Income_Statement!F7/AVERAGE(Balance_Sheet!E9,Balance_Sheet!F9),0) -> 10.701287 | G34: 10 | H34: Higher | I34: =IF(H34="Higher",IF(F34>=G34,"✔ Meets","▼ Below"),IF(F34<=G34,"✔ Meets","▲ Above")) -> ✔ Meets | J34: Net sales / average receivables
B35: Days sales outstanding | D35: =IFERROR(Days_Year/D34,0) -> 33.780318 | E35: =IFERROR(Days_Year/E34,0) -> 34.472977 | F35: =IFERROR(Days_Year/F34,0) -> 34.108047 | G35: 40 | H35: Lower | I35: =IF(H35="Higher",IF(F35>=G35,"✔ Meets","▼ Below"),IF(F35<=G35,"✔ Meets","▲ Above")) -> ✔ Meets | J35: Days in year / receivables turnover
B36: Inventory turnover (average) | D36: =IFERROR(-Income_Statement!D8/AVERAGE(Balance_Sheet!C10,Balance_Sheet!D10),0) -> 8.1756771 | E36: =IFERROR(-Income_Statement!E8/AVERAGE(Balance_Sheet!D10,Balance_Sheet!E10),0) -> 8.555407 | F36: =IFERROR(-Income_Statement!F8/AVERAGE(Balance_Sheet!E10,Balance_Sheet!F10),0) -> 8.7203693 | G36: 8 | H36: Higher | I36: =IF(H36="Higher",IF(F36>=G36,"✔ Meets","▼ Below"),IF(F36<=G36,"✔ Meets","▲ Above")) -> ✔ Meets | J36: Cost of sales / average inventories
B37: Days inventory outstanding | D37: =IFERROR(Days_Year/D36,0) -> 44.64462 | E37: =IFERROR(Days_Year/E36,0) -> 42.663079 | F37: =IFERROR(Days_Year/F36,0) -> 41.856025 | G37: 45 | H37: Lower | I37: =IF(H37="Higher",IF(F37>=G37,"✔ Meets","▼ Below"),IF(F37<=G37,"✔ Meets","▲ Above")) -> ✔ Meets | J37: Days in year / inventory turnover
B38: Payables turnover (average) | D38: =IFERROR(-Income_Statement!D8/AVERAGE(Balance_Sheet!C21,Balance_Sheet!D21),0) -> 9.4760505 | E38: =IFERROR(-Income_Statement!E8/AVERAGE(Balance_Sheet!D21,Balance_Sheet!E21),0) -> 9.3909807 | F38: =IFERROR(-Income_Statement!F8/AVERAGE(Balance_Sheet!E21,Balance_Sheet!F21),0) -> 9.1322476 | G38: 8 | H38: Lower | I38: =IF(H38="Higher",IF(F38>=G38,"✔ Meets","▼ Below"),IF(F38<=G38,"✔ Meets","▲ Above")) -> ▲ Above | J38: Cost of sales / average payables
B39: Days payables outstanding | D39: =IFERROR(Days_Year/D38,0) -> 38.518157 | E39: =IFERROR(Days_Year/E38,0) -> 38.86708 | F39: =IFERROR(Days_Year/F38,0) -> 39.968255 | G39: 45 | H39: Higher | I39: =IF(H39="Higher",IF(F39>=G39,"✔ Meets","▼ Below"),IF(F39<=G39,"✔ Meets","▲ Above")) -> ▼ Below | J39: Days in year / payables turnover
B40: Cash conversion cycle (days) | D40: =D35+D37-D39 -> 39.906782 | E40: =E35+E37-E39 -> 38.268975 | F40: =F35+F37-F39 -> 35.995818 | G40: 45 | H40: Lower | I40: =IF(H40="Higher",IF(F40>=G40,"✔ Meets","▼ Below"),IF(F40<=G40,"✔ Meets","▲ Above")) -> ✔ Meets | J40: DSO + DIO - DPO
B41: Total asset turnover (average) | D41: =IFERROR(Income_Statement!D7/AVERAGE(Balance_Sheet!C17,Balance_Sheet!D17),0) -> 2.0067035 | E41: =IFERROR(Income_Statement!E7/AVERAGE(Balance_Sheet!D17,Balance_Sheet!E17),0) -> 2.0459918 | F41: =IFERROR(Income_Statement!F7/AVERAGE(Balance_Sheet!E17,Balance_Sheet!F17),0) -> 2.0682356 | G41: 2 | H41: Higher | I41: =IF(H41="Higher",IF(F41>=G41,"✔ Meets","▼ Below"),IF(F41<=G41,"✔ Meets","▲ Above")) -> ✔ Meets | J41: Net sales / average total assets
B42: Fixed asset turnover (average) | D42: =IFERROR(Income_Statement!D7/AVERAGE(Balance_Sheet!C14,Balance_Sheet!D14),0) -> 4.6468163 | E42: =IFERROR(Income_Statement!E7/AVERAGE(Balance_Sheet!D14,Balance_Sheet!E14),0) -> 4.8700471 | F42: =IFERROR(Income_Statement!F7/AVERAGE(Balance_Sheet!E14,Balance_Sheet!F14),0) -> 5.0613093 | G42: 5 | H42: Higher | I42: =IF(H42="Higher",IF(F42>=G42,"✔ Meets","▼ Below"),IF(F42<=G42,"✔ Meets","▲ Above")) -> ✔ Meets | J42: Net sales / average net PPE
B43: ="Commentary: cash conversion cycle of "&TEXT(F40,"0.0")&" days ("&IF(F40<=E40,"shorter","longer")&" than the prior year): receivables "&TEXT(F35,"0.0")&" days, inventory "&TEXT(F37,"0.0")&" days, payables "&TEXT(F39,"0.0")&" days. Asset turnover "&TEXT(F41,"0.00")&"x." -> Commentary: cash conversion cycle of 36.0 days (shorter than the prior year): receivables 34.1 days, inventory 41.9 days, payables 40.0 days. Asset turnover 2.07x.
B44: CASH FLOW QUALITY
B45: Free cash flow (PHP '000) | D45: =Cash_Flow!D43 -> 10137 | E45: =Cash_Flow!E43 -> 13346 | F45: =Cash_Flow!F43 -> 30860 | I45: – | J45: Operating cash flow - capital expenditure
B46: Free cash flow margin | D46: =IFERROR(Cash_Flow!D43/Income_Statement!D7,0) -> 0.012345363 | E46: =IFERROR(Cash_Flow!E43/Income_Statement!E7,0) -> 0.014874537 | F46: =IFERROR(Cash_Flow!F43/Income_Statement!F7,0) -> 0.03173454 | G46: 0.02 | H46: Higher | I46: =IF(H46="Higher",IF(F46>=G46,"✔ Meets","▼ Below"),IF(F46<=G46,"✔ Meets","▲ Above")) -> ✔ Meets | J46: Free cash flow / net sales
B47: Cash conversion (CFO / net profit) | D47: =IFERROR(Cash_Flow!D22/Income_Statement!D20,0) -> 1.4339027 | E47: =IFERROR(Cash_Flow!E22/Income_Statement!E20,0) -> 1.5252508 | F47: =IFERROR(Cash_Flow!F22/Income_Statement!F20,0) -> 1.5441373 | G47: 1 | H47: Higher | I47: =IF(H47="Higher",IF(F47>=G47,"✔ Meets","▼ Below"),IF(F47<=G47,"✔ Meets","▲ Above")) -> ✔ Meets | J47: Net cash from operations / net profit
B48: DUPONT DECOMPOSITION OF RETURN ON EQUITY
B49: Net profit margin | D49: =IFERROR(Income_Statement!D20/Income_Statement!D7,0) -> 0.027379743 | E49: =IFERROR(Income_Statement!E20/Income_Statement!E7,0) -> 0.032331444 | F49: =IFERROR(Income_Statement!F20/Income_Statement!F7,0) -> 0.038466047 | I49: – | J49: Profitability driver
B50: x Asset turnover (average assets) | D50: =IFERROR(Income_Statement!D7/AVERAGE(Balance_Sheet!C17,Balance_Sheet!D17),0) -> 2.0067035 | E50: =IFERROR(Income_Statement!E7/AVERAGE(Balance_Sheet!D17,Balance_Sheet!E17),0) -> 2.0459918 | F50: =IFERROR(Income_Statement!F7/AVERAGE(Balance_Sheet!E17,Balance_Sheet!F17),0) -> 2.0682356 | I50: – | J50: Efficiency driver
B51: x Equity multiplier (average) | D51: =IFERROR(AVERAGE(Balance_Sheet!C17,Balance_Sheet!D17)/AVERAGE(Balance_Sheet!C34,Balance_Sheet!D34),0) -> 2.1750195 | E51: =IFERROR(AVERAGE(Balance_Sheet!D17,Balance_Sheet!E17)/AVERAGE(Balance_Sheet!D34,Balance_Sheet!E34),0) -> 2.1140357 | F51: =IFERROR(AVERAGE(Balance_Sheet!E17,Balance_Sheet!F17)/AVERAGE(Balance_Sheet!E34,Balance_Sheet!F34),0) -> 2.0318029 | I51: – | J51: Leverage driver
B52: Return on equity (product of the three drivers) | D52: =D49*D50*D51 -> 0.11950215 | E52: =E49*E50*E51 -> 0.13984318 | F52: =F49*F50*F51 -> 0.16164384 | I52: – | J52: Product of the three drivers
B53: Difference vs ROE above (should be 0) | D53: =ROUND(D52-D12,6) -> 0 | E53: =ROUND(E52-E12,6) -> 0 | F53: =ROUND(F52-F12,6) -> 0 | I53: – | J53: Integrity check

Sheet Inputs
B1: Inputs & Assumptions
B2: All hard-coded assumptions live on this sheet. Blue = input, yellow fill = key assumption. Change a value and every schedule, statement, ratio and chart updates.
B3: =HYPERLINK("#Cover!A1","◄ Back to Cover") -> ◄ Back to Cover
B5: 1. COMPANY PROFILE & GENERAL PARAMETERS
B6: Company name | C6: Sampaguita Foods & Distribution Corporation (SFDC)
B7: Short name | C7: SFDC
B8: Head office | C8: Taguig City, Metro Manila, Philippines (warehouses: Laguna, Cebu, Davao)
B9: Nature of business | C9: Wholesale distribution of packaged food, beverages, household products and fresh & frozen goods
B10: Financial year-end | C10: 31 December
B11: Presentation currency and unit | C11: PHP in thousands (unless otherwise stated)
B12: Prepared by | C12: Bengie Hirnani
B13: Regular corporate income tax (RCIT) rate | C13: 0.25 | G13: NIRC Sec. 27(A) as amended by CREATE (RA 11534): 25% for domestic corporations. Verify against current BIR rules.
B14: Minimum corporate income tax (MCIT) rate | C14: 0.02 | G14: NIRC Sec. 27(E): 2% of gross income (CREATE temporarily reduced it to 1% for Jul 2020 - Jun 2023). Verify the rate for each period.
B15: Final withholding tax on bank interest income | C15: 0.2 | G15: NIRC Sec. 27(D)(1): 20% final tax on interest from Philippine bank deposits.
B16: Days in year (turnover and days-based ratios) | C16: 365 | G16: Used for DSO, DIO, DPO and working capital balances.
B17: Horizontal analysis review threshold (+/- %) | C17: 0.1 | G17: Line items moving by more than this % year-on-year are flagged for review.
B18: Par value per share (PHP) | C18: 100 | G18: Used to derive shares outstanding and dividend per share in the Notes.
B19: Assumed term-loan tenor (years) | C19: 5 | G19: Used for the indicative PMT amortisation memo in the Notes.
B21: 2. ANNUAL DRIVERS AND BALANCES
B22: Fiscal year | C22: 2022 | D22: =C22+1 -> 2023 | E22: =D22+1 -> 2024 | F22: =E22+1 -> 2025 | G22: Remarks / source
B23: Income statement and tax drivers
B24: Interest rate - short-term loans | D24: 0.0725 | E24: 0.079 | F24: 0.081 | G24: Applied to average balance (opening + closing) / 2.
B25: Interest rate - long-term loans | D25: 0.075 | E25: 0.08 | F25: 0.0825 | G25: Applied to average balance.
B26: Yield on opening cash (interest income) | D26: 0.0125 | E26: 0.015 | F26: 0.015 | G26: Applied to prior year-end cash to avoid circularity.
B27: Other income (supplier rebates, rental, scrap sales) | D27: 1350 | E27: 1520 | F27: 1700
B28: Non-deductible expenses (representation excess, penalties) | D28: 1200 | E28: 1350 | F28: 1500 | G28: Permanent difference added back in the tax computation.
B29: Income tax paid during the year (% of current tax) | D29: 0.78 | E29: 0.8 | F29: 0.8 | G29: Quarterly payments; balance is the year-end income tax payable.
B30: Dividend payout ratio (% of net profit) | D30: 0.25 | E30: 0.25 | F30: 0.3 | G30: Cash dividends declared and paid within the year.
B31: Working capital drivers
B32: Days sales outstanding (DSO) | D32: 36 | E32: 36 | F32: 35 | G32: Trade receivables = DSO x net sales / days in year.
B33: Days inventory outstanding (DIO) | D33: 45 | E33: 44 | F33: 43 | G33: Inventories = DIO x cost of sales / days in year.
B34: Days payables outstanding (DPO) | D34: 40 | E34: 41 | F34: 42 | G34: Trade payables = DPO x cost of sales / days in year.
B35: Prepayments (% of operating expenses) | D35: 0.075 | E35: 0.075 | F35: 0.075
B36: Accrued expenses (% of operating expenses) | D36: 0.09 | E36: 0.09 | F36: 0.09
B37: Opening balances at FY2022 year-end (balance sheet date prior to first reporting year)
B38: Cash and cash equivalents | C38: 62000 | G38: Closing cash for FY2023-FY2025 is derived from the cash flow statement.
B39: Trade and other receivables | C39: 71000
B40: Inventories | C40: 74500
B41: Prepayments and other current assets | C41: 11200
B42: Trade and other payables | C42: 62300
B43: Accrued expenses | C43: 13400
B44: Income tax payable | C44: 2800
B45: Long-term loans (total, including current portion) | C45: 100000
B46: Share capital | C46: 120000
B47: Additional paid-in capital | C47: 18000
B48: Retained earnings | C48: 41700 | G48: Opening equity reconciles to opening assets less liabilities (see Checks).
B49: Balance sheet inputs by year
B50: Other non-current assets (deposits, software) | C50: 9800 | D50: 10200 | E50: 10500 | F50: 11100 | G50: Annual movement is shown as investing cash flow.
B51: Short-term loans - closing balance | C51: 45000 | D51: 48000 | E51: 42000 | F51: 38000 | G51: Revolving working capital lines.
B52: Long-term loans - drawdowns | D52: 0 | E52: 35000 | F52: 0 | G52: FY2024 drawdown funds the Laguna warehouse expansion.
B53: Long-term loans - repayments | D53: 12000 | E53: 13000 | F53: 15000
B54: Current portion of long-term loans at year-end | C54: 12000 | D54: 13000 | E54: 15000 | F54: 16500 | G54: Principal due within 12 months of the balance sheet date.
B55: Issuance of share capital | D55: 0 | E55: 0 | F55: 0
B56: Premium on shares issued (APIC) | D56: 0 | E56: 0 | F56: 0
B57: Disclosure splits used in the Notes
B58: Cash on hand (% of cash balance) | D58: 0.015 | E58: 0.015 | F58: 0.015
B59: Short-term placements (% of cash balance) | D59: 0.12 | E59: 0.12 | F59: 0.12 | G59: Cash in banks is the remainder.
B60: Receivables aged 31-60 days (%) | D60: 0.18 | E60: 0.17 | F60: 0.16 | G60: Current bucket (0-30 days) is the remainder.
B61: Receivables aged 61-90 days (%) | D61: 0.07 | E61: 0.065 | F61: 0.06
B62: Receivables aged over 90 days (%) | D62: 0.035 | E62: 0.03 | F62: 0.025
B64: 3. PROPERTY, PLANT AND EQUIPMENT
B65: Asset class | C65: Useful life (years) | D65: Cost at FY2022 | E65: Accum. depreciation at FY2022
B66: Land | C66: 0 | D66: 60000 | E66: 0 | G66: Land is not depreciated (life = 0). Straight-line depreciation on other classes with half-year convention for additions and disposals.
B67: Buildings & warehouse improvements | C67: 30 | D67: 96000 | E67: 26000
B68: Warehouse equipment & racking | C68: 12 | D68: 38000 | E68: 18500
B69: Delivery vehicles | C69: 7 | D69: 52000 | E69: 31000
B70: Office furniture & IT equipment | C70: 5 | D70: 14000 | E70: 9800
B72: Movements during the year | D72: =D$22 -> 2023 | E72: =E$22 -> 2024 | F72: =F$22 -> 2025
B73: Additions (capital expenditure)
B74: Land | D74: 0 | E74: 0 | F74: 0
B75: Buildings & warehouse improvements | D75: 4500 | E75: 11000 | F75: 6500
B76: Warehouse equipment & racking | D76: 5200 | E76: 8400 | F76: 6800
B77: Delivery vehicles | D77: 9800 | E77: 7600 | F77: 10400
B78: Office furniture & IT equipment | D78: 2600 | E78: 3900 | F78: 3200
B79: Disposals - cost
B80: Land | D80: 0 | E80: 0 | F80: 0
B81: Buildings & warehouse improvements | D81: 0 | E81: 0 | F81: 0
B82: Warehouse equipment & racking | D82: 0 | E82: 0 | F82: 0
B83: Delivery vehicles | D83: 6400 | E83: 5600 | F83: 7200
B84: Office furniture & IT equipment | D84: 0 | E84: 0 | F84: 0
B85: Disposals - accumulated depreciation
B86: Land | D86: 0 | E86: 0 | F86: 0
B87: Buildings & warehouse improvements | D87: 0 | E87: 0 | F87: 0
B88: Warehouse equipment & racking | D88: 0 | E88: 0 | F88: 0
B89: Delivery vehicles | D89: 5700 | E89: 5000 | F89: 6300
B90: Office furniture & IT equipment | D90: 0 | E90: 0 | F90: 0
B91: Disposals - cash proceeds
B92: Land | D92: 0 | E92: 0 | F92: 0
B93: Buildings & warehouse improvements | D93: 0 | E93: 0 | F93: 0
B94: Warehouse equipment & racking | D94: 0 | E94: 0 | F94: 0
B95: Delivery vehicles | D95: 1100 | E95: 450 | F95: 1250
B96: Office furniture & IT equipment | D96: 0 | E96: 0 | F96: 0
B98: 4. CHART OF ACCOUNTS MAPPING - OPERATING EXPENSES
B99: Expense line | C99: Account code | D99: Function | E99: Cost behaviour
B100: Sales commissions & incentives | C100: 6101 | D100: Selling & Distribution | E100: Variable | G100: Function and behaviour drive the SUMIFS in Income Statement, Expense Analysis and break-even.
B101: Advertising & promotions | C101: 6102 | D101: Selling & Distribution | E101: Variable
B102: Freight & delivery | C102: 6103 | D102: Selling & Distribution | E102: Variable
B103: Warehouse rent & utilities | C103: 6104 | D103: Selling & Distribution | E103: Fixed
B104: Selling & logistics staff costs | C104: 6105 | D104: Selling & Distribution | E104: Fixed
B105: Salaries & wages (G&A) | C105: 6201 | D105: General & Administrative | E105: Fixed
...

Sheet Data_Sales
B1: Data - Monthly Sales Ledger
B2: Month-end net sales and cost of sales by product category and region. Blue = ledger input (fictional data). Use the filter arrows; row 3 shows a SUBTOTAL of visible rows.
B3: =HYPERLINK("#Cover!A1","◄ Back to Cover") -> ◄ Back to Cover | F3: Visible total (SUBTOTAL) | G3: =SUBTOTAL(109,G5:G436) -> 2690798 | H3: =SUBTOTAL(109,H5:H436) -> 2005083 | I3: =SUBTOTAL(109,I5:I436) -> 685715
A4: Month-end | B4: Year | C4: Month | D4: Quarter | E4: Region | F4: Category | G4: Net sales | H4: Cost of sales | I4: Gross profit | J4: Record ID
A5: 44957 | B5: =YEAR(A5) -> 2023 | C5: =MONTH(A5) -> 1 | D5: ="Q"&ROUNDUP(C5/3,0) -> Q1 | E5: Luzon | F5: Packaged Food | G5: 14280 | H5: 10782 | I5: =G5-H5 -> 3498 | J5: ="S"&TEXT(A5,"yyyymm")&"-"&UPPER(LEFT(E5,3))&"-"&UPPER(LEFT(F5,3)) -> S202301-LUZ-PAC
A6: 44957 | B6: =YEAR(A6) -> 2023 | C6: =MONTH(A6) -> 1 | D6: ="Q"&ROUNDUP(C6/3,0) -> Q1 | E6: Visayas | F6: Packaged Food | G6: 5799 | H6: 4397 | I6: =G6-H6 -> 1402 | J6: ="S"&TEXT(A6,"yyyymm")&"-"&UPPER(LEFT(E6,3))&"-"&UPPER(LEFT(F6,3)) -> S202301-VIS-PAC
A7: 44957 | B7: =YEAR(A7) -> 2023 | C7: =MONTH(A7) -> 1 | D7: ="Q"&ROUNDUP(C7/3,0) -> Q1 | E7: Mindanao | F7: Packaged Food | G7: 4673 | H7: 3516 | I7: =G7-H7 -> 1157 | J7: ="S"&TEXT(A7,"yyyymm")&"-"&UPPER(LEFT(E7,3))&"-"&UPPER(LEFT(F7,3)) -> S202301-MIN-PAC
A8: 44957 | B8: =YEAR(A8) -> 2023 | C8: =MONTH(A8) -> 1 | D8: ="Q"&ROUNDUP(C8/3,0) -> Q1 | E8: Luzon | F8: Beverages | G8: 10453 | H8: 7688 | I8: =G8-H8 -> 2765 | J8: ="S"&TEXT(A8,"yyyymm")&"-"&UPPER(LEFT(E8,3))&"-"&UPPER(LEFT(F8,3)) -> S202301-LUZ-BEV
A9: 44957 | B9: =YEAR(A9) -> 2023 | C9: =MONTH(A9) -> 1 | D9: ="Q"&ROUNDUP(C9/3,0) -> Q1 | E9: Visayas | F9: Beverages | G9: 4190 | H9: 3081 | I9: =G9-H9 -> 1109 | J9: ="S"&TEXT(A9,"yyyymm")&"-"&UPPER(LEFT(E9,3))&"-"&UPPER(LEFT(F9,3)) -> S202301-VIS-BEV
A10: 44957 | B10: =YEAR(A10) -> 2023 | C10: =MONTH(A10) -> 1 | D10: ="Q"&ROUNDUP(C10/3,0) -> Q1 | E10: Mindanao | F10: Beverages | G10: 3451 | H10: 2545 | I10: =G10-H10 -> 906 | J10: ="S"&TEXT(A10,"yyyymm")&"-"&UPPER(LEFT(E10,3))&"-"&UPPER(LEFT(F10,3)) -> S202301-MIN-BEV
A11: 44957 | B11: =YEAR(A11) -> 2023 | C11: =MONTH(A11) -> 1 | D11: ="Q"&ROUNDUP(C11/3,0) -> Q1 | E11: Luzon | F11: Household & Personal Care | G11: 6743 | H11: 4759 | I11: =G11-H11 -> 1984 | J11: ="S"&TEXT(A11,"yyyymm")&"-"&UPPER(LEFT(E11,3))&"-"&UPPER(LEFT(F11,3)) -> S202301-LUZ-HOU
A12: 44957 | B12: =YEAR(A12) -> 2023 | C12: =MONTH(A12) -> 1 | D12: ="Q"&ROUNDUP(C12/3,0) -> Q1 | E12: Visayas | F12: Household & Personal Care | G12: 2593 | H12: 1831 | I12: =G12-H12 -> 762 | J12: ="S"&TEXT(A12,"yyyymm")&"-"&UPPER(LEFT(E12,3))&"-"&UPPER(LEFT(F12,3)) -> S202301-VIS-HOU
A13: 44957 | B13: =YEAR(A13) -> 2023 | C13: =MONTH(A13) -> 1 | D13: ="Q"&ROUNDUP(C13/3,0) -> Q1 | E13: Mindanao | F13: Household & Personal Care | G13: 2125 | H13: 1504 | I13: =G13-H13 -> 621 | J13: ="S"&TEXT(A13,"yyyymm")&"-"&UPPER(LEFT(E13,3))&"-"&UPPER(LEFT(F13,3)) -> S202301-MIN-HOU
A14: 44957 | B14: =YEAR(A14) -> 2023 | C14: =MONTH(A14) -> 1 | D14: ="Q"&ROUNDUP(C14/3,0) -> Q1 | E14: Luzon | F14: Fresh & Frozen | G14: 4615 | H14: 3775 | I14: =G14-H14 -> 840 | J14: ="S"&TEXT(A14,"yyyymm")&"-"&UPPER(LEFT(E14,3))&"-"&UPPER(LEFT(F14,3)) -> S202301-LUZ-FRE
A15: 44957 | B15: =YEAR(A15) -> 2023 | C15: =MONTH(A15) -> 1 | D15: ="Q"&ROUNDUP(C15/3,0) -> Q1 | E15: Visayas | F15: Fresh & Frozen | G15: 1856 | H15: 1516 | I15: =G15-H15 -> 340 | J15: ="S"&TEXT(A15,"yyyymm")&"-"&UPPER(LEFT(E15,3))&"-"&UPPER(LEFT(F15,3)) -> S202301-VIS-FRE
A16: 44957 | B16: =YEAR(A16) -> 2023 | C16: =MONTH(A16) -> 1 | D16: ="Q"&ROUNDUP(C16/3,0) -> Q1 | E16: Mindanao | F16: Fresh & Frozen | G16: 1490 | H16: 1211 | I16: =G16-H16 -> 279 | J16: ="S"&TEXT(A16,"yyyymm")&"-"&UPPER(LEFT(E16,3))&"-"&UPPER(LEFT(F16,3)) -> S202301-MIN-FRE
... A436: 46022 | B436: =YEAR(A436) -> 2025 | C436: =MONTH(A436) -> 12 | D436: ="Q"&ROUNDUP(C436/3,0) -> Q4 | E436: Mindanao | F436: Fresh & Frozen | G436: 2353 | H436: 1908 | I436: =G436-H436 -> 445 | J436: ="S"&TEXT(A436,"yyyymm")&"-"&UPPER(LEFT(E436,3))&"-"&UPPER(LEFT(F436,3)) -> S202512-MIN-FRE

Sheet Data_Expenses
B1: Data - Monthly Operating Expense Ledger
B2: Month-end operating expenses by expense line. Function and behaviour are looked up from the chart of accounts mapping on the Inputs sheet (VLOOKUP).
B3: =HYPERLINK("#Cover!A1","◄ Back to Cover") -> ◄ Back to Cover | F3: Visible total (SUBTOTAL) | G3: =SUBTOTAL(109,G5:G472) -> 482562
A4: Month-end | B4: Year | C4: Month | D4: Expense line | E4: Function | F4: Behaviour | G4: Amount | H4: Record ID
A5: 44957 | B5: =YEAR(A5) -> 2023 | C5: =MONTH(A5) -> 1 | D5: Sales commissions & incentives | E5: =VLOOKUP(D5,Map_Table,3,FALSE()) -> Selling & Distribution | F5: =VLOOKUP(D5,Map_Table,4,FALSE()) -> Variable | G5: 981 | H5: ="E"&TEXT(A5,"yyyymm")&"-"&TEXT(VLOOKUP(D5,Map_Table,2,FALSE()),"0") -> E202301-6101
A6: 44957 | B6: =YEAR(A6) -> 2023 | C6: =MONTH(A6) -> 1 | D6: Advertising & promotions | E6: =VLOOKUP(D6,Map_Table,3,FALSE()) -> Selling & Distribution | F6: =VLOOKUP(D6,Map_Table,4,FALSE()) -> Variable | G6: 559 | H6: ="E"&TEXT(A6,"yyyymm")&"-"&TEXT(VLOOKUP(D6,Map_Table,2,FALSE()),"0") -> E202301-6102
A7: 44957 | B7: =YEAR(A7) -> 2023 | C7: =MONTH(A7) -> 1 | D7: Freight & delivery | E7: =VLOOKUP(D7,Map_Table,3,FALSE()) -> Selling & Distribution | F7: =VLOOKUP(D7,Map_Table,4,FALSE()) -> Variable | G7: 1534 | H7: ="E"&TEXT(A7,"yyyymm")&"-"&TEXT(VLOOKUP(D7,Map_Table,2,FALSE()),"0") -> E202301-6103
A8: 44957 | B8: =YEAR(A8) -> 2023 | C8: =MONTH(A8) -> 1 | D8: Warehouse rent & utilities | E8: =VLOOKUP(D8,Map_Table,3,FALSE()) -> Selling & Distribution | F8: =VLOOKUP(D8,Map_Table,4,FALSE()) -> Fixed | G8: 1908 | H8: ="E"&TEXT(A8,"yyyymm")&"-"&TEXT(VLOOKUP(D8,Map_Table,2,FALSE()),"0") -> E202301-6104
A9: 44957 | B9: =YEAR(A9) -> 2023 | C9: =MONTH(A9) -> 1 | D9: Selling & logistics staff costs | E9: =VLOOKUP(D9,Map_Table,3,FALSE()) -> Selling & Distribution | F9: =VLOOKUP(D9,Map_Table,4,FALSE()) -> Fixed | G9: 2500 | H9: ="E"&TEXT(A9,"yyyymm")&"-"&TEXT(VLOOKUP(D9,Map_Table,2,FALSE()),"0") -> E202301-6105
A10: 44957 | B10: =YEAR(A10) -> 2023 | C10: =MONTH(A10) -> 1 | D10: Salaries & wages (G&A) | E10: =VLOOKUP(D10,Map_Table,3,FALSE()) -> General & Administrative | F10: =VLOOKUP(D10,Map_Table,4,FALSE()) -> Fixed | G10: 2315 | H10: ="E"&TEXT(A10,"yyyymm")&"-"&TEXT(VLOOKUP(D10,Map_Table,2,FALSE()),"0") -> E202301-6201
A11: 44957 | B11: =YEAR(A11) -> 2023 | C11: =MONTH(A11) -> 1 | D11: Employee benefits & contributions | E11: =VLOOKUP(D11,Map_Table,3,FALSE()) -> General & Administrative | F11: =VLOOKUP(D11,Map_Table,4,FALSE()) -> Fixed | G11: 610 | H11: ="E"&TEXT(A11,"yyyymm")&"-"&TEXT(VLOOKUP(D11,Map_Table,2,FALSE()),"0") -> E202301-6202
A12: 44957 | B12: =YEAR(A12) -> 2023 | C12: =MONTH(A12) -> 1 | D12: Professional fees | E12: =VLOOKUP(D12,Map_Table,3,FALSE()) -> General & Administrative | F12: =VLOOKUP(D12,Map_Table,4,FALSE()) -> Fixed | G12: 296 | H12: ="E"&TEXT(A12,"yyyymm")&"-"&TEXT(VLOOKUP(D12,Map_Table,2,FALSE()),"0") -> E202301-6203
A13: 44957 | B13: =YEAR(A13) -> 2023 | C13: =MONTH(A13) -> 1 | D13: Office rent & utilities | E13: =VLOOKUP(D13,Map_Table,3,FALSE()) -> General & Administrative | F13: =VLOOKUP(D13,Map_Table,4,FALSE()) -> Fixed | G13: 522 | H13: ="E"&TEXT(A13,"yyyymm")&"-"&TEXT(VLOOKUP(D13,Map_Table,2,FALSE()),"0") -> E202301-6204
A14: 44957 | B14: =YEAR(A14) -> 2023 | C14: =MONTH(A14) -> 1 | D14: Repairs & maintenance | E14: =VLOOKUP(D14,Map_Table,3,FALSE()) -> General & Administrative | F14: =VLOOKUP(D14,Map_Table,4,FALSE()) -> Fixed | G14: 204 | H14: ="E"&TEXT(A14,"yyyymm")&"-"&TEXT(VLOOKUP(D14,Map_Table,2,FALSE()),"0") -> E202301-6205
A15: 44957 | B15: =YEAR(A15) -> 2023 | C15: =MONTH(A15) -> 1 | D15: Taxes, licenses & insurance | E15: =VLOOKUP(D15,Map_Table,3,FALSE()) -> General & Administrative | F15: =VLOOKUP(D15,Map_Table,4,FALSE()) -> Fixed | G15: 416 | H15: ="E"&TEXT(A15,"yyyymm")&"-"&TEXT(VLOOKUP(D15,Map_Table,2,FALSE()),"0") -> E202301-6206
A16: 44957 | B16: =YEAR(A16) -> 2023 | C16: =MONTH(A16) -> 1 | D16: Communication, IT & supplies | E16: =VLOOKUP(D16,Map_Table,3,FALSE()) -> General & Administrative | F16: =VLOOKUP(D16,Map_Table,4,FALSE()) -> Fixed | G16: 339 | H16: ="E"&TEXT(A16,"yyyymm")&"-"&TEXT(VLOOKUP(D16,Map_Table,2,FALSE()),"0") -> E202301-6207
... A472: 46022 | B472: =YEAR(A472) -> 2025 | C472: =MONTH(A472) -> 12 | D472: Bad debts & credit losses | E472: =VLOOKUP(D472,Map_Table,3,FALSE()) -> General & Administrative | F472: =VLOOKUP(D472,Map_Table,4,FALSE()) -> Variable | G472: 145 | H472: ="E"&TEXT(A472,"yyyymm")&"-"&TEXT(VLOOKUP(D472,Map_Table,2,FALSE()),"0") -> E202512-6208

Sheet Chart_Data
B1: Chart Data
B2: Helper tables that feed the dashboard charts. All cells are formulas - do not overwrite.
B3: =HYPERLINK("#Cover!A1","◄ Back to Cover") -> ◄ Back to Cover
B5: Annual performance (PHP '000) | C5: ="FY"&Inputs!D$22 -> FY2023 | D5: ="FY"&Inputs!E$22 -> FY2024 | E5: ="FY"&Inputs!F$22 -> FY2025
B6: Net sales | C6: =Income_Statement!D7 -> 821118 | D6: =Income_Statement!E7 -> 897238 | E6: =Income_Statement!F7 -> 972442
B7: Gross profit | C7: =Income_Statement!D9 -> 207141 | D7: =Income_Statement!E9 -> 228680 | E7: =Income_Statement!F9 -> 249894
B8: EBITDA | C8: =Income_Statement!D24 -> 57360 | D8: =Income_Statement!E24 -> 68923 | E8: =Income_Statement!F24 -> 82040
B9: Net profit | C9: =Income_Statement!D20 -> 22482 | D9: =Income_Statement!E20 -> 29009 | E9: =Income_Statement!F20 -> 37406
B12: Margins | C12: ="FY"&Inputs!D$22 -> FY2023 | D12: ="FY"&Inputs!E$22 -> FY2024 | E12: ="FY"&Inputs!F$22 -> FY2025
B13: Gross margin | C13: =Ratio_Analysis!D7 -> 0.25226703 | D13: =Ratio_Analysis!E7 -> 0.25487106 | E13: =Ratio_Analysis!F7 -> 0.25697574
B14: EBITDA margin | C14: =Ratio_Analysis!D8 -> 0.069855977 | D14: =Ratio_Analysis!E8 -> 0.076816853 | E14: =Ratio_Analysis!F8 -> 0.084364929
B15: Net margin | C15: =Ratio_Analysis!D10 -> 0.027379743 | D15: =Ratio_Analysis!E10 -> 0.032331444 | E15: =Ratio_Analysis!F10 -> 0.038466047
B18: Revenue mix (selected year) | C18: ="FY"&Dash_Year -> FY2025
B19: =Lists!C5 -> Packaged Food | C19: =SUMIFS(Sales_Net,Sales_Year,Dash_Year,Sales_Cat,B19) -> 382510
B20: =Lists!C6 -> Beverages | C20: =SUMIFS(Sales_Net,Sales_Year,Dash_Year,Sales_Cat,B20) -> 292182
B21: =Lists!C7 -> Household & Personal Care | C21: =SUMIFS(Sales_Net,Sales_Year,Dash_Year,Sales_Cat,B21) -> 170561
B22: =Lists!C8 -> Fresh & Frozen | C22: =SUMIFS(Sales_Net,Sales_Year,Dash_Year,Sales_Cat,B22) -> 127189
B25: Cash flow by activity (PHP '000) | C25: ="FY"&Inputs!D$22 -> FY2023 | D25: ="FY"&Inputs!E$22 -> FY2024 | E25: ="FY"&Inputs!F$22 -> FY2025
B26: Operating | C26: =Cash_Flow!D22 -> 32237 | D26: =Cash_Flow!E22 -> 44246 | E26: =Cash_Flow!F22 -> 57760
B27: Investing | C27: =Cash_Flow!D28 -> -21400 | D27: =Cash_Flow!E28 -> -30750 | E27: =Cash_Flow!F28 -> -26250
B28: Financing | C28: =Cash_Flow!D36 -> -14621 | D28: =Cash_Flow!E36 -> 8748 | E28: =Cash_Flow!F36 -> -30222
B30: Liquidity and leverage | C30: ="FY"&Inputs!D$22 -> FY2023 | D30: ="FY"&Inputs!E$22 -> FY2024 | E30: ="FY"&Inputs!F$22 -> FY2025
B31: Current ratio | C31: =Ratio_Analysis!D16 -> 1.575501 | D31: =Ratio_Analysis!E16 -> 1.7609372 | E31: =Ratio_Analysis!F16 -> 1.7551507
B32: Quick ratio | C32: =Ratio_Analysis!D17 -> 0.96928572 | D32: =Ratio_Analysis!E17 -> 1.1371621 | E32: =Ratio_Analysis!F17 -> 1.125644
B33: Borrowings-to-equity | C33: =Ratio_Analysis!D24 -> 0.69189717 | D33: =Ratio_Analysis!E24 -> 0.6962321 | E33: =Ratio_Analysis!F24 -> 0.54396283
B34: Net debt / EBITDA | C34: =Ratio_Analysis!D30 -> 1.3560669 | D34: =Ratio_Analysis!E30 -> 1.0379699 | E34: =Ratio_Analysis!F30 -> 0.62471965
B36: Where each peso of sales goes | C36: ="FY"&Dash_Year -> FY2025
B37: Cost of sales | C37: =IFERROR(-INDEX(Income_Statement!$D$8:$F$8,MATCH(Dash_Year,Income_Statement!$D$5:$F$5,0))/INDEX(Income_Statement!$D$7:$F$7,MATCH(Dash_Year,Income_Statement!$D$5:$F$5,0)),0) -> 0.74302426
B38: Selling & distribution | C38: =IFERROR(-INDEX(Income_Statement!$D$10:$F$10,MATCH(Dash_Year,Income_Statement!$D$5:$F$5,0))/INDEX(Income_Statement!$D$7:$F$7,MATCH(Dash_Year,Income_Statement!$D$5:$F$5,0)),0) -> 0.10908311
B39: General & administrative | C39: =IFERROR(-INDEX(Income_Statement!$D$11:$F$11,MATCH(Dash_Year,Income_Statement!$D$5:$F$5,0))/INDEX(Income_Statement!$D$7:$F$7,MATCH(Dash_Year,Income_Statement!$D$5:$F$5,0)),0) -> 0.065635791
B40: Depreciation | C40: =IFERROR(-INDEX(Income_Statement!$D$12:$F$12,MATCH(Dash_Year,Income_Statement!$D$5:$F$5,0))/INDEX(Income_Statement!$D$7:$F$7,MATCH(Dash_Year,Income_Statement!$D$5:$F$5,0)),0) -> 0.021859401
B41: Finance costs | C41: =IFERROR(-INDEX(Income_Statement!$D$17:$F$17,MATCH(Dash_Year,Income_Statement!$D$5:$F$5,0))/INDEX(Income_Statement!$D$7:$F$7,MATCH(Dash_Year,Income_Statement!$D$5:$F$5,0)),0) -> 0.012027453
B42: Income tax | C42: =IFERROR(-INDEX(Income_Statement!$D$19:$F$19,MATCH(Dash_Year,Income_Statement!$D$5:$F$5,0))/INDEX(Income_Statement!$D$7:$F$7,MATCH(Dash_Year,Income_Statement!$D$5:$F$5,0)),0) -> 0.013253233
B43: Net profit | C43: =IFERROR(INDEX(Income_Statement!$D$20:$F$20,MATCH(Dash_Year,Income_Statement!$D$5:$F$5,0))/INDEX(Income_Statement!$D$7:$F$7,MATCH(Dash_Year,Income_Statement!$D$5:$F$5,0)),0) -> 0.038466047
B44: Other items (net other income, interest, gains) | C44: =1-SUM(C37:C43) -> -0.0033493
B47: Dashboard KPIs (PHP '000) | C47: ="FY"&Inputs!D$22 -> FY2023 | D47: ="FY"&Inputs!E$22 -> FY2024 | E47: ="FY"&Inputs!F$22 -> FY2025 | F47: Selected year | G47: Prior year | H47: Change %
B48: Net sales | C48: =Income_Statement!D7 -> 821118 | D48: =Income_Statement!E7 -> 897238 | E48: =Income_Statement!F7 -> 972442 | F48: =INDEX(C48:E48,MATCH(Dash_Year,FY_List,0)) -> 972442 | G48: =IF(MATCH(Dash_Year,FY_List,0)=1,"",INDEX(C48:E48,MATCH(Dash_Year,FY_List,0)-1)) -> 897238 | H48: =IF(G48="","n/a",IFERROR((F48-G48)/ABS(G48),0)) -> 0.083817226
B49: Gross profit | C49: =Income_Statement!D9 -> 207141 | D49: =Income_Statement!E9 -> 228680 | E49: =Income_Statement!F9 -> 249894 | F49: =INDEX(C49:E49,MATCH(Dash_Year,FY_List,0)) -> 249894 | G49: =IF(MATCH(Dash_Year,FY_List,0)=1,"",INDEX(C49:E49,MATCH(Dash_Year,FY_List,0)-1)) -> 228680 | H49: =IF(G49="","n/a",IFERROR((F49-G49)/ABS(G49),0)) -> 0.092767186
B50: EBITDA | C50: =Income_Statement!D24 -> 57360 | D50: =Income_Statement!E24 -> 68923 | E50: =Income_Statement!F24 -> 82040 | F50: =INDEX(C50:E50,MATCH(Dash_Year,FY_List,0)) -> 82040 | G50: =IF(MATCH(Dash_Year,FY_List,0)=1,"",INDEX(C50:E50,MATCH(Dash_Year,FY_List,0)-1)) -> 68923 | H50: =IF(G50="","n/a",IFERROR((F50-G50)/ABS(G50),0)) -> 0.19031383
B51: Net profit | C51: =Income_Statement!D20 -> 22482 | D51: =Income_Statement!E20 -> 29009 | E51: =Income_Statement!F20 -> 37406 | F51: =INDEX(C51:E51,MATCH(Dash_Year,FY_List,0)) -> 37406 | G51: =IF(MATCH(Dash_Year,FY_List,0)=1,"",INDEX(C51:E51,MATCH(Dash_Year,FY_List,0)-1)) -> 29009 | H51: =IF(G51="","n/a",IFERROR((F51-G51)/ABS(G51),0)) -> 0.28946189
B52: Total assets | C52: =Balance_Sheet!D17 -> 415175 | D52: =Balance_Sheet!E17 -> 461894 | E52: =Balance_Sheet!F17 -> 478465 | F52: =INDEX(C52:E52,MATCH(Dash_Year,FY_List,0)) -> 478465 | G52: =IF(MATCH(Dash_Year,FY_List,0)=1,"",INDEX(C52:E52,MATCH(Dash_Year,FY_List,0)-1)) -> 461894 | H52: =IF(G52="","n/a",IFERROR((F52-G52)/ABS(G52),0)) -> 0.035876197
B53: Total equity | C53: =Balance_Sheet!D34 -> 196561 | D53: =Balance_Sheet!E34 -> 218318 | E53: =Balance_Sheet!F34 -> 244502 | F53: =INDEX(C53:E53,MATCH(Dash_Year,FY_List,0)) -> 244502 | G53: =IF(MATCH(Dash_Year,FY_List,0)=1,"",INDEX(C53:E53,MATCH(Dash_Year,FY_List,0)-1)) -> 218318 | H53: =IF(G53="","n/a",IFERROR((F53-G53)/ABS(G53),0)) -> 0.11993514
B54: Net debt | C54: =Schedules!D87-Balance_Sheet!D8 -> 77784 | D54: =Schedules!E87-Balance_Sheet!E8 -> 71540 | E54: =Schedules!F87-Balance_Sheet!F8 -> 51252 | F54: =INDEX(C54:E54,MATCH(Dash_Year,FY_List,0)) -> 51252 | G54: =IF(MATCH(Dash_Year,FY_List,0)=1,"",INDEX(C54:E54,MATCH(Dash_Year,FY_List,0)-1)) -> 71540 | H54: =IF(G54="","n/a",IFERROR((F54-G54)/ABS(G54),0)) -> -0.2835896
B55: Free cash flow | C55: =Cash_Flow!D43 -> 10137 | D55: =Cash_Flow!E43 -> 13346 | E55: =Cash_Flow!F43 -> 30860 | F55: =INDEX(C55:E55,MATCH(Dash_Year,FY_List,0)) -> 30860 | G55: =IF(MATCH(Dash_Year,FY_List,0)=1,"",INDEX(C55:E55,MATCH(Dash_Year,FY_List,0)-1)) -> 13346 | H55: =IF(G55="","n/a",IFERROR((F55-G55)/ABS(G55),0)) -> 1.3123033
B59: Net sales: actual and projections | C59: ="FY"&Inputs!D$22 -> FY2023 | D59: ="FY"&Inputs!E$22 -> FY2024 | E59: ="FY"&Inputs!F$22 -> FY2025 | F59: ="FY"&(Inputs!F$22+1)&"F" -> FY2026F | G59: ="FY"&(Inputs!F$22+2)&"F" -> FY2027F
B60: Actual | C60: =Income_Statement!D7 -> 821118 | D60: =Income_Statement!E7 -> 897238 | E60: =Income_Statement!F7 -> 972442
B61: Linear projection | E61: =Income_Statement!F7 -> 972442 | F61: =Trend!F18 -> 1048256.7 | G61: =Trend!G18 -> 1123918.7
B62: CAGR projection | E62: =Income_Statement!F7 -> 972442 | F62: =Trend!H18 -> 1058261 | G62: =Trend!I18 -> 1151653.5

Sheet Lists
B1: Lists
B2: Source ranges for drop-down menus and named labels. Edit with care: names must match the data ledgers.
B3: =HYPERLINK("#Cover!A1","◄ Back to Cover") -> ◄ Back to Cover
A4: Fiscal years | C4: Categories | E4: Categories (All) | G4: Regions | I4: Regions (All) | K4: Measures | M4: Functions | O4: Months | Q4: Behaviour
A5: =Inputs!D$22 -> 2023 | C5: Packaged Food | E5: All | G5: Luzon | I5: All | K5: Net Sales | M5: Selling & Distribution | O5: Jan | Q5: Variable
A6: =Inputs!E$22 -> 2024 | C6: Beverages | E6: =C5 -> Packaged Food | G6: Visayas | I6: =G5 -> Luzon | K6: Cost of Sales | M6: General & Administrative | O6: Feb | Q6: Fixed
A7: =Inputs!F$22 -> 2025 | C7: Household & Personal Care | E7: =C6 -> Beverages | G7: Mindanao | I7: =G6 -> Visayas | K7: Gross Profit | O7: Mar
C8: Fresh & Frozen | E8: =C7 -> Household & Personal Care | I8: =G7 -> Mindanao | O8: Apr
E9: =C8 -> Fresh & Frozen | O9: May
O10: Jun
O11: Jul
O12: Aug
O13: Sep
O14: Oct
O15: Nov
O16: Dec

Sheet Checks
B1: Model Integrity Checks
B2: =Inputs!$C$6&" | "&Inputs!$C$11 -> Sampaguita Foods & Distribution Corporation (SFDC) | PHP in thousands (unless otherwise stated)
B3: =HYPERLINK("#Cover!A1","◄ Back to Cover") -> ◄ Back to Cover
B4: Overall status | C4: =IF(COUNTIF(G7:G29,"ERROR")=0,"✔ All "&COUNTA(G7:G29)&" integrity checks passed","✖ "&COUNTIF(G7:G29,"ERROR")&" check(s) failing - review the Checks sheet") -> ✔ All 23 integrity checks passed
B6: Check (difference should be zero) | C6: =Inputs!C$22 -> 2022 | D6: =Inputs!D$22 -> 2023 | E6: =Inputs!E$22 -> 2024 | F6: =Inputs!F$22 -> 2025 | G6: Status | H6: What it proves
B7: Balance sheet balances (assets = liabilities + equity) | C7: =Balance_Sheet!C37 -> 0 | D7: =Balance_Sheet!D37 -> 0 | E7: =Balance_Sheet!E37 -> 0 | F7: =Balance_Sheet!F37 -> 0 | G7: =IF(SUMPRODUCT(ABS(C7:F7))<0.5,"OK","ERROR") -> OK | H7: Double-entry integrity, including FY2022 opening balances
B8: Cash flow opening cash = prior-year balance sheet cash | D8: =Cash_Flow!D39-Balance_Sheet!C8 -> 0 | E8: =Cash_Flow!E39-Balance_Sheet!D8 -> 0 | F8: =Cash_Flow!F39-Balance_Sheet!E8 -> 0 | G8: =IF(SUMPRODUCT(ABS(C8:F8))<0.5,"OK","ERROR") -> OK | H8: Cash continuity between years
B9: Cash flow closing cash = balance sheet cash | D9: =Cash_Flow!D40-Balance_Sheet!D8 -> 0 | E9: =Cash_Flow!E40-Balance_Sheet!E8 -> 0 | F9: =Cash_Flow!F40-Balance_Sheet!F8 -> 0 | G9: =IF(SUMPRODUCT(ABS(C9:F9))<0.5,"OK","ERROR") -> OK | H9: Cash flow statement reconciles to the balance sheet
B10: Statement of changes in equity = balance sheet equity | D10: =Equity_Changes!F11-Balance_Sheet!D34 -> 0 | E10: =Equity_Changes!F19-Balance_Sheet!E34 -> 0 | F10: =Equity_Changes!F27-Balance_Sheet!F34 -> 0 | G10: =IF(SUMPRODUCT(ABS(C10:F10))<0.5,"OK","ERROR") -> OK | H10: Equity roll-forward integrity
B11: Net sales ledger: by category = income statement | D11: =Notes_to_FS!D90-Income_Statement!D7 -> 0 | E11: =Notes_to_FS!E90-Income_Statement!E7 -> 0 | F11: =Notes_to_FS!F90-Income_Statement!F7 -> 0 | G11: =IF(SUMPRODUCT(ABS(C11:F11))<0.5,"OK","ERROR") -> OK | H11: Category disaggregation is complete
B12: Net sales ledger: by region = income statement | D12: =Notes_to_FS!D94-Income_Statement!D7 -> 0 | E12: =Notes_to_FS!E94-Income_Statement!E7 -> 0 | F12: =Notes_to_FS!F94-Income_Statement!F7 -> 0 | G12: =IF(SUMPRODUCT(ABS(C12:F12))<0.5,"OK","ERROR") -> OK | H12: Region disaggregation is complete
B13: Expense ledger total = selling + G&A per income statement | D13: =SUMIFS(Exp_Amt,Exp_Year,D$6)+Income_Statement!D10+Income_Statement!D11 -> 0 | E13: =SUMIFS(Exp_Amt,Exp_Year,E$6)+Income_Statement!E10+Income_Statement!E11 -> 0 | F13: =SUMIFS(Exp_Amt,Exp_Year,F$6)+Income_Statement!F10+Income_Statement!F11 -> 0 | G13: =IF(SUMPRODUCT(ABS(C13:F13))<0.5,"OK","ERROR") -> OK | H13: Every ledger line maps to a function (no unmapped accounts)
B14: Note 3 cash components = balance sheet cash | D14: =Notes_to_FS!D22-Balance_Sheet!D8 -> 0 | E14: =Notes_to_FS!E22-Balance_Sheet!E8 -> 0 | F14: =Notes_to_FS!F22-Balance_Sheet!F8 -> 0 | G14: =IF(SUMPRODUCT(ABS(C14:F14))<0.5,"OK","ERROR") -> OK | H14: Disclosure ties to the face of the statements
B15: Note 4 receivables ageing = balance sheet receivables | D15: =Notes_to_FS!D30-Balance_Sheet!D9 -> 0 | E15: =Notes_to_FS!E30-Balance_Sheet!E9 -> 0 | F15: =Notes_to_FS!F30-Balance_Sheet!F9 -> 0 | G15: =IF(SUMPRODUCT(ABS(C15:F15))<0.5,"OK","ERROR") -> OK | H15: Disclosure ties to the face of the statements
B16: Note 5 inventories by category = balance sheet inventories | D16: =Notes_to_FS!D40-Balance_Sheet!D10 -> 0 | E16: =Notes_to_FS!E40-Balance_Sheet!E10 -> 0 | F16: =Notes_to_FS!F40-Balance_Sheet!F10 -> 0 | G16: =IF(SUMPRODUCT(ABS(C16:F16))<0.5,"OK","ERROR") -> OK | H16: Disclosure ties to the face of the statements
B17: Note 6 PPE net book value = balance sheet PPE | D17: =Notes_to_FS!D50-Balance_Sheet!D14 -> 0 | E17: =Notes_to_FS!E50-Balance_Sheet!E14 -> 0 | F17: =Notes_to_FS!F50-Balance_Sheet!F14 -> 0 | G17: =IF(SUMPRODUCT(ABS(C17:F17))<0.5,"OK","ERROR") -> OK | H17: Disclosure ties to the face of the statements
B18: Note 7 borrowings = schedule total | D18: =Notes_to_FS!D67-Schedules!D87 -> 0 | E18: =Notes_to_FS!E67-Schedules!E87 -> 0 | F18: =Notes_to_FS!F67-Schedules!F87 -> 0 | G18: =IF(SUMPRODUCT(ABS(C18:F18))<0.5,"OK","ERROR") -> OK | H18: Debt note agrees to the borrowings schedule
B19: Note 10 costs by nature = income statement costs | D19: =Notes_to_FS!D113+Income_Statement!D8+Income_Statement!D10+Income_Statement!D11+Income_Statement!D12 -> 0 | E19: =Notes_to_FS!E113+Income_Statement!E8+Income_Statement!E10+Income_Statement!E11+Income_Statement!E12 -> 0 | F19: =Notes_to_FS!F113+Income_Statement!F8+Income_Statement!F10+Income_Statement!F11+Income_Statement!F12 -> 0 | G19: =IF(SUMPRODUCT(ABS(C19:F19))<0.5,"OK","ERROR") -> OK | H19: Expense disclosure is complete
B20: Note 11 tax reconciliation = income tax expense | D20: =Notes_to_FS!D123+Income_Statement!D19 -> 0 | E20: =Notes_to_FS!E123+Income_Statement!E19 -> 0 | F20: =Notes_to_FS!F123+Income_Statement!F19 -> 0 | G20: =IF(SUMPRODUCT(ABS(C20:F20))<0.5,"OK","ERROR") -> OK | H20: Tax reconciliation agrees to the income statement
B21: Expense analysis break-even derivation = income statement (FY selected) | F21: =Expense_Analysis!C50 -> 0 | G21: =IF(SUMPRODUCT(ABS(C21:F21))<0.5,"OK","ERROR") -> OK | H21: Variable + fixed cost split reproduces operating profit
B22: DuPont ROE = average-based ROE | D22: =Ratio_Analysis!D53 -> 0 | E22: =Ratio_Analysis!E53 -> 0 | F22: =Ratio_Analysis!F53 -> 0 | G22: =IF(SUMPRODUCT(ABS(C22:F22))<0.5,"OK","ERROR") -> OK | H22: Ratio decomposition is arithmetically consistent
B23: No PPE class has a negative net book value | D23: =MIN(0,Schedules!D16,Schedules!D26,Schedules!D36,Schedules!D46,Schedules!D56) -> 0 | E23: =MIN(0,Schedules!E16,Schedules!E26,Schedules!E36,Schedules!E46,Schedules!E56) -> 0 | F23: =MIN(0,Schedules!F16,Schedules!F26,Schedules!F36,Schedules!F46,Schedules!F56) -> 0 | G23: =IF(SUMPRODUCT(ABS(C23:F23))<0.5,"OK","ERROR") -> OK | H23: Depreciation is capped at cost
B24: Cash balance is not negative | C24: =MIN(0,Balance_Sheet!C8) -> 0 | D24: =MIN(0,Balance_Sheet!D8) -> 0 | E24: =MIN(0,Balance_Sheet!E8) -> 0 | F24: =MIN(0,Balance_Sheet!F8) -> 0 | G24: =IF(SUMPRODUCT(ABS(C24:F24))<0.5,"OK","ERROR") -> OK | H24: No overdraft hidden in the cash flow
B25: Sales ledger row count = months x categories x regions | D25: =COUNTIFS(Sales_Year,D$6)-12*ROWS(Cat_List)*ROWS(Region_List) -> 0 | E25: =COUNTIFS(Sales_Year,E$6)-12*ROWS(Cat_List)*ROWS(Region_List) -> 0 | F25: =COUNTIFS(Sales_Year,F$6)-12*ROWS(Cat_List)*ROWS(Region_List) -> 0 | G25: =IF(SUMPRODUCT(ABS(C25:F25))<0.5,"OK","ERROR") -> OK | H25: No missing or duplicate ledger rows
B26: Expense ledger row count = months x expense lines | D26: =COUNTIFS(Exp_Year,D$6)-12*ROWS(Map_Table) -> 0 | E26: =COUNTIFS(Exp_Year,E$6)-12*ROWS(Map_Table) -> 0 | F26: =COUNTIFS(Exp_Year,F$6)-12*ROWS(Map_Table) -> 0 | G26: =IF(SUMPRODUCT(ABS(C26:F26))<0.5,"OK","ERROR") -> OK | H26: No missing or duplicate ledger rows
B27: Dividend payout ratio does not exceed 100% | D27: =MAX(0,Inputs!D30-1) -> 0 | E27: =MAX(0,Inputs!E30-1) -> 0 | F27: =MAX(0,Inputs!F30-1) -> 0 | G27: =IF(SUMPRODUCT(ABS(C27:F27))<0.5,"OK","ERROR") -> OK | H27: Input sanity
B28: Disclosure split percentages do not exceed 100% | D28: =MAX(0,Inputs!D60+Inputs!D61+Inputs!D62-1)+MAX(0,Inputs!D58+Inputs!D59-1) -> 0 | E28: =MAX(0,Inputs!E60+Inputs!E61+Inputs!E62-1)+MAX(0,Inputs!E58+Inputs!E59-1) -> 0 | F28: =MAX(0,Inputs!F60+Inputs!F61+Inputs!F62-1)+MAX(0,Inputs!F58+Inputs!F59-1) -> 0 | G28: =IF(SUMPRODUCT(ABS(C28:F28))<0.5,"OK","ERROR") -> OK | H28: Input sanity
B29: Interest cover is at least 1.0x (EBIT covers finance costs) | D29: =MIN(0,IFERROR(Income_Statement!D23/-Income_Statement!D17,1)-1) -> 0 | E29: =MIN(0,IFERROR(Income_Statement!E23/-Income_Statement!E17,1)-1) -> 0 | F29: =MIN(0,IFERROR(Income_Statement!F23/-Income_Statement!F17,1)-1) -> 0 | G29: =IF(SUMPRODUCT(ABS(C29:F29))<0.5,"OK","ERROR") -> OK | H29: Going-concern sanity flag
